Workbook

Sheet JELineItems
A1: JENumber | B1: GLAccountNumber | C1: BusinessUnitID | D1: PreparerID | E1: SourceID | F1: EffectiveDate | G1: JEDescription | H1: Debit | I1: Credit | J1: Amount
A2: 2033520 | B2: 76930 | C2: 1 | D2: 101 | E2: 1002 | F2: 44002 | G2: TELECOM GTA JUN 2016 | H2: 36.9 | J2: 36.9
A3: 2033520 | B3: 11845 | C3: 1 | D3: 101 | E3: 1002 | F3: 44002 | G3: TELECOM GTA JUN 2016 | I3: -36.9 | J3: -36.9
A4: 2033521 | B4: 11845 | C4: 3 | D4: 102 | E4: 1001 | F4: 44002 | G4: CASH RECEIPTS | H4: 63.1 | J4: 63.1
A5: 2033521 | B5: 43440 | C5: 3 | D5: 102 | E5: 1001 | F5: 44002 | G5: CASH RECEIPTS | I5: -63.1 | J5: -63.1
A6: 2033522 | B6: 11845 | C6: 1 | D6: 102 | E6: 1003 | F6: 44002 | G6: CREDIT CARD RECEIPTS | H6: 68.28 | J6: 68.28
A7: 2033522 | B7: 43310 | C7: 1 | D7: 102 | E7: 1003 | F7: 44002 | G7: CREDIT CARD RECEIPTS | I7: -68.28 | J7: -68.28
A8: 2033523 | B8: 11845 | C8: 2 | D8: 106 | E8: 1003 | F8: 44002 | G8: CONFERENCE - HOTEL | H8: 99 | J8: 99
A9: 2033523 | B9: 43180 | C9: 2 | D9: 106 | E9: 1003 | F9: 44002 | G9: CONFERENCE - HOTEL | I9: -99 | J9: -99
A10: 2033524 | B10: 11845 | C10: 3 | D10: 102 | E10: 1003 | F10: 44002 | G10: CREDIT CARD RECEIPTS | H10: 107.21 | J10: 107.21
A11: 2033524 | B11: 43440 | C11: 3 | D11: 102 | E11: 1003 | F11: 44002 | G11: CREDIT CARD RECEIPTS | I11: -107.21 | J11: -107.21
A12: 2033525 | B12: 11845 | C12: 2 | D12: 104 | E12: 1003 | F12: 44002 | G12: HENDERSON,KENNY | H12: 129 | J12: 129
A13: 2033525 | B13: 43180 | C13: 2 | D13: 104 | E13: 1003 | F13: 44002 | G13: HENDERSON,KENNY | I13: -129 | J13: -129
A14: 2033526 | B14: 11845 | C14: 2 | D14: 104 | E14: 1003 | F14: 44002 | G14: GENTRY,NIA | H14: 258 | J14: 258
A15: 2033526 | B15: 43180 | C15: 2 | D15: 104 | E15: 1003 | F15: 44002 | G15: GENTRY,NIA | I15: -258 | J15: -258
A16: 2033527 | B16: 11845 | C16: 2 | D16: 104 | E16: 1003 | F16: 44002 | G16: HODGES,CHAYA | H16: 418 | J16: 418
A17: 2033527 | B17: 43180 | C17: 2 | D17: 104 | E17: 1003 | F17: 44002 | G17: HODGES,CHAYA | I17: -418 | J17: -418
A18: 2033528 | B18: 71900 | C18: 1 | D18: 102 | E18: 1002 | F18: 44002 | G18: ALSCO INC | H18: 431.8 | J18: 431.8
A19: 2033528 | B19: 11845 | C19: 1 | D19: 102 | E19: 1002 | F19: 44002 | G19: ALSCO INC | I19: -431.8 | J19: -431.8
A20: 2033529 | B20: 11845 | C20: 1 | D20: 102 | E20: 1001 | F20: 44002 | G20: CASH RECEIPTS | H20: 612.54 | J20: 612.54
A21: 2033529 | B21: 43310 | C21: 1 | D21: 102 | E21: 1001 | F21: 44002 | G21: CASH RECEIPTS | I21: -612.54 | J21: -612.54
A22: 2033530 | B22: 76930 | C22: 2 | D22: 101 | E22: 1002 | F22: 44002 | G22: TELECOM GTA JUN 2016 | H22: 1015.21 | J22: 1015.21
A23: 2033530 | B23: 11845 | C23: 2 | D23: 101 | E23: 1002 | F23: 44002 | G23: TELECOM GTA JUN 2016 | I23: -1015.21 | J23: -1015.21
A24: 2033531 | B24: 11845 | C24: 1 | D24: 102 | E24: 1003 | F24: 44002 | G24: CREDIT CARD RECEIPTS | H24: 2157.22 | J24: 2157.22
A25: 2033531 | B25: 43310 | C25: 1 | D25: 102 | E25: 1003 | F25: 44002 | G25: CREDIT CARD RECEIPTS | I25: -2157.22 | J25: -2157.22
A26: 2033532 | B26: 11845 | C26: 1 | D26: 106 | E26: 1003 | F26: 44002 | G26: CONFERENCE - FOOD SERVICE | H26: 4503.3 | J26: 4503.3
A27: 2033532 | B27: 43310 | C27: 1 | D27: 106 | E27: 1003 | F27: 44002 | G27: CONFERENCE - FOOD SERVICE | I27: -4503.3 | J27: -4503.3
A28: 2033533 | B28: 11845 | C28: 2 | D28: 104 | E28: 1003 | F28: 44002 | G28: CREDIT CARD RECEIPTS | H28: 6197 | J28: 6197
A29: 2033533 | B29: 43180 | C29: 2 | D29: 104 | E29: 1003 | F29: 44002 | G29: CREDIT CARD RECEIPTS | I29: -6197 | J29: -6197
A30: 2033534 | B30: 71400 | C30: 2 | D30: 101 | E30: 1002 | F30: 44002 | G30: PARKING SERVICES OF AMERICA | H30: 26770 | J30: 26770
A31: 2033534 | B31: 11845 | C31: 2 | D31: 101 | E31: 1002 | F31: 44002 | G31: PARKING SERVICES OF AMERICA | I31: -26770 | J31: -26770
A32: 2033535 | B32: 11845 | C32: 3 | D32: 102 | E32: 1001 | F32: 44003 | G32: CASH RECEIPTS | H32: 38.29 | J32: 38.29
A33: 2033535 | B33: 43440 | C33: 3 | D33: 102 | E33: 1001 | F33: 44003 | G33: CASH RECEIPTS | I33: -38.29 | J33: -38.29
A34: 2033536 | B34: 11845 | C34: 3 | D34: 102 | E34: 1003 | F34: 44003 | G34: CREDIT CARD RECEIPTS | H34: 47.96 | J34: 47.96
A35: 2033536 | B35: 43440 | C35: 3 | D35: 102 | E35: 1003 | F35: 44003 | G35: CREDIT CARD RECEIPTS | I35: -47.96 | J35: -47.96
A36: 2033537 | B36: 14250 | C36: 3 | D36: 102 | E36: 1002 | F36: 44003 | G36: TROPICAL NUT & FRUIT | H36: 197.08 | J36: 197.08
A37: 2033537 | B37: 11845 | C37: 3 | D37: 102 | E37: 1002 | F37: 44003 | G37: TROPICAL NUT & FRUIT | I37: -197.08 | J37: -197.08
A38: 2033538 | B38: 72760 | C38: 6 | D38: 101 | E38: 1002 | F38: 44003 | G38: DYNAMIC SECU64605456 | H38: 236.32 | J38: 236.32
A39: 2033538 | B39: 11845 | C39: 6 | D39: 101 | E39: 1002 | F39: 44003 | G39: DYNAMIC SECU64605456 | I39: -236.32 | J39: -236.32
A40: 2033539 | B40: 72760 | C40: 6 | D40: 101 | E40: 1002 | F40: 44003 | G40: DYNAMIC SECU64605456 | H40: 236.32 | J40: 236.32
A41: 2033539 | B41: 11845 | C41: 6 | D41: 101 | E41: 1002 | F41: 44003 | G41: DYNAMIC SECU64605456 | I41: -236.32 | J41: -236.32
A42: 2033540 | B42: 14250 | C42: 3 | D42: 102 | E42: 1002 | F42: 44003 | G42: COCA-COLA ENTERPRIS | H42: 328.56 | J42: 328.56
A43: 2033540 | B43: 11845 | C43: 3 | D43: 102 | E43: 1002 | F43: 44003 | G43: COCA-COLA ENTERPRIS | I43: -328.56 | J43: -328.56
A44: 2033541 | B44: 11845 | C44: 1 | D44: 102 | E44: 1001 | F44: 44003 | G44: CASH RECEIPTS | H44: 603.45 | J44: 603.45
A45: 2033541 | B45: 43310 | C45: 1 | D45: 102 | E45: 1001 | F45: 44003 | G45: CASH RECEIPTS | I45: -603.45 | J45: -603.45
A46: 2033542 | B46: 11845 | C46: 1 | D46: 102 | E46: 1003 | F46: 44003 | G46: CREDIT CARD RECEIPTS | H46: 2422.96 | J46: 2422.96
A47: 2033542 | B47: 43310 | C47: 1 | D47: 102 | E47: 1003 | F47: 44003 | G47: CREDIT CARD RECEIPTS | I47: -2422.96 | J47: -2422.96
A48: 2033543 | B48: 11845 | C48: 2 | D48: 104 | E48: 1003 | F48: 44003 | G48: CREDIT CARD RECEIPTS | H48: 3400 | J48: 3400
A49: 2033543 | B49: 43180 | C49: 2 | D49: 104 | E49: 1003 | F49: 44003 | G49: CREDIT CARD RECEIPTS | I49: -3400 | J49: -3400
A50: 2033544 | B50: 16200 | C50: 2 | D50: 102 | E50: 1002 | F50: 44003 | G50: ATLAS ENVIRO | H50: 3000 | J50: 3000
A51: 2033544 | B51: 11845 | C51: 2 | D51: 102 | E51: 1002 | F51: 44003 | G51: ATLAS ENVIRO | I51: -3000 | J51: -3000
A52: 2033545 | B52: 71400 | C52: 1 | D52: 101 | E52: 1002 | F52: 44004 | G52: CENTRAL DUPLICATING | H52: 6.37 | J52: 6.37
A53: 2033545 | B53: 11845 | C53: 1 | D53: 101 | E53: 1002 | F53: 44004 | G53: CENTRAL DUPLICATING | I53: -6.37 | J53: -6.37
A54: 2033546 | B54: 11845 | C54: 1 | D54: 102 | E54: 1001 | F54: 44004 | G54: COPELAND,MELODY | H54: 7.66 | J54: 7.66
A55: 2033546 | B55: 43310 | C55: 1 | D55: 102 | E55: 1001 | F55: 44004 | G55: COPELAND,MELODY | I55: -7.66 | J55: -7.66
A56: 2033547 | B56: 11845 | C56: 3 | D56: 102 | E56: 1003 | F56: 44004 | G56: CREDIT CARD RECEIPTS | H56: 17.21 | J56: 17.21
A57: 2033547 | B57: 43440 | C57: 3 | D57: 102 | E57: 1003 | F57: 44004 | G57: CREDIT CARD RECEIPTS | I57: -17.21 | J57: -17.21
A58: 2033548 | B58: 11845 | C58: 1 | D58: 102 | E58: 1003 | F58: 44004 | G58: CREDIT CARD RECEIPTS | H58: 26.98 | J58: 26.98
A59: 2033548 | B59: 43310 | C59: 1 | D59: 102 | E59: 1003 | F59: 44004 | G59: CREDIT CARD RECEIPTS | I59: -26.98 | J59: -26.98
A60: 2033549 | B60: 71400 | C60: 2 | D60: 101 | E60: 1002 | F60: 44004 | G60: SA647 CARD JUN | H60: 40 | J60: 40
A61: 2033549 | B61: 11845 | C61: 2 | D61: 101 | E61: 1002 | F61: 44004 | G61: SA647 CARD JUN | I61: -40 | J61: -40
A62: 2033550 | B62: 71400 | C62: 1 | D62: 101 | E62: 1002 | F62: 44004 | G62: CENTRAL DUPLICATING | H62: 45 | J62: 45
A63: 2033550 | B63: 11845 | C63: 1 | D63: 101 | E63: 1002 | F63: 44004 | G63: CENTRAL DUPLICATING | I63: -45 | J63: -45
A64: 2033551 | B64: 11845 | C64: 3 | D64: 102 | E64: 1001 | F64: 44004 | G64: CASH RECEIPTS | H64: 49.51 | J64: 49.51
A65: 2033551 | B65: 43440 | C65: 3 | D65: 102 | E65: 1001 | F65: 44004 | G65: CASH RECEIPTS | I65: -49.51 | J65: -49.51
A66: 2033552 | B66: 72732 | C66: 1 | D66: 101 | E66: 1002 | F66: 44004 | G66: FEDEX | H66: 55 | J66: 55
A67: 2033552 | B67: 11845 | C67: 1 | D67: 101 | E67: 1002 | F67: 44004 | G67: FEDEX | I67: -55 | J67: -55
A68: 2033553 | B68: 11845 | C68: 3 | D68: 102 | E68: 1003 | F68: 44004 | G68: CREDIT CARD RECEIPTS | H68: 58.02 | J68: 58.02
A69: 2033553 | B69: 43440 | C69: 3 | D69: 102 | E69: 1003 | F69: 44004 | G69: CREDIT CARD RECEIPTS | I69: -58.02 | J69: -58.02
A70: 2033554 | B70: 11845 | C70: 1 | D70: 102 | E70: 1003 | F70: 44004 | G70: DINING JUN | H70: 80.24 | J70: 80.24
A71: 2033554 | B71: 43310 | C71: 1 | D71: 102 | E71: 1003 | F71: 44004 | G71: DINING JUN | I71: -80.24 | J71: -80.24
A72: 2033555 | B72: 11845 | C72: 1 | D72: 102 | E72: 1003 | F72: 44004 | G72: CREDIT CARD RECEIPTS | H72: 91 | J72: 91
A73: 2033555 | B73: 43310 | C73: 1 | D73: 102 | E73: 1003 | F73: 44004 | G73: CREDIT CARD RECEIPTS | I73: -91 | J73: -91
A74: 2033556 | B74: 71400 | C74: 1 | D74: 101 | E74: 1002 | F74: 44004 | G74: SA647 CARD JUN | H74: 100 | J74: 100
A75: 2033556 | B75: 11845 | C75: 1 | D75: 101 | E75: 1002 | F75: 44004 | G75: SA647 CARD JUN | I75: -100 | J75: -100
A76: 2033557 | B76: 72702 | C76: 2 | D76: 101 | E76: 1002 | F76: 44004 | G76: ONE PRICE DRY CLEANI | H76: 111.15 | J76: 111.15
A77: 2033557 | B77: 11845 | C77: 2 | D77: 101 | E77: 1002 | F77: 44004 | G77: ONE PRICE DRY CLEANI | I77: -111.15 | J77: -111.15
A78: 2033558 | B78: 11845 | C78: 1 | D78: 106 | E78: 1003 | F78: 44004 | G78: CONFERENCE - FOOD SERVICE | H78: 138.16 | J78: 138.16
A79: 2033558 | B79: 43310 | C79: 1 | D79: 106 | E79: 1003 | F79: 44004 | G79: CONFERENCE - FOOD SERVICE | I79: -138.16 | J79: -138.16
A80: 2033559 | B80: 71400 | C80: 1 | D80: 101 | E80: 1002 | F80: 44004 | G80: PURE WATER TECHNOLOG | H80: 159.9 | J80: 159.9
A81: 2033559 | B81: 11845 | C81: 1 | D81: 101 | E81: 1002 | F81: 44004 | G81: PURE WATER TECHNOLOG | I81: -159.9 | J81: -159.9
A82: 2033560 | B82: 71400 | C82: 1 | D82: 101 | E82: 1002 | F82: 44004 | G82: PURE WATER TECHNOLOG | H82: 159.9 | J82: 159.9
A83: 2033560 | B83: 11845 | C83: 1 | D83: 101 | E83: 1002 | F83: 44004 | G83: PURE WATER TECHNOLOG | I83: -159.9 | J83: -159.9
A84: 2033561 | B84: 71400 | C84: 1 | D84: 101 | E84: 1002 | F84: 44004 | G84: PURE WATER TECHNOLOG | H84: 159.9 | J84: 159.9
A85: 2033561 | B85: 11845 | C85: 1 | D85: 101 | E85: 1002 | F85: 44004 | G85: PURE WATER TECHNOLOG | I85: -159.9 | J85: -159.9
A86: 2033562 | B86: 71400 | C86: 1 | D86: 101 | E86: 1002 | F86: 44004 | G86: PURE WATER TECHNOLOG | H86: 159.9 | J86: 159.9
A87: 2033562 | B87: 11845 | C87: 1 | D87: 101 | E87: 1002 | F87: 44004 | G87: PURE WATER TECHNOLOG | I87: -159.9 | J87: -159.9
A88: 2033563 | B88: 71400 | C88: 1 | D88: 101 | E88: 1002 | F88: 44004 | G88: PURE WATER TECHNOLOG | H88: 159.9 | J88: 159.9
A89: 2033563 | B89: 11845 | C89: 1 | D89: 101 | E89: 1002 | F89: 44004 | G89: PURE WATER TECHNOLOG | I89: -159.9 | J89: -159.9
A90: 2033564 | B90: 11845 | C90: 2 | D90: 104 | E90: 1003 | F90: 44004 | G90: COPELAND,MELODY | H90: 198 | J90: 198
A91: 2033564 | B91: 43180 | C91: 2 | D91: 104 | E91: 1003 | F91: 44004 | G91: COPELAND,MELODY | I91: -198 | J91: -198
A92: 2033565 | B92: 14260 | C92: 1 | D92: 101 | E92: 1002 | F92: 44004 | G92: EMILY R ANDERSON P | H92: 223 | J92: 223
A93: 2033565 | B93: 11845 | C93: 1 | D93: 101 | E93: 1002 | F93: 44004 | G93: EMILY R ANDERSON P | I93: -223 | J93: -223
A94: 2033566 | B94: 11845 | C94: 1 | D94: 102 | E94: 1003 | F94: 44004 | G94: CREDIT CARD RECEIPTS | H94: 228.59 | J94: 228.59
A95: 2033566 | B95: 43310 | C95: 1 | D95: 102 | E95: 1003 | F95: 44004 | G95: CREDIT CARD RECEIPTS | I95: -228.59 | J95: -228.59
A96: 2033567 | B96: 71400 | C96: 2 | D96: 101 | E96: 1002 | F96: 44004 | G96: ZEP SALES & 68668209 | H96: 240.73 | J96: 240.73
A97: 2033567 | B97: 11845 | C97: 2 | D97: 101 | E97: 1002 | F97: 44004 | G97: ZEP SALES & 68668209 | I97: -240.73 | J97: -240.73
A98: 2033568 | B98: 11845 | C98: 2 | D98: 104 | E98: 1003 | F98: 44004 | G98: MCCONNELL,MARCOS | H98: 258 | J98: 258
A99: 2033568 | B99: 43180 | C99: 2 | D99: 104 | E99: 1003 | F99: 44004 | G99: MCCONNELL,MARCOS | I99: -258 | J99: -258
A100: 2033569 | B100: 11845 | C100: 2 | D100: 104 | E100: 1003 | F100: 44004 | G100: CAIN,HAVEN | H100: 258 | J100: 258
...

Sheet BusinessUnits
A1: BusinessUnitID | B1: BusinessUnit | C1: Description
A2: 1 | B2: FOOD SERVICE | C2: Transactions related to food and beverage service. Includes all guest transactions in the hotel restaurants, catering-related transactions and food service payroll.
A3: 2 | B3: HOTEL | C3: Transactions related to guest rooms and overall hotel operations. Includes payroll for administrative staff, clerks and interns.
A4: 3 | B4: HOTEL PANTRY | C4: Transactions related to the hotel convenience store, including some food and beverage costs.
A5: 4 | B5: HOUSEKEEPING | C5: Transactions related to the Housekeeping Department. Primarily includes payroll for housekeepers and housekeeping supplies.
A6: 5 | B6: INTEREST | C6: Interest from the cash operations account.
A7: 6 | B7: MAINTENANCE | C7: Transactions related to the hotel Maintenance Department. Primarily includes payroll for maintenance, grounds keepers and related supplies.
A8: 7 | B8: OPER - GENERAL | C8: Transactions related to corporate accounting functions, e.g., monthly depreciation entries.
A9: 8 | B9: PAYROLL S/B JV | C9: Transactions related to payroll for employees.

Sheet ChartOfAccounts
A1: GLAccountNumber | B1: GLAccountName | C1: GLAccountNumber | D1: AccountType | E1: GLAccountNumber | F1: AccountClass
A2: 11200 | B2: Petty Cash | C2: 11200 | D2: Assets | E2: 11200 | F2: Cash
A3: 11845 | B3: Operating Bank Account | C3: 11845 | D3: Assets | E3: 11845 | F3: Cash
A4: 12987 | B4: Food Service Conference Accounts Receivable | C4: 12987 | D4: Assets | E4: 12987 | F4: Accounts Receivable
A5: 13100 | B5: Prepaid Expenses | C5: 13100 | D5: Assets | E5: 13100 | F5: Prepaid Expenses
A6: 14250 | B6: Hotel Pantry Inventory | C6: 14250 | D6: Assets | E6: 14250 | F6: Inventory
A7: 14260 | B7: Food Service Inventory | C7: 14260 | D7: Assets | E7: 14260 | F7: Inventory
A8: 15100 | B8: Short-term Investments | C8: 15100 | D8: Assets | E8: 15100 | F8: Other ST Assets
A9: 16100 | B9: Land and Improvements | C9: 16100 | D9: Assets | E9: 16100 | F9: Plant, Property and Equipment
A10: 16200 | B10: Buildings & Building Improvements | C10: 16200 | D10: Assets | E10: 16200 | F10: Plant, Property and Equipment
A11: 16290 | B11: Accumulated Depreciation - Building & Improvements | C11: 16290 | D11: Assets | E11: 16290 | F11: Plant, Property and Equipment
A12: 16500 | B12: Equipment | C12: 16500 | D12: Assets | E12: 16500 | F12: Plant, Property and Equipment
A13: 16590 | B13: Accumulated Depreciation - Equipment | C13: 16590 | D13: Assets | E13: 16590 | F13: Plant, Property and Equipment
... A84: 86200 | B84: Depreciation Expense - Equipment | C84: 86200 | D84: Expenses | E84: 86200 | F84: Depreciation Expense
A85: 70300-FS | B85: Cost of Goods Sold | C85: 70300-FS | D85: Expenses | E85: 70300-FS | F85: COGS-Food
A86: 70300-HP | B86: Cost of Goods Sold | C86: 70300-HP | D86: Expenses | E86: 70300-HP | F86: COGS-Hotel Pantry

Sheet PreparerInfo
A1: PreparerID | B1: PreparerName | C1: BusinessUnitID
A2: 101 | B2: Carolyn Slater|Food Operations Manager | C2: 1
A3: 101 | B3: Alexander Knox|Assistant Manager | C3: 2
A4: 101 | B4: Gavin McGrath|Dining Commons Manager | C4: 3
A5: 101 | B5: Trevor Roberts|Housekeeping Supervisor | C5: 4
A6: 101 | B6: Rodney Wilkins|Maintenance Supervisor | C6: 6
A7: 102 | B7: Elizabeth Rees|Food Operations Manager | C7: 1
A8: 102 | B8: Brian Gibson|Assistant Manager | C8: 2
A9: 102 | B9: POS | C9: 3
A10: 103 | B10: David Brown|Accounting Manager | C10: 2
A11: 104 | B11: GUESTSYS | C11: 2
A12: 105 | B12: Victoria Simpson|Accounting Manager | C12: 2
A13: 106 | B13: Yvonne Chapman|Catering Manager | C13: 2

Sheet Source
A1: SourceID | B1: Source
A2: 1001 | B2: CASH RECEIPT
A3: 1002 | B3: CHECK
A4: 1003 | B4: CREDIT CARD RECEIPT
A5: 1004 | B5: PAYROLL JV
A6: 1005 | B6: PAYROLL MANUAL JV
A7: 1006 | B7: PAYROLL S/B JV
A8: 1007 | B8: PURCHASE CARD
A9: 1008 | B9: REGULAR JV

Sheet Case 4 solution
A1: JENumber | B1: GLAccountNumber | C1: BusinessUnitID | D1: PreparerID | E1: SourceID | F1: EffectiveDate | G1: JEDescription | H1: Debit | I1: Credit | J1: Amount | K1: BusinessUnit | L1: BUDescription | M1: GLAccountName | N1: AccountType | O1: AccountClass | P1: PreparerName | Q1: Source
A2: 2033520 | B2: 76930 | C2: 1 | D2: 101 | E2: 1002 | F2: 44002 | G2: TELECOM GTA JUN 2016 | H2: 36.9 | J2: 36.9 | K2: =IFERROR(INDEX(BusinessUnits!$B:$B,MATCH($C2,BusinessUnits!$A:$A,0)),"") -> FOOD SERVICE | L2: =IFERROR(INDEX(Table1[[#All],[Description]],MATCH($C2,BusinessUnits!$A:$A,0)),"") -> Transactions related to food and beverage service. Includes all guest transactions in the hotel restaurants, catering-related transactions and food service payroll. | M2: =IFERROR(INDEX(ChartOfAccounts!B1:B86,MATCH($B2,ChartOfAccounts!A1:A86,0)),"") -> Telecommunications - Other | N2: =IFERROR(INDEX(ChartOfAccounts!D:D,MATCH($B2,ChartOfAccounts!A1:A86,0)),"") -> Expenses | O2: =IFERROR(INDEX(ChartOfAccounts!F:F,MATCH($B2,ChartOfAccounts!A1:A86,0)),"") -> SG&A | P2: {=IFERROR(INDEX(PreparerInfo!B1:B13,MATCH($D2&$C2,PreparerInfo!A1:A13&PreparerInfo!C1:C13,0)),"")} -> Carolyn Slater|Food Operations Manager | Q2: =IFERROR(INDEX(Source!B1:B9,MATCH('Case 4 solution'!E2,Source!A1:A9,0)),"") -> CHECK
A3: 2033520 | B3: 11845 | C3: 1 | D3: 101 | E3: 1002 | F3: 44002 | G3: TELECOM GTA JUN 2016 | I3: -36.9 | J3: -36.9 | K3: =IFERROR(INDEX(BusinessUnits!$B:$B,MATCH($C3,BusinessUnits!$A:$A,0)),"") -> FOOD SERVICE | L3: =IFERROR(INDEX(Table1[[#All],[Description]],MATCH($C3,BusinessUnits!$A:$A,0)),"") -> Transactions related to food and beverage service. Includes all guest transactions in the hotel restaurants, catering-related transactions and food service payroll. | M3: =IFERROR(INDEX(ChartOfAccounts!B2:B87,MATCH($B3,ChartOfAccounts!A2:A87,0)),"") -> Operating Bank Account | N3: =IFERROR(INDEX(ChartOfAccounts!D:D,MATCH($B3,ChartOfAccounts!A2:A87,0)),"") -> Assets | O3: =IFERROR(INDEX(ChartOfAccounts!F:F,MATCH($B3,ChartOfAccounts!A2:A87,0)),"") -> Cash | P3: {=IFERROR(INDEX(PreparerInfo!B2:B14,MATCH($D3&$C3,PreparerInfo!A2:A14&PreparerInfo!C2:C14,0)),"")} -> Carolyn Slater|Food Operations Manager | Q3: =IFERROR(INDEX(Source!B2:B10,MATCH('Case 4 solution'!E3,Source!A2:A10,0)),"") -> CHECK
A4: 2033521 | B4: 11845 | C4: 3 | D4: 102 | E4: 1001 | F4: 44002 | G4: CASH RECEIPTS | H4: 63.1 | J4: 63.1 | K4: =IFERROR(INDEX(BusinessUnits!$B:$B,MATCH($C4,BusinessUnits!$A:$A,0)),"") -> HOTEL PANTRY | L4: =IFERROR(INDEX(Table1[[#All],[Description]],MATCH($C4,BusinessUnits!$A:$A,0)),"") -> Transactions related to the hotel convenience store, including some food and beverage costs. | M4: =IFERROR(INDEX(ChartOfAccounts!B3:B88,MATCH($B4,ChartOfAccounts!A3:A88,0)),"") -> Operating Bank Account | N4: =IFERROR(INDEX(ChartOfAccounts!D:D,MATCH($B4,ChartOfAccounts!A3:A88,0)),"") -> AccountType | O4: =IFERROR(INDEX(ChartOfAccounts!F:F,MATCH($B4,ChartOfAccounts!A3:A88,0)),"") -> AccountClass | P4: {=IFERROR(INDEX(PreparerInfo!B3:B15,MATCH($D4&$C4,PreparerInfo!A3:A15&PreparerInfo!C3:C15,0)),"")} -> POS | Q4: =IFERROR(INDEX(Source!B3:B11,MATCH('Case 4 solution'!E4,Source!A3:A11,0)),"")
A5: 2033521 | B5: 43440 | C5: 3 | D5: 102 | E5: 1001 | F5: 44002 | G5: CASH RECEIPTS | I5: -63.1 | J5: -63.1 | K5: =IFERROR(INDEX(BusinessUnits!$B:$B,MATCH($C5,BusinessUnits!$A:$A,0)),"") -> HOTEL PANTRY | L5: =IFERROR(INDEX(Table1[[#All],[Description]],MATCH($C5,BusinessUnits!$A:$A,0)),"") -> Transactions related to the hotel convenience store, including some food and beverage costs. | M5: =IFERROR(INDEX(ChartOfAccounts!B4:B89,MATCH($B5,ChartOfAccounts!A4:A89,0)),"") -> Sales - Other | N5: =IFERROR(INDEX(ChartOfAccounts!D:D,MATCH($B5,ChartOfAccounts!A4:A89,0)),"") -> Revenue | O5: =IFERROR(INDEX(ChartOfAccounts!F:F,MATCH($B5,ChartOfAccounts!A4:A89,0)),"") -> Other Income | P5: {=IFERROR(INDEX(PreparerInfo!B4:B16,MATCH($D5&$C5,PreparerInfo!A4:A16&PreparerInfo!C4:C16,0)),"")} -> POS | Q5: =IFERROR(INDEX(Source!B4:B12,MATCH('Case 4 solution'!E5,Source!A4:A12,0)),"")
A6: 2033522 | B6: 11845 | C6: 1 | D6: 102 | E6: 1003 | F6: 44002 | G6: CREDIT CARD RECEIPTS | H6: 68.28 | J6: 68.28 | K6: =IFERROR(INDEX(BusinessUnits!$B:$B,MATCH($C6,BusinessUnits!$A:$A,0)),"") -> FOOD SERVICE | L6: =IFERROR(INDEX(Table1[[#All],[Description]],MATCH($C6,BusinessUnits!$A:$A,0)),"") -> Transactions related to food and beverage service. Includes all guest transactions in the hotel restaurants, catering-related transactions and food service payroll. | M6: =IFERROR(INDEX(ChartOfAccounts!B5:B90,MATCH($B6,ChartOfAccounts!A5:A90,0)),"") | N6: =IFERROR(INDEX(ChartOfAccounts!D:D,MATCH($B6,ChartOfAccounts!A5:A90,0)),"") | O6: =IFERROR(INDEX(ChartOfAccounts!F:F,MATCH($B6,ChartOfAccounts!A5:A90,0)),"") | P6: {=IFERROR(INDEX(PreparerInfo!B5:B17,MATCH($D6&$C6,PreparerInfo!A5:A17&PreparerInfo!C5:C17,0)),"")} -> Elizabeth Rees|Food Operations Manager | Q6: =IFERROR(INDEX(Source!B5:B13,MATCH('Case 4 solution'!E6,Source!A5:A13,0)),"")
A7: 2033522 | B7: 43310 | C7: 1 | D7: 102 | E7: 1003 | F7: 44002 | G7: CREDIT CARD RECEIPTS | I7: -68.28 | J7: -68.28 | K7: =IFERROR(INDEX(BusinessUnits!$B:$B,MATCH($C7,BusinessUnits!$A:$A,0)),"") -> FOOD SERVICE | L7: =IFERROR(INDEX(Table1[[#All],[Description]],MATCH($C7,BusinessUnits!$A:$A,0)),"") -> Transactions related to food and beverage service. Includes all guest transactions in the hotel restaurants, catering-related transactions and food service payroll. | M7: =IFERROR(INDEX(ChartOfAccounts!B6:B91,MATCH($B7,ChartOfAccounts!A6:A91,0)),"") -> Sales - Dining Halls | N7: =IFERROR(INDEX(ChartOfAccounts!D:D,MATCH($B7,ChartOfAccounts!A6:A91,0)),"") -> Liabilities | O7: =IFERROR(INDEX(ChartOfAccounts!F:F,MATCH($B7,ChartOfAccounts!A6:A91,0)),"") -> Other LT Liabilities | P7: {=IFERROR(INDEX(PreparerInfo!B6:B18,MATCH($D7&$C7,PreparerInfo!A6:A18&PreparerInfo!C6:C18,0)),"")} -> Elizabeth Rees|Food Operations Manager | Q7: =IFERROR(INDEX(Source!B6:B14,MATCH('Case 4 solution'!E7,Source!A6:A14,0)),"")
A8: 2033523 | B8: 11845 | C8: 2 | D8: 106 | E8: 1003 | F8: 44002 | G8: CONFERENCE - HOTEL | H8: 99 | J8: 99 | K8: =IFERROR(INDEX(BusinessUnits!$B:$B,MATCH($C8,BusinessUnits!$A:$A,0)),"") -> HOTEL | L8: =IFERROR(INDEX(Table1[[#All],[Description]],MATCH($C8,BusinessUnits!$A:$A,0)),"") -> Transactions related to guest rooms and overall hotel operations. Includes payroll for administrative staff, clerks and interns. | M8: =IFERROR(INDEX(ChartOfAccounts!B7:B92,MATCH($B8,ChartOfAccounts!A7:A92,0)),"") | N8: =IFERROR(INDEX(ChartOfAccounts!D:D,MATCH($B8,ChartOfAccounts!A7:A92,0)),"") | O8: =IFERROR(INDEX(ChartOfAccounts!F:F,MATCH($B8,ChartOfAccounts!A7:A92,0)),"") | P8: {=IFERROR(INDEX(PreparerInfo!B7:B19,MATCH($D8&$C8,PreparerInfo!A7:A19&PreparerInfo!C7:C19,0)),"")} -> Yvonne Chapman|Catering Manager | Q8: =IFERROR(INDEX(Source!B7:B15,MATCH('Case 4 solution'!E8,Source!A7:A15,0)),"")
A9: 2033523 | B9: 43180 | C9: 2 | D9: 106 | E9: 1003 | F9: 44002 | G9: CONFERENCE - HOTEL | I9: -99 | J9: -99 | K9: =IFERROR(INDEX(BusinessUnits!$B:$B,MATCH($C9,BusinessUnits!$A:$A,0)),"") -> HOTEL | L9: =IFERROR(INDEX(Table1[[#All],[Description]],MATCH($C9,BusinessUnits!$A:$A,0)),"") -> Transactions related to guest rooms and overall hotel operations. Includes payroll for administrative staff, clerks and interns. | M9: =IFERROR(INDEX(ChartOfAccounts!B8:B93,MATCH($B9,ChartOfAccounts!A8:A93,0)),"") -> Rents - Hotels | N9: =IFERROR(INDEX(ChartOfAccounts!D:D,MATCH($B9,ChartOfAccounts!A8:A93,0)),"") -> Liabilities | O9: =IFERROR(INDEX(ChartOfAccounts!F:F,MATCH($B9,ChartOfAccounts!A8:A93,0)),"") -> Other ST Liabilities | P9: {=IFERROR(INDEX(PreparerInfo!B8:B20,MATCH($D9&$C9,PreparerInfo!A8:A20&PreparerInfo!C8:C20,0)),"")} -> Yvonne Chapman|Catering Manager | Q9: =IFERROR(INDEX(Source!B8:B16,MATCH('Case 4 solution'!E9,Source!A8:A16,0)),"")
A10: 2033524 | B10: 11845 | C10: 3 | D10: 102 | E10: 1003 | F10: 44002 | G10: CREDIT CARD RECEIPTS | H10: 107.21 | J10: 107.21 | K10: =IFERROR(INDEX(BusinessUnits!$B:$B,MATCH($C10,BusinessUnits!$A:$A,0)),"") -> HOTEL PANTRY | L10: =IFERROR(INDEX(Table1[[#All],[Description]],MATCH($C10,BusinessUnits!$A:$A,0)),"") -> Transactions related to the hotel convenience store, including some food and beverage costs. | M10: =IFERROR(INDEX(ChartOfAccounts!B9:B94,MATCH($B10,ChartOfAccounts!A9:A94,0)),"") | N10: =IFERROR(INDEX(ChartOfAccounts!D:D,MATCH($B10,ChartOfAccounts!A9:A94,0)),"") | O10: =IFERROR(INDEX(ChartOfAccounts!F:F,MATCH($B10,ChartOfAccounts!A9:A94,0)),"") | P10: {=IFERROR(INDEX(PreparerInfo!B9:B21,MATCH($D10&$C10,PreparerInfo!A9:A21&PreparerInfo!C9:C21,0)),"")} -> POS | Q10: =IFERROR(INDEX(Source!B9:B17,MATCH('Case 4 solution'!E10,Source!A9:A17,0)),"")
A11: 2033524 | B11: 43440 | C11: 3 | D11: 102 | E11: 1003 | F11: 44002 | G11: CREDIT CARD RECEIPTS | I11: -107.21 | J11: -107.21 | K11: =IFERROR(INDEX(BusinessUnits!$B:$B,MATCH($C11,BusinessUnits!$A:$A,0)),"") -> HOTEL PANTRY | L11: =IFERROR(INDEX(Table1[[#All],[Description]],MATCH($C11,BusinessUnits!$A:$A,0)),"") -> Transactions related to the hotel convenience store, including some food and beverage costs. | M11: =IFERROR(INDEX(ChartOfAccounts!B10:B95,MATCH($B11,ChartOfAccounts!A10:A95,0)),"") -> Sales - Other | N11: =IFERROR(INDEX(ChartOfAccounts!D:D,MATCH($B11,ChartOfAccounts!A10:A95,0)),"") -> Liabilities | O11: =IFERROR(INDEX(ChartOfAccounts!F:F,MATCH($B11,ChartOfAccounts!A10:A95,0)),"") -> Other ST Liabilities | P11: {=IFERROR(INDEX(PreparerInfo!B10:B22,MATCH($D11&$C11,PreparerInfo!A10:A22&PreparerInfo!C10:C22,0)),"")} | Q11: =IFERROR(INDEX(Source!B10:B18,MATCH('Case 4 solution'!E11,Source!A10:A18,0)),"")
A12: 2033525 | B12: 11845 | C12: 2 | D12: 104 | E12: 1003 | F12: 44002 | G12: HENDERSON,KENNY | H12: 129 | J12: 129 | K12: =IFERROR(INDEX(BusinessUnits!$B:$B,MATCH($C12,BusinessUnits!$A:$A,0)),"") -> HOTEL | L12: =IFERROR(INDEX(Table1[[#All],[Description]],MATCH($C12,BusinessUnits!$A:$A,0)),"") -> Transactions related to guest rooms and overall hotel operations. Includes payroll for administrative staff, clerks and interns. | M12: =IFERROR(INDEX(ChartOfAccounts!B11:B96,MATCH($B12,ChartOfAccounts!A11:A96,0)),"") | N12: =IFERROR(INDEX(ChartOfAccounts!D:D,MATCH($B12,ChartOfAccounts!A11:A96,0)),"") | O12: =IFERROR(INDEX(ChartOfAccounts!F:F,MATCH($B12,ChartOfAccounts!A11:A96,0)),"") | P12: {=IFERROR(INDEX(PreparerInfo!B11:B23,MATCH($D12&$C12,PreparerInfo!A11:A23&PreparerInfo!C11:C23,0)),"")} -> GUESTSYS | Q12: =IFERROR(INDEX(Source!B11:B19,MATCH('Case 4 solution'!E12,Source!A11:A19,0)),"")
A13: 2033525 | B13: 43180 | C13: 2 | D13: 104 | E13: 1003 | F13: 44002 | G13: HENDERSON,KENNY | I13: -129 | J13: -129 | K13: =IFERROR(INDEX(BusinessUnits!$B:$B,MATCH($C13,BusinessUnits!$A:$A,0)),"") -> HOTEL | L13: =IFERROR(INDEX(Table1[[#All],[Description]],MATCH($C13,BusinessUnits!$A:$A,0)),"") -> Transactions related to guest rooms and overall hotel operations. Includes payroll for administrative staff, clerks and interns. | M13: =IFERROR(INDEX(ChartOfAccounts!B12:B97,MATCH($B13,ChartOfAccounts!A12:A97,0)),"") -> Rents - Hotels | N13: =IFERROR(INDEX(ChartOfAccounts!D:D,MATCH($B13,ChartOfAccounts!A12:A97,0)),"") -> Assets | O13: =IFERROR(INDEX(ChartOfAccounts!F:F,MATCH($B13,ChartOfAccounts!A12:A97,0)),"") -> Plant, Property and Equipment | P13: {=IFERROR(INDEX(PreparerInfo!B12:B24,MATCH($D13&$C13,PreparerInfo!A12:A24&PreparerInfo!C12:C24,0)),"")} | Q13: =IFERROR(INDEX(Source!B12:B20,MATCH('Case 4 solution'!E13,Source!A12:A20,0)),"")
A14: 2033526 | B14: 11845 | C14: 2 | D14: 104 | E14: 1003 | F14: 44002 | G14: GENTRY,NIA | H14: 258 | J14: 258 | K14: =IFERROR(INDEX(BusinessUnits!$B:$B,MATCH($C14,BusinessUnits!$A:$A,0)),"") -> HOTEL | L14: =IFERROR(INDEX(Table1[[#All],[Description]],MATCH($C14,BusinessUnits!$A:$A,0)),"") -> Transactions related to guest rooms and overall hotel operations. Includes payroll for administrative staff, clerks and interns. | M14: =IFERROR(INDEX(ChartOfAccounts!B13:B98,MATCH($B14,ChartOfAccounts!A13:A98,0)),"") | N14: =IFERROR(INDEX(ChartOfAccounts!D:D,MATCH($B14,ChartOfAccounts!A13:A98,0)),"") | O14: =IFERROR(INDEX(ChartOfAccounts!F:F,MATCH($B14,ChartOfAccounts!A13:A98,0)),"") | P14: {=IFERROR(INDEX(PreparerInfo!B13:B25,MATCH($D14&$C14,PreparerInfo!A13:A25&PreparerInfo!C13:C25,0)),"")} | Q14: =IFERROR(INDEX(Source!B13:B21,MATCH('Case 4 solution'!E14,Source!A13:A21,0)),"")
A15: 2033526 | B15: 43180 | C15: 2 | D15: 104 | E15: 1003 | F15: 44002 | G15: GENTRY,NIA | I15: -258 | J15: -258 | K15: =IFERROR(INDEX(BusinessUnits!$B:$B,MATCH($C15,BusinessUnits!$A:$A,0)),"") -> HOTEL | L15: =IFERROR(INDEX(Table1[[#All],[Description]],MATCH($C15,BusinessUnits!$A:$A,0)),"") -> Transactions related to guest rooms and overall hotel operations. Includes payroll for administrative staff, clerks and interns. | M15: =IFERROR(INDEX(ChartOfAccounts!B14:B99,MATCH($B15,ChartOfAccounts!A14:A99,0)),"") -> Rents - Hotels | N15: =IFERROR(INDEX(ChartOfAccounts!D:D,MATCH($B15,ChartOfAccounts!A14:A99,0)),"") -> Assets | O15: =IFERROR(INDEX(ChartOfAccounts!F:F,MATCH($B15,ChartOfAccounts!A14:A99,0)),"") -> Plant, Property and Equipment | P15: {=IFERROR(INDEX(PreparerInfo!B14:B26,MATCH($D15&$C15,PreparerInfo!A14:A26&PreparerInfo!C14:C26,0)),"")} | Q15: =IFERROR(INDEX(Source!B14:B22,MATCH('Case 4 solution'!E15,Source!A14:A22,0)),"")
A16: 2033527 | B16: 11845 | C16: 2 | D16: 104 | E16: 1003 | F16: 44002 | G16: HODGES,CHAYA | H16: 418 | J16: 418 | K16: =IFERROR(INDEX(BusinessUnits!$B:$B,MATCH($C16,BusinessUnits!$A:$A,0)),"") -> HOTEL | L16: =IFERROR(INDEX(Table1[[#All],[Description]],MATCH($C16,BusinessUnits!$A:$A,0)),"") -> Transactions related to guest rooms and overall hotel operations. Includes payroll for administrative staff, clerks and interns. | M16: =IFERROR(INDEX(ChartOfAccounts!B15:B100,MATCH($B16,ChartOfAccounts!A15:A100,0)),"") | N16: =IFERROR(INDEX(ChartOfAccounts!D:D,MATCH($B16,ChartOfAccounts!A15:A100,0)),"") | O16: =IFERROR(INDEX(ChartOfAccounts!F:F,MATCH($B16,ChartOfAccounts!A15:A100,0)),"") | P16: {=IFERROR(INDEX(PreparerInfo!B15:B27,MATCH($D16&$C16,PreparerInfo!A15:A27&PreparerInfo!C15:C27,0)),"")} | Q16: =IFERROR(INDEX(Source!B15:B23,MATCH('Case 4 solution'!E16,Source!A15:A23,0)),"")
A17: 2033527 | B17: 43180 | C17: 2 | D17: 104 | E17: 1003 | F17: 44002 | G17: HODGES,CHAYA | I17: -418 | J17: -418 | K17: =IFERROR(INDEX(BusinessUnits!$B:$B,MATCH($C17,BusinessUnits!$A:$A,0)),"") -> HOTEL | L17: =IFERROR(INDEX(Table1[[#All],[Description]],MATCH($C17,BusinessUnits!$A:$A,0)),"") -> Transactions related to guest rooms and overall hotel operations. Includes payroll for administrative staff, clerks and interns. | M17: =IFERROR(INDEX(ChartOfAccounts!B16:B101,MATCH($B17,ChartOfAccounts!A16:A101,0)),"") -> Rents - Hotels | N17: =IFERROR(INDEX(ChartOfAccounts!D:D,MATCH($B17,ChartOfAccounts!A16:A101,0)),"") -> Assets | O17: =IFERROR(INDEX(ChartOfAccounts!F:F,MATCH($B17,ChartOfAccounts!A16:A101,0)),"") -> Inventory | P17: {=IFERROR(INDEX(PreparerInfo!B16:B28,MATCH($D17&$C17,PreparerInfo!A16:A28&PreparerInfo!C16:C28,0)),"")} | Q17: =IFERROR(INDEX(Source!B16:B24,MATCH('Case 4 solution'!E17,Source!A16:A24,0)),"")
A18: 2033528 | B18: 71900 | C18: 1 | D18: 102 | E18: 1002 | F18: 44002 | G18: ALSCO INC | H18: 431.8 | J18: 431.8 | K18: =IFERROR(INDEX(BusinessUnits!$B:$B,MATCH($C18,BusinessUnits!$A:$A,0)),"") -> FOOD SERVICE | L18: =IFERROR(INDEX(Table1[[#All],[Description]],MATCH($C18,BusinessUnits!$A:$A,0)),"") -> Transactions related to food and beverage service. Includes all guest transactions in the hotel restaurants, catering-related transactions and food service payroll. | M18: =IFERROR(INDEX(ChartOfAccounts!B17:B102,MATCH($B18,ChartOfAccounts!A17:A102,0)),"") -> Rents - Other Than Real Estate | N18: =IFERROR(INDEX(ChartOfAccounts!D:D,MATCH($B18,ChartOfAccounts!A17:A102,0)),"") -> Expenses | O18: =IFERROR(INDEX(ChartOfAccounts!F:F,MATCH($B18,ChartOfAccounts!A17:A102,0)),"") -> Payroll Taxes | P18: {=IFERROR(INDEX(PreparerInfo!B17:B29,MATCH($D18&$C18,PreparerInfo!A17:A29&PreparerInfo!C17:C29,0)),"")} | Q18: =IFERROR(INDEX(Source!B17:B25,MATCH('Case 4 solution'!E18,Source!A17:A25,0)),"")
A19: 2033528 | B19: 11845 | C19: 1 | D19: 102 | E19: 1002 | F19: 44002 | G19: ALSCO INC | I19: -431.8 | J19: -431.8 | K19: =IFERROR(INDEX(BusinessUnits!$B:$B,MATCH($C19,BusinessUnits!$A:$A,0)),"") -> FOOD SERVICE | L19: =IFERROR(INDEX(Table1[[#All],[Description]],MATCH($C19,BusinessUnits!$A:$A,0)),"") -> Transactions related to food and beverage service. Includes all guest transactions in the hotel restaurants, catering-related transactions and food service payroll. | M19: =IFERROR(INDEX(ChartOfAccounts!B18:B103,MATCH($B19,ChartOfAccounts!A18:A103,0)),"") | N19: =IFERROR(INDEX(ChartOfAccounts!D:D,MATCH($B19,ChartOfAccounts!A18:A103,0)),"") | O19: =IFERROR(INDEX(ChartOfAccounts!F:F,MATCH($B19,ChartOfAccounts!A18:A103,0)),"") | P19: {=IFERROR(INDEX(PreparerInfo!B18:B30,MATCH($D19&$C19,PreparerInfo!A18:A30&PreparerInfo!C18:C30,0)),"")} | Q19: =IFERROR(INDEX(Source!B18:B26,MATCH('Case 4 solution'!E19,Source!A18:A26,0)),"")
A20: 2033529 | B20: 11845 | C20: 1 | D20: 102 | E20: 1001 | F20: 44002 | G20: CASH RECEIPTS | H20: 612.54 | J20: 612.54 | K20: =IFERROR(INDEX(BusinessUnits!$B:$B,MATCH($C20,BusinessUnits!$A:$A,0)),"") -> FOOD SERVICE | L20: =IFERROR(INDEX(Table1[[#All],[Description]],MATCH($C20,BusinessUnits!$A:$A,0)),"") -> Transactions related to food and beverage service. Includes all guest transactions in the hotel restaurants, catering-related transactions and food service payroll. | M20: =IFERROR(INDEX(ChartOfAccounts!B19:B104,MATCH($B20,ChartOfAccounts!A19:A104,0)),"") | N20: =IFERROR(INDEX(ChartOfAccounts!D:D,MATCH($B20,ChartOfAccounts!A19:A104,0)),"") | O20: =IFERROR(INDEX(ChartOfAccounts!F:F,MATCH($B20,ChartOfAccounts!A19:A104,0)),"") | P20: {=IFERROR(INDEX(PreparerInfo!B19:B31,MATCH($D20&$C20,PreparerInfo!A19:A31&PreparerInfo!C19:C31,0)),"")} | Q20: =IFERROR(INDEX(Source!B19:B27,MATCH('Case 4 solution'!E20,Source!A19:A27,0)),"")
A21: 2033529 | B21: 43310 | C21: 1 | D21: 102 | E21: 1001 | F21: 44002 | G21: CASH RECEIPTS | I21: -612.54 | J21: -612.54 | K21: =IFERROR(INDEX(BusinessUnits!$B:$B,MATCH($C21,BusinessUnits!$A:$A,0)),"") -> FOOD SERVICE | L21: =IFERROR(INDEX(Table1[[#All],[Description]],MATCH($C21,BusinessUnits!$A:$A,0)),"") -> Transactions related to food and beverage service. Includes all guest transactions in the hotel restaurants, catering-related transactions and food service payroll. | M21: =IFERROR(INDEX(ChartOfAccounts!B20:B105,MATCH($B21,ChartOfAccounts!A20:A105,0)),"") -> Sales - Dining Halls | N21: =IFERROR(INDEX(ChartOfAccounts!D:D,MATCH($B21,ChartOfAccounts!A20:A105,0)),"") -> Assets | O21: =IFERROR(INDEX(ChartOfAccounts!F:F,MATCH($B21,ChartOfAccounts!A20:A105,0)),"") -> Accounts Receivable | P21: {=IFERROR(INDEX(PreparerInfo!B20:B32,MATCH($D21&$C21,PreparerInfo!A20:A32&PreparerInfo!C20:C32,0)),"")} | Q21: =IFERROR(INDEX(Source!B20:B28,MATCH('Case 4 solution'!E21,Source!A20:A28,0)),"")
A22: 2033530 | B22: 76930 | C22: 2 | D22: 101 | E22: 1002 | F22: 44002 | G22: TELECOM GTA JUN 2016 | H22: 1015.21 | J22: 1015.21 | K22: =IFERROR(INDEX(BusinessUnits!$B:$B,MATCH($C22,BusinessUnits!$A:$A,0)),"") -> HOTEL | L22: =IFERROR(INDEX(Table1[[#All],[Description]],MATCH($C22,BusinessUnits!$A:$A,0)),"") -> Transactions related to guest rooms and overall hotel operations. Includes payroll for administrative staff, clerks and interns. | M22: =IFERROR(INDEX(ChartOfAccounts!B21:B106,MATCH($B22,ChartOfAccounts!A21:A106,0)),"") -> Telecommunications - Other | N22: =IFERROR(INDEX(ChartOfAccounts!D:D,MATCH($B22,ChartOfAccounts!A21:A106,0)),"") -> Expenses | O22: =IFERROR(INDEX(ChartOfAccounts!F:F,MATCH($B22,ChartOfAccounts!A21:A106,0)),"") -> SG&A | P22: {=IFERROR(INDEX(PreparerInfo!B21:B33,MATCH($D22&$C22,PreparerInfo!A21:A33&PreparerInfo!C21:C33,0)),"")} | Q22: =IFERROR(INDEX(Source!B21:B29,MATCH('Case 4 solution'!E22,Source!A21:A29,0)),"")
A23: 2033530 | B23: 11845 | C23: 2 | D23: 101 | E23: 1002 | F23: 44002 | G23: TELECOM GTA JUN 2016 | I23: -1015.21 | J23: -1015.21 | K23: =IFERROR(INDEX(BusinessUnits!$B:$B,MATCH($C23,BusinessUnits!$A:$A,0)),"") -> HOTEL | L23: =IFERROR(INDEX(Table1[[#All],[Description]],MATCH($C23,BusinessUnits!$A:$A,0)),"") -> Transactions related to guest rooms and overall hotel operations. Includes payroll for administrative staff, clerks and interns. | M23: =IFERROR(INDEX(ChartOfAccounts!B22:B107,MATCH($B23,ChartOfAccounts!A22:A107,0)),"") | N23: =IFERROR(INDEX(ChartOfAccounts!D:D,MATCH($B23,ChartOfAccounts!A22:A107,0)),"") | O23: =IFERROR(INDEX(ChartOfAccounts!F:F,MATCH($B23,ChartOfAccounts!A22:A107,0)),"") | P23: {=IFERROR(INDEX(PreparerInfo!B22:B34,MATCH($D23&$C23,PreparerInfo!A22:A34&PreparerInfo!C22:C34,0)),"")} | Q23: =IFERROR(INDEX(Source!B22:B30,MATCH('Case 4 solution'!E23,Source!A22:A30,0)),"")
A24: 2033531 | B24: 11845 | C24: 1 | D24: 102 | E24: 1003 | F24: 44002 | G24: CREDIT CARD RECEIPTS | H24: 2157.22 | J24: 2157.22 | K24: =IFERROR(INDEX(BusinessUnits!$B:$B,MATCH($C24,BusinessUnits!$A:$A,0)),"") -> FOOD SERVICE | L24: =IFERROR(INDEX(Table1[[#All],[Description]],MATCH($C24,BusinessUnits!$A:$A,0)),"") -> Transactions related to food and beverage service. Includes all guest transactions in the hotel restaurants, catering-related transactions and food service payroll. | M24: =IFERROR(INDEX(ChartOfAccounts!B23:B108,MATCH($B24,ChartOfAccounts!A23:A108,0)),"") | N24: =IFERROR(INDEX(ChartOfAccounts!D:D,MATCH($B24,ChartOfAccounts!A23:A108,0)),"") | O24: =IFERROR(INDEX(ChartOfAccounts!F:F,MATCH($B24,ChartOfAccounts!A23:A108,0)),"") | P24: {=IFERROR(INDEX(PreparerInfo!B23:B35,MATCH($D24&$C24,PreparerInfo!A23:A35&PreparerInfo!C23:C35,0)),"")} | Q24: =IFERROR(INDEX(Source!B23:B31,MATCH('Case 4 solution'!E24,Source!A23:A31,0)),"")
A25: 2033531 | B25: 43310 | C25: 1 | D25: 102 | E25: 1003 | F25: 44002 | G25: CREDIT CARD RECEIPTS | I25: -2157.22 | J25: -2157.22 | K25: =IFERROR(INDEX(BusinessUnits!$B:$B,MATCH($C25,BusinessUnits!$A:$A,0)),"") -> FOOD SERVICE | L25: =IFERROR(INDEX(Table1[[#All],[Description]],MATCH($C25,BusinessUnits!$A:$A,0)),"") -> Transactions related to food and beverage service. Includes all guest transactions in the hotel restaurants, catering-related transactions and food service payroll. | M25: =IFERROR(INDEX(ChartOfAccounts!B24:B109,MATCH($B25,ChartOfAccounts!A24:A109,0)),"") | N25: =IFERROR(INDEX(ChartOfAccounts!D:D,MATCH($B25,ChartOfAccounts!A24:A109,0)),"") | O25: =IFERROR(INDEX(ChartOfAccounts!F:F,MATCH($B25,ChartOfAccounts!A24:A109,0)),"") | P25: {=IFERROR(INDEX(PreparerInfo!B24:B36,MATCH($D25&$C25,PreparerInfo!A24:A36&PreparerInfo!C24:C36,0)),"")} | Q25: =IFERROR(INDEX(Source!B24:B32,MATCH('Case 4 solution'!E25,Source!A24:A32,0)),"")
A26: 2033532 | B26: 11845 | C26: 1 | D26: 106 | E26: 1003 | F26: 44002 | G26: CONFERENCE - FOOD SERVICE | H26: 4503.3 | J26: 4503.3 | K26: =IFERROR(INDEX(BusinessUnits!$B:$B,MATCH($C26,BusinessUnits!$A:$A,0)),"") -> FOOD SERVICE | L26: =IFERROR(INDEX(Table1[[#All],[Description]],MATCH($C26,BusinessUnits!$A:$A,0)),"") -> Transactions related to food and beverage service. Includes all guest transactions in the hotel restaurants, catering-related transactions and food service payroll. | M26: =IFERROR(INDEX(ChartOfAccounts!B25:B110,MATCH($B26,ChartOfAccounts!A25:A110,0)),"") | N26: =IFERROR(INDEX(ChartOfAccounts!D:D,MATCH($B26,ChartOfAccounts!A25:A110,0)),"") | O26: =IFERROR(INDEX(ChartOfAccounts!F:F,MATCH($B26,ChartOfAccounts!A25:A110,0)),"") | P26: {=IFERROR(INDEX(PreparerInfo!B25:B37,MATCH($D26&$C26,PreparerInfo!A25:A37&PreparerInfo!C25:C37,0)),"")} | Q26: =IFERROR(INDEX(Source!B25:B33,MATCH('Case 4 solution'!E26,Source!A25:A33,0)),"")
A27: 2033532 | B27: 43310 | C27: 1 | D27: 106 | E27: 1003 | F27: 44002 | G27: CONFERENCE - FOOD SERVICE | I27: -4503.3 | J27: -4503.3 | K27: =IFERROR(INDEX(BusinessUnits!$B:$B,MATCH($C27,BusinessUnits!$A:$A,0)),"") -> FOOD SERVICE | L27: =IFERROR(INDEX(Table1[[#All],[Description]],MATCH($C27,BusinessUnits!$A:$A,0)),"") -> Transactions related to food and beverage service. Includes all guest transactions in the hotel restaurants, catering-related transactions and food service payroll. | M27: =IFERROR(INDEX(ChartOfAccounts!B26:B111,MATCH($B27,ChartOfAccounts!A26:A111,0)),"") | N27: =IFERROR(INDEX(ChartOfAccounts!D:D,MATCH($B27,ChartOfAccounts!A26:A111,0)),"") | O27: =IFERROR(INDEX(ChartOfAccounts!F:F,MATCH($B27,ChartOfAccounts!A26:A111,0)),"") | P27: {=IFERROR(INDEX(PreparerInfo!B26:B38,MATCH($D27&$C27,PreparerInfo!A26:A38&PreparerInfo!C26:C38,0)),"")} | Q27: =IFERROR(INDEX(Source!B26:B34,MATCH('Case 4 solution'!E27,Source!A26:A34,0)),"")
A28: 2033533 | B28: 11845 | C28: 2 | D28: 104 | E28: 1003 | F28: 44002 | G28: CREDIT CARD RECEIPTS | H28: 6197 | J28: 6197 | K28: =IFERROR(INDEX(BusinessUnits!$B:$B,MATCH($C28,BusinessUnits!$A:$A,0)),"") -> HOTEL | L28: =IFERROR(INDEX(Table1[[#All],[Description]],MATCH($C28,BusinessUnits!$A:$A,0)),"") -> Transactions related to guest rooms and overall hotel operations. Includes payroll for administrative staff, clerks and interns. | M28: =IFERROR(INDEX(ChartOfAccounts!B27:B112,MATCH($B28,ChartOfAccounts!A27:A112,0)),"") | N28: =IFERROR(INDEX(ChartOfAccounts!D:D,MATCH($B28,ChartOfAccounts!A27:A112,0)),"") | O28: =IFERROR(INDEX(ChartOfAccounts!F:F,MATCH($B28,ChartOfAccounts!A27:A112,0)),"") | P28: {=IFERROR(INDEX(PreparerInfo!B27:B39,MATCH($D28&$C28,PreparerInfo!A27:A39&PreparerInfo!C27:C39,0)),"")} | Q28: =IFERROR(INDEX(Source!B27:B35,MATCH('Case 4 solution'!E28,Source!A27:A35,0)),"")
A29: 2033533 | B29: 43180 | C29: 2 | D29: 104 | E29: 1003 | F29: 44002 | G29: CREDIT CARD RECEIPTS | I29: -6197 | J29: -6197 | K29: =IFERROR(INDEX(BusinessUnits!$B:$B,MATCH($C29,BusinessUnits!$A:$A,0)),"") -> HOTEL | L29: =IFERROR(INDEX(Table1[[#All],[Description]],MATCH($C29,BusinessUnits!$A:$A,0)),"") -> Transactions related to guest rooms and overall hotel operations. Includes payroll for administrative staff, clerks and interns. | M29: =IFERROR(INDEX(ChartOfAccounts!B28:B113,MATCH($B29,ChartOfAccounts!A28:A113,0)),"") | N29: =IFERROR(INDEX(ChartOfAccounts!D:D,MATCH($B29,ChartOfAccounts!A28:A113,0)),"") | O29: =IFERROR(INDEX(ChartOfAccounts!F:F,MATCH($B29,ChartOfAccounts!A28:A113,0)),"") | P29: {=IFERROR(INDEX(PreparerInfo!B28:B40,MATCH($D29&$C29,PreparerInfo!A28:A40&PreparerInfo!C28:C40,0)),"")} | Q29: =IFERROR(INDEX(Source!B28:B36,MATCH('Case 4 solution'!E29,Source!A28:A36,0)),"")
A30: 2033534 | B30: 71400 | C30: 2 | D30: 101 | E30: 1002 | F30: 44002 | G30: PARKING SERVICES OF AMERICA | H30: 26770 | J30: 26770 | K30: =IFERROR(INDEX(BusinessUnits!$B:$B,MATCH($C30,BusinessUnits!$A:$A,0)),"") -> HOTEL | L30: =IFERROR(INDEX(Table1[[#All],[Description]],MATCH($C30,BusinessUnits!$A:$A,0)),"") -> Transactions related to guest rooms and overall hotel operations. Includes payroll for administrative staff, clerks and interns. | M30: =IFERROR(INDEX(ChartOfAccounts!B29:B114,MATCH($B30,ChartOfAccounts!A29:A114,0)),"") -> Supplies and Materials | N30: =IFERROR(INDEX(ChartOfAccounts!D:D,MATCH($B30,ChartOfAccounts!A29:A114,0)),"") -> Liabilities | O30: =IFERROR(INDEX(ChartOfAccounts!F:F,MATCH($B30,ChartOfAccounts!A29:A114,0)),"") -> Accrued Payroll | P30: {=IFERROR(INDEX(PreparerInfo!B29:B41,MATCH($D30&$C30,PreparerInfo!A29:A41&PreparerInfo!C29:C41,0)),"")} | Q30: =IFERROR(INDEX(Source!B29:B37,MATCH('Case 4 solution'!E30,Source!A29:A37,0)),"")
A31: 2033534 | B31: 11845 | C31: 2 | D31: 101 | E31: 1002 | F31: 44002 | G31: PARKING SERVICES OF AMERICA | I31: -26770 | J31: -26770 | K31: =IFERROR(INDEX(BusinessUnits!$B:$B,MATCH($C31,BusinessUnits!$A:$A,0)),"") -> HOTEL | L31: =IFERROR(INDEX(Table1[[#All],[Description]],MATCH($C31,BusinessUnits!$A:$A,0)),"") -> Transactions related to guest rooms and overall hotel operations. Includes payroll for administrative staff, clerks and interns. | M31: =IFERROR(INDEX(ChartOfAccounts!B30:B115,MATCH($B31,ChartOfAccounts!A30:A115,0)),"") | N31: =IFERROR(INDEX(ChartOfAccounts!D:D,MATCH($B31,ChartOfAccounts!A30:A115,0)),"") | O31: =IFERROR(INDEX(ChartOfAccounts!F:F,MATCH($B31,ChartOfAccounts!A30:A115,0)),"") | P31: {=IFERROR(INDEX(PreparerInfo!B30:B42,MATCH($D31&$C31,PreparerInfo!A30:A42&PreparerInfo!C30:C42,0)),"")} | Q31: =IFERROR(INDEX(Source!B30:B38,MATCH('Case 4 solution'!E31,Source!A30:A38,0)),"")
A32: 2033535 | B32: 11845 | C32: 3 | D32: 102 | E32: 1001 | F32: 44003 | G32: CASH RECEIPTS | H32: 38.29 | J32: 38.29 | K32: =IFERROR(INDEX(BusinessUnits!$B:$B,MATCH($C32,BusinessUnits!$A:$A,0)),"") -> HOTEL PANTRY | L32: =IFERROR(INDEX(Table1[[#All],[Description]],MATCH($C32,BusinessUnits!$A:$A,0)),"") -> Transactions related to the hotel convenience store, including some food and beverage costs. | M32: =IFERROR(INDEX(ChartOfAccounts!B31:B116,MATCH($B32,ChartOfAccounts!A31:A116,0)),"") | N32: =IFERROR(INDEX(ChartOfAccounts!D:D,MATCH($B32,ChartOfAccounts!A31:A116,0)),"") | O32: =IFERROR(INDEX(ChartOfAccounts!F:F,MATCH($B32,ChartOfAccounts!A31:A116,0)),"") | P32: {=IFERROR(INDEX(PreparerInfo!B31:B43,MATCH($D32&$C32,PreparerInfo!A31:A43&PreparerInfo!C31:C43,0)),"")} | Q32: =IFERROR(INDEX(Source!B31:B39,MATCH('Case 4 solution'!E32,Source!A31:A39,0)),"")
A33: 2033535 | B33: 43440 | C33: 3 | D33: 102 | E33: 1001 | F33: 44003 | G33: CASH RECEIPTS | I33: -38.29 | J33: -38.29 | K33: =IFERROR(INDEX(BusinessUnits!$B:$B,MATCH($C33,BusinessUnits!$A:$A,0)),"") -> HOTEL PANTRY | L33: =IFERROR(INDEX(Table1[[#All],[Description]],MATCH($C33,BusinessUnits!$A:$A,0)),"") -> Transactions related to the hotel convenience store, including some food and beverage costs. | M33: =IFERROR(INDEX(ChartOfAccounts!B32:B117,MATCH($B33,ChartOfAccounts!A32:A117,0)),"") | N33: =IFERROR(INDEX(ChartOfAccounts!D:D,MATCH($B33,ChartOfAccounts!A32:A117,0)),"") | O33: =IFERROR(INDEX(ChartOfAccounts!F:F,MATCH($B33,ChartOfAccounts!A32:A117,0)),"") | P33: {=IFERROR(INDEX(PreparerInfo!B32:B44,MATCH($D33&$C33,PreparerInfo!A32:A44&PreparerInfo!C32:C44,0)),"")} | Q33: =IFERROR(INDEX(Source!B32:B40,MATCH('Case 4 solution'!E33,Source!A32:A40,0)),"")
A34: 2033536 | B34: 11845 | C34: 3 | D34: 102 | E34: 1003 | F34: 44003 | G34: CREDIT CARD RECEIPTS | H34: 47.96 | J34: 47.96 | K34: =IFERROR(INDEX(BusinessUnits!$B:$B,MATCH($C34,BusinessUnits!$A:$A,0)),"") -> HOTEL PANTRY | L34: =IFERROR(INDEX(Table1[[#All],[Description]],MATCH($C34,BusinessUnits!$A:$A,0)),"") -> Transactions related to the hotel convenience store, including some food and beverage costs. | M34: =IFERROR(INDEX(ChartOfAccounts!B33:B118,MATCH($B34,ChartOfAccounts!A33:A118,0)),"") | N34: =IFERROR(INDEX(ChartOfAccounts!D:D,MATCH($B34,ChartOfAccounts!A33:A118,0)),"") | O34: =IFERROR(INDEX(ChartOfAccounts!F:F,MATCH($B34,ChartOfAccounts!A33:A118,0)),"") | P34: {=IFERROR(INDEX(PreparerInfo!B33:B45,MATCH($D34&$C34,PreparerInfo!A33:A45&PreparerInfo!C33:C45,0)),"")} | Q34: =IFERROR(INDEX(Source!B33:B41,MATCH('Case 4 solution'!E34,Source!A33:A41,0)),"")
A35: 2033536 | B35: 43440 | C35: 3 | D35: 102 | E35: 1003 | F35: 44003 | G35: CREDIT CARD RECEIPTS | I35: -47.96 | J35: -47.96 | K35: =IFERROR(INDEX(BusinessUnits!$B:$B,MATCH($C35,BusinessUnits!$A:$A,0)),"") -> HOTEL PANTRY | L35: =IFERROR(INDEX(Table1[[#All],[Description]],MATCH($C35,BusinessUnits!$A:$A,0)),"") -> Transactions related to the hotel convenience store, including some food and beverage costs. | M35: =IFERROR(INDEX(ChartOfAccounts!B34:B119,MATCH($B35,ChartOfAccounts!A34:A119,0)),"") | N35: =IFERROR(INDEX(ChartOfAccounts!D:D,MATCH($B35,ChartOfAccounts!A34:A119,0)),"") | O35: =IFERROR(INDEX(ChartOfAccounts!F:F,MATCH($B35,ChartOfAccounts!A34:A119,0)),"") | P35: {=IFERROR(INDEX(PreparerInfo!B34:B46,MATCH($D35&$C35,PreparerInfo!A34:A46&PreparerInfo!C34:C46,0)),"")} | Q35: =IFERROR(INDEX(Source!B34:B42,MATCH('Case 4 solution'!E35,Source!A34:A42,0)),"")
A36: 2033537 | B36: 14250 | C36: 3 | D36: 102 | E36: 1002 | F36: 44003 | G36: TROPICAL NUT & FRUIT | H36: 197.08 | J36: 197.08 | K36: =IFERROR(INDEX(BusinessUnits!$B:$B,MATCH($C36,BusinessUnits!$A:$A,0)),"") -> HOTEL PANTRY | L36: =IFERROR(INDEX(Table1[[#All],[Description]],MATCH($C36,BusinessUnits!$A:$A,0)),"") -> Transactions related to the hotel convenience store, including some food and beverage costs. | M36: =IFERROR(INDEX(ChartOfAccounts!B35:B120,MATCH($B36,ChartOfAccounts!A35:A120,0)),"") | N36: =IFERROR(INDEX(ChartOfAccounts!D:D,MATCH($B36,ChartOfAccounts!A35:A120,0)),"") | O36: =IFERROR(INDEX(ChartOfAccounts!F:F,MATCH($B36,ChartOfAccounts!A35:A120,0)),"") | P36: {=IFERROR(INDEX(PreparerInfo!B35:B47,MATCH($D36&$C36,PreparerInfo!A35:A47&PreparerInfo!C35:C47,0)),"")} | Q36: =IFERROR(INDEX(Source!B35:B43,MATCH('Case 4 solution'!E36,Source!A35:A43,0)),"")
A37: 2033537 | B37: 11845 | C37: 3 | D37: 102 | E37: 1002 | F37: 44003 | G37: TROPICAL NUT & FRUIT | I37: -197.08 | J37: -197.08 | K37: =IFERROR(INDEX(BusinessUnits!$B:$B,MATCH($C37,BusinessUnits!$A:$A,0)),"") -> HOTEL PANTRY | L37: =IFERROR(INDEX(Table1[[#All],[Description]],MATCH($C37,BusinessUnits!$A:$A,0)),"") -> Transactions related to the hotel convenience store, including some food and beverage costs. | M37: =IFERROR(INDEX(ChartOfAccounts!B36:B121,MATCH($B37,ChartOfAccounts!A36:A121,0)),"") | N37: =IFERROR(INDEX(ChartOfAccounts!D:D,MATCH($B37,ChartOfAccounts!A36:A121,0)),"") | O37: =IFERROR(INDEX(ChartOfAccounts!F:F,MATCH($B37,ChartOfAccounts!A36:A121,0)),"") | P37: {=IFERROR(INDEX(PreparerInfo!B36:B48,MATCH($D37&$C37,PreparerInfo!A36:A48&PreparerInfo!C36:C48,0)),"")} | Q37: =IFERROR(INDEX(Source!B36:B44,MATCH('Case 4 solution'!E37,Source!A36:A44,0)),"")
A38: 2033538 | B38: 72760 | C38: 6 | D38: 101 | E38: 1002 | F38: 44003 | G38: DYNAMIC SECU64605456 | H38: 236.32 | J38: 236.32 | K38: =IFERROR(INDEX(BusinessUnits!$B:$B,MATCH($C38,BusinessUnits!$A:$A,0)),"") -> MAINTENANCE | L38: =IFERROR(INDEX(Table1[[#All],[Description]],MATCH($C38,BusinessUnits!$A:$A,0)),"") -> Transactions related to the hotel Maintenance Department. Primarily includes payroll for maintenance, grounds keepers and related supplies. | M38: =IFERROR(INDEX(ChartOfAccounts!B37:B122,MATCH($B38,ChartOfAccounts!A37:A122,0)),"") -> Other Services | N38: =IFERROR(INDEX(ChartOfAccounts!D:D,MATCH($B38,ChartOfAccounts!A37:A122,0)),"") -> Revenue | O38: =IFERROR(INDEX(ChartOfAccounts!F:F,MATCH($B38,ChartOfAccounts!A37:A122,0)),"") -> Sales-Other | P38: {=IFERROR(INDEX(PreparerInfo!B37:B49,MATCH($D38&$C38,PreparerInfo!A37:A49&PreparerInfo!C37:C49,0)),"")} | Q38: =IFERROR(INDEX(Source!B37:B45,MATCH('Case 4 solution'!E38,Source!A37:A45,0)),"")
A39: 2033538 | B39: 11845 | C39: 6 | D39: 101 | E39: 1002 | F39: 44003 | G39: DYNAMIC SECU64605456 | I39: -236.32 | J39: -236.32 | K39: =IFERROR(INDEX(BusinessUnits!$B:$B,MATCH($C39,BusinessUnits!$A:$A,0)),"") -> MAINTENANCE | L39: =IFERROR(INDEX(Table1[[#All],[Description]],MATCH($C39,BusinessUnits!$A:$A,0)),"") -> Transactions related to the hotel Maintenance Department. Primarily includes payroll for maintenance, grounds keepers and related supplies. | M39: =IFERROR(INDEX(ChartOfAccounts!B38:B123,MATCH($B39,ChartOfAccounts!A38:A123,0)),"") | N39: =IFERROR(INDEX(ChartOfAccounts!D:D,MATCH($B39,ChartOfAccounts!A38:A123,0)),"") | O39: =IFERROR(INDEX(ChartOfAccounts!F:F,MATCH($B39,ChartOfAccounts!A38:A123,0)),"") | P39: {=IFERROR(INDEX(PreparerInfo!B38:B50,MATCH($D39&$C39,PreparerInfo!A38:A50&PreparerInfo!C38:C50,0)),"")} | Q39: =IFERROR(INDEX(Source!B38:B46,MATCH('Case 4 solution'!E39,Source!A38:A46,0)),"")
A40: 2033539 | B40: 72760 | C40: 6 | D40: 101 | E40: 1002 | F40: 44003 | G40: DYNAMIC SECU64605456 | H40: 236.32 | J40: 236.32 | K40: =IFERROR(INDEX(BusinessUnits!$B:$B,MATCH($C40,BusinessUnits!$A:$A,0)),"") -> MAINTENANCE | L40: =IFERROR(INDEX(Table1[[#All],[Description]],MATCH($C40,BusinessUnits!$A:$A,0)),"") -> Transactions related to the hotel Maintenance Department. Primarily includes payroll for maintenance, grounds keepers and related supplies. | M40: =IFERROR(INDEX(ChartOfAccounts!B39:B124,MATCH($B40,ChartOfAccounts!A39:A124,0)),"") -> Other Services | N40: =IFERROR(INDEX(ChartOfAccounts!D:D,MATCH($B40,ChartOfAccounts!A39:A124,0)),"") -> Revenue | O40: =IFERROR(INDEX(ChartOfAccounts!F:F,MATCH($B40,ChartOfAccounts!A39:A124,0)),"") -> Sales-Dining | P40: {=IFERROR(INDEX(PreparerInfo!B39:B51,MATCH($D40&$C40,PreparerInfo!A39:A51&PreparerInfo!C39:C51,0)),"")} | Q40: =IFERROR(INDEX(Source!B39:B47,MATCH('Case 4 solution'!E40,Source!A39:A47,0)),"")
A41: 2033539 | B41: 11845 | C41: 6 | D41: 101 | E41: 1002 | F41: 44003 | G41: DYNAMIC SECU64605456 | I41: -236.32 | J41: -236.32 | K41: =IFERROR(INDEX(BusinessUnits!$B:$B,MATCH($C41,BusinessUnits!$A:$A,0)),"") -> MAINTENANCE | L41: =IFERROR(INDEX(Table1[[#All],[Description]],MATCH($C41,BusinessUnits!$A:$A,0)),"") -> Transactions related to the hotel Maintenance Department. Primarily includes payroll for maintenance, grounds keepers and related supplies. | M41: =IFERROR(INDEX(ChartOfAccounts!B40:B125,MATCH($B41,ChartOfAccounts!A40:A125,0)),"") | N41: =IFERROR(INDEX(ChartOfAccounts!D:D,MATCH($B41,ChartOfAccounts!A40:A125,0)),"") | O41: =IFERROR(INDEX(ChartOfAccounts!F:F,MATCH($B41,ChartOfAccounts!A40:A125,0)),"") | P41: {=IFERROR(INDEX(PreparerInfo!B40:B52,MATCH($D41&$C41,PreparerInfo!A40:A52&PreparerInfo!C40:C52,0)),"")} | Q41: =IFERROR(INDEX(Source!B40:B48,MATCH('Case 4 solution'!E41,Source!A40:A48,0)),"")
A42: 2033540 | B42: 14250 | C42: 3 | D42: 102 | E42: 1002 | F42: 44003 | G42: COCA-COLA ENTERPRIS | H42: 328.56 | J42: 328.56 | K42: =IFERROR(INDEX(BusinessUnits!$B:$B,MATCH($C42,BusinessUnits!$A:$A,0)),"") -> HOTEL PANTRY | L42: =IFERROR(INDEX(Table1[[#All],[Description]],MATCH($C42,BusinessUnits!$A:$A,0)),"") -> Transactions related to the hotel convenience store, including some food and beverage costs. | M42: =IFERROR(INDEX(ChartOfAccounts!B41:B126,MATCH($B42,ChartOfAccounts!A41:A126,0)),"") | N42: =IFERROR(INDEX(ChartOfAccounts!D:D,MATCH($B42,ChartOfAccounts!A41:A126,0)),"") | O42: =IFERROR(INDEX(ChartOfAccounts!F:F,MATCH($B42,ChartOfAccounts!A41:A126,0)),"") | P42: {=IFERROR(INDEX(PreparerInfo!B41:B53,MATCH($D42&$C42,PreparerInfo!A41:A53&PreparerInfo!C41:C53,0)),"")} | Q42: =IFERROR(INDEX(Source!B41:B49,MATCH('Case 4 solution'!E42,Source!A41:A49,0)),"")
A43: 2033540 | B43: 11845 | C43: 3 | D43: 102 | E43: 1002 | F43: 44003 | G43: COCA-COLA ENTERPRIS | I43: -328.56 | J43: -328.56 | K43: =IFERROR(INDEX(BusinessUnits!$B:$B,MATCH($C43,BusinessUnits!$A:$A,0)),"") -> HOTEL PANTRY | L43: =IFERROR(INDEX(Table1[[#All],[Description]],MATCH($C43,BusinessUnits!$A:$A,0)),"") -> Transactions related to the hotel convenience store, including some food and beverage costs. | M43: =IFERROR(INDEX(ChartOfAccounts!B42:B127,MATCH($B43,ChartOfAccounts!A42:A127,0)),"") | N43: =IFERROR(INDEX(ChartOfAccounts!D:D,MATCH($B43,ChartOfAccounts!A42:A127,0)),"") | O43: =IFERROR(INDEX(ChartOfAccounts!F:F,MATCH($B43,ChartOfAccounts!A42:A127,0)),"") | P43: {=IFERROR(INDEX(PreparerInfo!B42:B54,MATCH($D43&$C43,PreparerInfo!A42:A54&PreparerInfo!C42:C54,0)),"")} | Q43: =IFERROR(INDEX(Source!B42:B50,MATCH('Case 4 solution'!E43,Source!A42:A50,0)),"")
A44: 2033541 | B44: 11845 | C44: 1 | D44: 102 | E44: 1001 | F44: 44003 | G44: CASH RECEIPTS | H44: 603.45 | J44: 603.45 | K44: =IFERROR(INDEX(BusinessUnits!$B:$B,MATCH($C44,BusinessUnits!$A:$A,0)),"") -> FOOD SERVICE | L44: =IFERROR(INDEX(Table1[[#All],[Description]],MATCH($C44,BusinessUnits!$A:$A,0)),"") -> Transactions related to food and beverage service. Includes all guest transactions in the hotel restaurants, catering-related transactions and food service payroll. | M44: =IFERROR(INDEX(ChartOfAccounts!B43:B128,MATCH($B44,ChartOfAccounts!A43:A128,0)),"") | N44: =IFERROR(INDEX(ChartOfAccounts!D:D,MATCH($B44,ChartOfAccounts!A43:A128,0)),"") | O44: =IFERROR(INDEX(ChartOfAccounts!F:F,MATCH($B44,ChartOfAccounts!A43:A128,0)),"") | P44: {=IFERROR(INDEX(PreparerInfo!B43:B55,MATCH($D44&$C44,PreparerInfo!A43:A55&PreparerInfo!C43:C55,0)),"")} | Q44: =IFERROR(INDEX(Source!B43:B51,MATCH('Case 4 solution'!E44,Source!A43:A51,0)),"")
A45: 2033541 | B45: 43310 | C45: 1 | D45: 102 | E45: 1001 | F45: 44003 | G45: CASH RECEIPTS | I45: -603.45 | J45: -603.45 | K45: =IFERROR(INDEX(BusinessUnits!$B:$B,MATCH($C45,BusinessUnits!$A:$A,0)),"") -> FOOD SERVICE | L45: =IFERROR(INDEX(Table1[[#All],[Description]],MATCH($C45,BusinessUnits!$A:$A,0)),"") -> Transactions related to food and beverage service. Includes all guest transactions in the hotel restaurants, catering-related transactions and food service payroll. | M45: =IFERROR(INDEX(ChartOfAccounts!B44:B129,MATCH($B45,ChartOfAccounts!A44:A129,0)),"") | N45: =IFERROR(INDEX(ChartOfAccounts!D:D,MATCH($B45,ChartOfAccounts!A44:A129,0)),"") | O45: =IFERROR(INDEX(ChartOfAccounts!F:F,MATCH($B45,ChartOfAccounts!A44:A129,0)),"") | P45: {=IFERROR(INDEX(PreparerInfo!B44:B56,MATCH($D45&$C45,PreparerInfo!A44:A56&PreparerInfo!C44:C56,0)),"")} | Q45: =IFERROR(INDEX(Source!B44:B52,MATCH('Case 4 solution'!E45,Source!A44:A52,0)),"")
A46: 2033542 | B46: 11845 | C46: 1 | D46: 102 | E46: 1003 | F46: 44003 | G46: CREDIT CARD RECEIPTS | H46: 2422.96 | J46: 2422.96 | K46: =IFERROR(INDEX(BusinessUnits!$B:$B,MATCH($C46,BusinessUnits!$A:$A,0)),"") -> FOOD SERVICE | L46: =IFERROR(INDEX(Table1[[#All],[Description]],MATCH($C46,BusinessUnits!$A:$A,0)),"") -> Transactions related to food and beverage service. Includes all guest transactions in the hotel restaurants, catering-related transactions and food service payroll. | M46: =IFERROR(INDEX(ChartOfAccounts!B45:B130,MATCH($B46,ChartOfAccounts!A45:A130,0)),"") | N46: =IFERROR(INDEX(ChartOfAccounts!D:D,MATCH($B46,ChartOfAccounts!A45:A130,0)),"") | O46: =IFERROR(INDEX(ChartOfAccounts!F:F,MATCH($B46,ChartOfAccounts!A45:A130,0)),"") | P46: {=IFERROR(INDEX(PreparerInfo!B45:B57,MATCH($D46&$C46,PreparerInfo!A45:A57&PreparerInfo!C45:C57,0)),"")} | Q46: =IFERROR(INDEX(Source!B45:B53,MATCH('Case 4 solution'!E46,Source!A45:A53,0)),"")
A47: 2033542 | B47: 43310 | C47: 1 | D47: 102 | E47: 1003 | F47: 44003 | G47: CREDIT CARD RECEIPTS | I47: -2422.96 | J47: -2422.96 | K47: =IFERROR(INDEX(BusinessUnits!$B:$B,MATCH($C47,BusinessUnits!$A:$A,0)),"") -> FOOD SERVICE | L47: =IFERROR(INDEX(Table1[[#All],[Description]],MATCH($C47,BusinessUnits!$A:$A,0)),"") -> Transactions related to food and beverage service. Includes all guest transactions in the hotel restaurants, catering-related transactions and food service payroll. | M47: =IFERROR(INDEX(ChartOfAccounts!B46:B131,MATCH($B47,ChartOfAccounts!A46:A131,0)),"") | N47: =IFERROR(INDEX(ChartOfAccounts!D:D,MATCH($B47,ChartOfAccounts!A46:A131,0)),"") | O47: =IFERROR(INDEX(ChartOfAccounts!F:F,MATCH($B47,ChartOfAccounts!A46:A131,0)),"") | P47: {=IFERROR(INDEX(PreparerInfo!B46:B58,MATCH($D47&$C47,PreparerInfo!A46:A58&PreparerInfo!C46:C58,0)),"")} | Q47: =IFERROR(INDEX(Source!B46:B54,MATCH('Case 4 solution'!E47,Source!A46:A54,0)),"")
A48: 2033543 | B48: 11845 | C48: 2 | D48: 104 | E48: 1003 | F48: 44003 | G48: CREDIT CARD RECEIPTS | H48: 3400 | J48: 3400 | K48: =IFERROR(INDEX(BusinessUnits!$B:$B,MATCH($C48,BusinessUnits!$A:$A,0)),"") -> HOTEL | L48: =IFERROR(INDEX(Table1[[#All],[Description]],MATCH($C48,BusinessUnits!$A:$A,0)),"") -> Transactions related to guest rooms and overall hotel operations. Includes payroll for administrative staff, clerks and interns. | M48: =IFERROR(INDEX(ChartOfAccounts!B47:B132,MATCH($B48,ChartOfAccounts!A47:A132,0)),"") | N48: =IFERROR(INDEX(ChartOfAccounts!D:D,MATCH($B48,ChartOfAccounts!A47:A132,0)),"") | O48: =IFERROR(INDEX(ChartOfAccounts!F:F,MATCH($B48,ChartOfAccounts!A47:A132,0)),"") | P48: {=IFERROR(INDEX(PreparerInfo!B47:B59,MATCH($D48&$C48,PreparerInfo!A47:A59&PreparerInfo!C47:C59,0)),"")} | Q48: =IFERROR(INDEX(Source!B47:B55,MATCH('Case 4 solution'!E48,Source!A47:A55,0)),"")
A49: 2033543 | B49: 43180 | C49: 2 | D49: 104 | E49: 1003 | F49: 44003 | G49: CREDIT CARD RECEIPTS | I49: -3400 | J49: -3400 | K49: =IFERROR(INDEX(BusinessUnits!$B:$B,MATCH($C49,BusinessUnits!$A:$A,0)),"") -> HOTEL | L49: =IFERROR(INDEX(Table1[[#All],[Description]],MATCH($C49,BusinessUnits!$A:$A,0)),"") -> Transactions related to guest rooms and overall hotel operations. Includes payroll for administrative staff, clerks and interns. | M49: =IFERROR(INDEX(ChartOfAccounts!B48:B133,MATCH($B49,ChartOfAccounts!A48:A133,0)),"") | N49: =IFERROR(INDEX(ChartOfAccounts!D:D,MATCH($B49,ChartOfAccounts!A48:A133,0)),"") | O49: =IFERROR(INDEX(ChartOfAccounts!F:F,MATCH($B49,ChartOfAccounts!A48:A133,0)),"") | P49: {=IFERROR(INDEX(PreparerInfo!B48:B60,MATCH($D49&$C49,PreparerInfo!A48:A60&PreparerInfo!C48:C60,0)),"")} | Q49: =IFERROR(INDEX(Source!B48:B56,MATCH('Case 4 solution'!E49,Source!A48:A56,0)),"")
A50: 2033544 | B50: 16200 | C50: 2 | D50: 102 | E50: 1002 | F50: 44003 | G50: ATLAS ENVIRO | H50: 3000 | J50: 3000 | K50: =IFERROR(INDEX(BusinessUnits!$B:$B,MATCH($C50,BusinessUnits!$A:$A,0)),"") -> HOTEL | L50: =IFERROR(INDEX(Table1[[#All],[Description]],MATCH($C50,BusinessUnits!$A:$A,0)),"") -> Transactions related to guest rooms and overall hotel operations. Includes payroll for administrative staff, clerks and interns. | M50: =IFERROR(INDEX(ChartOfAccounts!B49:B134,MATCH($B50,ChartOfAccounts!A49:A134,0)),"") | N50: =IFERROR(INDEX(ChartOfAccounts!D:D,MATCH($B50,ChartOfAccounts!A49:A134,0)),"") | O50: =IFERROR(INDEX(ChartOfAccounts!F:F,MATCH($B50,ChartOfAccounts!A49:A134,0)),"") | P50: {=IFERROR(INDEX(PreparerInfo!B49:B61,MATCH($D50&$C50,PreparerInfo!A49:A61&PreparerInfo!C49:C61,0)),"")} | Q50: =IFERROR(INDEX(Source!B49:B57,MATCH('Case 4 solution'!E50,Source!A49:A57,0)),"")
A51: 2033544 | B51: 11845 | C51: 2 | D51: 102 | E51: 1002 | F51: 44003 | G51: ATLAS ENVIRO | I51: -3000 | J51: -3000 | K51: =IFERROR(INDEX(BusinessUnits!$B:$B,MATCH($C51,BusinessUnits!$A:$A,0)),"") -> HOTEL | L51: =IFERROR(INDEX(Table1[[#All],[Description]],MATCH($C51,BusinessUnits!$A:$A,0)),"") -> Transactions related to guest rooms and overall hotel operations. Includes payroll for administrative staff, clerks and interns. | M51: =IFERROR(INDEX(ChartOfAccounts!B50:B135,MATCH($B51,ChartOfAccounts!A50:A135,0)),"") | N51: =IFERROR(INDEX(ChartOfAccounts!D:D,MATCH($B51,ChartOfAccounts!A50:A135,0)),"") | O51: =IFERROR(INDEX(ChartOfAccounts!F:F,MATCH($B51,ChartOfAccounts!A50:A135,0)),"") | P51: {=IFERROR(INDEX(PreparerInfo!B50:B62,MATCH($D51&$C51,PreparerInfo!A50:A62&PreparerInfo!C50:C62,0)),"")} | Q51: =IFERROR(INDEX(Source!B50:B58,MATCH('Case 4 solution'!E51,Source!A50:A58,0)),"")
A52: 2033545 | B52: 71400 | C52: 1 | D52: 101 | E52: 1002 | F52: 44004 | G52: CENTRAL DUPLICATING | H52: 6.37 | J52: 6.37 | K52: =IFERROR(INDEX(BusinessUnits!$B:$B,MATCH($C52,BusinessUnits!$A:$A,0)),"") -> FOOD SERVICE | L52: =IFERROR(INDEX(Table1[[#All],[Description]],MATCH($C52,BusinessUnits!$A:$A,0)),"") -> Transactions related to food and beverage service. Includes all guest transactions in the hotel restaurants, catering-related transactions and food service payroll. | M52: =IFERROR(INDEX(ChartOfAccounts!B51:B136,MATCH($B52,ChartOfAccounts!A51:A136,0)),"") | N52: =IFERROR(INDEX(ChartOfAccounts!D:D,MATCH($B52,ChartOfAccounts!A51:A136,0)),"") | O52: =IFERROR(INDEX(ChartOfAccounts!F:F,MATCH($B52,ChartOfAccounts!A51:A136,0)),"") | P52: {=IFERROR(INDEX(PreparerInfo!B51:B63,MATCH($D52&$C52,PreparerInfo!A51:A63&PreparerInfo!C51:C63,0)),"")} | Q52: =IFERROR(INDEX(Source!B51:B59,MATCH('Case 4 solution'!E52,Source!A51:A59,0)),"")
A53: 2033545 | B53: 11845 | C53: 1 | D53: 101 | E53: 1002 | F53: 44004 | G53: CENTRAL DUPLICATING | I53: -6.37 | J53: -6.37 | K53: =IFERROR(INDEX(BusinessUnits!$B:$B,MATCH($C53,BusinessUnits!$A:$A,0)),"") -> FOOD SERVICE | L53: =IFERROR(INDEX(Table1[[#All],[Description]],MATCH($C53,BusinessUnits!$A:$A,0)),"") -> Transactions related to food and beverage service. Includes all guest transactions in the hotel restaurants, catering-related transactions and food service payroll. | M53: =IFERROR(INDEX(ChartOfAccounts!B52:B137,MATCH($B53,ChartOfAccounts!A52:A137,0)),"") | N53: =IFERROR(INDEX(ChartOfAccounts!D:D,MATCH($B53,ChartOfAccounts!A52:A137,0)),"") | O53: =IFERROR(INDEX(ChartOfAccounts!F:F,MATCH($B53,ChartOfAccounts!A52:A137,0)),"") | P53: {=IFERROR(INDEX(PreparerInfo!B52:B64,MATCH($D53&$C53,PreparerInfo!A52:A64&PreparerInfo!C52:C64,0)),"")} | Q53: =IFERROR(INDEX(Source!B52:B60,MATCH('Case 4 solution'!E53,Source!A52:A60,0)),"")
A54: 2033546 | B54: 11845 | C54: 1 | D54: 102 | E54: 1001 | F54: 44004 | G54: COPELAND,MELODY | H54: 7.66 | J54: 7.66 | K54: =IFERROR(INDEX(BusinessUnits!$B:$B,MATCH($C54,BusinessUnits!$A:$A,0)),"") -> FOOD SERVICE | L54: =IFERROR(INDEX(Table1[[#All],[Description]],MATCH($C54,BusinessUnits!$A:$A,0)),"") -> Transactions related to food and beverage service. Includes all guest transactions in the hotel restaurants, catering-related transactions and food service payroll. | M54: =IFERROR(INDEX(ChartOfAccounts!B53:B138,MATCH($B54,ChartOfAccounts!A53:A138,0)),"") | N54: =IFERROR(INDEX(ChartOfAccounts!D:D,MATCH($B54,ChartOfAccounts!A53:A138,0)),"") | O54: =IFERROR(INDEX(ChartOfAccounts!F:F,MATCH($B54,ChartOfAccounts!A53:A138,0)),"") | P54: {=IFERROR(INDEX(PreparerInfo!B53:B65,MATCH($D54&$C54,PreparerInfo!A53:A65&PreparerInfo!C53:C65,0)),"")} | Q54: =IFERROR(INDEX(Source!B53:B61,MATCH('Case 4 solution'!E54,Source!A53:A61,0)),"")
A55: 2033546 | B55: 43310 | C55: 1 | D55: 102 | E55: 1001 | F55: 44004 | G55: COPELAND,MELODY | I55: -7.66 | J55: -7.66 | K55: =IFERROR(INDEX(BusinessUnits!$B:$B,MATCH($C55,BusinessUnits!$A:$A,0)),"") -> FOOD SERVICE | L55: =IFERROR(INDEX(Table1[[#All],[Description]],MATCH($C55,BusinessUnits!$A:$A,0)),"") -> Transactions related to food and beverage service. Includes all guest transactions in the hotel restaurants, catering-related transactions and food service payroll. | M55: =IFERROR(INDEX(ChartOfAccounts!B54:B139,MATCH($B55,ChartOfAccounts!A54:A139,0)),"") | N55: =IFERROR(INDEX(ChartOfAccounts!D:D,MATCH($B55,ChartOfAccounts!A54:A139,0)),"") | O55: =IFERROR(INDEX(ChartOfAccounts!F:F,MATCH($B55,ChartOfAccounts!A54:A139,0)),"") | P55: {=IFERROR(INDEX(PreparerInfo!B54:B66,MATCH($D55&$C55,PreparerInfo!A54:A66&PreparerInfo!C54:C66,0)),"")} | Q55: =IFERROR(INDEX(Source!B54:B62,MATCH('Case 4 solution'!E55,Source!A54:A62,0)),"")
A56: 2033547 | B56: 11845 | C56: 3 | D56: 102 | E56: 1003 | F56: 44004 | G56: CREDIT CARD RECEIPTS | H56: 17.21 | J56: 17.21 | K56: =IFERROR(INDEX(BusinessUnits!$B:$B,MATCH($C56,BusinessUnits!$A:$A,0)),"") -> HOTEL PANTRY | L56: =IFERROR(INDEX(Table1[[#All],[Description]],MATCH($C56,BusinessUnits!$A:$A,0)),"") -> Transactions related to the hotel convenience store, including some food and beverage costs. | M56: =IFERROR(INDEX(ChartOfAccounts!B55:B140,MATCH($B56,ChartOfAccounts!A55:A140,0)),"") | N56: =IFERROR(INDEX(ChartOfAccounts!D:D,MATCH($B56,ChartOfAccounts!A55:A140,0)),"") | O56: =IFERROR(INDEX(ChartOfAccounts!F:F,MATCH($B56,ChartOfAccounts!A55:A140,0)),"") | P56: {=IFERROR(INDEX(PreparerInfo!B55:B67,MATCH($D56&$C56,PreparerInfo!A55:A67&PreparerInfo!C55:C67,0)),"")} | Q56: =IFERROR(INDEX(Source!B55:B63,MATCH('Case 4 solution'!E56,Source!A55:A63,0)),"")
A57: 2033547 | B57: 43440 | C57: 3 | D57: 102 | E57: 1003 | F57: 44004 | G57: CREDIT CARD RECEIPTS | I57: -17.21 | J57: -17.21 | K57: =IFERROR(INDEX(BusinessUnits!$B:$B,MATCH($C57,BusinessUnits!$A:$A,0)),"") -> HOTEL PANTRY | L57: =IFERROR(INDEX(Table1[[#All],[Description]],MATCH($C57,BusinessUnits!$A:$A,0)),"") -> Transactions related to the hotel convenience store, including some food and beverage costs. | M57: =IFERROR(INDEX(ChartOfAccounts!B56:B141,MATCH($B57,ChartOfAccounts!A56:A141,0)),"") | N57: =IFERROR(INDEX(ChartOfAccounts!D:D,MATCH($B57,ChartOfAccounts!A56:A141,0)),"") | O57: =IFERROR(INDEX(ChartOfAccounts!F:F,MATCH($B57,ChartOfAccounts!A56:A141,0)),"") | P57: {=IFERROR(INDEX(PreparerInfo!B56:B68,MATCH($D57&$C57,PreparerInfo!A56:A68&PreparerInfo!C56:C68,0)),"")} | Q57: =IFERROR(INDEX(Source!B56:B64,MATCH('Case 4 solution'!E57,Source!A56:A64,0)),"")
A58: 2033548 | B58: 11845 | C58: 1 | D58: 102 | E58: 1003 | F58: 44004 | G58: CREDIT CARD RECEIPTS | H58: 26.98 | J58: 26.98 | K58: =IFERROR(INDEX(BusinessUnits!$B:$B,MATCH($C58,BusinessUnits!$A:$A,0)),"") -> FOOD SERVICE | L58: =IFERROR(INDEX(Table1[[#All],[Description]],MATCH($C58,BusinessUnits!$A:$A,0)),"") -> Transactions related to food and beverage service. Includes all guest transactions in the hotel restaurants, catering-related transactions and food service payroll. | M58: =IFERROR(INDEX(ChartOfAccounts!B57:B142,MATCH($B58,ChartOfAccounts!A57:A142,0)),"") | N58: =IFERROR(INDEX(ChartOfAccounts!D:D,MATCH($B58,ChartOfAccounts!A57:A142,0)),"") | O58: =IFERROR(INDEX(ChartOfAccounts!F:F,MATCH($B58,ChartOfAccounts!A57:A142,0)),"") | P58: {=IFERROR(INDEX(PreparerInfo!B57:B69,MATCH($D58&$C58,PreparerInfo!A57:A69&PreparerInfo!C57:C69,0)),"")} | Q58: =IFERROR(INDEX(Source!B57:B65,MATCH('Case 4 solution'!E58,Source!A57:A65,0)),"")
A59: 2033548 | B59: 43310 | C59: 1 | D59: 102 | E59: 1003 | F59: 44004 | G59: CREDIT CARD RECEIPTS | I59: -26.98 | J59: -26.98 | K59: =IFERROR(INDEX(BusinessUnits!$B:$B,MATCH($C59,BusinessUnits!$A:$A,0)),"") -> FOOD SERVICE | L59: =IFERROR(INDEX(Table1[[#All],[Description]],MATCH($C59,BusinessUnits!$A:$A,0)),"") -> Transactions related to food and beverage service. Includes all guest transactions in the hotel restaurants, catering-related transactions and food service payroll. | M59: =IFERROR(INDEX(ChartOfAccounts!B58:B143,MATCH($B59,ChartOfAccounts!A58:A143,0)),"") | N59: =IFERROR(INDEX(ChartOfAccounts!D:D,MATCH($B59,ChartOfAccounts!A58:A143,0)),"") | O59: =IFERROR(INDEX(ChartOfAccounts!F:F,MATCH($B59,ChartOfAccounts!A58:A143,0)),"") | P59: {=IFERROR(INDEX(PreparerInfo!B58:B70,MATCH($D59&$C59,PreparerInfo!A58:A70&PreparerInfo!C58:C70,0)),"")} | Q59: =IFERROR(INDEX(Source!B58:B66,MATCH('Case 4 solution'!E59,Source!A58:A66,0)),"")
A60: 2033549 | B60: 71400 | C60: 2 | D60: 101 | E60: 1002 | F60: 44004 | G60: SA647 CARD JUN | H60: 40 | J60: 40 | K60: =IFERROR(INDEX(BusinessUnits!$B:$B,MATCH($C60,BusinessUnits!$A:$A,0)),"") -> HOTEL | L60: =IFERROR(INDEX(Table1[[#All],[Description]],MATCH($C60,BusinessUnits!$A:$A,0)),"") -> Transactions related to guest rooms and overall hotel operations. Includes payroll for administrative staff, clerks and interns. | M60: =IFERROR(INDEX(ChartOfAccounts!B59:B144,MATCH($B60,ChartOfAccounts!A59:A144,0)),"") | N60: =IFERROR(INDEX(ChartOfAccounts!D:D,MATCH($B60,ChartOfAccounts!A59:A144,0)),"") | O60: =IFERROR(INDEX(ChartOfAccounts!F:F,MATCH($B60,ChartOfAccounts!A59:A144,0)),"") | P60: {=IFERROR(INDEX(PreparerInfo!B59:B71,MATCH($D60&$C60,PreparerInfo!A59:A71&PreparerInfo!C59:C71,0)),"")} | Q60: =IFERROR(INDEX(Source!B59:B67,MATCH('Case 4 solution'!E60,Source!A59:A67,0)),"")
A61: 2033549 | B61: 11845 | C61: 2 | D61: 101 | E61: 1002 | F61: 44004 | G61: SA647 CARD JUN | I61: -40 | J61: -40 | K61: =IFERROR(INDEX(BusinessUnits!$B:$B,MATCH($C61,BusinessUnits!$A:$A,0)),"") -> HOTEL | L61: =IFERROR(INDEX(Table1[[#All],[Description]],MATCH($C61,BusinessUnits!$A:$A,0)),"") -> Transactions related to guest rooms and overall hotel operations. Includes payroll for administrative staff, clerks and interns. | M61: =IFERROR(INDEX(ChartOfAccounts!B60:B145,MATCH($B61,ChartOfAccounts!A60:A145,0)),"") | N61: =IFERROR(INDEX(ChartOfAccounts!D:D,MATCH($B61,ChartOfAccounts!A60:A145,0)),"") | O61: =IFERROR(INDEX(ChartOfAccounts!F:F,MATCH($B61,ChartOfAccounts!A60:A145,0)),"") | P61: {=IFERROR(INDEX(PreparerInfo!B60:B72,MATCH($D61&$C61,PreparerInfo!A60:A72&PreparerInfo!C60:C72,0)),"")} | Q61: =IFERROR(INDEX(Source!B60:B68,MATCH('Case 4 solution'!E61,Source!A60:A68,0)),"")
A62: 2033550 | B62: 71400 | C62: 1 | D62: 101 | E62: 1002 | F62: 44004 | G62: CENTRAL DUPLICATING | H62: 45 | J62: 45 | K62: =IFERROR(INDEX(BusinessUnits!$B:$B,MATCH($C62,BusinessUnits!$A:$A,0)),"") -> FOOD SERVICE | L62: =IFERROR(INDEX(Table1[[#All],[Description]],MATCH($C62,BusinessUnits!$A:$A,0)),"") -> Transactions related to food and beverage service. Includes all guest transactions in the hotel restaurants, catering-related transactions and food service payroll. | M62: =IFERROR(INDEX(ChartOfAccounts!B61:B146,MATCH($B62,ChartOfAccounts!A61:A146,0)),"") | N62: =IFERROR(INDEX(ChartOfAccounts!D:D,MATCH($B62,ChartOfAccounts!A61:A146,0)),"") | O62: =IFERROR(INDEX(ChartOfAccounts!F:F,MATCH($B62,ChartOfAccounts!A61:A146,0)),"") | P62: {=IFERROR(INDEX(PreparerInfo!B61:B73,MATCH($D62&$C62,PreparerInfo!A61:A73&PreparerInfo!C61:C73,0)),"")} | Q62: =IFERROR(INDEX(Source!B61:B69,MATCH('Case 4 solution'!E62,Source!A61:A69,0)),"")
A63: 2033550 | B63: 11845 | C63: 1 | D63: 101 | E63: 1002 | F63: 44004 | G63: CENTRAL DUPLICATING | I63: -45 | J63: -45 | K63: =IFERROR(INDEX(BusinessUnits!$B:$B,MATCH($C63,BusinessUnits!$A:$A,0)),"") -> FOOD SERVICE | L63: =IFERROR(INDEX(Table1[[#All],[Description]],MATCH($C63,BusinessUnits!$A:$A,0)),"") -> Transactions related to food and beverage service. Includes all guest transactions in the hotel restaurants, catering-related transactions and food service payroll. | M63: =IFERROR(INDEX(ChartOfAccounts!B62:B147,MATCH($B63,ChartOfAccounts!A62:A147,0)),"") | N63: =IFERROR(INDEX(ChartOfAccounts!D:D,MATCH($B63,ChartOfAccounts!A62:A147,0)),"") | O63: =IFERROR(INDEX(ChartOfAccounts!F:F,MATCH($B63,ChartOfAccounts!A62:A147,0)),"") | P63: {=IFERROR(INDEX(PreparerInfo!B62:B74,MATCH($D63&$C63,PreparerInfo!A62:A74&PreparerInfo!C62:C74,0)),"")} | Q63: =IFERROR(INDEX(Source!B62:B70,MATCH('Case 4 solution'!E63,Source!A62:A70,0)),"")
A64: 2033551 | B64: 11845 | C64: 3 | D64: 102 | E64: 1001 | F64: 44004 | G64: CASH RECEIPTS | H64: 49.51 | J64: 49.51 | K64: =IFERROR(INDEX(BusinessUnits!$B:$B,MATCH($C64,BusinessUnits!$A:$A,0)),"") -> HOTEL PANTRY | L64: =IFERROR(INDEX(Table1[[#All],[Description]],MATCH($C64,BusinessUnits!$A:$A,0)),"") -> Transactions related to the hotel convenience store, including some food and beverage costs. | M64: =IFERROR(INDEX(ChartOfAccounts!B63:B148,MATCH($B64,ChartOfAccounts!A63:A148,0)),"") | N64: =IFERROR(INDEX(ChartOfAccounts!D:D,MATCH($B64,ChartOfAccounts!A63:A148,0)),"") | O64: =IFERROR(INDEX(ChartOfAccounts!F:F,MATCH($B64,ChartOfAccounts!A63:A148,0)),"") | P64: {=IFERROR(INDEX(PreparerInfo!B63:B75,MATCH($D64&$C64,PreparerInfo!A63:A75&PreparerInfo!C63:C75,0)),"")} | Q64: =IFERROR(INDEX(Source!B63:B71,MATCH('Case 4 solution'!E64,Source!A63:A71,0)),"")
A65: 2033551 | B65: 43440 | C65: 3 | D65: 102 | E65: 1001 | F65: 44004 | G65: CASH RECEIPTS | I65: -49.51 | J65: -49.51 | K65: =IFERROR(INDEX(BusinessUnits!$B:$B,MATCH($C65,BusinessUnits!$A:$A,0)),"") -> HOTEL PANTRY | L65: =IFERROR(INDEX(Table1[[#All],[Description]],MATCH($C65,BusinessUnits!$A:$A,0)),"") -> Transactions related to the hotel convenience store, including some food and beverage costs. | M65: =IFERROR(INDEX(ChartOfAccounts!B64:B149,MATCH($B65,ChartOfAccounts!A64:A149,0)),"") | N65: =IFERROR(INDEX(ChartOfAccounts!D:D,MATCH($B65,ChartOfAccounts!A64:A149,0)),"") | O65: =IFERROR(INDEX(ChartOfAccounts!F:F,MATCH($B65,ChartOfAccounts!A64:A149,0)),"") | P65: {=IFERROR(INDEX(PreparerInfo!B64:B76,MATCH($D65&$C65,PreparerInfo!A64:A76&PreparerInfo!C64:C76,0)),"")} | Q65: =IFERROR(INDEX(Source!B64:B72,MATCH('Case 4 solution'!E65,Source!A64:A72,0)),"")
A66: 2033552 | B66: 72732 | C66: 1 | D66: 101 | E66: 1002 | F66: 44004 | G66: FEDEX | H66: 55 | J66: 55 | K66: =IFERROR(INDEX(BusinessUnits!$B:$B,MATCH($C66,BusinessUnits!$A:$A,0)),"") -> FOOD SERVICE | L66: =IFERROR(INDEX(Table1[[#All],[Description]],MATCH($C66,BusinessUnits!$A:$A,0)),"") -> Transactions related to food and beverage service. Includes all guest transactions in the hotel restaurants, catering-related transactions and food service payroll. | M66: =IFERROR(INDEX(ChartOfAccounts!B65:B150,MATCH($B66,ChartOfAccounts!A65:A150,0)),"") | N66: =IFERROR(INDEX(ChartOfAccounts!D:D,MATCH($B66,ChartOfAccounts!A65:A150,0)),"") | O66: =IFERROR(INDEX(ChartOfAccounts!F:F,MATCH($B66,ChartOfAccounts!A65:A150,0)),"") | P66: {=IFERROR(INDEX(PreparerInfo!B65:B77,MATCH($D66&$C66,PreparerInfo!A65:A77&PreparerInfo!C65:C77,0)),"")} | Q66: =IFERROR(INDEX(Source!B65:B73,MATCH('Case 4 solution'!E66,Source!A65:A73,0)),"")
A67: 2033552 | B67: 11845 | C67: 1 | D67: 101 | E67: 1002 | F67: 44004 | G67: FEDEX | I67: -55 | J67: -55 | K67: =IFERROR(INDEX(BusinessUnits!$B:$B,MATCH($C67,BusinessUnits!$A:$A,0)),"") -> FOOD SERVICE | L67: =IFERROR(INDEX(Table1[[#All],[Description]],MATCH($C67,BusinessUnits!$A:$A,0)),"") -> Transactions related to food and beverage service. Includes all guest transactions in the hotel restaurants, catering-related transactions and food service payroll. | M67: =IFERROR(INDEX(ChartOfAccounts!B66:B151,MATCH($B67,ChartOfAccounts!A66:A151,0)),"") | N67: =IFERROR(INDEX(ChartOfAccounts!D:D,MATCH($B67,ChartOfAccounts!A66:A151,0)),"") | O67: =IFERROR(INDEX(ChartOfAccounts!F:F,MATCH($B67,ChartOfAccounts!A66:A151,0)),"") | P67: {=IFERROR(INDEX(PreparerInfo!B66:B78,MATCH($D67&$C67,PreparerInfo!A66:A78&PreparerInfo!C66:C78,0)),"")} | Q67: =IFERROR(INDEX(Source!B66:B74,MATCH('Case 4 solution'!E67,Source!A66:A74,0)),"")
A68: 2033553 | B68: 11845 | C68: 3 | D68: 102 | E68: 1003 | F68: 44004 | G68: CREDIT CARD RECEIPTS | H68: 58.02 | J68: 58.02 | K68: =IFERROR(INDEX(BusinessUnits!$B:$B,MATCH($C68,BusinessUnits!$A:$A,0)),"") -> HOTEL PANTRY | L68: =IFERROR(INDEX(Table1[[#All],[Description]],MATCH($C68,BusinessUnits!$A:$A,0)),"") -> Transactions related to the hotel convenience store, including some food and beverage costs. | M68: =IFERROR(INDEX(ChartOfAccounts!B67:B152,MATCH($B68,ChartOfAccounts!A67:A152,0)),"") | N68: =IFERROR(INDEX(ChartOfAccounts!D:D,MATCH($B68,ChartOfAccounts!A67:A152,0)),"") | O68: =IFERROR(INDEX(ChartOfAccounts!F:F,MATCH($B68,ChartOfAccounts!A67:A152,0)),"") | P68: {=IFERROR(INDEX(PreparerInfo!B67:B79,MATCH($D68&$C68,PreparerInfo!A67:A79&PreparerInfo!C67:C79,0)),"")} | Q68: =IFERROR(INDEX(Source!B67:B75,MATCH('Case 4 solution'!E68,Source!A67:A75,0)),"")
A69: 2033553 | B69: 43440 | C69: 3 | D69: 102 | E69: 1003 | F69: 44004 | G69: CREDIT CARD RECEIPTS | I69: -58.02 | J69: -58.02 | K69: =IFERROR(INDEX(BusinessUnits!$B:$B,MATCH($C69,BusinessUnits!$A:$A,0)),"") -> HOTEL PANTRY | L69: =IFERROR(INDEX(Table1[[#All],[Description]],MATCH($C69,BusinessUnits!$A:$A,0)),"") -> Transactions related to the hotel convenience store, including some food and beverage costs. | M69: =IFERROR(INDEX(ChartOfAccounts!B68:B153,MATCH($B69,ChartOfAccounts!A68:A153,0)),"") | N69: =IFERROR(INDEX(ChartOfAccounts!D:D,MATCH($B69,ChartOfAccounts!A68:A153,0)),"") | O69: =IFERROR(INDEX(ChartOfAccounts!F:F,MATCH($B69,ChartOfAccounts!A68:A153,0)),"") | P69: {=IFERROR(INDEX(PreparerInfo!B68:B80,MATCH($D69&$C69,PreparerInfo!A68:A80&PreparerInfo!C68:C80,0)),"")} | Q69: =IFERROR(INDEX(Source!B68:B76,MATCH('Case 4 solution'!E69,Source!A68:A76,0)),"")
A70: 2033554 | B70: 11845 | C70: 1 | D70: 102 | E70: 1003 | F70: 44004 | G70: DINING JUN | H70: 80.24 | J70: 80.24 | K70: =IFERROR(INDEX(BusinessUnits!$B:$B,MATCH($C70,BusinessUnits!$A:$A,0)),"") -> FOOD SERVICE | L70: =IFERROR(INDEX(Table1[[#All],[Description]],MATCH($C70,BusinessUnits!$A:$A,0)),"") -> Transactions related to food and beverage service. Includes all guest transactions in the hotel restaurants, catering-related transactions and food service payroll. | M70: =IFERROR(INDEX(ChartOfAccounts!B69:B154,MATCH($B70,ChartOfAccounts!A69:A154,0)),"") | N70: =IFERROR(INDEX(ChartOfAccounts!D:D,MATCH($B70,ChartOfAccounts!A69:A154,0)),"") | O70: =IFERROR(INDEX(ChartOfAccounts!F:F,MATCH($B70,ChartOfAccounts!A69:A154,0)),"") | P70: {=IFERROR(INDEX(PreparerInfo!B69:B81,MATCH($D70&$C70,PreparerInfo!A69:A81&PreparerInfo!C69:C81,0)),"")} | Q70: =IFERROR(INDEX(Source!B69:B77,MATCH('Case 4 solution'!E70,Source!A69:A77,0)),"")
A71: 2033554 | B71: 43310 | C71: 1 | D71: 102 | E71: 1003 | F71: 44004 | G71: DINING JUN | I71: -80.24 | J71: -80.24 | K71: =IFERROR(INDEX(BusinessUnits!$B:$B,MATCH($C71,BusinessUnits!$A:$A,0)),"") -> FOOD SERVICE | L71: =IFERROR(INDEX(Table1[[#All],[Description]],MATCH($C71,BusinessUnits!$A:$A,0)),"") -> Transactions related to food and beverage service. Includes all guest transactions in the hotel restaurants, catering-related transactions and food service payroll. | M71: =IFERROR(INDEX(ChartOfAccounts!B70:B155,MATCH($B71,ChartOfAccounts!A70:A155,0)),"") | N71: =IFERROR(INDEX(ChartOfAccounts!D:D,MATCH($B71,ChartOfAccounts!A70:A155,0)),"") | O71: =IFERROR(INDEX(ChartOfAccounts!F:F,MATCH($B71,ChartOfAccounts!A70:A155,0)),"") | P71: {=IFERROR(INDEX(PreparerInfo!B70:B82,MATCH($D71&$C71,PreparerInfo!A70:A82&PreparerInfo!C70:C82,0)),"")} | Q71: =IFERROR(INDEX(Source!B70:B78,MATCH('Case 4 solution'!E71,Source!A70:A78,0)),"")
A72: 2033555 | B72: 11845 | C72: 1 | D72: 102 | E72: 1003 | F72: 44004 | G72: CREDIT CARD RECEIPTS | H72: 91 | J72: 91 | K72: =IFERROR(INDEX(BusinessUnits!$B:$B,MATCH($C72,BusinessUnits!$A:$A,0)),"") -> FOOD SERVICE | L72: =IFERROR(INDEX(Table1[[#All],[Description]],MATCH($C72,BusinessUnits!$A:$A,0)),"") -> Transactions related to food and beverage service. Includes all guest transactions in the hotel restaurants, catering-related transactions and food service payroll. | M72: =IFERROR(INDEX(ChartOfAccounts!B71:B156,MATCH($B72,ChartOfAccounts!A71:A156,0)),"") | N72: =IFERROR(INDEX(ChartOfAccounts!D:D,MATCH($B72,ChartOfAccounts!A71:A156,0)),"") | O72: =IFERROR(INDEX(ChartOfAccounts!F:F,MATCH($B72,ChartOfAccounts!A71:A156,0)),"") | P72: {=IFERROR(INDEX(PreparerInfo!B71:B83,MATCH($D72&$C72,PreparerInfo!A71:A83&PreparerInfo!C71:C83,0)),"")} | Q72: =IFERROR(INDEX(Source!B71:B79,MATCH('Case 4 solution'!E72,Source!A71:A79,0)),"")
A73: 2033555 | B73: 43310 | C73: 1 | D73: 102 | E73: 1003 | F73: 44004 | G73: CREDIT CARD RECEIPTS | I73: -91 | J73: -91 | K73: =IFERROR(INDEX(BusinessUnits!$B:$B,MATCH($C73,BusinessUnits!$A:$A,0)),"") -> FOOD SERVICE | L73: =IFERROR(INDEX(Table1[[#All],[Description]],MATCH($C73,BusinessUnits!$A:$A,0)),"") -> Transactions related to food and beverage service. Includes all guest transactions in the hotel restaurants, catering-related transactions and food service payroll. | M73: =IFERROR(INDEX(ChartOfAccounts!B72:B157,MATCH($B73,ChartOfAccounts!A72:A157,0)),"") | N73: =IFERROR(INDEX(ChartOfAccounts!D:D,MATCH($B73,ChartOfAccounts!A72:A157,0)),"") | O73: =IFERROR(INDEX(ChartOfAccounts!F:F,MATCH($B73,ChartOfAccounts!A72:A157,0)),"") | P73: {=IFERROR(INDEX(PreparerInfo!B72:B84,MATCH($D73&$C73,PreparerInfo!A72:A84&PreparerInfo!C72:C84,0)),"")} | Q73: =IFERROR(INDEX(Source!B72:B80,MATCH('Case 4 solution'!E73,Source!A72:A80,0)),"")
A74: 2033556 | B74: 71400 | C74: 1 | D74: 101 | E74: 1002 | F74: 44004 | G74: SA647 CARD JUN | H74: 100 | J74: 100 | K74: =IFERROR(INDEX(BusinessUnits!$B:$B,MATCH($C74,BusinessUnits!$A:$A,0)),"") -> FOOD SERVICE | L74: =IFERROR(INDEX(Table1[[#All],[Description]],MATCH($C74,BusinessUnits!$A:$A,0)),"") -> Transactions related to food and beverage service. Includes all guest transactions in the hotel restaurants, catering-related transactions and food service payroll. | M74: =IFERROR(INDEX(ChartOfAccounts!B73:B158,MATCH($B74,ChartOfAccounts!A73:A158,0)),"") | N74: =IFERROR(INDEX(ChartOfAccounts!D:D,MATCH($B74,ChartOfAccounts!A73:A158,0)),"") | O74: =IFERROR(INDEX(ChartOfAccounts!F:F,MATCH($B74,ChartOfAccounts!A73:A158,0)),"") | P74: {=IFERROR(INDEX(PreparerInfo!B73:B85,MATCH($D74&$C74,PreparerInfo!A73:A85&PreparerInfo!C73:C85,0)),"")} | Q74: =IFERROR(INDEX(Source!B73:B81,MATCH('Case 4 solution'!E74,Source!A73:A81,0)),"")
A75: 2033556 | B75: 11845 | C75: 1 | D75: 101 | E75: 1002 | F75: 44004 | G75: SA647 CARD JUN | I75: -100 | J75: -100 | K75: =IFERROR(INDEX(BusinessUnits!$B:$B,MATCH($C75,BusinessUnits!$A:$A,0)),"") -> FOOD SERVICE | L75: =IFERROR(INDEX(Table1[[#All],[Description]],MATCH($C75,BusinessUnits!$A:$A,0)),"") -> Transactions related to food and beverage service. Includes all guest transactions in the hotel restaurants, catering-related transactions and food service payroll. | M75: =IFERROR(INDEX(ChartOfAccounts!B74:B159,MATCH($B75,ChartOfAccounts!A74:A159,0)),"") | N75: =IFERROR(INDEX(ChartOfAccounts!D:D,MATCH($B75,ChartOfAccounts!A74:A159,0)),"") | O75: =IFERROR(INDEX(ChartOfAccounts!F:F,MATCH($B75,ChartOfAccounts!A74:A159,0)),"") | P75: {=IFERROR(INDEX(PreparerInfo!B74:B86,MATCH($D75&$C75,PreparerInfo!A74:A86&PreparerInfo!C74:C86,0)),"")} | Q75: =IFERROR(INDEX(Source!B74:B82,MATCH('Case 4 solution'!E75,Source!A74:A82,0)),"")
A76: 2033557 | B76: 72702 | C76: 2 | D76: 101 | E76: 1002 | F76: 44004 | G76: ONE PRICE DRY CLEANI | H76: 111.15 | J76: 111.15 | K76: =IFERROR(INDEX(BusinessUnits!$B:$B,MATCH($C76,BusinessUnits!$A:$A,0)),"") -> HOTEL | L76: =IFERROR(INDEX(Table1[[#All],[Description]],MATCH($C76,BusinessUnits!$A:$A,0)),"") -> Transactions related to guest rooms and overall hotel operations. Includes payroll for administrative staff, clerks and interns. | M76: =IFERROR(INDEX(ChartOfAccounts!B75:B160,MATCH($B76,ChartOfAccounts!A75:A160,0)),"") | N76: =IFERROR(INDEX(ChartOfAccounts!D:D,MATCH($B76,ChartOfAccounts!A75:A160,0)),"") | O76: =IFERROR(INDEX(ChartOfAccounts!F:F,MATCH($B76,ChartOfAccounts!A75:A160,0)),"") | P76: {=IFERROR(INDEX(PreparerInfo!B75:B87,MATCH($D76&$C76,PreparerInfo!A75:A87&PreparerInfo!C75:C87,0)),"")} | Q76: =IFERROR(INDEX(Source!B75:B83,MATCH('Case 4 solution'!E76,Source!A75:A83,0)),"")
A77: 2033557 | B77: 11845 | C77: 2 | D77: 101 | E77: 1002 | F77: 44004 | G77: ONE PRICE DRY CLEANI | I77: -111.15 | J77: -111.15 | K77: =IFERROR(INDEX(BusinessUnits!$B:$B,MATCH($C77,BusinessUnits!$A:$A,0)),"") -> HOTEL | L77: =IFERROR(INDEX(Table1[[#All],[Description]],MATCH($C77,BusinessUnits!$A:$A,0)),"") -> Transactions related to guest rooms and overall hotel operations. Includes payroll for administrative staff, clerks and interns. | M77: =IFERROR(INDEX(ChartOfAccounts!B76:B161,MATCH($B77,ChartOfAccounts!A76:A161,0)),"") | N77: =IFERROR(INDEX(ChartOfAccounts!D:D,MATCH($B77,ChartOfAccounts!A76:A161,0)),"") | O77: =IFERROR(INDEX(ChartOfAccounts!F:F,MATCH($B77,ChartOfAccounts!A76:A161,0)),"") | P77: {=IFERROR(INDEX(PreparerInfo!B76:B88,MATCH($D77&$C77,PreparerInfo!A76:A88&PreparerInfo!C76:C88,0)),"")} | Q77: =IFERROR(INDEX(Source!B76:B84,MATCH('Case 4 solution'!E77,Source!A76:A84,0)),"")
A78: 2033558 | B78: 11845 | C78: 1 | D78: 106 | E78: 1003 | F78: 44004 | G78: CONFERENCE - FOOD SERVICE | H78: 138.16 | J78: 138.16 | K78: =IFERROR(INDEX(BusinessUnits!$B:$B,MATCH($C78,BusinessUnits!$A:$A,0)),"") -> FOOD SERVICE | L78: =IFERROR(INDEX(Table1[[#All],[Description]],MATCH($C78,BusinessUnits!$A:$A,0)),"") -> Transactions related to food and beverage service. Includes all guest transactions in the hotel restaurants, catering-related transactions and food service payroll. | M78: =IFERROR(INDEX(ChartOfAccounts!B77:B162,MATCH($B78,ChartOfAccounts!A77:A162,0)),"") | N78: =IFERROR(INDEX(ChartOfAccounts!D:D,MATCH($B78,ChartOfAccounts!A77:A162,0)),"") | O78: =IFERROR(INDEX(ChartOfAccounts!F:F,MATCH($B78,ChartOfAccounts!A77:A162,0)),"") | P78: {=IFERROR(INDEX(PreparerInfo!B77:B89,MATCH($D78&$C78,PreparerInfo!A77:A89&PreparerInfo!C77:C89,0)),"")} | Q78: =IFERROR(INDEX(Source!B77:B85,MATCH('Case 4 solution'!E78,Source!A77:A85,0)),"")
A79: 2033558 | B79: 43310 | C79: 1 | D79: 106 | E79: 1003 | F79: 44004 | G79: CONFERENCE - FOOD SERVICE | I79: -138.16 | J79: -138.16 | K79: =IFERROR(INDEX(BusinessUnits!$B:$B,MATCH($C79,BusinessUnits!$A:$A,0)),"") -> FOOD SERVICE | L79: =IFERROR(INDEX(Table1[[#All],[Description]],MATCH($C79,BusinessUnits!$A:$A,0)),"") -> Transactions related to food and beverage service. Includes all guest transactions in the hotel restaurants, catering-related transactions and food service payroll. | M79: =IFERROR(INDEX(ChartOfAccounts!B78:B163,MATCH($B79,ChartOfAccounts!A78:A163,0)),"") | N79: =IFERROR(INDEX(ChartOfAccounts!D:D,MATCH($B79,ChartOfAccounts!A78:A163,0)),"") | O79: =IFERROR(INDEX(ChartOfAccounts!F:F,MATCH($B79,ChartOfAccounts!A78:A163,0)),"") | P79: {=IFERROR(INDEX(PreparerInfo!B78:B90,MATCH($D79&$C79,PreparerInfo!A78:A90&PreparerInfo!C78:C90,0)),"")} | Q79: =IFERROR(INDEX(Source!B78:B86,MATCH('Case 4 solution'!E79,Source!A78:A86,0)),"")
A80: 2033559 | B80: 71400 | C80: 1 | D80: 101 | E80: 1002 | F80: 44004 | G80: PURE WATER TECHNOLOG | H80: 159.9 | J80: 159.9 | K80: =IFERROR(INDEX(BusinessUnits!$B:$B,MATCH($C80,BusinessUnits!$A:$A,0)),"") -> FOOD SERVICE | L80: =IFERROR(INDEX(Table1[[#All],[Description]],MATCH($C80,BusinessUnits!$A:$A,0)),"") -> Transactions related to food and beverage service. Includes all guest transactions in the hotel restaurants, catering-related transactions and food service payroll. | M80: =IFERROR(INDEX(ChartOfAccounts!B79:B164,MATCH($B80,ChartOfAccounts!A79:A164,0)),"") | N80: =IFERROR(INDEX(ChartOfAccounts!D:D,MATCH($B80,ChartOfAccounts!A79:A164,0)),"") | O80: =IFERROR(INDEX(ChartOfAccounts!F:F,MATCH($B80,ChartOfAccounts!A79:A164,0)),"") | P80: {=IFERROR(INDEX(PreparerInfo!B79:B91,MATCH($D80&$C80,PreparerInfo!A79:A91&PreparerInfo!C79:C91,0)),"")} | Q80: =IFERROR(INDEX(Source!B79:B87,MATCH('Case 4 solution'!E80,Source!A79:A87,0)),"")
A81: 2033559 | B81: 11845 | C81: 1 | D81: 101 | E81: 1002 | F81: 44004 | G81: PURE WATER TECHNOLOG | I81: -159.9 | J81: -159.9 | K81: =IFERROR(INDEX(BusinessUnits!$B:$B,MATCH($C81,BusinessUnits!$A:$A,0)),"") -> FOOD SERVICE | L81: =IFERROR(INDEX(Table1[[#All],[Description]],MATCH($C81,BusinessUnits!$A:$A,0)),"") -> Transactions related to food and beverage service. Includes all guest transactions in the hotel restaurants, catering-related transactions and food service payroll. | M81: =IFERROR(INDEX(ChartOfAccounts!B80:B165,MATCH($B81,ChartOfAccounts!A80:A165,0)),"") | N81: =IFERROR(INDEX(ChartOfAccounts!D:D,MATCH($B81,ChartOfAccounts!A80:A165,0)),"") | O81: =IFERROR(INDEX(ChartOfAccounts!F:F,MATCH($B81,ChartOfAccounts!A80:A165,0)),"") | P81: {=IFERROR(INDEX(PreparerInfo!B80:B92,MATCH($D81&$C81,PreparerInfo!A80:A92&PreparerInfo!C80:C92,0)),"")} | Q81: =IFERROR(INDEX(Source!B80:B88,MATCH('Case 4 solution'!E81,Source!A80:A88,0)),"")
A82: 2033560 | B82: 71400 | C82: 1 | D82: 101 | E82: 1002 | F82: 44004 | G82: PURE WATER TECHNOLOG | H82: 159.9 | J82: 159.9 | K82: =IFERROR(INDEX(BusinessUnits!$B:$B,MATCH($C82,BusinessUnits!$A:$A,0)),"") -> FOOD SERVICE | L82: =IFERROR(INDEX(Table1[[#All],[Description]],MATCH($C82,BusinessUnits!$A:$A,0)),"") -> Transactions related to food and beverage service. Includes all guest transactions in the hotel restaurants, catering-related transactions and food service payroll. | M82: =IFERROR(INDEX(ChartOfAccounts!B81:B166,MATCH($B82,ChartOfAccounts!A81:A166,0)),"") | N82: =IFERROR(INDEX(ChartOfAccounts!D:D,MATCH($B82,ChartOfAccounts!A81:A166,0)),"") | O82: =IFERROR(INDEX(ChartOfAccounts!F:F,MATCH($B82,ChartOfAccounts!A81:A166,0)),"") | P82: {=IFERROR(INDEX(PreparerInfo!B81:B93,MATCH($D82&$C82,PreparerInfo!A81:A93&PreparerInfo!C81:C93,0)),"")} | Q82: =IFERROR(INDEX(Source!B81:B89,MATCH('Case 4 solution'!E82,Source!A81:A89,0)),"")
A83: 2033560 | B83: 11845 | C83: 1 | D83: 101 | E83: 1002 | F83: 44004 | G83: PURE WATER TECHNOLOG | I83: -159.9 | J83: -159.9 | K83: =IFERROR(INDEX(BusinessUnits!$B:$B,MATCH($C83,BusinessUnits!$A:$A,0)),"") -> FOOD SERVICE | L83: =IFERROR(INDEX(Table1[[#All],[Description]],MATCH($C83,BusinessUnits!$A:$A,0)),"") -> Transactions related to food and beverage service. Includes all guest transactions in the hotel restaurants, catering-related transactions and food service payroll. | M83: =IFERROR(INDEX(ChartOfAccounts!B82:B167,MATCH($B83,ChartOfAccounts!A82:A167,0)),"") | N83: =IFERROR(INDEX(ChartOfAccounts!D:D,MATCH($B83,ChartOfAccounts!A82:A167,0)),"") | O83: =IFERROR(INDEX(ChartOfAccounts!F:F,MATCH($B83,ChartOfAccounts!A82:A167,0)),"") | P83: {=IFERROR(INDEX(PreparerInfo!B82:B94,MATCH($D83&$C83,PreparerInfo!A82:A94&PreparerInfo!C82:C94,0)),"")} | Q83: =IFERROR(INDEX(Source!B82:B90,MATCH('Case 4 solution'!E83,Source!A82:A90,0)),"")
A84: 2033561 | B84: 71400 | C84: 1 | D84: 101 | E84: 1002 | F84: 44004 | G84: PURE WATER TECHNOLOG | H84: 159.9 | J84: 159.9 | K84: =IFERROR(INDEX(BusinessUnits!$B:$B,MATCH($C84,BusinessUnits!$A:$A,0)),"") -> FOOD SERVICE | L84: =IFERROR(INDEX(Table1[[#All],[Description]],MATCH($C84,BusinessUnits!$A:$A,0)),"") -> Transactions related to food and beverage service. Includes all guest transactions in the hotel restaurants, catering-related transactions and food service payroll. | M84: =IFERROR(INDEX(ChartOfAccounts!B83:B168,MATCH($B84,ChartOfAccounts!A83:A168,0)),"") | N84: =IFERROR(INDEX(ChartOfAccounts!D:D,MATCH($B84,ChartOfAccounts!A83:A168,0)),"") | O84: =IFERROR(INDEX(ChartOfAccounts!F:F,MATCH($B84,ChartOfAccounts!A83:A168,0)),"") | P84: {=IFERROR(INDEX(PreparerInfo!B83:B95,MATCH($D84&$C84,PreparerInfo!A83:A95&PreparerInfo!C83:C95,0)),"")} | Q84: =IFERROR(INDEX(Source!B83:B91,MATCH('Case 4 solution'!E84,Source!A83:A91,0)),"")
A85: 2033561 | B85: 11845 | C85: 1 | D85: 101 | E85: 1002 | F85: 44004 | G85: PURE WATER TECHNOLOG | I85: -159.9 | J85: -159.9 | K85: =IFERROR(INDEX(BusinessUnits!$B:$B,MATCH($C85,BusinessUnits!$A:$A,0)),"") -> FOOD SERVICE | L85: =IFERROR(INDEX(Table1[[#All],[Description]],MATCH($C85,BusinessUnits!$A:$A,0)),"") -> Transactions related to food and beverage service. Includes all guest transactions in the hotel restaurants, catering-related transactions and food service payroll. | M85: =IFERROR(INDEX(ChartOfAccounts!B84:B169,MATCH($B85,ChartOfAccounts!A84:A169,0)),"") | N85: =IFERROR(INDEX(ChartOfAccounts!D:D,MATCH($B85,ChartOfAccounts!A84:A169,0)),"") | O85: =IFERROR(INDEX(ChartOfAccounts!F:F,MATCH($B85,ChartOfAccounts!A84:A169,0)),"") | P85: {=IFERROR(INDEX(PreparerInfo!B84:B96,MATCH($D85&$C85,PreparerInfo!A84:A96&PreparerInfo!C84:C96,0)),"")} | Q85: =IFERROR(INDEX(Source!B84:B92,MATCH('Case 4 solution'!E85,Source!A84:A92,0)),"")
A86: 2033562 | B86: 71400 | C86: 1 | D86: 101 | E86: 1002 | F86: 44004 | G86: PURE WATER TECHNOLOG | H86: 159.9 | J86: 159.9 | K86: =IFERROR(INDEX(BusinessUnits!$B:$B,MATCH($C86,BusinessUnits!$A:$A,0)),"") -> FOOD SERVICE | L86: =IFERROR(INDEX(Table1[[#All],[Description]],MATCH($C86,BusinessUnits!$A:$A,0)),"") -> Transactions related to food and beverage service. Includes all guest transactions in the hotel restaurants, catering-related transactions and food service payroll. | M86: =IFERROR(INDEX(ChartOfAccounts!B85:B170,MATCH($B86,ChartOfAccounts!A85:A170,0)),"") | N86: =IFERROR(INDEX(ChartOfAccounts!D:D,MATCH($B86,ChartOfAccounts!A85:A170,0)),"") | O86: =IFERROR(INDEX(ChartOfAccounts!F:F,MATCH($B86,ChartOfAccounts!A85:A170,0)),"") | P86: {=IFERROR(INDEX(PreparerInfo!B85:B97,MATCH($D86&$C86,PreparerInfo!A85:A97&PreparerInfo!C85:C97,0)),"")} | Q86: =IFERROR(INDEX(Source!B85:B93,MATCH('Case 4 solution'!E86,Source!A85:A93,0)),"")
A87: 2033562 | B87: 11845 | C87: 1 | D87: 101 | E87: 1002 | F87: 44004 | G87: PURE WATER TECHNOLOG | I87: -159.9 | J87: -159.9 | K87: =IFERROR(INDEX(BusinessUnits!$B:$B,MATCH($C87,BusinessUnits!$A:$A,0)),"") -> FOOD SERVICE | L87: =IFERROR(INDEX(Table1[[#All],[Description]],MATCH($C87,BusinessUnits!$A:$A,0)),"") -> Transactions related to food and beverage service. Includes all guest transactions in the hotel restaurants, catering-related transactions and food service payroll. | M87: =IFERROR(INDEX(ChartOfAccounts!B86:B171,MATCH($B87,ChartOfAccounts!A86:A171,0)),"") | N87: =IFERROR(INDEX(ChartOfAccounts!D:D,MATCH($B87,ChartOfAccounts!A86:A171,0)),"") | O87: =IFERROR(INDEX(ChartOfAccounts!F:F,MATCH($B87,ChartOfAccounts!A86:A171,0)),"") | P87: {=IFERROR(INDEX(PreparerInfo!B86:B98,MATCH($D87&$C87,PreparerInfo!A86:A98&PreparerInfo!C86:C98,0)),"")} | Q87: =IFERROR(INDEX(Source!B86:B94,MATCH('Case 4 solution'!E87,Source!A86:A94,0)),"")
A88: 2033563 | B88: 71400 | C88: 1 | D88: 101 | E88: 1002 | F88: 44004 | G88: PURE WATER TECHNOLOG | H88: 159.9 | J88: 159.9 | K88: =IFERROR(INDEX(BusinessUnits!$B:$B,MATCH($C88,BusinessUnits!$A:$A,0)),"") -> FOOD SERVICE | L88: =IFERROR(INDEX(Table1[[#All],[Description]],MATCH($C88,BusinessUnits!$A:$A,0)),"") -> Transactions related to food and beverage service. Includes all guest transactions in the hotel restaurants, catering-related transactions and food service payroll. | M88: =IFERROR(INDEX(ChartOfAccounts!B87:B172,MATCH($B88,ChartOfAccounts!A87:A172,0)),"") | N88: =IFERROR(INDEX(ChartOfAccounts!D:D,MATCH($B88,ChartOfAccounts!A87:A172,0)),"") | O88: =IFERROR(INDEX(ChartOfAccounts!F:F,MATCH($B88,ChartOfAccounts!A87:A172,0)),"") | P88: {=IFERROR(INDEX(PreparerInfo!B87:B99,MATCH($D88&$C88,PreparerInfo!A87:A99&PreparerInfo!C87:C99,0)),"")} | Q88: =IFERROR(INDEX(Source!B87:B95,MATCH('Case 4 solution'!E88,Source!A87:A95,0)),"")
A89: 2033563 | B89: 11845 | C89: 1 | D89: 101 | E89: 1002 | F89: 44004 | G89: PURE WATER TECHNOLOG | I89: -159.9 | J89: -159.9 | K89: =IFERROR(INDEX(BusinessUnits!$B:$B,MATCH($C89,BusinessUnits!$A:$A,0)),"") -> FOOD SERVICE | L89: =IFERROR(INDEX(Table1[[#All],[Description]],MATCH($C89,BusinessUnits!$A:$A,0)),"") -> Transactions related to food and beverage service. Includes all guest transactions in the hotel restaurants, catering-related transactions and food service payroll. | M89: =IFERROR(INDEX(ChartOfAccounts!B88:B173,MATCH($B89,ChartOfAccounts!A88:A173,0)),"") | N89: =IFERROR(INDEX(ChartOfAccounts!D:D,MATCH($B89,ChartOfAccounts!A88:A173,0)),"") | O89: =IFERROR(INDEX(ChartOfAccounts!F:F,MATCH($B89,ChartOfAccounts!A88:A173,0)),"") | P89: {=IFERROR(INDEX(PreparerInfo!B88:B100,MATCH($D89&$C89,PreparerInfo!A88:A100&PreparerInfo!C88:C100,0)),"")} | Q89: =IFERROR(INDEX(Source!B88:B96,MATCH('Case 4 solution'!E89,Source!A88:A96,0)),"")
A90: 2033564 | B90: 11845 | C90: 2 | D90: 104 | E90: 1003 | F90: 44004 | G90: COPELAND,MELODY | H90: 198 | J90: 198 | K90: =IFERROR(INDEX(BusinessUnits!$B:$B,MATCH($C90,BusinessUnits!$A:$A,0)),"") -> HOTEL | L90: =IFERROR(INDEX(Table1[[#All],[Description]],MATCH($C90,BusinessUnits!$A:$A,0)),"") -> Transactions related to guest rooms and overall hotel operations. Includes payroll for administrative staff, clerks and interns. | M90: =IFERROR(INDEX(ChartOfAccounts!B89:B174,MATCH($B90,ChartOfAccounts!A89:A174,0)),"") | N90: =IFERROR(INDEX(ChartOfAccounts!D:D,MATCH($B90,ChartOfAccounts!A89:A174,0)),"") | O90: =IFERROR(INDEX(ChartOfAccounts!F:F,MATCH($B90,ChartOfAccounts!A89:A174,0)),"") | P90: {=IFERROR(INDEX(PreparerInfo!B89:B101,MATCH($D90&$C90,PreparerInfo!A89:A101&PreparerInfo!C89:C101,0)),"")} | Q90: =IFERROR(INDEX(Source!B89:B97,MATCH('Case 4 solution'!E90,Source!A89:A97,0)),"")
A91: 2033564 | B91: 43180 | C91: 2 | D91: 104 | E91: 1003 | F91: 44004 | G91: COPELAND,MELODY | I91: -198 | J91: -198 | K91: =IFERROR(INDEX(BusinessUnits!$B:$B,MATCH($C91,BusinessUnits!$A:$A,0)),"") -> HOTEL | L91: =IFERROR(INDEX(Table1[[#All],[Description]],MATCH($C91,BusinessUnits!$A:$A,0)),"") -> Transactions related to guest rooms and overall hotel operations. Includes payroll for administrative staff, clerks and interns. | M91: =IFERROR(INDEX(ChartOfAccounts!B90:B175,MATCH($B91,ChartOfAccounts!A90:A175,0)),"") | N91: =IFERROR(INDEX(ChartOfAccounts!D:D,MATCH($B91,ChartOfAccounts!A90:A175,0)),"") | O91: =IFERROR(INDEX(ChartOfAccounts!F:F,MATCH($B91,ChartOfAccounts!A90:A175,0)),"") | P91: {=IFERROR(INDEX(PreparerInfo!B90:B102,MATCH($D91&$C91,PreparerInfo!A90:A102&PreparerInfo!C90:C102,0)),"")} | Q91: =IFERROR(INDEX(Source!B90:B98,MATCH('Case 4 solution'!E91,Source!A90:A98,0)),"")
A92: 2033565 | B92: 14260 | C92: 1 | D92: 101 | E92: 1002 | F92: 44004 | G92: EMILY R ANDERSON P | H92: 223 | J92: 223 | K92: =IFERROR(INDEX(BusinessUnits!$B:$B,MATCH($C92,BusinessUnits!$A:$A,0)),"") -> FOOD SERVICE | L92: =IFERROR(INDEX(Table1[[#All],[Description]],MATCH($C92,BusinessUnits!$A:$A,0)),"") -> Transactions related to food and beverage service. Includes all guest transactions in the hotel restaurants, catering-related transactions and food service payroll. | M92: =IFERROR(INDEX(ChartOfAccounts!B91:B176,MATCH($B92,ChartOfAccounts!A91:A176,0)),"") | N92: =IFERROR(INDEX(ChartOfAccounts!D:D,MATCH($B92,ChartOfAccounts!A91:A176,0)),"") | O92: =IFERROR(INDEX(ChartOfAccounts!F:F,MATCH($B92,ChartOfAccounts!A91:A176,0)),"") | P92: {=IFERROR(INDEX(PreparerInfo!B91:B103,MATCH($D92&$C92,PreparerInfo!A91:A103&PreparerInfo!C91:C103,0)),"")} | Q92: =IFERROR(INDEX(Source!B91:B99,MATCH('Case 4 solution'!E92,Source!A91:A99,0)),"")
A93: 2033565 | B93: 11845 | C93: 1 | D93: 101 | E93: 1002 | F93: 44004 | G93: EMILY R ANDERSON P | I93: -223 | J93: -223 | K93: =IFERROR(INDEX(BusinessUnits!$B:$B,MATCH($C93,BusinessUnits!$A:$A,0)),"") -> FOOD SERVICE | L93: =IFERROR(INDEX(Table1[[#All],[Description]],MATCH($C93,BusinessUnits!$A:$A,0)),"") -> Transactions related to food and beverage service. Includes all guest transactions in the hotel restaurants, catering-related transactions and food service payroll. | M93: =IFERROR(INDEX(ChartOfAccounts!B92:B177,MATCH($B93,ChartOfAccounts!A92:A177,0)),"") | N93: =IFERROR(INDEX(ChartOfAccounts!D:D,MATCH($B93,ChartOfAccounts!A92:A177,0)),"") | O93: =IFERROR(INDEX(ChartOfAccounts!F:F,MATCH($B93,ChartOfAccounts!A92:A177,0)),"") | P93: {=IFERROR(INDEX(PreparerInfo!B92:B104,MATCH($D93&$C93,PreparerInfo!A92:A104&PreparerInfo!C92:C104,0)),"")} | Q93: =IFERROR(INDEX(Source!B92:B100,MATCH('Case 4 solution'!E93,Source!A92:A100,0)),"")
A94: 2033566 | B94: 11845 | C94: 1 | D94: 102 | E94: 1003 | F94: 44004 | G94: CREDIT CARD RECEIPTS | H94: 228.59 | J94: 228.59 | K94: =IFERROR(INDEX(BusinessUnits!$B:$B,MATCH($C94,BusinessUnits!$A:$A,0)),"") -> FOOD SERVICE | L94: =IFERROR(INDEX(Table1[[#All],[Description]],MATCH($C94,BusinessUnits!$A:$A,0)),"") -> Transactions related to food and beverage service. Includes all guest transactions in the hotel restaurants, catering-related transactions and food service payroll. | M94: =IFERROR(INDEX(ChartOfAccounts!B93:B178,MATCH($B94,ChartOfAccounts!A93:A178,0)),"") | N94: =IFERROR(INDEX(ChartOfAccounts!D:D,MATCH($B94,ChartOfAccounts!A93:A178,0)),"") | O94: =IFERROR(INDEX(ChartOfAccounts!F:F,MATCH($B94,ChartOfAccounts!A93:A178,0)),"") | P94: {=IFERROR(INDEX(PreparerInfo!B93:B105,MATCH($D94&$C94,PreparerInfo!A93:A105&PreparerInfo!C93:C105,0)),"")} | Q94: =IFERROR(INDEX(Source!B93:B101,MATCH('Case 4 solution'!E94,Source!A93:A101,0)),"")
A95: 2033566 | B95: 43310 | C95: 1 | D95: 102 | E95: 1003 | F95: 44004 | G95: CREDIT CARD RECEIPTS | I95: -228.59 | J95: -228.59 | K95: =IFERROR(INDEX(BusinessUnits!$B:$B,MATCH($C95,BusinessUnits!$A:$A,0)),"") -> FOOD SERVICE | L95: =IFERROR(INDEX(Table1[[#All],[Description]],MATCH($C95,BusinessUnits!$A:$A,0)),"") -> Transactions related to food and beverage service. Includes all guest transactions in the hotel restaurants, catering-related transactions and food service payroll. | M95: =IFERROR(INDEX(ChartOfAccounts!B94:B179,MATCH($B95,ChartOfAccounts!A94:A179,0)),"") | N95: =IFERROR(INDEX(ChartOfAccounts!D:D,MATCH($B95,ChartOfAccounts!A94:A179,0)),"") | O95: =IFERROR(INDEX(ChartOfAccounts!F:F,MATCH($B95,ChartOfAccounts!A94:A179,0)),"") | P95: {=IFERROR(INDEX(PreparerInfo!B94:B106,MATCH($D95&$C95,PreparerInfo!A94:A106&PreparerInfo!C94:C106,0)),"")} | Q95: =IFERROR(INDEX(Source!B94:B102,MATCH('Case 4 solution'!E95,Source!A94:A102,0)),"")
A96: 2033567 | B96: 71400 | C96: 2 | D96: 101 | E96: 1002 | F96: 44004 | G96: ZEP SALES & 68668209 | H96: 240.73 | J96: 240.73 | K96: =IFERROR(INDEX(BusinessUnits!$B:$B,MATCH($C96,BusinessUnits!$A:$A,0)),"") -> HOTEL | L96: =IFERROR(INDEX(Table1[[#All],[Description]],MATCH($C96,BusinessUnits!$A:$A,0)),"") -> Transactions related to guest rooms and overall hotel operations. Includes payroll for administrative staff, clerks and interns. | M96: =IFERROR(INDEX(ChartOfAccounts!B95:B180,MATCH($B96,ChartOfAccounts!A95:A180,0)),"") | N96: =IFERROR(INDEX(ChartOfAccounts!D:D,MATCH($B96,ChartOfAccounts!A95:A180,0)),"") | O96: =IFERROR(INDEX(ChartOfAccounts!F:F,MATCH($B96,ChartOfAccounts!A95:A180,0)),"") | P96: {=IFERROR(INDEX(PreparerInfo!B95:B107,MATCH($D96&$C96,PreparerInfo!A95:A107&PreparerInfo!C95:C107,0)),"")} | Q96: =IFERROR(INDEX(Source!B95:B103,MATCH('Case 4 solution'!E96,Source!A95:A103,0)),"")
A97: 2033567 | B97: 11845 | C97: 2 | D97: 101 | E97: 1002 | F97: 44004 | G97: ZEP SALES & 68668209 | I97: -240.73 | J97: -240.73 | K97: =IFERROR(INDEX(BusinessUnits!$B:$B,MATCH($C97,BusinessUnits!$A:$A,0)),"") -> HOTEL | L97: =IFERROR(INDEX(Table1[[#All],[Description]],MATCH($C97,BusinessUnits!$A:$A,0)),"") -> Transactions related to guest rooms and overall hotel operations. Includes payroll for administrative staff, clerks and interns. | M97: =IFERROR(INDEX(ChartOfAccounts!B96:B181,MATCH($B97,ChartOfAccounts!A96:A181,0)),"") | N97: =IFERROR(INDEX(ChartOfAccounts!D:D,MATCH($B97,ChartOfAccounts!A96:A181,0)),"") | O97: =IFERROR(INDEX(ChartOfAccounts!F:F,MATCH($B97,ChartOfAccounts!A96:A181,0)),"") | P97: {=IFERROR(INDEX(PreparerInfo!B96:B108,MATCH($D97&$C97,PreparerInfo!A96:A108&PreparerInfo!C96:C108,0)),"")} | Q97: =IFERROR(INDEX(Source!B96:B104,MATCH('Case 4 solution'!E97,Source!A96:A104,0)),"")
A98: 2033568 | B98: 11845 | C98: 2 | D98: 104 | E98: 1003 | F98: 44004 | G98: MCCONNELL,MARCOS | H98: 258 | J98: 258 | K98: =IFERROR(INDEX(BusinessUnits!$B:$B,MATCH($C98,BusinessUnits!$A:$A,0)),"") -> HOTEL | L98: =IFERROR(INDEX(Table1[[#All],[Description]],MATCH($C98,BusinessUnits!$A:$A,0)),"") -> Transactions related to guest rooms and overall hotel operations. Includes payroll for administrative staff, clerks and interns. | M98: =IFERROR(INDEX(ChartOfAccounts!B97:B182,MATCH($B98,ChartOfAccounts!A97:A182,0)),"") | N98: =IFERROR(INDEX(ChartOfAccounts!D:D,MATCH($B98,ChartOfAccounts!A97:A182,0)),"") | O98: =IFERROR(INDEX(ChartOfAccounts!F:F,MATCH($B98,ChartOfAccounts!A97:A182,0)),"") | P98: {=IFERROR(INDEX(PreparerInfo!B97:B109,MATCH($D98&$C98,PreparerInfo!A97:A109&PreparerInfo!C97:C109,0)),"")} | Q98: =IFERROR(INDEX(Source!B97:B105,MATCH('Case 4 solution'!E98,Source!A97:A105,0)),"")
A99: 2033568 | B99: 43180 | C99: 2 | D99: 104 | E99: 1003 | F99: 44004 | G99: MCCONNELL,MARCOS | I99: -258 | J99: -258 | K99: =IFERROR(INDEX(BusinessUnits!$B:$B,MATCH($C99,BusinessUnits!$A:$A,0)),"") -> HOTEL | L99: =IFERROR(INDEX(Table1[[#All],[Description]],MATCH($C99,BusinessUnits!$A:$A,0)),"") -> Transactions related to guest rooms and overall hotel operations. Includes payroll for administrative staff, clerks and interns. | M99: =IFERROR(INDEX(ChartOfAccounts!B98:B183,MATCH($B99,ChartOfAccounts!A98:A183,0)),"") | N99: =IFERROR(INDEX(ChartOfAccounts!D:D,MATCH($B99,ChartOfAccounts!A98:A183,0)),"") | O99: =IFERROR(INDEX(ChartOfAccounts!F:F,MATCH($B99,ChartOfAccounts!A98:A183,0)),"") | P99: {=IFERROR(INDEX(PreparerInfo!B98:B110,MATCH($D99&$C99,PreparerInfo!A98:A110&PreparerInfo!C98:C110,0)),"")} | Q99: =IFERROR(INDEX(Source!B98:B106,MATCH('Case 4 solution'!E99,Source!A98:A106,0)),"")
A100: 2033569 | B100: 11845 | C100: 2 | D100: 104 | E100: 1003 | F100: 44004 | G100: CAIN,HAVEN | H100: 258 | J100: 258 | K100: =IFERROR(INDEX(BusinessUnits!$B:$B,MATCH($C100,BusinessUnits!$A:$A,0)),"") -> HOTEL | L100: =IFERROR(INDEX(Table1[[#All],[Description]],MATCH($C100,BusinessUnits!$A:$A,0)),"") -> Transactions related to guest rooms and overall hotel operations. Includes payroll for administrative staff, clerks and interns. | M100: =IFERROR(INDEX(ChartOfAccounts!B99:B184,MATCH($B100,ChartOfAccounts!A99:A184,0)),"") | N100: =IFERROR(INDEX(ChartOfAccounts!D:D,MATCH($B100,ChartOfAccounts!A99:A184,0)),"") | O100: =IFERROR(INDEX(ChartOfAccounts!F:F,MATCH($B100,ChartOfAccounts!A99:A184,0)),"") | P100: {=IFERROR(INDEX(PreparerInfo!B99:B111,MATCH($D100&$C100,PreparerInfo!A99:A111&PreparerInfo!C99:C111,0)),"")} | Q100: =IFERROR(INDEX(Source!B99:B107,MATCH('Case 4 solution'!E100,Source!A99:A107,0)),"")
...

Sheet use Xloopup
A1: JENumber | B1: GLAccountNumber | C1: BusinessUnitID | D1: PreparerID | E1: SourceID | F1: EffectiveDate | G1: JEDescription | H1: Debit | I1: Credit | J1: Amount | K1: BusinessUnit | L1: BUDescription | M1: GLAccountName | N1: AccountType | O1: AccountClass | P1: PreparerName | Q1: Source
A2: 2033520 | B2: 76930 | C2: 1 | D2: 101 | E2: 1002 | F2: 44002 | G2: TELECOM GTA JUN 2016 | H2: 36.9 | J2: 36.9 | K2: =_xlfn.XLOOKUP($C2,Table1[BusinessUnitID],Table1[BusinessUnit],"",0) -> FOOD SERVICE | L2: {=_xlfn.XLOOKUP($C2,Table1[[#All],[BusinessUnitID]],Table1[[#All],[Description]],"",0,1)} -> Transactions related to food and beverage service. Includes all guest transactions in the hotel restaurants, catering-related transactions and food service payroll. | M2: =_xlfn.XLOOKUP($B2,ChartOfAccounts!A1:A86,ChartOfAccounts!B1:B86,"",0,1) -> Telecommunications - Other | N2: =_xlfn.XLOOKUP($B2,ChartOfAccounts!A1:A86,ChartOfAccounts!D1:D86,0,1) -> Expenses | O2: =_xlfn.XLOOKUP($B2,ChartOfAccounts!A1:A86,ChartOfAccounts!F1:F86,"",0,1) -> SG&A | P2: {=_xlfn.XLOOKUP($D2&$C2,PreparerInfo!A1:A13&PreparerInfo!C1:C13,PreparerInfo!B1:B13,"",0,1)} -> Carolyn Slater|Food Operations Manager | Q2: =_xlfn.XLOOKUP($E2,Source!A1:A9,Source!B1:B9,"",0,1) -> CHECK
A3: 2033520 | B3: 11845 | C3: 1 | D3: 101 | E3: 1002 | F3: 44002 | G3: TELECOM GTA JUN 2016 | I3: -36.9 | J3: -36.9 | K3: =_xlfn.XLOOKUP($C3,Table1[BusinessUnitID],Table1[BusinessUnit],"",0) -> FOOD SERVICE | L3: {=_xlfn.XLOOKUP($C3,Table1[[#All],[BusinessUnitID]],Table1[[#All],[Description]],"",0,1)} -> Transactions related to food and beverage service. Includes all guest transactions in the hotel restaurants, catering-related transactions and food service payroll. | M3: =_xlfn.XLOOKUP($B3,ChartOfAccounts!A2:A87,ChartOfAccounts!B2:B87,"",0,1) -> Operating Bank Account | N3: =_xlfn.XLOOKUP($B3,ChartOfAccounts!A2:A87,ChartOfAccounts!D2:D87,0,1) -> Assets | O3: =_xlfn.XLOOKUP($B3,ChartOfAccounts!A2:A87,ChartOfAccounts!F2:F87,"",0,1) -> Cash | P3: {=_xlfn.XLOOKUP($D3&$C3,PreparerInfo!A2:A14&PreparerInfo!C2:C14,PreparerInfo!B2:B14,"",0,1)} -> Carolyn Slater|Food Operations Manager | Q3: =_xlfn.XLOOKUP($E3,Source!A2:A10,Source!B2:B10,"",0,1) -> CHECK
A4: 2033521 | B4: 11845 | C4: 3 | D4: 102 | E4: 1001 | F4: 44002 | G4: CASH RECEIPTS | H4: 63.1 | J4: 63.1 | K4: =_xlfn.XLOOKUP($C4,Table1[BusinessUnitID],Table1[BusinessUnit],"",0) -> HOTEL PANTRY | L4: {=_xlfn.XLOOKUP($C4,Table1[[#All],[BusinessUnitID]],Table1[[#All],[Description]],"",0,1)} -> Transactions related to the hotel convenience store, including some food and beverage costs. | M4: =_xlfn.XLOOKUP($B4,ChartOfAccounts!A3:A88,ChartOfAccounts!B3:B88,"",0,1) -> Operating Bank Account | N4: =_xlfn.XLOOKUP($B4,ChartOfAccounts!A3:A88,ChartOfAccounts!D3:D88,0,1) -> Assets | O4: =_xlfn.XLOOKUP($B4,ChartOfAccounts!A3:A88,ChartOfAccounts!F3:F88,"",0,1) -> Cash | P4: {=_xlfn.XLOOKUP($D4&$C4,PreparerInfo!A3:A15&PreparerInfo!C3:C15,PreparerInfo!B3:B15,"",0,1)} -> POS | Q4: =_xlfn.XLOOKUP($E4,Source!A3:A11,Source!B3:B11,"",0,1)
A5: 2033521 | B5: 43440 | C5: 3 | D5: 102 | E5: 1001 | F5: 44002 | G5: CASH RECEIPTS | I5: -63.1 | J5: -63.1 | K5: =_xlfn.XLOOKUP($C5,Table1[BusinessUnitID],Table1[BusinessUnit],"",0) -> HOTEL PANTRY | L5: {=_xlfn.XLOOKUP($C5,Table1[[#All],[BusinessUnitID]],Table1[[#All],[Description]],"",0,1)} -> Transactions related to the hotel convenience store, including some food and beverage costs. | M5: =_xlfn.XLOOKUP($B5,ChartOfAccounts!A4:A89,ChartOfAccounts!B4:B89,"",0,1) -> Sales - Other | N5: =_xlfn.XLOOKUP($B5,ChartOfAccounts!A4:A89,ChartOfAccounts!D4:D89,0,1) -> Revenue | O5: =_xlfn.XLOOKUP($B5,ChartOfAccounts!A4:A89,ChartOfAccounts!F4:F89,"",0,1) -> Sales-Other | P5: {=_xlfn.XLOOKUP($D5&$C5,PreparerInfo!A4:A16&PreparerInfo!C4:C16,PreparerInfo!B4:B16,"",0,1)} -> POS | Q5: =_xlfn.XLOOKUP($E5,Source!A4:A12,Source!B4:B12,"",0,1)
A6: 2033522 | B6: 11845 | C6: 1 | D6: 102 | E6: 1003 | F6: 44002 | G6: CREDIT CARD RECEIPTS | H6: 68.28 | J6: 68.28 | K6: =_xlfn.XLOOKUP($C6,Table1[BusinessUnitID],Table1[BusinessUnit],"",0) -> FOOD SERVICE | L6: {=_xlfn.XLOOKUP($C6,Table1[[#All],[BusinessUnitID]],Table1[[#All],[Description]],"",0,1)} -> Transactions related to food and beverage service. Includes all guest transactions in the hotel restaurants, catering-related transactions and food service payroll. | M6: =_xlfn.XLOOKUP($B6,ChartOfAccounts!A5:A90,ChartOfAccounts!B5:B90,"",0,1) | N6: =_xlfn.XLOOKUP($B6,ChartOfAccounts!A5:A90,ChartOfAccounts!D5:D90,0,1) -> Assets | O6: =_xlfn.XLOOKUP($B6,ChartOfAccounts!A5:A90,ChartOfAccounts!F5:F90,"",0,1) | P6: {=_xlfn.XLOOKUP($D6&$C6,PreparerInfo!A5:A17&PreparerInfo!C5:C17,PreparerInfo!B5:B17,"",0,1)} -> Elizabeth Rees|Food Operations Manager | Q6: =_xlfn.XLOOKUP($E6,Source!A5:A13,Source!B5:B13,"",0,1)
A7: 2033522 | B7: 43310 | C7: 1 | D7: 102 | E7: 1003 | F7: 44002 | G7: CREDIT CARD RECEIPTS | I7: -68.28 | J7: -68.28 | K7: =_xlfn.XLOOKUP($C7,Table1[BusinessUnitID],Table1[BusinessUnit],"",0) -> FOOD SERVICE | L7: {=_xlfn.XLOOKUP($C7,Table1[[#All],[BusinessUnitID]],Table1[[#All],[Description]],"",0,1)} -> Transactions related to food and beverage service. Includes all guest transactions in the hotel restaurants, catering-related transactions and food service payroll. | M7: =_xlfn.XLOOKUP($B7,ChartOfAccounts!A6:A91,ChartOfAccounts!B6:B91,"",0,1) -> Sales - Dining Halls | N7: =_xlfn.XLOOKUP($B7,ChartOfAccounts!A6:A91,ChartOfAccounts!D6:D91,0,1) -> Revenue | O7: =_xlfn.XLOOKUP($B7,ChartOfAccounts!A6:A91,ChartOfAccounts!F6:F91,"",0,1) -> Sales-Dining | P7: {=_xlfn.XLOOKUP($D7&$C7,PreparerInfo!A6:A18&PreparerInfo!C6:C18,PreparerInfo!B6:B18,"",0,1)} -> Elizabeth Rees|Food Operations Manager | Q7: =_xlfn.XLOOKUP($E7,Source!A6:A14,Source!B6:B14,"",0,1)
A8: 2033523 | B8: 11845 | C8: 2 | D8: 106 | E8: 1003 | F8: 44002 | G8: CONFERENCE - HOTEL | H8: 99 | J8: 99 | K8: =_xlfn.XLOOKUP($C8,Table1[BusinessUnitID],Table1[BusinessUnit],"",0) -> HOTEL | L8: {=_xlfn.XLOOKUP($C8,Table1[[#All],[BusinessUnitID]],Table1[[#All],[Description]],"",0,1)} -> Transactions related to guest rooms and overall hotel operations. Includes payroll for administrative staff, clerks and interns. | M8: =_xlfn.XLOOKUP($B8,ChartOfAccounts!A7:A92,ChartOfAccounts!B7:B92,"",0,1) | N8: =_xlfn.XLOOKUP($B8,ChartOfAccounts!A7:A92,ChartOfAccounts!D7:D92,0,1) -> Assets | O8: =_xlfn.XLOOKUP($B8,ChartOfAccounts!A7:A92,ChartOfAccounts!F7:F92,"",0,1) | P8: {=_xlfn.XLOOKUP($D8&$C8,PreparerInfo!A7:A19&PreparerInfo!C7:C19,PreparerInfo!B7:B19,"",0,1)} -> Yvonne Chapman|Catering Manager | Q8: =_xlfn.XLOOKUP($E8,Source!A7:A15,Source!B7:B15,"",0,1)
A9: 2033523 | B9: 43180 | C9: 2 | D9: 106 | E9: 1003 | F9: 44002 | G9: CONFERENCE - HOTEL | I9: -99 | J9: -99 | K9: =_xlfn.XLOOKUP($C9,Table1[BusinessUnitID],Table1[BusinessUnit],"",0) -> HOTEL | L9: {=_xlfn.XLOOKUP($C9,Table1[[#All],[BusinessUnitID]],Table1[[#All],[Description]],"",0,1)} -> Transactions related to guest rooms and overall hotel operations. Includes payroll for administrative staff, clerks and interns. | M9: =_xlfn.XLOOKUP($B9,ChartOfAccounts!A8:A93,ChartOfAccounts!B8:B93,"",0,1) -> Rents - Hotels | N9: =_xlfn.XLOOKUP($B9,ChartOfAccounts!A8:A93,ChartOfAccounts!D8:D93,0,1) -> Revenue | O9: =_xlfn.XLOOKUP($B9,ChartOfAccounts!A8:A93,ChartOfAccounts!F8:F93,"",0,1) -> Sales-Hotel | P9: {=_xlfn.XLOOKUP($D9&$C9,PreparerInfo!A8:A20&PreparerInfo!C8:C20,PreparerInfo!B8:B20,"",0,1)} -> Yvonne Chapman|Catering Manager | Q9: =_xlfn.XLOOKUP($E9,Source!A8:A16,Source!B8:B16,"",0,1)
A10: 2033524 | B10: 11845 | C10: 3 | D10: 102 | E10: 1003 | F10: 44002 | G10: CREDIT CARD RECEIPTS | H10: 107.21 | J10: 107.21 | K10: =_xlfn.XLOOKUP($C10,Table1[BusinessUnitID],Table1[BusinessUnit],"",0) -> HOTEL PANTRY | L10: {=_xlfn.XLOOKUP($C10,Table1[[#All],[BusinessUnitID]],Table1[[#All],[Description]],"",0,1)} -> Transactions related to the hotel convenience store, including some food and beverage costs. | M10: =_xlfn.XLOOKUP($B10,ChartOfAccounts!A9:A94,ChartOfAccounts!B9:B94,"",0,1) | N10: =_xlfn.XLOOKUP($B10,ChartOfAccounts!A9:A94,ChartOfAccounts!D9:D94,0,1) -> Assets | O10: =_xlfn.XLOOKUP($B10,ChartOfAccounts!A9:A94,ChartOfAccounts!F9:F94,"",0,1) | P10: {=_xlfn.XLOOKUP($D10&$C10,PreparerInfo!A9:A21&PreparerInfo!C9:C21,PreparerInfo!B9:B21,"",0,1)} -> POS | Q10: =_xlfn.XLOOKUP($E10,Source!A9:A17,Source!B9:B17,"",0,1)
A11: 2033524 | B11: 43440 | C11: 3 | D11: 102 | E11: 1003 | F11: 44002 | G11: CREDIT CARD RECEIPTS | I11: -107.21 | J11: -107.21 | K11: =_xlfn.XLOOKUP($C11,Table1[BusinessUnitID],Table1[BusinessUnit],"",0) -> HOTEL PANTRY | L11: {=_xlfn.XLOOKUP($C11,Table1[[#All],[BusinessUnitID]],Table1[[#All],[Description]],"",0,1)} -> Transactions related to the hotel convenience store, including some food and beverage costs. | M11: =_xlfn.XLOOKUP($B11,ChartOfAccounts!A10:A95,ChartOfAccounts!B10:B95,"",0,1) -> Sales - Other | N11: =_xlfn.XLOOKUP($B11,ChartOfAccounts!A10:A95,ChartOfAccounts!D10:D95,0,1) -> Revenue | O11: =_xlfn.XLOOKUP($B11,ChartOfAccounts!A10:A95,ChartOfAccounts!F10:F95,"",0,1) -> Sales-Other | P11: {=_xlfn.XLOOKUP($D11&$C11,PreparerInfo!A10:A22&PreparerInfo!C10:C22,PreparerInfo!B10:B22,"",0,1)} | Q11: =_xlfn.XLOOKUP($E11,Source!A10:A18,Source!B10:B18,"",0,1)
A12: 2033525 | B12: 11845 | C12: 2 | D12: 104 | E12: 1003 | F12: 44002 | G12: HENDERSON,KENNY | H12: 129 | J12: 129 | K12: =_xlfn.XLOOKUP($C12,Table1[BusinessUnitID],Table1[BusinessUnit],"",0) -> HOTEL | L12: {=_xlfn.XLOOKUP($C12,Table1[[#All],[BusinessUnitID]],Table1[[#All],[Description]],"",0,1)} -> Transactions related to guest rooms and overall hotel operations. Includes payroll for administrative staff, clerks and interns. | M12: =_xlfn.XLOOKUP($B12,ChartOfAccounts!A11:A96,ChartOfAccounts!B11:B96,"",0,1) | N12: =_xlfn.XLOOKUP($B12,ChartOfAccounts!A11:A96,ChartOfAccounts!D11:D96,0,1) -> Assets | O12: =_xlfn.XLOOKUP($B12,ChartOfAccounts!A11:A96,ChartOfAccounts!F11:F96,"",0,1) | P12: {=_xlfn.XLOOKUP($D12&$C12,PreparerInfo!A11:A23&PreparerInfo!C11:C23,PreparerInfo!B11:B23,"",0,1)} -> GUESTSYS | Q12: =_xlfn.XLOOKUP($E12,Source!A11:A19,Source!B11:B19,"",0,1)
A13: 2033525 | B13: 43180 | C13: 2 | D13: 104 | E13: 1003 | F13: 44002 | G13: HENDERSON,KENNY | I13: -129 | J13: -129 | K13: =_xlfn.XLOOKUP($C13,Table1[BusinessUnitID],Table1[BusinessUnit],"",0) -> HOTEL | L13: {=_xlfn.XLOOKUP($C13,Table1[[#All],[BusinessUnitID]],Table1[[#All],[Description]],"",0,1)} -> Transactions related to guest rooms and overall hotel operations. Includes payroll for administrative staff, clerks and interns. | M13: =_xlfn.XLOOKUP($B13,ChartOfAccounts!A12:A97,ChartOfAccounts!B12:B97,"",0,1) -> Rents - Hotels | N13: =_xlfn.XLOOKUP($B13,ChartOfAccounts!A12:A97,ChartOfAccounts!D12:D97,0,1) -> Revenue | O13: =_xlfn.XLOOKUP($B13,ChartOfAccounts!A12:A97,ChartOfAccounts!F12:F97,"",0,1) -> Sales-Hotel | P13: {=_xlfn.XLOOKUP($D13&$C13,PreparerInfo!A12:A24&PreparerInfo!C12:C24,PreparerInfo!B12:B24,"",0,1)} | Q13: =_xlfn.XLOOKUP($E13,Source!A12:A20,Source!B12:B20,"",0,1)
A14: 2033526 | B14: 11845 | C14: 2 | D14: 104 | E14: 1003 | F14: 44002 | G14: GENTRY,NIA | H14: 258 | J14: 258 | K14: =_xlfn.XLOOKUP($C14,Table1[BusinessUnitID],Table1[BusinessUnit],"",0) -> HOTEL | L14: {=_xlfn.XLOOKUP($C14,Table1[[#All],[BusinessUnitID]],Table1[[#All],[Description]],"",0,1)} -> Transactions related to guest rooms and overall hotel operations. Includes payroll for administrative staff, clerks and interns. | M14: =_xlfn.XLOOKUP($B14,ChartOfAccounts!A13:A98,ChartOfAccounts!B13:B98,"",0,1) | N14: =_xlfn.XLOOKUP($B14,ChartOfAccounts!A13:A98,ChartOfAccounts!D13:D98,0,1) -> Assets | O14: =_xlfn.XLOOKUP($B14,ChartOfAccounts!A13:A98,ChartOfAccounts!F13:F98,"",0,1) | P14: {=_xlfn.XLOOKUP($D14&$C14,PreparerInfo!A13:A25&PreparerInfo!C13:C25,PreparerInfo!B13:B25,"",0,1)} | Q14: =_xlfn.XLOOKUP($E14,Source!A13:A21,Source!B13:B21,"",0,1)
A15: 2033526 | B15: 43180 | C15: 2 | D15: 104 | E15: 1003 | F15: 44002 | G15: GENTRY,NIA | I15: -258 | J15: -258 | K15: =_xlfn.XLOOKUP($C15,Table1[BusinessUnitID],Table1[BusinessUnit],"",0) -> HOTEL | L15: {=_xlfn.XLOOKUP($C15,Table1[[#All],[BusinessUnitID]],Table1[[#All],[Description]],"",0,1)} -> Transactions related to guest rooms and overall hotel operations. Includes payroll for administrative staff, clerks and interns. | M15: =_xlfn.XLOOKUP($B15,ChartOfAccounts!A14:A99,ChartOfAccounts!B14:B99,"",0,1) -> Rents - Hotels | N15: =_xlfn.XLOOKUP($B15,ChartOfAccounts!A14:A99,ChartOfAccounts!D14:D99,0,1) -> Revenue | O15: =_xlfn.XLOOKUP($B15,ChartOfAccounts!A14:A99,ChartOfAccounts!F14:F99,"",0,1) -> Sales-Hotel | P15: {=_xlfn.XLOOKUP($D15&$C15,PreparerInfo!A14:A26&PreparerInfo!C14:C26,PreparerInfo!B14:B26,"",0,1)} | Q15: =_xlfn.XLOOKUP($E15,Source!A14:A22,Source!B14:B22,"",0,1)
A16: 2033527 | B16: 11845 | C16: 2 | D16: 104 | E16: 1003 | F16: 44002 | G16: HODGES,CHAYA | H16: 418 | J16: 418 | K16: =_xlfn.XLOOKUP($C16,Table1[BusinessUnitID],Table1[BusinessUnit],"",0) -> HOTEL | L16: {=_xlfn.XLOOKUP($C16,Table1[[#All],[BusinessUnitID]],Table1[[#All],[Description]],"",0,1)} -> Transactions related to guest rooms and overall hotel operations. Includes payroll for administrative staff, clerks and interns. | M16: =_xlfn.XLOOKUP($B16,ChartOfAccounts!A15:A100,ChartOfAccounts!B15:B100,"",0,1) | N16: =_xlfn.XLOOKUP($B16,ChartOfAccounts!A15:A100,ChartOfAccounts!D15:D100,0,1) -> Liabilities | O16: =_xlfn.XLOOKUP($B16,ChartOfAccounts!A15:A100,ChartOfAccounts!F15:F100,"",0,1) | P16: {=_xlfn.XLOOKUP($D16&$C16,PreparerInfo!A15:A27&PreparerInfo!C15:C27,PreparerInfo!B15:B27,"",0,1)} | Q16: =_xlfn.XLOOKUP($E16,Source!A15:A23,Source!B15:B23,"",0,1)
A17: 2033527 | B17: 43180 | C17: 2 | D17: 104 | E17: 1003 | F17: 44002 | G17: HODGES,CHAYA | I17: -418 | J17: -418 | K17: =_xlfn.XLOOKUP($C17,Table1[BusinessUnitID],Table1[BusinessUnit],"",0) -> HOTEL | L17: {=_xlfn.XLOOKUP($C17,Table1[[#All],[BusinessUnitID]],Table1[[#All],[Description]],"",0,1)} -> Transactions related to guest rooms and overall hotel operations. Includes payroll for administrative staff, clerks and interns. | M17: =_xlfn.XLOOKUP($B17,ChartOfAccounts!A16:A101,ChartOfAccounts!B16:B101,"",0,1) -> Rents - Hotels | N17: =_xlfn.XLOOKUP($B17,ChartOfAccounts!A16:A101,ChartOfAccounts!D16:D101,0,1) -> Revenue | O17: =_xlfn.XLOOKUP($B17,ChartOfAccounts!A16:A101,ChartOfAccounts!F16:F101,"",0,1) -> Sales-Hotel | P17: {=_xlfn.XLOOKUP($D17&$C17,PreparerInfo!A16:A28&PreparerInfo!C16:C28,PreparerInfo!B16:B28,"",0,1)} | Q17: =_xlfn.XLOOKUP($E17,Source!A16:A24,Source!B16:B24,"",0,1)
A18: 2033528 | B18: 71900 | C18: 1 | D18: 102 | E18: 1002 | F18: 44002 | G18: ALSCO INC | H18: 431.8 | J18: 431.8 | K18: =_xlfn.XLOOKUP($C18,Table1[BusinessUnitID],Table1[BusinessUnit],"",0) -> FOOD SERVICE | L18: {=_xlfn.XLOOKUP($C18,Table1[[#All],[BusinessUnitID]],Table1[[#All],[Description]],"",0,1)} -> Transactions related to food and beverage service. Includes all guest transactions in the hotel restaurants, catering-related transactions and food service payroll. | M18: =_xlfn.XLOOKUP($B18,ChartOfAccounts!A17:A102,ChartOfAccounts!B17:B102,"",0,1) -> Rents - Other Than Real Estate | N18: =_xlfn.XLOOKUP($B18,ChartOfAccounts!A17:A102,ChartOfAccounts!D17:D102,0,1) -> Expenses | O18: =_xlfn.XLOOKUP($B18,ChartOfAccounts!A17:A102,ChartOfAccounts!F17:F102,"",0,1) -> SG&A | P18: {=_xlfn.XLOOKUP($D18&$C18,PreparerInfo!A17:A29&PreparerInfo!C17:C29,PreparerInfo!B17:B29,"",0,1)} | Q18: =_xlfn.XLOOKUP($E18,Source!A17:A25,Source!B17:B25,"",0,1)
A19: 2033528 | B19: 11845 | C19: 1 | D19: 102 | E19: 1002 | F19: 44002 | G19: ALSCO INC | I19: -431.8 | J19: -431.8 | K19: =_xlfn.XLOOKUP($C19,Table1[BusinessUnitID],Table1[BusinessUnit],"",0) -> FOOD SERVICE | L19: {=_xlfn.XLOOKUP($C19,Table1[[#All],[BusinessUnitID]],Table1[[#All],[Description]],"",0,1)} -> Transactions related to food and beverage service. Includes all guest transactions in the hotel restaurants, catering-related transactions and food service payroll. | M19: =_xlfn.XLOOKUP($B19,ChartOfAccounts!A18:A103,ChartOfAccounts!B18:B103,"",0,1) | N19: =_xlfn.XLOOKUP($B19,ChartOfAccounts!A18:A103,ChartOfAccounts!D18:D103,0,1) -> Liabilities | O19: =_xlfn.XLOOKUP($B19,ChartOfAccounts!A18:A103,ChartOfAccounts!F18:F103,"",0,1) | P19: {=_xlfn.XLOOKUP($D19&$C19,PreparerInfo!A18:A30&PreparerInfo!C18:C30,PreparerInfo!B18:B30,"",0,1)} | Q19: =_xlfn.XLOOKUP($E19,Source!A18:A26,Source!B18:B26,"",0,1)
A20: 2033529 | B20: 11845 | C20: 1 | D20: 102 | E20: 1001 | F20: 44002 | G20: CASH RECEIPTS | H20: 612.54 | J20: 612.54 | K20: =_xlfn.XLOOKUP($C20,Table1[BusinessUnitID],Table1[BusinessUnit],"",0) -> FOOD SERVICE | L20: {=_xlfn.XLOOKUP($C20,Table1[[#All],[BusinessUnitID]],Table1[[#All],[Description]],"",0,1)} -> Transactions related to food and beverage service. Includes all guest transactions in the hotel restaurants, catering-related transactions and food service payroll. | M20: =_xlfn.XLOOKUP($B20,ChartOfAccounts!A19:A104,ChartOfAccounts!B19:B104,"",0,1) | N20: =_xlfn.XLOOKUP($B20,ChartOfAccounts!A19:A104,ChartOfAccounts!D19:D104,0,1) -> Equity | O20: =_xlfn.XLOOKUP($B20,ChartOfAccounts!A19:A104,ChartOfAccounts!F19:F104,"",0,1) | P20: {=_xlfn.XLOOKUP($D20&$C20,PreparerInfo!A19:A31&PreparerInfo!C19:C31,PreparerInfo!B19:B31,"",0,1)} | Q20: =_xlfn.XLOOKUP($E20,Source!A19:A27,Source!B19:B27,"",0,1)
A21: 2033529 | B21: 43310 | C21: 1 | D21: 102 | E21: 1001 | F21: 44002 | G21: CASH RECEIPTS | I21: -612.54 | J21: -612.54 | K21: =_xlfn.XLOOKUP($C21,Table1[BusinessUnitID],Table1[BusinessUnit],"",0) -> FOOD SERVICE | L21: {=_xlfn.XLOOKUP($C21,Table1[[#All],[BusinessUnitID]],Table1[[#All],[Description]],"",0,1)} -> Transactions related to food and beverage service. Includes all guest transactions in the hotel restaurants, catering-related transactions and food service payroll. | M21: =_xlfn.XLOOKUP($B21,ChartOfAccounts!A20:A105,ChartOfAccounts!B20:B105,"",0,1) -> Sales - Dining Halls | N21: =_xlfn.XLOOKUP($B21,ChartOfAccounts!A20:A105,ChartOfAccounts!D20:D105,0,1) -> Revenue | O21: =_xlfn.XLOOKUP($B21,ChartOfAccounts!A20:A105,ChartOfAccounts!F20:F105,"",0,1) -> Sales-Dining | P21: {=_xlfn.XLOOKUP($D21&$C21,PreparerInfo!A20:A32&PreparerInfo!C20:C32,PreparerInfo!B20:B32,"",0,1)} | Q21: =_xlfn.XLOOKUP($E21,Source!A20:A28,Source!B20:B28,"",0,1)
A22: 2033530 | B22: 76930 | C22: 2 | D22: 101 | E22: 1002 | F22: 44002 | G22: TELECOM GTA JUN 2016 | H22: 1015.21 | J22: 1015.21 | K22: =_xlfn.XLOOKUP($C22,Table1[BusinessUnitID],Table1[BusinessUnit],"",0) -> HOTEL | L22: {=_xlfn.XLOOKUP($C22,Table1[[#All],[BusinessUnitID]],Table1[[#All],[Description]],"",0,1)} -> Transactions related to guest rooms and overall hotel operations. Includes payroll for administrative staff, clerks and interns. | M22: =_xlfn.XLOOKUP($B22,ChartOfAccounts!A21:A106,ChartOfAccounts!B21:B106,"",0,1) -> Telecommunications - Other | N22: =_xlfn.XLOOKUP($B22,ChartOfAccounts!A21:A106,ChartOfAccounts!D21:D106,0,1) -> Expenses | O22: =_xlfn.XLOOKUP($B22,ChartOfAccounts!A21:A106,ChartOfAccounts!F21:F106,"",0,1) -> SG&A | P22: {=_xlfn.XLOOKUP($D22&$C22,PreparerInfo!A21:A33&PreparerInfo!C21:C33,PreparerInfo!B21:B33,"",0,1)} | Q22: =_xlfn.XLOOKUP($E22,Source!A21:A29,Source!B21:B29,"",0,1)
A23: 2033530 | B23: 11845 | C23: 2 | D23: 101 | E23: 1002 | F23: 44002 | G23: TELECOM GTA JUN 2016 | I23: -1015.21 | J23: -1015.21 | K23: =_xlfn.XLOOKUP($C23,Table1[BusinessUnitID],Table1[BusinessUnit],"",0) -> HOTEL | L23: {=_xlfn.XLOOKUP($C23,Table1[[#All],[BusinessUnitID]],Table1[[#All],[Description]],"",0,1)} -> Transactions related to guest rooms and overall hotel operations. Includes payroll for administrative staff, clerks and interns. | M23: =_xlfn.XLOOKUP($B23,ChartOfAccounts!A22:A107,ChartOfAccounts!B22:B107,"",0,1) | N23: =_xlfn.XLOOKUP($B23,ChartOfAccounts!A22:A107,ChartOfAccounts!D22:D107,0,1) -> Revenue | O23: =_xlfn.XLOOKUP($B23,ChartOfAccounts!A22:A107,ChartOfAccounts!F22:F107,"",0,1) | P23: {=_xlfn.XLOOKUP($D23&$C23,PreparerInfo!A22:A34&PreparerInfo!C22:C34,PreparerInfo!B22:B34,"",0,1)} | Q23: =_xlfn.XLOOKUP($E23,Source!A22:A30,Source!B22:B30,"",0,1)
A24: 2033531 | B24: 11845 | C24: 1 | D24: 102 | E24: 1003 | F24: 44002 | G24: CREDIT CARD RECEIPTS | H24: 2157.22 | J24: 2157.22 | K24: =_xlfn.XLOOKUP($C24,Table1[BusinessUnitID],Table1[BusinessUnit],"",0) -> FOOD SERVICE | L24: {=_xlfn.XLOOKUP($C24,Table1[[#All],[BusinessUnitID]],Table1[[#All],[Description]],"",0,1)} -> Transactions related to food and beverage service. Includes all guest transactions in the hotel restaurants, catering-related transactions and food service payroll. | M24: =_xlfn.XLOOKUP($B24,ChartOfAccounts!A23:A108,ChartOfAccounts!B23:B108,"",0,1) | N24: =_xlfn.XLOOKUP($B24,ChartOfAccounts!A23:A108,ChartOfAccounts!D23:D108,0,1) -> Revenue | O24: =_xlfn.XLOOKUP($B24,ChartOfAccounts!A23:A108,ChartOfAccounts!F23:F108,"",0,1) | P24: {=_xlfn.XLOOKUP($D24&$C24,PreparerInfo!A23:A35&PreparerInfo!C23:C35,PreparerInfo!B23:B35,"",0,1)} | Q24: =_xlfn.XLOOKUP($E24,Source!A23:A31,Source!B23:B31,"",0,1)
A25: 2033531 | B25: 43310 | C25: 1 | D25: 102 | E25: 1003 | F25: 44002 | G25: CREDIT CARD RECEIPTS | I25: -2157.22 | J25: -2157.22 | K25: =_xlfn.XLOOKUP($C25,Table1[BusinessUnitID],Table1[BusinessUnit],"",0) -> FOOD SERVICE | L25: {=_xlfn.XLOOKUP($C25,Table1[[#All],[BusinessUnitID]],Table1[[#All],[Description]],"",0,1)} -> Transactions related to food and beverage service. Includes all guest transactions in the hotel restaurants, catering-related transactions and food service payroll. | M25: =_xlfn.XLOOKUP($B25,ChartOfAccounts!A24:A109,ChartOfAccounts!B24:B109,"",0,1) | N25: =_xlfn.XLOOKUP($B25,ChartOfAccounts!A24:A109,ChartOfAccounts!D24:D109,0,1) -> Revenue | O25: =_xlfn.XLOOKUP($B25,ChartOfAccounts!A24:A109,ChartOfAccounts!F24:F109,"",0,1) | P25: {=_xlfn.XLOOKUP($D25&$C25,PreparerInfo!A24:A36&PreparerInfo!C24:C36,PreparerInfo!B24:B36,"",0,1)} | Q25: =_xlfn.XLOOKUP($E25,Source!A24:A32,Source!B24:B32,"",0,1)
A26: 2033532 | B26: 11845 | C26: 1 | D26: 106 | E26: 1003 | F26: 44002 | G26: CONFERENCE - FOOD SERVICE | H26: 4503.3 | J26: 4503.3 | K26: =_xlfn.XLOOKUP($C26,Table1[BusinessUnitID],Table1[BusinessUnit],"",0) -> FOOD SERVICE | L26: {=_xlfn.XLOOKUP($C26,Table1[[#All],[BusinessUnitID]],Table1[[#All],[Description]],"",0,1)} -> Transactions related to food and beverage service. Includes all guest transactions in the hotel restaurants, catering-related transactions and food service payroll. | M26: =_xlfn.XLOOKUP($B26,ChartOfAccounts!A25:A110,ChartOfAccounts!B25:B110,"",0,1) | N26: =_xlfn.XLOOKUP($B26,ChartOfAccounts!A25:A110,ChartOfAccounts!D25:D110,0,1) -> Revenue | O26: =_xlfn.XLOOKUP($B26,ChartOfAccounts!A25:A110,ChartOfAccounts!F25:F110,"",0,1) | P26: {=_xlfn.XLOOKUP($D26&$C26,PreparerInfo!A25:A37&PreparerInfo!C25:C37,PreparerInfo!B25:B37,"",0,1)} | Q26: =_xlfn.XLOOKUP($E26,Source!A25:A33,Source!B25:B33,"",0,1)
A27: 2033532 | B27: 43310 | C27: 1 | D27: 106 | E27: 1003 | F27: 44002 | G27: CONFERENCE - FOOD SERVICE | I27: -4503.3 | J27: -4503.3 | K27: =_xlfn.XLOOKUP($C27,Table1[BusinessUnitID],Table1[BusinessUnit],"",0) -> FOOD SERVICE | L27: {=_xlfn.XLOOKUP($C27,Table1[[#All],[BusinessUnitID]],Table1[[#All],[Description]],"",0,1)} -> Transactions related to food and beverage service. Includes all guest transactions in the hotel restaurants, catering-related transactions and food service payroll. | M27: =_xlfn.XLOOKUP($B27,ChartOfAccounts!A26:A111,ChartOfAccounts!B26:B111,"",0,1) | N27: =_xlfn.XLOOKUP($B27,ChartOfAccounts!A26:A111,ChartOfAccounts!D26:D111,0,1) -> Revenue | O27: =_xlfn.XLOOKUP($B27,ChartOfAccounts!A26:A111,ChartOfAccounts!F26:F111,"",0,1) | P27: {=_xlfn.XLOOKUP($D27&$C27,PreparerInfo!A26:A38&PreparerInfo!C26:C38,PreparerInfo!B26:B38,"",0,1)} | Q27: =_xlfn.XLOOKUP($E27,Source!A26:A34,Source!B26:B34,"",0,1)
A28: 2033533 | B28: 11845 | C28: 2 | D28: 104 | E28: 1003 | F28: 44002 | G28: CREDIT CARD RECEIPTS | H28: 6197 | J28: 6197 | K28: =_xlfn.XLOOKUP($C28,Table1[BusinessUnitID],Table1[BusinessUnit],"",0) -> HOTEL | L28: {=_xlfn.XLOOKUP($C28,Table1[[#All],[BusinessUnitID]],Table1[[#All],[Description]],"",0,1)} -> Transactions related to guest rooms and overall hotel operations. Includes payroll for administrative staff, clerks and interns. | M28: =_xlfn.XLOOKUP($B28,ChartOfAccounts!A27:A112,ChartOfAccounts!B27:B112,"",0,1) | N28: =_xlfn.XLOOKUP($B28,ChartOfAccounts!A27:A112,ChartOfAccounts!D27:D112,0,1) -> Expenses | O28: =_xlfn.XLOOKUP($B28,ChartOfAccounts!A27:A112,ChartOfAccounts!F27:F112,"",0,1) | P28: {=_xlfn.XLOOKUP($D28&$C28,PreparerInfo!A27:A39&PreparerInfo!C27:C39,PreparerInfo!B27:B39,"",0,1)} | Q28: =_xlfn.XLOOKUP($E28,Source!A27:A35,Source!B27:B35,"",0,1)
A29: 2033533 | B29: 43180 | C29: 2 | D29: 104 | E29: 1003 | F29: 44002 | G29: CREDIT CARD RECEIPTS | I29: -6197 | J29: -6197 | K29: =_xlfn.XLOOKUP($C29,Table1[BusinessUnitID],Table1[BusinessUnit],"",0) -> HOTEL | L29: {=_xlfn.XLOOKUP($C29,Table1[[#All],[BusinessUnitID]],Table1[[#All],[Description]],"",0,1)} -> Transactions related to guest rooms and overall hotel operations. Includes payroll for administrative staff, clerks and interns. | M29: =_xlfn.XLOOKUP($B29,ChartOfAccounts!A28:A113,ChartOfAccounts!B28:B113,"",0,1) | N29: =_xlfn.XLOOKUP($B29,ChartOfAccounts!A28:A113,ChartOfAccounts!D28:D113,0,1) -> Expenses | O29: =_xlfn.XLOOKUP($B29,ChartOfAccounts!A28:A113,ChartOfAccounts!F28:F113,"",0,1) | P29: {=_xlfn.XLOOKUP($D29&$C29,PreparerInfo!A28:A40&PreparerInfo!C28:C40,PreparerInfo!B28:B40,"",0,1)} | Q29: =_xlfn.XLOOKUP($E29,Source!A28:A36,Source!B28:B36,"",0,1)
A30: 2033534 | B30: 71400 | C30: 2 | D30: 101 | E30: 1002 | F30: 44002 | G30: PARKING SERVICES OF AMERICA | H30: 26770 | J30: 26770 | K30: =_xlfn.XLOOKUP($C30,Table1[BusinessUnitID],Table1[BusinessUnit],"",0) -> HOTEL | L30: {=_xlfn.XLOOKUP($C30,Table1[[#All],[BusinessUnitID]],Table1[[#All],[Description]],"",0,1)} -> Transactions related to guest rooms and overall hotel operations. Includes payroll for administrative staff, clerks and interns. | M30: =_xlfn.XLOOKUP($B30,ChartOfAccounts!A29:A114,ChartOfAccounts!B29:B114,"",0,1) -> Supplies and Materials | N30: =_xlfn.XLOOKUP($B30,ChartOfAccounts!A29:A114,ChartOfAccounts!D29:D114,0,1) -> Expenses | O30: =_xlfn.XLOOKUP($B30,ChartOfAccounts!A29:A114,ChartOfAccounts!F29:F114,"",0,1) -> SG&A | P30: {=_xlfn.XLOOKUP($D30&$C30,PreparerInfo!A29:A41&PreparerInfo!C29:C41,PreparerInfo!B29:B41,"",0,1)} | Q30: =_xlfn.XLOOKUP($E30,Source!A29:A37,Source!B29:B37,"",0,1)
A31: 2033534 | B31: 11845 | C31: 2 | D31: 101 | E31: 1002 | F31: 44002 | G31: PARKING SERVICES OF AMERICA | I31: -26770 | J31: -26770 | K31: =_xlfn.XLOOKUP($C31,Table1[BusinessUnitID],Table1[BusinessUnit],"",0) -> HOTEL | L31: {=_xlfn.XLOOKUP($C31,Table1[[#All],[BusinessUnitID]],Table1[[#All],[Description]],"",0,1)} -> Transactions related to guest rooms and overall hotel operations. Includes payroll for administrative staff, clerks and interns. | M31: =_xlfn.XLOOKUP($B31,ChartOfAccounts!A30:A115,ChartOfAccounts!B30:B115,"",0,1) | N31: =_xlfn.XLOOKUP($B31,ChartOfAccounts!A30:A115,ChartOfAccounts!D30:D115,0,1) -> Expenses | O31: =_xlfn.XLOOKUP($B31,ChartOfAccounts!A30:A115,ChartOfAccounts!F30:F115,"",0,1) | P31: {=_xlfn.XLOOKUP($D31&$C31,PreparerInfo!A30:A42&PreparerInfo!C30:C42,PreparerInfo!B30:B42,"",0,1)} | Q31: =_xlfn.XLOOKUP($E31,Source!A30:A38,Source!B30:B38,"",0,1)
A32: 2033535 | B32: 11845 | C32: 3 | D32: 102 | E32: 1001 | F32: 44003 | G32: CASH RECEIPTS | H32: 38.29 | J32: 38.29 | K32: =_xlfn.XLOOKUP($C32,Table1[BusinessUnitID],Table1[BusinessUnit],"",0) -> HOTEL PANTRY | L32: {=_xlfn.XLOOKUP($C32,Table1[[#All],[BusinessUnitID]],Table1[[#All],[Description]],"",0,1)} -> Transactions related to the hotel convenience store, including some food and beverage costs. | M32: =_xlfn.XLOOKUP($B32,ChartOfAccounts!A31:A116,ChartOfAccounts!B31:B116,"",0,1) | N32: =_xlfn.XLOOKUP($B32,ChartOfAccounts!A31:A116,ChartOfAccounts!D31:D116,0,1) -> Expenses | O32: =_xlfn.XLOOKUP($B32,ChartOfAccounts!A31:A116,ChartOfAccounts!F31:F116,"",0,1) | P32: {=_xlfn.XLOOKUP($D32&$C32,PreparerInfo!A31:A43&PreparerInfo!C31:C43,PreparerInfo!B31:B43,"",0,1)} | Q32: =_xlfn.XLOOKUP($E32,Source!A31:A39,Source!B31:B39,"",0,1)
A33: 2033535 | B33: 43440 | C33: 3 | D33: 102 | E33: 1001 | F33: 44003 | G33: CASH RECEIPTS | I33: -38.29 | J33: -38.29 | K33: =_xlfn.XLOOKUP($C33,Table1[BusinessUnitID],Table1[BusinessUnit],"",0) -> HOTEL PANTRY | L33: {=_xlfn.XLOOKUP($C33,Table1[[#All],[BusinessUnitID]],Table1[[#All],[Description]],"",0,1)} -> Transactions related to the hotel convenience store, including some food and beverage costs. | M33: =_xlfn.XLOOKUP($B33,ChartOfAccounts!A32:A117,ChartOfAccounts!B32:B117,"",0,1) | N33: =_xlfn.XLOOKUP($B33,ChartOfAccounts!A32:A117,ChartOfAccounts!D32:D117,0,1) -> Expenses | O33: =_xlfn.XLOOKUP($B33,ChartOfAccounts!A32:A117,ChartOfAccounts!F32:F117,"",0,1) | P33: {=_xlfn.XLOOKUP($D33&$C33,PreparerInfo!A32:A44&PreparerInfo!C32:C44,PreparerInfo!B32:B44,"",0,1)} | Q33: =_xlfn.XLOOKUP($E33,Source!A32:A40,Source!B32:B40,"",0,1)
A34: 2033536 | B34: 11845 | C34: 3 | D34: 102 | E34: 1003 | F34: 44003 | G34: CREDIT CARD RECEIPTS | H34: 47.96 | J34: 47.96 | K34: =_xlfn.XLOOKUP($C34,Table1[BusinessUnitID],Table1[BusinessUnit],"",0) -> HOTEL PANTRY | L34: {=_xlfn.XLOOKUP($C34,Table1[[#All],[BusinessUnitID]],Table1[[#All],[Description]],"",0,1)} -> Transactions related to the hotel convenience store, including some food and beverage costs. | M34: =_xlfn.XLOOKUP($B34,ChartOfAccounts!A33:A118,ChartOfAccounts!B33:B118,"",0,1) | N34: =_xlfn.XLOOKUP($B34,ChartOfAccounts!A33:A118,ChartOfAccounts!D33:D118,0,1) -> Expenses | O34: =_xlfn.XLOOKUP($B34,ChartOfAccounts!A33:A118,ChartOfAccounts!F33:F118,"",0,1) | P34: {=_xlfn.XLOOKUP($D34&$C34,PreparerInfo!A33:A45&PreparerInfo!C33:C45,PreparerInfo!B33:B45,"",0,1)} | Q34: =_xlfn.XLOOKUP($E34,Source!A33:A41,Source!B33:B41,"",0,1)
A35: 2033536 | B35: 43440 | C35: 3 | D35: 102 | E35: 1003 | F35: 44003 | G35: CREDIT CARD RECEIPTS | I35: -47.96 | J35: -47.96 | K35: =_xlfn.XLOOKUP($C35,Table1[BusinessUnitID],Table1[BusinessUnit],"",0) -> HOTEL PANTRY | L35: {=_xlfn.XLOOKUP($C35,Table1[[#All],[BusinessUnitID]],Table1[[#All],[Description]],"",0,1)} -> Transactions related to the hotel convenience store, including some food and beverage costs. | M35: =_xlfn.XLOOKUP($B35,ChartOfAccounts!A34:A119,ChartOfAccounts!B34:B119,"",0,1) | N35: =_xlfn.XLOOKUP($B35,ChartOfAccounts!A34:A119,ChartOfAccounts!D34:D119,0,1) -> Expenses | O35: =_xlfn.XLOOKUP($B35,ChartOfAccounts!A34:A119,ChartOfAccounts!F34:F119,"",0,1) | P35: {=_xlfn.XLOOKUP($D35&$C35,PreparerInfo!A34:A46&PreparerInfo!C34:C46,PreparerInfo!B34:B46,"",0,1)} | Q35: =_xlfn.XLOOKUP($E35,Source!A34:A42,Source!B34:B42,"",0,1)
A36: 2033537 | B36: 14250 | C36: 3 | D36: 102 | E36: 1002 | F36: 44003 | G36: TROPICAL NUT & FRUIT | H36: 197.08 | J36: 197.08 | K36: =_xlfn.XLOOKUP($C36,Table1[BusinessUnitID],Table1[BusinessUnit],"",0) -> HOTEL PANTRY | L36: {=_xlfn.XLOOKUP($C36,Table1[[#All],[BusinessUnitID]],Table1[[#All],[Description]],"",0,1)} -> Transactions related to the hotel convenience store, including some food and beverage costs. | M36: =_xlfn.XLOOKUP($B36,ChartOfAccounts!A35:A120,ChartOfAccounts!B35:B120,"",0,1) | N36: =_xlfn.XLOOKUP($B36,ChartOfAccounts!A35:A120,ChartOfAccounts!D35:D120,0,1) -> Expenses | O36: =_xlfn.XLOOKUP($B36,ChartOfAccounts!A35:A120,ChartOfAccounts!F35:F120,"",0,1) | P36: {=_xlfn.XLOOKUP($D36&$C36,PreparerInfo!A35:A47&PreparerInfo!C35:C47,PreparerInfo!B35:B47,"",0,1)} | Q36: =_xlfn.XLOOKUP($E36,Source!A35:A43,Source!B35:B43,"",0,1)
A37: 2033537 | B37: 11845 | C37: 3 | D37: 102 | E37: 1002 | F37: 44003 | G37: TROPICAL NUT & FRUIT | I37: -197.08 | J37: -197.08 | K37: =_xlfn.XLOOKUP($C37,Table1[BusinessUnitID],Table1[BusinessUnit],"",0) -> HOTEL PANTRY | L37: {=_xlfn.XLOOKUP($C37,Table1[[#All],[BusinessUnitID]],Table1[[#All],[Description]],"",0,1)} -> Transactions related to the hotel convenience store, including some food and beverage costs. | M37: =_xlfn.XLOOKUP($B37,ChartOfAccounts!A36:A121,ChartOfAccounts!B36:B121,"",0,1) | N37: =_xlfn.XLOOKUP($B37,ChartOfAccounts!A36:A121,ChartOfAccounts!D36:D121,0,1) -> Expenses | O37: =_xlfn.XLOOKUP($B37,ChartOfAccounts!A36:A121,ChartOfAccounts!F36:F121,"",0,1) | P37: {=_xlfn.XLOOKUP($D37&$C37,PreparerInfo!A36:A48&PreparerInfo!C36:C48,PreparerInfo!B36:B48,"",0,1)} | Q37: =_xlfn.XLOOKUP($E37,Source!A36:A44,Source!B36:B44,"",0,1)
A38: 2033538 | B38: 72760 | C38: 6 | D38: 101 | E38: 1002 | F38: 44003 | G38: DYNAMIC SECU64605456 | H38: 236.32 | J38: 236.32 | K38: =_xlfn.XLOOKUP($C38,Table1[BusinessUnitID],Table1[BusinessUnit],"",0) -> MAINTENANCE | L38: {=_xlfn.XLOOKUP($C38,Table1[[#All],[BusinessUnitID]],Table1[[#All],[Description]],"",0,1)} -> Transactions related to the hotel Maintenance Department. Primarily includes payroll for maintenance, grounds keepers and related supplies. | M38: =_xlfn.XLOOKUP($B38,ChartOfAccounts!A37:A122,ChartOfAccounts!B37:B122,"",0,1) -> Other Services | N38: =_xlfn.XLOOKUP($B38,ChartOfAccounts!A37:A122,ChartOfAccounts!D37:D122,0,1) -> Expenses | O38: =_xlfn.XLOOKUP($B38,ChartOfAccounts!A37:A122,ChartOfAccounts!F37:F122,"",0,1) -> SG&A | P38: {=_xlfn.XLOOKUP($D38&$C38,PreparerInfo!A37:A49&PreparerInfo!C37:C49,PreparerInfo!B37:B49,"",0,1)} | Q38: =_xlfn.XLOOKUP($E38,Source!A37:A45,Source!B37:B45,"",0,1)
A39: 2033538 | B39: 11845 | C39: 6 | D39: 101 | E39: 1002 | F39: 44003 | G39: DYNAMIC SECU64605456 | I39: -236.32 | J39: -236.32 | K39: =_xlfn.XLOOKUP($C39,Table1[BusinessUnitID],Table1[BusinessUnit],"",0) -> MAINTENANCE | L39: {=_xlfn.XLOOKUP($C39,Table1[[#All],[BusinessUnitID]],Table1[[#All],[Description]],"",0,1)} -> Transactions related to the hotel Maintenance Department. Primarily includes payroll for maintenance, grounds keepers and related supplies. | M39: =_xlfn.XLOOKUP($B39,ChartOfAccounts!A38:A123,ChartOfAccounts!B38:B123,"",0,1) | N39: =_xlfn.XLOOKUP($B39,ChartOfAccounts!A38:A123,ChartOfAccounts!D38:D123,0,1) -> Expenses | O39: =_xlfn.XLOOKUP($B39,ChartOfAccounts!A38:A123,ChartOfAccounts!F38:F123,"",0,1) | P39: {=_xlfn.XLOOKUP($D39&$C39,PreparerInfo!A38:A50&PreparerInfo!C38:C50,PreparerInfo!B38:B50,"",0,1)} | Q39: =_xlfn.XLOOKUP($E39,Source!A38:A46,Source!B38:B46,"",0,1)
A40: 2033539 | B40: 72760 | C40: 6 | D40: 101 | E40: 1002 | F40: 44003 | G40: DYNAMIC SECU64605456 | H40: 236.32 | J40: 236.32 | K40: =_xlfn.XLOOKUP($C40,Table1[BusinessUnitID],Table1[BusinessUnit],"",0) -> MAINTENANCE | L40: {=_xlfn.XLOOKUP($C40,Table1[[#All],[BusinessUnitID]],Table1[[#All],[Description]],"",0,1)} -> Transactions related to the hotel Maintenance Department. Primarily includes payroll for maintenance, grounds keepers and related supplies. | M40: =_xlfn.XLOOKUP($B40,ChartOfAccounts!A39:A124,ChartOfAccounts!B39:B124,"",0,1) -> Other Services | N40: =_xlfn.XLOOKUP($B40,ChartOfAccounts!A39:A124,ChartOfAccounts!D39:D124,0,1) -> Expenses | O40: =_xlfn.XLOOKUP($B40,ChartOfAccounts!A39:A124,ChartOfAccounts!F39:F124,"",0,1) -> SG&A | P40: {=_xlfn.XLOOKUP($D40&$C40,PreparerInfo!A39:A51&PreparerInfo!C39:C51,PreparerInfo!B39:B51,"",0,1)} | Q40: =_xlfn.XLOOKUP($E40,Source!A39:A47,Source!B39:B47,"",0,1)
A41: 2033539 | B41: 11845 | C41: 6 | D41: 101 | E41: 1002 | F41: 44003 | G41: DYNAMIC SECU64605456 | I41: -236.32 | J41: -236.32 | K41: =_xlfn.XLOOKUP($C41,Table1[BusinessUnitID],Table1[BusinessUnit],"",0) -> MAINTENANCE | L41: {=_xlfn.XLOOKUP($C41,Table1[[#All],[BusinessUnitID]],Table1[[#All],[Description]],"",0,1)} -> Transactions related to the hotel Maintenance Department. Primarily includes payroll for maintenance, grounds keepers and related supplies. | M41: =_xlfn.XLOOKUP($B41,ChartOfAccounts!A40:A125,ChartOfAccounts!B40:B125,"",0,1) | N41: =_xlfn.XLOOKUP($B41,ChartOfAccounts!A40:A125,ChartOfAccounts!D40:D125,0,1) -> Expenses | O41: =_xlfn.XLOOKUP($B41,ChartOfAccounts!A40:A125,ChartOfAccounts!F40:F125,"",0,1) | P41: {=_xlfn.XLOOKUP($D41&$C41,PreparerInfo!A40:A52&PreparerInfo!C40:C52,PreparerInfo!B40:B52,"",0,1)} | Q41: =_xlfn.XLOOKUP($E41,Source!A40:A48,Source!B40:B48,"",0,1)
A42: 2033540 | B42: 14250 | C42: 3 | D42: 102 | E42: 1002 | F42: 44003 | G42: COCA-COLA ENTERPRIS | H42: 328.56 | J42: 328.56 | K42: =_xlfn.XLOOKUP($C42,Table1[BusinessUnitID],Table1[BusinessUnit],"",0) -> HOTEL PANTRY | L42: {=_xlfn.XLOOKUP($C42,Table1[[#All],[BusinessUnitID]],Table1[[#All],[Description]],"",0,1)} -> Transactions related to the hotel convenience store, including some food and beverage costs. | M42: =_xlfn.XLOOKUP($B42,ChartOfAccounts!A41:A126,ChartOfAccounts!B41:B126,"",0,1) | N42: =_xlfn.XLOOKUP($B42,ChartOfAccounts!A41:A126,ChartOfAccounts!D41:D126,0,1) -> Expenses | O42: =_xlfn.XLOOKUP($B42,ChartOfAccounts!A41:A126,ChartOfAccounts!F41:F126,"",0,1) | P42: {=_xlfn.XLOOKUP($D42&$C42,PreparerInfo!A41:A53&PreparerInfo!C41:C53,PreparerInfo!B41:B53,"",0,1)} | Q42: =_xlfn.XLOOKUP($E42,Source!A41:A49,Source!B41:B49,"",0,1)
A43: 2033540 | B43: 11845 | C43: 3 | D43: 102 | E43: 1002 | F43: 44003 | G43: COCA-COLA ENTERPRIS | I43: -328.56 | J43: -328.56 | K43: =_xlfn.XLOOKUP($C43,Table1[BusinessUnitID],Table1[BusinessUnit],"",0) -> HOTEL PANTRY | L43: {=_xlfn.XLOOKUP($C43,Table1[[#All],[BusinessUnitID]],Table1[[#All],[Description]],"",0,1)} -> Transactions related to the hotel convenience store, including some food and beverage costs. | M43: =_xlfn.XLOOKUP($B43,ChartOfAccounts!A42:A127,ChartOfAccounts!B42:B127,"",0,1) | N43: =_xlfn.XLOOKUP($B43,ChartOfAccounts!A42:A127,ChartOfAccounts!D42:D127,0,1) -> Expenses | O43: =_xlfn.XLOOKUP($B43,ChartOfAccounts!A42:A127,ChartOfAccounts!F42:F127,"",0,1) | P43: {=_xlfn.XLOOKUP($D43&$C43,PreparerInfo!A42:A54&PreparerInfo!C42:C54,PreparerInfo!B42:B54,"",0,1)} | Q43: =_xlfn.XLOOKUP($E43,Source!A42:A50,Source!B42:B50,"",0,1)
A44: 2033541 | B44: 11845 | C44: 1 | D44: 102 | E44: 1001 | F44: 44003 | G44: CASH RECEIPTS | H44: 603.45 | J44: 603.45 | K44: =_xlfn.XLOOKUP($C44,Table1[BusinessUnitID],Table1[BusinessUnit],"",0) -> FOOD SERVICE | L44: {=_xlfn.XLOOKUP($C44,Table1[[#All],[BusinessUnitID]],Table1[[#All],[Description]],"",0,1)} -> Transactions related to food and beverage service. Includes all guest transactions in the hotel restaurants, catering-related transactions and food service payroll. | M44: =_xlfn.XLOOKUP($B44,ChartOfAccounts!A43:A128,ChartOfAccounts!B43:B128,"",0,1) | N44: =_xlfn.XLOOKUP($B44,ChartOfAccounts!A43:A128,ChartOfAccounts!D43:D128,0,1) -> Expenses | O44: =_xlfn.XLOOKUP($B44,ChartOfAccounts!A43:A128,ChartOfAccounts!F43:F128,"",0,1) | P44: {=_xlfn.XLOOKUP($D44&$C44,PreparerInfo!A43:A55&PreparerInfo!C43:C55,PreparerInfo!B43:B55,"",0,1)} | Q44: =_xlfn.XLOOKUP($E44,Source!A43:A51,Source!B43:B51,"",0,1)
A45: 2033541 | B45: 43310 | C45: 1 | D45: 102 | E45: 1001 | F45: 44003 | G45: CASH RECEIPTS | I45: -603.45 | J45: -603.45 | K45: =_xlfn.XLOOKUP($C45,Table1[BusinessUnitID],Table1[BusinessUnit],"",0) -> FOOD SERVICE | L45: {=_xlfn.XLOOKUP($C45,Table1[[#All],[BusinessUnitID]],Table1[[#All],[Description]],"",0,1)} -> Transactions related to food and beverage service. Includes all guest transactions in the hotel restaurants, catering-related transactions and food service payroll. | M45: =_xlfn.XLOOKUP($B45,ChartOfAccounts!A44:A129,ChartOfAccounts!B44:B129,"",0,1) | N45: =_xlfn.XLOOKUP($B45,ChartOfAccounts!A44:A129,ChartOfAccounts!D44:D129,0,1) -> Expenses | O45: =_xlfn.XLOOKUP($B45,ChartOfAccounts!A44:A129,ChartOfAccounts!F44:F129,"",0,1) | P45: {=_xlfn.XLOOKUP($D45&$C45,PreparerInfo!A44:A56&PreparerInfo!C44:C56,PreparerInfo!B44:B56,"",0,1)} | Q45: =_xlfn.XLOOKUP($E45,Source!A44:A52,Source!B44:B52,"",0,1)
A46: 2033542 | B46: 11845 | C46: 1 | D46: 102 | E46: 1003 | F46: 44003 | G46: CREDIT CARD RECEIPTS | H46: 2422.96 | J46: 2422.96 | K46: =_xlfn.XLOOKUP($C46,Table1[BusinessUnitID],Table1[BusinessUnit],"",0) -> FOOD SERVICE | L46: {=_xlfn.XLOOKUP($C46,Table1[[#All],[BusinessUnitID]],Table1[[#All],[Description]],"",0,1)} -> Transactions related to food and beverage service. Includes all guest transactions in the hotel restaurants, catering-related transactions and food service payroll. | M46: =_xlfn.XLOOKUP($B46,ChartOfAccounts!A45:A130,ChartOfAccounts!B45:B130,"",0,1) | N46: =_xlfn.XLOOKUP($B46,ChartOfAccounts!A45:A130,ChartOfAccounts!D45:D130,0,1) -> Expenses | O46: =_xlfn.XLOOKUP($B46,ChartOfAccounts!A45:A130,ChartOfAccounts!F45:F130,"",0,1) | P46: {=_xlfn.XLOOKUP($D46&$C46,PreparerInfo!A45:A57&PreparerInfo!C45:C57,PreparerInfo!B45:B57,"",0,1)} | Q46: =_xlfn.XLOOKUP($E46,Source!A45:A53,Source!B45:B53,"",0,1)
A47: 2033542 | B47: 43310 | C47: 1 | D47: 102 | E47: 1003 | F47: 44003 | G47: CREDIT CARD RECEIPTS | I47: -2422.96 | J47: -2422.96 | K47: =_xlfn.XLOOKUP($C47,Table1[BusinessUnitID],Table1[BusinessUnit],"",0) -> FOOD SERVICE | L47: {=_xlfn.XLOOKUP($C47,Table1[[#All],[BusinessUnitID]],Table1[[#All],[Description]],"",0,1)} -> Transactions related to food and beverage service. Includes all guest transactions in the hotel restaurants, catering-related transactions and food service payroll. | M47: =_xlfn.XLOOKUP($B47,ChartOfAccounts!A46:A131,ChartOfAccounts!B46:B131,"",0,1) | N47: =_xlfn.XLOOKUP($B47,ChartOfAccounts!A46:A131,ChartOfAccounts!D46:D131,0,1) -> Expenses | O47: =_xlfn.XLOOKUP($B47,ChartOfAccounts!A46:A131,ChartOfAccounts!F46:F131,"",0,1) | P47: {=_xlfn.XLOOKUP($D47&$C47,PreparerInfo!A46:A58&PreparerInfo!C46:C58,PreparerInfo!B46:B58,"",0,1)} | Q47: =_xlfn.XLOOKUP($E47,Source!A46:A54,Source!B46:B54,"",0,1)
A48: 2033543 | B48: 11845 | C48: 2 | D48: 104 | E48: 1003 | F48: 44003 | G48: CREDIT CARD RECEIPTS | H48: 3400 | J48: 3400 | K48: =_xlfn.XLOOKUP($C48,Table1[BusinessUnitID],Table1[BusinessUnit],"",0) -> HOTEL | L48: {=_xlfn.XLOOKUP($C48,Table1[[#All],[BusinessUnitID]],Table1[[#All],[Description]],"",0,1)} -> Transactions related to guest rooms and overall hotel operations. Includes payroll for administrative staff, clerks and interns. | M48: =_xlfn.XLOOKUP($B48,ChartOfAccounts!A47:A132,ChartOfAccounts!B47:B132,"",0,1) | N48: =_xlfn.XLOOKUP($B48,ChartOfAccounts!A47:A132,ChartOfAccounts!D47:D132,0,1) -> Expenses | O48: =_xlfn.XLOOKUP($B48,ChartOfAccounts!A47:A132,ChartOfAccounts!F47:F132,"",0,1) | P48: {=_xlfn.XLOOKUP($D48&$C48,PreparerInfo!A47:A59&PreparerInfo!C47:C59,PreparerInfo!B47:B59,"",0,1)} | Q48: =_xlfn.XLOOKUP($E48,Source!A47:A55,Source!B47:B55,"",0,1)
A49: 2033543 | B49: 43180 | C49: 2 | D49: 104 | E49: 1003 | F49: 44003 | G49: CREDIT CARD RECEIPTS | I49: -3400 | J49: -3400 | K49: =_xlfn.XLOOKUP($C49,Table1[BusinessUnitID],Table1[BusinessUnit],"",0) -> HOTEL | L49: {=_xlfn.XLOOKUP($C49,Table1[[#All],[BusinessUnitID]],Table1[[#All],[Description]],"",0,1)} -> Transactions related to guest rooms and overall hotel operations. Includes payroll for administrative staff, clerks and interns. | M49: =_xlfn.XLOOKUP($B49,ChartOfAccounts!A48:A133,ChartOfAccounts!B48:B133,"",0,1) | N49: =_xlfn.XLOOKUP($B49,ChartOfAccounts!A48:A133,ChartOfAccounts!D48:D133,0,1) -> Expenses | O49: =_xlfn.XLOOKUP($B49,ChartOfAccounts!A48:A133,ChartOfAccounts!F48:F133,"",0,1) | P49: {=_xlfn.XLOOKUP($D49&$C49,PreparerInfo!A48:A60&PreparerInfo!C48:C60,PreparerInfo!B48:B60,"",0,1)} | Q49: =_xlfn.XLOOKUP($E49,Source!A48:A56,Source!B48:B56,"",0,1)
A50: 2033544 | B50: 16200 | C50: 2 | D50: 102 | E50: 1002 | F50: 44003 | G50: ATLAS ENVIRO | H50: 3000 | J50: 3000 | K50: =_xlfn.XLOOKUP($C50,Table1[BusinessUnitID],Table1[BusinessUnit],"",0) -> HOTEL | L50: {=_xlfn.XLOOKUP($C50,Table1[[#All],[BusinessUnitID]],Table1[[#All],[Description]],"",0,1)} -> Transactions related to guest rooms and overall hotel operations. Includes payroll for administrative staff, clerks and interns. | M50: =_xlfn.XLOOKUP($B50,ChartOfAccounts!A49:A134,ChartOfAccounts!B49:B134,"",0,1) | N50: =_xlfn.XLOOKUP($B50,ChartOfAccounts!A49:A134,ChartOfAccounts!D49:D134,0,1) -> Expenses | O50: =_xlfn.XLOOKUP($B50,ChartOfAccounts!A49:A134,ChartOfAccounts!F49:F134,"",0,1) | P50: {=_xlfn.XLOOKUP($D50&$C50,PreparerInfo!A49:A61&PreparerInfo!C49:C61,PreparerInfo!B49:B61,"",0,1)} | Q50: =_xlfn.XLOOKUP($E50,Source!A49:A57,Source!B49:B57,"",0,1)
A51: 2033544 | B51: 11845 | C51: 2 | D51: 102 | E51: 1002 | F51: 44003 | G51: ATLAS ENVIRO | I51: -3000 | J51: -3000 | K51: =_xlfn.XLOOKUP($C51,Table1[BusinessUnitID],Table1[BusinessUnit],"",0) -> HOTEL | L51: {=_xlfn.XLOOKUP($C51,Table1[[#All],[BusinessUnitID]],Table1[[#All],[Description]],"",0,1)} -> Transactions related to guest rooms and overall hotel operations. Includes payroll for administrative staff, clerks and interns. | M51: =_xlfn.XLOOKUP($B51,ChartOfAccounts!A50:A135,ChartOfAccounts!B50:B135,"",0,1) | N51: =_xlfn.XLOOKUP($B51,ChartOfAccounts!A50:A135,ChartOfAccounts!D50:D135,0,1) -> Expenses | O51: =_xlfn.XLOOKUP($B51,ChartOfAccounts!A50:A135,ChartOfAccounts!F50:F135,"",0,1) | P51: {=_xlfn.XLOOKUP($D51&$C51,PreparerInfo!A50:A62&PreparerInfo!C50:C62,PreparerInfo!B50:B62,"",0,1)} | Q51: =_xlfn.XLOOKUP($E51,Source!A50:A58,Source!B50:B58,"",0,1)
A52: 2033545 | B52: 71400 | C52: 1 | D52: 101 | E52: 1002 | F52: 44004 | G52: CENTRAL DUPLICATING | H52: 6.37 | J52: 6.37 | K52: =_xlfn.XLOOKUP($C52,Table1[BusinessUnitID],Table1[BusinessUnit],"",0) -> FOOD SERVICE | L52: {=_xlfn.XLOOKUP($C52,Table1[[#All],[BusinessUnitID]],Table1[[#All],[Description]],"",0,1)} -> Transactions related to food and beverage service. Includes all guest transactions in the hotel restaurants, catering-related transactions and food service payroll. | M52: =_xlfn.XLOOKUP($B52,ChartOfAccounts!A51:A136,ChartOfAccounts!B51:B136,"",0,1) | N52: =_xlfn.XLOOKUP($B52,ChartOfAccounts!A51:A136,ChartOfAccounts!D51:D136,0,1) -> Expenses | O52: =_xlfn.XLOOKUP($B52,ChartOfAccounts!A51:A136,ChartOfAccounts!F51:F136,"",0,1) | P52: {=_xlfn.XLOOKUP($D52&$C52,PreparerInfo!A51:A63&PreparerInfo!C51:C63,PreparerInfo!B51:B63,"",0,1)} | Q52: =_xlfn.XLOOKUP($E52,Source!A51:A59,Source!B51:B59,"",0,1)
A53: 2033545 | B53: 11845 | C53: 1 | D53: 101 | E53: 1002 | F53: 44004 | G53: CENTRAL DUPLICATING | I53: -6.37 | J53: -6.37 | K53: =_xlfn.XLOOKUP($C53,Table1[BusinessUnitID],Table1[BusinessUnit],"",0) -> FOOD SERVICE | L53: {=_xlfn.XLOOKUP($C53,Table1[[#All],[BusinessUnitID]],Table1[[#All],[Description]],"",0,1)} -> Transactions related to food and beverage service. Includes all guest transactions in the hotel restaurants, catering-related transactions and food service payroll. | M53: =_xlfn.XLOOKUP($B53,ChartOfAccounts!A52:A137,ChartOfAccounts!B52:B137,"",0,1) | N53: =_xlfn.XLOOKUP($B53,ChartOfAccounts!A52:A137,ChartOfAccounts!D52:D137,0,1) -> Expenses | O53: =_xlfn.XLOOKUP($B53,ChartOfAccounts!A52:A137,ChartOfAccounts!F52:F137,"",0,1) | P53: {=_xlfn.XLOOKUP($D53&$C53,PreparerInfo!A52:A64&PreparerInfo!C52:C64,PreparerInfo!B52:B64,"",0,1)} | Q53: =_xlfn.XLOOKUP($E53,Source!A52:A60,Source!B52:B60,"",0,1)
A54: 2033546 | B54: 11845 | C54: 1 | D54: 102 | E54: 1001 | F54: 44004 | G54: COPELAND,MELODY | H54: 7.66 | J54: 7.66 | K54: =_xlfn.XLOOKUP($C54,Table1[BusinessUnitID],Table1[BusinessUnit],"",0) -> FOOD SERVICE | L54: {=_xlfn.XLOOKUP($C54,Table1[[#All],[BusinessUnitID]],Table1[[#All],[Description]],"",0,1)} -> Transactions related to food and beverage service. Includes all guest transactions in the hotel restaurants, catering-related transactions and food service payroll. | M54: =_xlfn.XLOOKUP($B54,ChartOfAccounts!A53:A138,ChartOfAccounts!B53:B138,"",0,1) | N54: =_xlfn.XLOOKUP($B54,ChartOfAccounts!A53:A138,ChartOfAccounts!D53:D138,0,1) -> Expenses | O54: =_xlfn.XLOOKUP($B54,ChartOfAccounts!A53:A138,ChartOfAccounts!F53:F138,"",0,1) | P54: {=_xlfn.XLOOKUP($D54&$C54,PreparerInfo!A53:A65&PreparerInfo!C53:C65,PreparerInfo!B53:B65,"",0,1)} | Q54: =_xlfn.XLOOKUP($E54,Source!A53:A61,Source!B53:B61,"",0,1)
A55: 2033546 | B55: 43310 | C55: 1 | D55: 102 | E55: 1001 | F55: 44004 | G55: COPELAND,MELODY | I55: -7.66 | J55: -7.66 | K55: =_xlfn.XLOOKUP($C55,Table1[BusinessUnitID],Table1[BusinessUnit],"",0) -> FOOD SERVICE | L55: {=_xlfn.XLOOKUP($C55,Table1[[#All],[BusinessUnitID]],Table1[[#All],[Description]],"",0,1)} -> Transactions related to food and beverage service. Includes all guest transactions in the hotel restaurants, catering-related transactions and food service payroll. | M55: =_xlfn.XLOOKUP($B55,ChartOfAccounts!A54:A139,ChartOfAccounts!B54:B139,"",0,1) | N55: =_xlfn.XLOOKUP($B55,ChartOfAccounts!A54:A139,ChartOfAccounts!D54:D139,0,1) -> Expenses | O55: =_xlfn.XLOOKUP($B55,ChartOfAccounts!A54:A139,ChartOfAccounts!F54:F139,"",0,1) | P55: {=_xlfn.XLOOKUP($D55&$C55,PreparerInfo!A54:A66&PreparerInfo!C54:C66,PreparerInfo!B54:B66,"",0,1)} | Q55: =_xlfn.XLOOKUP($E55,Source!A54:A62,Source!B54:B62,"",0,1)
A56: 2033547 | B56: 11845 | C56: 3 | D56: 102 | E56: 1003 | F56: 44004 | G56: CREDIT CARD RECEIPTS | H56: 17.21 | J56: 17.21 | K56: =_xlfn.XLOOKUP($C56,Table1[BusinessUnitID],Table1[BusinessUnit],"",0) -> HOTEL PANTRY | L56: {=_xlfn.XLOOKUP($C56,Table1[[#All],[BusinessUnitID]],Table1[[#All],[Description]],"",0,1)} -> Transactions related to the hotel convenience store, including some food and beverage costs. | M56: =_xlfn.XLOOKUP($B56,ChartOfAccounts!A55:A140,ChartOfAccounts!B55:B140,"",0,1) | N56: =_xlfn.XLOOKUP($B56,ChartOfAccounts!A55:A140,ChartOfAccounts!D55:D140,0,1) -> Expenses | O56: =_xlfn.XLOOKUP($B56,ChartOfAccounts!A55:A140,ChartOfAccounts!F55:F140,"",0,1) | P56: {=_xlfn.XLOOKUP($D56&$C56,PreparerInfo!A55:A67&PreparerInfo!C55:C67,PreparerInfo!B55:B67,"",0,1)} | Q56: =_xlfn.XLOOKUP($E56,Source!A55:A63,Source!B55:B63,"",0,1)
A57: 2033547 | B57: 43440 | C57: 3 | D57: 102 | E57: 1003 | F57: 44004 | G57: CREDIT CARD RECEIPTS | I57: -17.21 | J57: -17.21 | K57: =_xlfn.XLOOKUP($C57,Table1[BusinessUnitID],Table1[BusinessUnit],"",0) -> HOTEL PANTRY | L57: {=_xlfn.XLOOKUP($C57,Table1[[#All],[BusinessUnitID]],Table1[[#All],[Description]],"",0,1)} -> Transactions related to the hotel convenience store, including some food and beverage costs. | M57: =_xlfn.XLOOKUP($B57,ChartOfAccounts!A56:A141,ChartOfAccounts!B56:B141,"",0,1) | N57: =_xlfn.XLOOKUP($B57,ChartOfAccounts!A56:A141,ChartOfAccounts!D56:D141,0,1) -> Expenses | O57: =_xlfn.XLOOKUP($B57,ChartOfAccounts!A56:A141,ChartOfAccounts!F56:F141,"",0,1) | P57: {=_xlfn.XLOOKUP($D57&$C57,PreparerInfo!A56:A68&PreparerInfo!C56:C68,PreparerInfo!B56:B68,"",0,1)} | Q57: =_xlfn.XLOOKUP($E57,Source!A56:A64,Source!B56:B64,"",0,1)
A58: 2033548 | B58: 11845 | C58: 1 | D58: 102 | E58: 1003 | F58: 44004 | G58: CREDIT CARD RECEIPTS | H58: 26.98 | J58: 26.98 | K58: =_xlfn.XLOOKUP($C58,Table1[BusinessUnitID],Table1[BusinessUnit],"",0) -> FOOD SERVICE | L58: {=_xlfn.XLOOKUP($C58,Table1[[#All],[BusinessUnitID]],Table1[[#All],[Description]],"",0,1)} -> Transactions related to food and beverage service. Includes all guest transactions in the hotel restaurants, catering-related transactions and food service payroll. | M58: =_xlfn.XLOOKUP($B58,ChartOfAccounts!A57:A142,ChartOfAccounts!B57:B142,"",0,1) | N58: =_xlfn.XLOOKUP($B58,ChartOfAccounts!A57:A142,ChartOfAccounts!D57:D142,0,1) -> Expenses | O58: =_xlfn.XLOOKUP($B58,ChartOfAccounts!A57:A142,ChartOfAccounts!F57:F142,"",0,1) | P58: {=_xlfn.XLOOKUP($D58&$C58,PreparerInfo!A57:A69&PreparerInfo!C57:C69,PreparerInfo!B57:B69,"",0,1)} | Q58: =_xlfn.XLOOKUP($E58,Source!A57:A65,Source!B57:B65,"",0,1)
A59: 2033548 | B59: 43310 | C59: 1 | D59: 102 | E59: 1003 | F59: 44004 | G59: CREDIT CARD RECEIPTS | I59: -26.98 | J59: -26.98 | K59: =_xlfn.XLOOKUP($C59,Table1[BusinessUnitID],Table1[BusinessUnit],"",0) -> FOOD SERVICE | L59: {=_xlfn.XLOOKUP($C59,Table1[[#All],[BusinessUnitID]],Table1[[#All],[Description]],"",0,1)} -> Transactions related to food and beverage service. Includes all guest transactions in the hotel restaurants, catering-related transactions and food service payroll. | M59: =_xlfn.XLOOKUP($B59,ChartOfAccounts!A58:A143,ChartOfAccounts!B58:B143,"",0,1) | N59: =_xlfn.XLOOKUP($B59,ChartOfAccounts!A58:A143,ChartOfAccounts!D58:D143,0,1) -> Expenses | O59: =_xlfn.XLOOKUP($B59,ChartOfAccounts!A58:A143,ChartOfAccounts!F58:F143,"",0,1) | P59: {=_xlfn.XLOOKUP($D59&$C59,PreparerInfo!A58:A70&PreparerInfo!C58:C70,PreparerInfo!B58:B70,"",0,1)} | Q59: =_xlfn.XLOOKUP($E59,Source!A58:A66,Source!B58:B66,"",0,1)
A60: 2033549 | B60: 71400 | C60: 2 | D60: 101 | E60: 1002 | F60: 44004 | G60: SA647 CARD JUN | H60: 40 | J60: 40 | K60: =_xlfn.XLOOKUP($C60,Table1[BusinessUnitID],Table1[BusinessUnit],"",0) -> HOTEL | L60: {=_xlfn.XLOOKUP($C60,Table1[[#All],[BusinessUnitID]],Table1[[#All],[Description]],"",0,1)} -> Transactions related to guest rooms and overall hotel operations. Includes payroll for administrative staff, clerks and interns. | M60: =_xlfn.XLOOKUP($B60,ChartOfAccounts!A59:A144,ChartOfAccounts!B59:B144,"",0,1) | N60: =_xlfn.XLOOKUP($B60,ChartOfAccounts!A59:A144,ChartOfAccounts!D59:D144,0,1) -> Expenses | O60: =_xlfn.XLOOKUP($B60,ChartOfAccounts!A59:A144,ChartOfAccounts!F59:F144,"",0,1) | P60: {=_xlfn.XLOOKUP($D60&$C60,PreparerInfo!A59:A71&PreparerInfo!C59:C71,PreparerInfo!B59:B71,"",0,1)} | Q60: =_xlfn.XLOOKUP($E60,Source!A59:A67,Source!B59:B67,"",0,1)
A61: 2033549 | B61: 11845 | C61: 2 | D61: 101 | E61: 1002 | F61: 44004 | G61: SA647 CARD JUN | I61: -40 | J61: -40 | K61: =_xlfn.XLOOKUP($C61,Table1[BusinessUnitID],Table1[BusinessUnit],"",0) -> HOTEL | L61: {=_xlfn.XLOOKUP($C61,Table1[[#All],[BusinessUnitID]],Table1[[#All],[Description]],"",0,1)} -> Transactions related to guest rooms and overall hotel operations. Includes payroll for administrative staff, clerks and interns. | M61: =_xlfn.XLOOKUP($B61,ChartOfAccounts!A60:A145,ChartOfAccounts!B60:B145,"",0,1) | N61: =_xlfn.XLOOKUP($B61,ChartOfAccounts!A60:A145,ChartOfAccounts!D60:D145,0,1) -> Expenses | O61: =_xlfn.XLOOKUP($B61,ChartOfAccounts!A60:A145,ChartOfAccounts!F60:F145,"",0,1) | P61: {=_xlfn.XLOOKUP($D61&$C61,PreparerInfo!A60:A72&PreparerInfo!C60:C72,PreparerInfo!B60:B72,"",0,1)} | Q61: =_xlfn.XLOOKUP($E61,Source!A60:A68,Source!B60:B68,"",0,1)
A62: 2033550 | B62: 71400 | C62: 1 | D62: 101 | E62: 1002 | F62: 44004 | G62: CENTRAL DUPLICATING | H62: 45 | J62: 45 | K62: =_xlfn.XLOOKUP($C62,Table1[BusinessUnitID],Table1[BusinessUnit],"",0) -> FOOD SERVICE | L62: {=_xlfn.XLOOKUP($C62,Table1[[#All],[BusinessUnitID]],Table1[[#All],[Description]],"",0,1)} -> Transactions related to food and beverage service. Includes all guest transactions in the hotel restaurants, catering-related transactions and food service payroll. | M62: =_xlfn.XLOOKUP($B62,ChartOfAccounts!A61:A146,ChartOfAccounts!B61:B146,"",0,1) | N62: =_xlfn.XLOOKUP($B62,ChartOfAccounts!A61:A146,ChartOfAccounts!D61:D146,0,1) -> Expenses | O62: =_xlfn.XLOOKUP($B62,ChartOfAccounts!A61:A146,ChartOfAccounts!F61:F146,"",0,1) | P62: {=_xlfn.XLOOKUP($D62&$C62,PreparerInfo!A61:A73&PreparerInfo!C61:C73,PreparerInfo!B61:B73,"",0,1)} | Q62: =_xlfn.XLOOKUP($E62,Source!A61:A69,Source!B61:B69,"",0,1)
A63: 2033550 | B63: 11845 | C63: 1 | D63: 101 | E63: 1002 | F63: 44004 | G63: CENTRAL DUPLICATING | I63: -45 | J63: -45 | K63: =_xlfn.XLOOKUP($C63,Table1[BusinessUnitID],Table1[BusinessUnit],"",0) -> FOOD SERVICE | L63: {=_xlfn.XLOOKUP($C63,Table1[[#All],[BusinessUnitID]],Table1[[#All],[Description]],"",0,1)} -> Transactions related to food and beverage service. Includes all guest transactions in the hotel restaurants, catering-related transactions and food service payroll. | M63: =_xlfn.XLOOKUP($B63,ChartOfAccounts!A62:A147,ChartOfAccounts!B62:B147,"",0,1) | N63: =_xlfn.XLOOKUP($B63,ChartOfAccounts!A62:A147,ChartOfAccounts!D62:D147,0,1) -> Expenses | O63: =_xlfn.XLOOKUP($B63,ChartOfAccounts!A62:A147,ChartOfAccounts!F62:F147,"",0,1) | P63: {=_xlfn.XLOOKUP($D63&$C63,PreparerInfo!A62:A74&PreparerInfo!C62:C74,PreparerInfo!B62:B74,"",0,1)} | Q63: =_xlfn.XLOOKUP($E63,Source!A62:A70,Source!B62:B70,"",0,1)
A64: 2033551 | B64: 11845 | C64: 3 | D64: 102 | E64: 1001 | F64: 44004 | G64: CASH RECEIPTS | H64: 49.51 | J64: 49.51 | K64: =_xlfn.XLOOKUP($C64,Table1[BusinessUnitID],Table1[BusinessUnit],"",0) -> HOTEL PANTRY | L64: {=_xlfn.XLOOKUP($C64,Table1[[#All],[BusinessUnitID]],Table1[[#All],[Description]],"",0,1)} -> Transactions related to the hotel convenience store, including some food and beverage costs. | M64: =_xlfn.XLOOKUP($B64,ChartOfAccounts!A63:A148,ChartOfAccounts!B63:B148,"",0,1) | N64: =_xlfn.XLOOKUP($B64,ChartOfAccounts!A63:A148,ChartOfAccounts!D63:D148,0,1) -> Expenses | O64: =_xlfn.XLOOKUP($B64,ChartOfAccounts!A63:A148,ChartOfAccounts!F63:F148,"",0,1) | P64: {=_xlfn.XLOOKUP($D64&$C64,PreparerInfo!A63:A75&PreparerInfo!C63:C75,PreparerInfo!B63:B75,"",0,1)} | Q64: =_xlfn.XLOOKUP($E64,Source!A63:A71,Source!B63:B71,"",0,1)
A65: 2033551 | B65: 43440 | C65: 3 | D65: 102 | E65: 1001 | F65: 44004 | G65: CASH RECEIPTS | I65: -49.51 | J65: -49.51 | K65: =_xlfn.XLOOKUP($C65,Table1[BusinessUnitID],Table1[BusinessUnit],"",0) -> HOTEL PANTRY | L65: {=_xlfn.XLOOKUP($C65,Table1[[#All],[BusinessUnitID]],Table1[[#All],[Description]],"",0,1)} -> Transactions related to the hotel convenience store, including some food and beverage costs. | M65: =_xlfn.XLOOKUP($B65,ChartOfAccounts!A64:A149,ChartOfAccounts!B64:B149,"",0,1) | N65: =_xlfn.XLOOKUP($B65,ChartOfAccounts!A64:A149,ChartOfAccounts!D64:D149,0,1) -> Expenses | O65: =_xlfn.XLOOKUP($B65,ChartOfAccounts!A64:A149,ChartOfAccounts!F64:F149,"",0,1) | P65: {=_xlfn.XLOOKUP($D65&$C65,PreparerInfo!A64:A76&PreparerInfo!C64:C76,PreparerInfo!B64:B76,"",0,1)} | Q65: =_xlfn.XLOOKUP($E65,Source!A64:A72,Source!B64:B72,"",0,1)
A66: 2033552 | B66: 72732 | C66: 1 | D66: 101 | E66: 1002 | F66: 44004 | G66: FEDEX | H66: 55 | J66: 55 | K66: =_xlfn.XLOOKUP($C66,Table1[BusinessUnitID],Table1[BusinessUnit],"",0) -> FOOD SERVICE | L66: {=_xlfn.XLOOKUP($C66,Table1[[#All],[BusinessUnitID]],Table1[[#All],[Description]],"",0,1)} -> Transactions related to food and beverage service. Includes all guest transactions in the hotel restaurants, catering-related transactions and food service payroll. | M66: =_xlfn.XLOOKUP($B66,ChartOfAccounts!A65:A150,ChartOfAccounts!B65:B150,"",0,1) | N66: =_xlfn.XLOOKUP($B66,ChartOfAccounts!A65:A150,ChartOfAccounts!D65:D150,0,1) -> Expenses | O66: =_xlfn.XLOOKUP($B66,ChartOfAccounts!A65:A150,ChartOfAccounts!F65:F150,"",0,1) | P66: {=_xlfn.XLOOKUP($D66&$C66,PreparerInfo!A65:A77&PreparerInfo!C65:C77,PreparerInfo!B65:B77,"",0,1)} | Q66: =_xlfn.XLOOKUP($E66,Source!A65:A73,Source!B65:B73,"",0,1)
A67: 2033552 | B67: 11845 | C67: 1 | D67: 101 | E67: 1002 | F67: 44004 | G67: FEDEX | I67: -55 | J67: -55 | K67: =_xlfn.XLOOKUP($C67,Table1[BusinessUnitID],Table1[BusinessUnit],"",0) -> FOOD SERVICE | L67: {=_xlfn.XLOOKUP($C67,Table1[[#All],[BusinessUnitID]],Table1[[#All],[Description]],"",0,1)} -> Transactions related to food and beverage service. Includes all guest transactions in the hotel restaurants, catering-related transactions and food service payroll. | M67: =_xlfn.XLOOKUP($B67,ChartOfAccounts!A66:A151,ChartOfAccounts!B66:B151,"",0,1) | N67: =_xlfn.XLOOKUP($B67,ChartOfAccounts!A66:A151,ChartOfAccounts!D66:D151,0,1) -> Expenses | O67: =_xlfn.XLOOKUP($B67,ChartOfAccounts!A66:A151,ChartOfAccounts!F66:F151,"",0,1) | P67: {=_xlfn.XLOOKUP($D67&$C67,PreparerInfo!A66:A78&PreparerInfo!C66:C78,PreparerInfo!B66:B78,"",0,1)} | Q67: =_xlfn.XLOOKUP($E67,Source!A66:A74,Source!B66:B74,"",0,1)
A68: 2033553 | B68: 11845 | C68: 3 | D68: 102 | E68: 1003 | F68: 44004 | G68: CREDIT CARD RECEIPTS | H68: 58.02 | J68: 58.02 | K68: =_xlfn.XLOOKUP($C68,Table1[BusinessUnitID],Table1[BusinessUnit],"",0) -> HOTEL PANTRY | L68: {=_xlfn.XLOOKUP($C68,Table1[[#All],[BusinessUnitID]],Table1[[#All],[Description]],"",0,1)} -> Transactions related to the hotel convenience store, including some food and beverage costs. | M68: =_xlfn.XLOOKUP($B68,ChartOfAccounts!A67:A152,ChartOfAccounts!B67:B152,"",0,1) | N68: =_xlfn.XLOOKUP($B68,ChartOfAccounts!A67:A152,ChartOfAccounts!D67:D152,0,1) -> Expenses | O68: =_xlfn.XLOOKUP($B68,ChartOfAccounts!A67:A152,ChartOfAccounts!F67:F152,"",0,1) | P68: {=_xlfn.XLOOKUP($D68&$C68,PreparerInfo!A67:A79&PreparerInfo!C67:C79,PreparerInfo!B67:B79,"",0,1)} | Q68: =_xlfn.XLOOKUP($E68,Source!A67:A75,Source!B67:B75,"",0,1)
A69: 2033553 | B69: 43440 | C69: 3 | D69: 102 | E69: 1003 | F69: 44004 | G69: CREDIT CARD RECEIPTS | I69: -58.02 | J69: -58.02 | K69: =_xlfn.XLOOKUP($C69,Table1[BusinessUnitID],Table1[BusinessUnit],"",0) -> HOTEL PANTRY | L69: {=_xlfn.XLOOKUP($C69,Table1[[#All],[BusinessUnitID]],Table1[[#All],[Description]],"",0,1)} -> Transactions related to the hotel convenience store, including some food and beverage costs. | M69: =_xlfn.XLOOKUP($B69,ChartOfAccounts!A68:A153,ChartOfAccounts!B68:B153,"",0,1) | N69: =_xlfn.XLOOKUP($B69,ChartOfAccounts!A68:A153,ChartOfAccounts!D68:D153,0,1) -> Expenses | O69: =_xlfn.XLOOKUP($B69,ChartOfAccounts!A68:A153,ChartOfAccounts!F68:F153,"",0,1) | P69: {=_xlfn.XLOOKUP($D69&$C69,PreparerInfo!A68:A80&PreparerInfo!C68:C80,PreparerInfo!B68:B80,"",0,1)} | Q69: =_xlfn.XLOOKUP($E69,Source!A68:A76,Source!B68:B76,"",0,1)
A70: 2033554 | B70: 11845 | C70: 1 | D70: 102 | E70: 1003 | F70: 44004 | G70: DINING JUN | H70: 80.24 | J70: 80.24 | K70: =_xlfn.XLOOKUP($C70,Table1[BusinessUnitID],Table1[BusinessUnit],"",0) -> FOOD SERVICE | L70: {=_xlfn.XLOOKUP($C70,Table1[[#All],[BusinessUnitID]],Table1[[#All],[Description]],"",0,1)} -> Transactions related to food and beverage service. Includes all guest transactions in the hotel restaurants, catering-related transactions and food service payroll. | M70: =_xlfn.XLOOKUP($B70,ChartOfAccounts!A69:A154,ChartOfAccounts!B69:B154,"",0,1) | N70: =_xlfn.XLOOKUP($B70,ChartOfAccounts!A69:A154,ChartOfAccounts!D69:D154,0,1) -> Expenses | O70: =_xlfn.XLOOKUP($B70,ChartOfAccounts!A69:A154,ChartOfAccounts!F69:F154,"",0,1) | P70: {=_xlfn.XLOOKUP($D70&$C70,PreparerInfo!A69:A81&PreparerInfo!C69:C81,PreparerInfo!B69:B81,"",0,1)} | Q70: =_xlfn.XLOOKUP($E70,Source!A69:A77,Source!B69:B77,"",0,1)
A71: 2033554 | B71: 43310 | C71: 1 | D71: 102 | E71: 1003 | F71: 44004 | G71: DINING JUN | I71: -80.24 | J71: -80.24 | K71: =_xlfn.XLOOKUP($C71,Table1[BusinessUnitID],Table1[BusinessUnit],"",0) -> FOOD SERVICE | L71: {=_xlfn.XLOOKUP($C71,Table1[[#All],[BusinessUnitID]],Table1[[#All],[Description]],"",0,1)} -> Transactions related to food and beverage service. Includes all guest transactions in the hotel restaurants, catering-related transactions and food service payroll. | M71: =_xlfn.XLOOKUP($B71,ChartOfAccounts!A70:A155,ChartOfAccounts!B70:B155,"",0,1) | N71: =_xlfn.XLOOKUP($B71,ChartOfAccounts!A70:A155,ChartOfAccounts!D70:D155,0,1) -> Expenses | O71: =_xlfn.XLOOKUP($B71,ChartOfAccounts!A70:A155,ChartOfAccounts!F70:F155,"",0,1) | P71: {=_xlfn.XLOOKUP($D71&$C71,PreparerInfo!A70:A82&PreparerInfo!C70:C82,PreparerInfo!B70:B82,"",0,1)} | Q71: =_xlfn.XLOOKUP($E71,Source!A70:A78,Source!B70:B78,"",0,1)
A72: 2033555 | B72: 11845 | C72: 1 | D72: 102 | E72: 1003 | F72: 44004 | G72: CREDIT CARD RECEIPTS | H72: 91 | J72: 91 | K72: =_xlfn.XLOOKUP($C72,Table1[BusinessUnitID],Table1[BusinessUnit],"",0) -> FOOD SERVICE | L72: {=_xlfn.XLOOKUP($C72,Table1[[#All],[BusinessUnitID]],Table1[[#All],[Description]],"",0,1)} -> Transactions related to food and beverage service. Includes all guest transactions in the hotel restaurants, catering-related transactions and food service payroll. | M72: =_xlfn.XLOOKUP($B72,ChartOfAccounts!A71:A156,ChartOfAccounts!B71:B156,"",0,1) | N72: =_xlfn.XLOOKUP($B72,ChartOfAccounts!A71:A156,ChartOfAccounts!D71:D156,0,1) -> Expenses | O72: =_xlfn.XLOOKUP($B72,ChartOfAccounts!A71:A156,ChartOfAccounts!F71:F156,"",0,1) | P72: {=_xlfn.XLOOKUP($D72&$C72,PreparerInfo!A71:A83&PreparerInfo!C71:C83,PreparerInfo!B71:B83,"",0,1)} | Q72: =_xlfn.XLOOKUP($E72,Source!A71:A79,Source!B71:B79,"",0,1)
A73: 2033555 | B73: 43310 | C73: 1 | D73: 102 | E73: 1003 | F73: 44004 | G73: CREDIT CARD RECEIPTS | I73: -91 | J73: -91 | K73: =_xlfn.XLOOKUP($C73,Table1[BusinessUnitID],Table1[BusinessUnit],"",0) -> FOOD SERVICE | L73: {=_xlfn.XLOOKUP($C73,Table1[[#All],[BusinessUnitID]],Table1[[#All],[Description]],"",0,1)} -> Transactions related to food and beverage service. Includes all guest transactions in the hotel restaurants, catering-related transactions and food service payroll. | M73: =_xlfn.XLOOKUP($B73,ChartOfAccounts!A72:A157,ChartOfAccounts!B72:B157,"",0,1) | N73: =_xlfn.XLOOKUP($B73,ChartOfAccounts!A72:A157,ChartOfAccounts!D72:D157,0,1) -> Expenses | O73: =_xlfn.XLOOKUP($B73,ChartOfAccounts!A72:A157,ChartOfAccounts!F72:F157,"",0,1) | P73: {=_xlfn.XLOOKUP($D73&$C73,PreparerInfo!A72:A84&PreparerInfo!C72:C84,PreparerInfo!B72:B84,"",0,1)} | Q73: =_xlfn.XLOOKUP($E73,Source!A72:A80,Source!B72:B80,"",0,1)
A74: 2033556 | B74: 71400 | C74: 1 | D74: 101 | E74: 1002 | F74: 44004 | G74: SA647 CARD JUN | H74: 100 | J74: 100 | K74: =_xlfn.XLOOKUP($C74,Table1[BusinessUnitID],Table1[BusinessUnit],"",0) -> FOOD SERVICE | L74: {=_xlfn.XLOOKUP($C74,Table1[[#All],[BusinessUnitID]],Table1[[#All],[Description]],"",0,1)} -> Transactions related to food and beverage service. Includes all guest transactions in the hotel restaurants, catering-related transactions and food service payroll. | M74: =_xlfn.XLOOKUP($B74,ChartOfAccounts!A73:A158,ChartOfAccounts!B73:B158,"",0,1) | N74: =_xlfn.XLOOKUP($B74,ChartOfAccounts!A73:A158,ChartOfAccounts!D73:D158,0,1) -> Expenses | O74: =_xlfn.XLOOKUP($B74,ChartOfAccounts!A73:A158,ChartOfAccounts!F73:F158,"",0,1) | P74: {=_xlfn.XLOOKUP($D74&$C74,PreparerInfo!A73:A85&PreparerInfo!C73:C85,PreparerInfo!B73:B85,"",0,1)} | Q74: =_xlfn.XLOOKUP($E74,Source!A73:A81,Source!B73:B81,"",0,1)
A75: 2033556 | B75: 11845 | C75: 1 | D75: 101 | E75: 1002 | F75: 44004 | G75: SA647 CARD JUN | I75: -100 | J75: -100 | K75: =_xlfn.XLOOKUP($C75,Table1[BusinessUnitID],Table1[BusinessUnit],"",0) -> FOOD SERVICE | L75: {=_xlfn.XLOOKUP($C75,Table1[[#All],[BusinessUnitID]],Table1[[#All],[Description]],"",0,1)} -> Transactions related to food and beverage service. Includes all guest transactions in the hotel restaurants, catering-related transactions and food service payroll. | M75: =_xlfn.XLOOKUP($B75,ChartOfAccounts!A74:A159,ChartOfAccounts!B74:B159,"",0,1) | N75: =_xlfn.XLOOKUP($B75,ChartOfAccounts!A74:A159,ChartOfAccounts!D74:D159,0,1) -> Expenses | O75: =_xlfn.XLOOKUP($B75,ChartOfAccounts!A74:A159,ChartOfAccounts!F74:F159,"",0,1) | P75: {=_xlfn.XLOOKUP($D75&$C75,PreparerInfo!A74:A86&PreparerInfo!C74:C86,PreparerInfo!B74:B86,"",0,1)} | Q75: =_xlfn.XLOOKUP($E75,Source!A74:A82,Source!B74:B82,"",0,1)
A76: 2033557 | B76: 72702 | C76: 2 | D76: 101 | E76: 1002 | F76: 44004 | G76: ONE PRICE DRY CLEANI | H76: 111.15 | J76: 111.15 | K76: =_xlfn.XLOOKUP($C76,Table1[BusinessUnitID],Table1[BusinessUnit],"",0) -> HOTEL | L76: {=_xlfn.XLOOKUP($C76,Table1[[#All],[BusinessUnitID]],Table1[[#All],[Description]],"",0,1)} -> Transactions related to guest rooms and overall hotel operations. Includes payroll for administrative staff, clerks and interns. | M76: =_xlfn.XLOOKUP($B76,ChartOfAccounts!A75:A160,ChartOfAccounts!B75:B160,"",0,1) | N76: =_xlfn.XLOOKUP($B76,ChartOfAccounts!A75:A160,ChartOfAccounts!D75:D160,0,1) -> Expenses | O76: =_xlfn.XLOOKUP($B76,ChartOfAccounts!A75:A160,ChartOfAccounts!F75:F160,"",0,1) | P76: {=_xlfn.XLOOKUP($D76&$C76,PreparerInfo!A75:A87&PreparerInfo!C75:C87,PreparerInfo!B75:B87,"",0,1)} | Q76: =_xlfn.XLOOKUP($E76,Source!A75:A83,Source!B75:B83,"",0,1)
A77: 2033557 | B77: 11845 | C77: 2 | D77: 101 | E77: 1002 | F77: 44004 | G77: ONE PRICE DRY CLEANI | I77: -111.15 | J77: -111.15 | K77: =_xlfn.XLOOKUP($C77,Table1[BusinessUnitID],Table1[BusinessUnit],"",0) -> HOTEL | L77: {=_xlfn.XLOOKUP($C77,Table1[[#All],[BusinessUnitID]],Table1[[#All],[Description]],"",0,1)} -> Transactions related to guest rooms and overall hotel operations. Includes payroll for administrative staff, clerks and interns. | M77: =_xlfn.XLOOKUP($B77,ChartOfAccounts!A76:A161,ChartOfAccounts!B76:B161,"",0,1) | N77: =_xlfn.XLOOKUP($B77,ChartOfAccounts!A76:A161,ChartOfAccounts!D76:D161,0,1) -> Expenses | O77: =_xlfn.XLOOKUP($B77,ChartOfAccounts!A76:A161,ChartOfAccounts!F76:F161,"",0,1) | P77: {=_xlfn.XLOOKUP($D77&$C77,PreparerInfo!A76:A88&PreparerInfo!C76:C88,PreparerInfo!B76:B88,"",0,1)} | Q77: =_xlfn.XLOOKUP($E77,Source!A76:A84,Source!B76:B84,"",0,1)
A78: 2033558 | B78: 11845 | C78: 1 | D78: 106 | E78: 1003 | F78: 44004 | G78: CONFERENCE - FOOD SERVICE | H78: 138.16 | J78: 138.16 | K78: =_xlfn.XLOOKUP($C78,Table1[BusinessUnitID],Table1[BusinessUnit],"",0) -> FOOD SERVICE | L78: {=_xlfn.XLOOKUP($C78,Table1[[#All],[BusinessUnitID]],Table1[[#All],[Description]],"",0,1)} -> Transactions related to food and beverage service. Includes all guest transactions in the hotel restaurants, catering-related transactions and food service payroll. | M78: =_xlfn.XLOOKUP($B78,ChartOfAccounts!A77:A162,ChartOfAccounts!B77:B162,"",0,1) | N78: =_xlfn.XLOOKUP($B78,ChartOfAccounts!A77:A162,ChartOfAccounts!D77:D162,0,1) -> Expenses | O78: =_xlfn.XLOOKUP($B78,ChartOfAccounts!A77:A162,ChartOfAccounts!F77:F162,"",0,1) | P78: {=_xlfn.XLOOKUP($D78&$C78,PreparerInfo!A77:A89&PreparerInfo!C77:C89,PreparerInfo!B77:B89,"",0,1)} | Q78: =_xlfn.XLOOKUP($E78,Source!A77:A85,Source!B77:B85,"",0,1)
A79: 2033558 | B79: 43310 | C79: 1 | D79: 106 | E79: 1003 | F79: 44004 | G79: CONFERENCE - FOOD SERVICE | I79: -138.16 | J79: -138.16 | K79: =_xlfn.XLOOKUP($C79,Table1[BusinessUnitID],Table1[BusinessUnit],"",0) -> FOOD SERVICE | L79: {=_xlfn.XLOOKUP($C79,Table1[[#All],[BusinessUnitID]],Table1[[#All],[Description]],"",0,1)} -> Transactions related to food and beverage service. Includes all guest transactions in the hotel restaurants, catering-related transactions and food service payroll. | M79: =_xlfn.XLOOKUP($B79,ChartOfAccounts!A78:A163,ChartOfAccounts!B78:B163,"",0,1) | N79: =_xlfn.XLOOKUP($B79,ChartOfAccounts!A78:A163,ChartOfAccounts!D78:D163,0,1) -> Expenses | O79: =_xlfn.XLOOKUP($B79,ChartOfAccounts!A78:A163,ChartOfAccounts!F78:F163,"",0,1) | P79: {=_xlfn.XLOOKUP($D79&$C79,PreparerInfo!A78:A90&PreparerInfo!C78:C90,PreparerInfo!B78:B90,"",0,1)} | Q79: =_xlfn.XLOOKUP($E79,Source!A78:A86,Source!B78:B86,"",0,1)
A80: 2033559 | B80: 71400 | C80: 1 | D80: 101 | E80: 1002 | F80: 44004 | G80: PURE WATER TECHNOLOG | H80: 159.9 | J80: 159.9 | K80: =_xlfn.XLOOKUP($C80,Table1[BusinessUnitID],Table1[BusinessUnit],"",0) -> FOOD SERVICE | L80: {=_xlfn.XLOOKUP($C80,Table1[[#All],[BusinessUnitID]],Table1[[#All],[Description]],"",0,1)} -> Transactions related to food and beverage service. Includes all guest transactions in the hotel restaurants, catering-related transactions and food service payroll. | M80: =_xlfn.XLOOKUP($B80,ChartOfAccounts!A79:A164,ChartOfAccounts!B79:B164,"",0,1) | N80: =_xlfn.XLOOKUP($B80,ChartOfAccounts!A79:A164,ChartOfAccounts!D79:D164,0,1) -> Expenses | O80: =_xlfn.XLOOKUP($B80,ChartOfAccounts!A79:A164,ChartOfAccounts!F79:F164,"",0,1) | P80: {=_xlfn.XLOOKUP($D80&$C80,PreparerInfo!A79:A91&PreparerInfo!C79:C91,PreparerInfo!B79:B91,"",0,1)} | Q80: =_xlfn.XLOOKUP($E80,Source!A79:A87,Source!B79:B87,"",0,1)
A81: 2033559 | B81: 11845 | C81: 1 | D81: 101 | E81: 1002 | F81: 44004 | G81: PURE WATER TECHNOLOG | I81: -159.9 | J81: -159.9 | K81: =_xlfn.XLOOKUP($C81,Table1[BusinessUnitID],Table1[BusinessUnit],"",0) -> FOOD SERVICE | L81: {=_xlfn.XLOOKUP($C81,Table1[[#All],[BusinessUnitID]],Table1[[#All],[Description]],"",0,1)} -> Transactions related to food and beverage service. Includes all guest transactions in the hotel restaurants, catering-related transactions and food service payroll. | M81: =_xlfn.XLOOKUP($B81,ChartOfAccounts!A80:A165,ChartOfAccounts!B80:B165,"",0,1) | N81: =_xlfn.XLOOKUP($B81,ChartOfAccounts!A80:A165,ChartOfAccounts!D80:D165,0,1) -> Expenses | O81: =_xlfn.XLOOKUP($B81,ChartOfAccounts!A80:A165,ChartOfAccounts!F80:F165,"",0,1) | P81: {=_xlfn.XLOOKUP($D81&$C81,PreparerInfo!A80:A92&PreparerInfo!C80:C92,PreparerInfo!B80:B92,"",0,1)} | Q81: =_xlfn.XLOOKUP($E81,Source!A80:A88,Source!B80:B88,"",0,1)
A82: 2033560 | B82: 71400 | C82: 1 | D82: 101 | E82: 1002 | F82: 44004 | G82: PURE WATER TECHNOLOG | H82: 159.9 | J82: 159.9 | K82: =_xlfn.XLOOKUP($C82,Table1[BusinessUnitID],Table1[BusinessUnit],"",0) -> FOOD SERVICE | L82: {=_xlfn.XLOOKUP($C82,Table1[[#All],[BusinessUnitID]],Table1[[#All],[Description]],"",0,1)} -> Transactions related to food and beverage service. Includes all guest transactions in the hotel restaurants, catering-related transactions and food service payroll. | M82: =_xlfn.XLOOKUP($B82,ChartOfAccounts!A81:A166,ChartOfAccounts!B81:B166,"",0,1) | N82: =_xlfn.XLOOKUP($B82,ChartOfAccounts!A81:A166,ChartOfAccounts!D81:D166,0,1) -> Expenses | O82: =_xlfn.XLOOKUP($B82,ChartOfAccounts!A81:A166,ChartOfAccounts!F81:F166,"",0,1) | P82: {=_xlfn.XLOOKUP($D82&$C82,PreparerInfo!A81:A93&PreparerInfo!C81:C93,PreparerInfo!B81:B93,"",0,1)} | Q82: =_xlfn.XLOOKUP($E82,Source!A81:A89,Source!B81:B89,"",0,1)
A83: 2033560 | B83: 11845 | C83: 1 | D83: 101 | E83: 1002 | F83: 44004 | G83: PURE WATER TECHNOLOG | I83: -159.9 | J83: -159.9 | K83: =_xlfn.XLOOKUP($C83,Table1[BusinessUnitID],Table1[BusinessUnit],"",0) -> FOOD SERVICE | L83: {=_xlfn.XLOOKUP($C83,Table1[[#All],[BusinessUnitID]],Table1[[#All],[Description]],"",0,1)} -> Transactions related to food and beverage service. Includes all guest transactions in the hotel restaurants, catering-related transactions and food service payroll. | M83: =_xlfn.XLOOKUP($B83,ChartOfAccounts!A82:A167,ChartOfAccounts!B82:B167,"",0,1) | N83: =_xlfn.XLOOKUP($B83,ChartOfAccounts!A82:A167,ChartOfAccounts!D82:D167,0,1) -> Expenses | O83: =_xlfn.XLOOKUP($B83,ChartOfAccounts!A82:A167,ChartOfAccounts!F82:F167,"",0,1) | P83: {=_xlfn.XLOOKUP($D83&$C83,PreparerInfo!A82:A94&PreparerInfo!C82:C94,PreparerInfo!B82:B94,"",0,1)} | Q83: =_xlfn.XLOOKUP($E83,Source!A82:A90,Source!B82:B90,"",0,1)
A84: 2033561 | B84: 71400 | C84: 1 | D84: 101 | E84: 1002 | F84: 44004 | G84: PURE WATER TECHNOLOG | H84: 159.9 | J84: 159.9 | K84: =_xlfn.XLOOKUP($C84,Table1[BusinessUnitID],Table1[BusinessUnit],"",0) -> FOOD SERVICE | L84: {=_xlfn.XLOOKUP($C84,Table1[[#All],[BusinessUnitID]],Table1[[#All],[Description]],"",0,1)} -> Transactions related to food and beverage service. Includes all guest transactions in the hotel restaurants, catering-related transactions and food service payroll. | M84: =_xlfn.XLOOKUP($B84,ChartOfAccounts!A83:A168,ChartOfAccounts!B83:B168,"",0,1) | N84: =_xlfn.XLOOKUP($B84,ChartOfAccounts!A83:A168,ChartOfAccounts!D83:D168,0,1) -> Expenses | O84: =_xlfn.XLOOKUP($B84,ChartOfAccounts!A83:A168,ChartOfAccounts!F83:F168,"",0,1) | P84: {=_xlfn.XLOOKUP($D84&$C84,PreparerInfo!A83:A95&PreparerInfo!C83:C95,PreparerInfo!B83:B95,"",0,1)} | Q84: =_xlfn.XLOOKUP($E84,Source!A83:A91,Source!B83:B91,"",0,1)
A85: 2033561 | B85: 11845 | C85: 1 | D85: 101 | E85: 1002 | F85: 44004 | G85: PURE WATER TECHNOLOG | I85: -159.9 | J85: -159.9 | K85: =_xlfn.XLOOKUP($C85,Table1[BusinessUnitID],Table1[BusinessUnit],"",0) -> FOOD SERVICE | L85: {=_xlfn.XLOOKUP($C85,Table1[[#All],[BusinessUnitID]],Table1[[#All],[Description]],"",0,1)} -> Transactions related to food and beverage service. Includes all guest transactions in the hotel restaurants, catering-related transactions and food service payroll. | M85: =_xlfn.XLOOKUP($B85,ChartOfAccounts!A84:A169,ChartOfAccounts!B84:B169,"",0,1) | N85: =_xlfn.XLOOKUP($B85,ChartOfAccounts!A84:A169,ChartOfAccounts!D84:D169,0,1) -> Expenses | O85: =_xlfn.XLOOKUP($B85,ChartOfAccounts!A84:A169,ChartOfAccounts!F84:F169,"",0,1) | P85: {=_xlfn.XLOOKUP($D85&$C85,PreparerInfo!A84:A96&PreparerInfo!C84:C96,PreparerInfo!B84:B96,"",0,1)} | Q85: =_xlfn.XLOOKUP($E85,Source!A84:A92,Source!B84:B92,"",0,1)
A86: 2033562 | B86: 71400 | C86: 1 | D86: 101 | E86: 1002 | F86: 44004 | G86: PURE WATER TECHNOLOG | H86: 159.9 | J86: 159.9 | K86: =_xlfn.XLOOKUP($C86,Table1[BusinessUnitID],Table1[BusinessUnit],"",0) -> FOOD SERVICE | L86: {=_xlfn.XLOOKUP($C86,Table1[[#All],[BusinessUnitID]],Table1[[#All],[Description]],"",0,1)} -> Transactions related to food and beverage service. Includes all guest transactions in the hotel restaurants, catering-related transactions and food service payroll. | M86: =_xlfn.XLOOKUP($B86,ChartOfAccounts!A85:A170,ChartOfAccounts!B85:B170,"",0,1) | N86: =_xlfn.XLOOKUP($B86,ChartOfAccounts!A85:A170,ChartOfAccounts!D85:D170,0,1) -> Expenses | O86: =_xlfn.XLOOKUP($B86,ChartOfAccounts!A85:A170,ChartOfAccounts!F85:F170,"",0,1) | P86: {=_xlfn.XLOOKUP($D86&$C86,PreparerInfo!A85:A97&PreparerInfo!C85:C97,PreparerInfo!B85:B97,"",0,1)} | Q86: =_xlfn.XLOOKUP($E86,Source!A85:A93,Source!B85:B93,"",0,1)
A87: 2033562 | B87: 11845 | C87: 1 | D87: 101 | E87: 1002 | F87: 44004 | G87: PURE WATER TECHNOLOG | I87: -159.9 | J87: -159.9 | K87: =_xlfn.XLOOKUP($C87,Table1[BusinessUnitID],Table1[BusinessUnit],"",0) -> FOOD SERVICE | L87: {=_xlfn.XLOOKUP($C87,Table1[[#All],[BusinessUnitID]],Table1[[#All],[Description]],"",0,1)} -> Transactions related to food and beverage service. Includes all guest transactions in the hotel restaurants, catering-related transactions and food service payroll. | M87: =_xlfn.XLOOKUP($B87,ChartOfAccounts!A86:A171,ChartOfAccounts!B86:B171,"",0,1) | N87: =_xlfn.XLOOKUP($B87,ChartOfAccounts!A86:A171,ChartOfAccounts!D86:D171,0,1) -> Expenses | O87: =_xlfn.XLOOKUP($B87,ChartOfAccounts!A86:A171,ChartOfAccounts!F86:F171,"",0,1) | P87: {=_xlfn.XLOOKUP($D87&$C87,PreparerInfo!A86:A98&PreparerInfo!C86:C98,PreparerInfo!B86:B98,"",0,1)} | Q87: =_xlfn.XLOOKUP($E87,Source!A86:A94,Source!B86:B94,"",0,1)
A88: 2033563 | B88: 71400 | C88: 1 | D88: 101 | E88: 1002 | F88: 44004 | G88: PURE WATER TECHNOLOG | H88: 159.9 | J88: 159.9 | K88: =_xlfn.XLOOKUP($C88,Table1[BusinessUnitID],Table1[BusinessUnit],"",0) -> FOOD SERVICE | L88: {=_xlfn.XLOOKUP($C88,Table1[[#All],[BusinessUnitID]],Table1[[#All],[Description]],"",0,1)} -> Transactions related to food and beverage service. Includes all guest transactions in the hotel restaurants, catering-related transactions and food service payroll. | M88: =_xlfn.XLOOKUP($B88,ChartOfAccounts!A87:A172,ChartOfAccounts!B87:B172,"",0,1) | N88: =_xlfn.XLOOKUP($B88,ChartOfAccounts!A87:A172,ChartOfAccounts!D87:D172,0,1) -> 0 | O88: =_xlfn.XLOOKUP($B88,ChartOfAccounts!A87:A172,ChartOfAccounts!F87:F172,"",0,1) | P88: {=_xlfn.XLOOKUP($D88&$C88,PreparerInfo!A87:A99&PreparerInfo!C87:C99,PreparerInfo!B87:B99,"",0,1)} | Q88: =_xlfn.XLOOKUP($E88,Source!A87:A95,Source!B87:B95,"",0,1)
A89: 2033563 | B89: 11845 | C89: 1 | D89: 101 | E89: 1002 | F89: 44004 | G89: PURE WATER TECHNOLOG | I89: -159.9 | J89: -159.9 | K89: =_xlfn.XLOOKUP($C89,Table1[BusinessUnitID],Table1[BusinessUnit],"",0) -> FOOD SERVICE | L89: {=_xlfn.XLOOKUP($C89,Table1[[#All],[BusinessUnitID]],Table1[[#All],[Description]],"",0,1)} -> Transactions related to food and beverage service. Includes all guest transactions in the hotel restaurants, catering-related transactions and food service payroll. | M89: =_xlfn.XLOOKUP($B89,ChartOfAccounts!A88:A173,ChartOfAccounts!B88:B173,"",0,1) | N89: =_xlfn.XLOOKUP($B89,ChartOfAccounts!A88:A173,ChartOfAccounts!D88:D173,0,1) -> 0 | O89: =_xlfn.XLOOKUP($B89,ChartOfAccounts!A88:A173,ChartOfAccounts!F88:F173,"",0,1) | P89: {=_xlfn.XLOOKUP($D89&$C89,PreparerInfo!A88:A100&PreparerInfo!C88:C100,PreparerInfo!B88:B100,"",0,1)} | Q89: =_xlfn.XLOOKUP($E89,Source!A88:A96,Source!B88:B96,"",0,1)
A90: 2033564 | B90: 11845 | C90: 2 | D90: 104 | E90: 1003 | F90: 44004 | G90: COPELAND,MELODY | H90: 198 | J90: 198 | K90: =_xlfn.XLOOKUP($C90,Table1[BusinessUnitID],Table1[BusinessUnit],"",0) -> HOTEL | L90: {=_xlfn.XLOOKUP($C90,Table1[[#All],[BusinessUnitID]],Table1[[#All],[Description]],"",0,1)} -> Transactions related to guest rooms and overall hotel operations. Includes payroll for administrative staff, clerks and interns. | M90: =_xlfn.XLOOKUP($B90,ChartOfAccounts!A89:A174,ChartOfAccounts!B89:B174,"",0,1) | N90: =_xlfn.XLOOKUP($B90,ChartOfAccounts!A89:A174,ChartOfAccounts!D89:D174,0,1) -> 0 | O90: =_xlfn.XLOOKUP($B90,ChartOfAccounts!A89:A174,ChartOfAccounts!F89:F174,"",0,1) | P90: {=_xlfn.XLOOKUP($D90&$C90,PreparerInfo!A89:A101&PreparerInfo!C89:C101,PreparerInfo!B89:B101,"",0,1)} | Q90: =_xlfn.XLOOKUP($E90,Source!A89:A97,Source!B89:B97,"",0,1)
A91: 2033564 | B91: 43180 | C91: 2 | D91: 104 | E91: 1003 | F91: 44004 | G91: COPELAND,MELODY | I91: -198 | J91: -198 | K91: =_xlfn.XLOOKUP($C91,Table1[BusinessUnitID],Table1[BusinessUnit],"",0) -> HOTEL | L91: {=_xlfn.XLOOKUP($C91,Table1[[#All],[BusinessUnitID]],Table1[[#All],[Description]],"",0,1)} -> Transactions related to guest rooms and overall hotel operations. Includes payroll for administrative staff, clerks and interns. | M91: =_xlfn.XLOOKUP($B91,ChartOfAccounts!A90:A175,ChartOfAccounts!B90:B175,"",0,1) | N91: =_xlfn.XLOOKUP($B91,ChartOfAccounts!A90:A175,ChartOfAccounts!D90:D175,0,1) -> 0 | O91: =_xlfn.XLOOKUP($B91,ChartOfAccounts!A90:A175,ChartOfAccounts!F90:F175,"",0,1) | P91: {=_xlfn.XLOOKUP($D91&$C91,PreparerInfo!A90:A102&PreparerInfo!C90:C102,PreparerInfo!B90:B102,"",0,1)} | Q91: =_xlfn.XLOOKUP($E91,Source!A90:A98,Source!B90:B98,"",0,1)
A92: 2033565 | B92: 14260 | C92: 1 | D92: 101 | E92: 1002 | F92: 44004 | G92: EMILY R ANDERSON P | H92: 223 | J92: 223 | K92: =_xlfn.XLOOKUP($C92,Table1[BusinessUnitID],Table1[BusinessUnit],"",0) -> FOOD SERVICE | L92: {=_xlfn.XLOOKUP($C92,Table1[[#All],[BusinessUnitID]],Table1[[#All],[Description]],"",0,1)} -> Transactions related to food and beverage service. Includes all guest transactions in the hotel restaurants, catering-related transactions and food service payroll. | M92: =_xlfn.XLOOKUP($B92,ChartOfAccounts!A91:A176,ChartOfAccounts!B91:B176,"",0,1) | N92: =_xlfn.XLOOKUP($B92,ChartOfAccounts!A91:A176,ChartOfAccounts!D91:D176,0,1) -> 0 | O92: =_xlfn.XLOOKUP($B92,ChartOfAccounts!A91:A176,ChartOfAccounts!F91:F176,"",0,1) | P92: {=_xlfn.XLOOKUP($D92&$C92,PreparerInfo!A91:A103&PreparerInfo!C91:C103,PreparerInfo!B91:B103,"",0,1)} | Q92: =_xlfn.XLOOKUP($E92,Source!A91:A99,Source!B91:B99,"",0,1)
A93: 2033565 | B93: 11845 | C93: 1 | D93: 101 | E93: 1002 | F93: 44004 | G93: EMILY R ANDERSON P | I93: -223 | J93: -223 | K93: =_xlfn.XLOOKUP($C93,Table1[BusinessUnitID],Table1[BusinessUnit],"",0) -> FOOD SERVICE | L93: {=_xlfn.XLOOKUP($C93,Table1[[#All],[BusinessUnitID]],Table1[[#All],[Description]],"",0,1)} -> Transactions related to food and beverage service. Includes all guest transactions in the hotel restaurants, catering-related transactions and food service payroll. | M93: =_xlfn.XLOOKUP($B93,ChartOfAccounts!A92:A177,ChartOfAccounts!B92:B177,"",0,1) | N93: =_xlfn.XLOOKUP($B93,ChartOfAccounts!A92:A177,ChartOfAccounts!D92:D177,0,1) -> 0 | O93: =_xlfn.XLOOKUP($B93,ChartOfAccounts!A92:A177,ChartOfAccounts!F92:F177,"",0,1) | P93: {=_xlfn.XLOOKUP($D93&$C93,PreparerInfo!A92:A104&PreparerInfo!C92:C104,PreparerInfo!B92:B104,"",0,1)} | Q93: =_xlfn.XLOOKUP($E93,Source!A92:A100,Source!B92:B100,"",0,1)
A94: 2033566 | B94: 11845 | C94: 1 | D94: 102 | E94: 1003 | F94: 44004 | G94: CREDIT CARD RECEIPTS | H94: 228.59 | J94: 228.59 | K94: =_xlfn.XLOOKUP($C94,Table1[BusinessUnitID],Table1[BusinessUnit],"",0) -> FOOD SERVICE | L94: {=_xlfn.XLOOKUP($C94,Table1[[#All],[BusinessUnitID]],Table1[[#All],[Description]],"",0,1)} -> Transactions related to food and beverage service. Includes all guest transactions in the hotel restaurants, catering-related transactions and food service payroll. | M94: =_xlfn.XLOOKUP($B94,ChartOfAccounts!A93:A178,ChartOfAccounts!B93:B178,"",0,1) | N94: =_xlfn.XLOOKUP($B94,ChartOfAccounts!A93:A178,ChartOfAccounts!D93:D178,0,1) -> 0 | O94: =_xlfn.XLOOKUP($B94,ChartOfAccounts!A93:A178,ChartOfAccounts!F93:F178,"",0,1) | P94: {=_xlfn.XLOOKUP($D94&$C94,PreparerInfo!A93:A105&PreparerInfo!C93:C105,PreparerInfo!B93:B105,"",0,1)} | Q94: =_xlfn.XLOOKUP($E94,Source!A93:A101,Source!B93:B101,"",0,1)
A95: 2033566 | B95: 43310 | C95: 1 | D95: 102 | E95: 1003 | F95: 44004 | G95: CREDIT CARD RECEIPTS | I95: -228.59 | J95: -228.59 | K95: =_xlfn.XLOOKUP($C95,Table1[BusinessUnitID],Table1[BusinessUnit],"",0) -> FOOD SERVICE | L95: {=_xlfn.XLOOKUP($C95,Table1[[#All],[BusinessUnitID]],Table1[[#All],[Description]],"",0,1)} -> Transactions related to food and beverage service. Includes all guest transactions in the hotel restaurants, catering-related transactions and food service payroll. | M95: =_xlfn.XLOOKUP($B95,ChartOfAccounts!A94:A179,ChartOfAccounts!B94:B179,"",0,1) | N95: =_xlfn.XLOOKUP($B95,ChartOfAccounts!A94:A179,ChartOfAccounts!D94:D179,0,1) -> 0 | O95: =_xlfn.XLOOKUP($B95,ChartOfAccounts!A94:A179,ChartOfAccounts!F94:F179,"",0,1) | P95: {=_xlfn.XLOOKUP($D95&$C95,PreparerInfo!A94:A106&PreparerInfo!C94:C106,PreparerInfo!B94:B106,"",0,1)} | Q95: =_xlfn.XLOOKUP($E95,Source!A94:A102,Source!B94:B102,"",0,1)
A96: 2033567 | B96: 71400 | C96: 2 | D96: 101 | E96: 1002 | F96: 44004 | G96: ZEP SALES & 68668209 | H96: 240.73 | J96: 240.73 | K96: =_xlfn.XLOOKUP($C96,Table1[BusinessUnitID],Table1[BusinessUnit],"",0) -> HOTEL | L96: {=_xlfn.XLOOKUP($C96,Table1[[#All],[BusinessUnitID]],Table1[[#All],[Description]],"",0,1)} -> Transactions related to guest rooms and overall hotel operations. Includes payroll for administrative staff, clerks and interns. | M96: =_xlfn.XLOOKUP($B96,ChartOfAccounts!A95:A180,ChartOfAccounts!B95:B180,"",0,1) | N96: =_xlfn.XLOOKUP($B96,ChartOfAccounts!A95:A180,ChartOfAccounts!D95:D180,0,1) -> 0 | O96: =_xlfn.XLOOKUP($B96,ChartOfAccounts!A95:A180,ChartOfAccounts!F95:F180,"",0,1) | P96: {=_xlfn.XLOOKUP($D96&$C96,PreparerInfo!A95:A107&PreparerInfo!C95:C107,PreparerInfo!B95:B107,"",0,1)} | Q96: =_xlfn.XLOOKUP($E96,Source!A95:A103,Source!B95:B103,"",0,1)
A97: 2033567 | B97: 11845 | C97: 2 | D97: 101 | E97: 1002 | F97: 44004 | G97: ZEP SALES & 68668209 | I97: -240.73 | J97: -240.73 | K97: =_xlfn.XLOOKUP($C97,Table1[BusinessUnitID],Table1[BusinessUnit],"",0) -> HOTEL | L97: {=_xlfn.XLOOKUP($C97,Table1[[#All],[BusinessUnitID]],Table1[[#All],[Description]],"",0,1)} -> Transactions related to guest rooms and overall hotel operations. Includes payroll for administrative staff, clerks and interns. | M97: =_xlfn.XLOOKUP($B97,ChartOfAccounts!A96:A181,ChartOfAccounts!B96:B181,"",0,1) | N97: =_xlfn.XLOOKUP($B97,ChartOfAccounts!A96:A181,ChartOfAccounts!D96:D181,0,1) -> 0 | O97: =_xlfn.XLOOKUP($B97,ChartOfAccounts!A96:A181,ChartOfAccounts!F96:F181,"",0,1) | P97: {=_xlfn.XLOOKUP($D97&$C97,PreparerInfo!A96:A108&PreparerInfo!C96:C108,PreparerInfo!B96:B108,"",0,1)} | Q97: =_xlfn.XLOOKUP($E97,Source!A96:A104,Source!B96:B104,"",0,1)
A98: 2033568 | B98: 11845 | C98: 2 | D98: 104 | E98: 1003 | F98: 44004 | G98: MCCONNELL,MARCOS | H98: 258 | J98: 258 | K98: =_xlfn.XLOOKUP($C98,Table1[BusinessUnitID],Table1[BusinessUnit],"",0) -> HOTEL | L98: {=_xlfn.XLOOKUP($C98,Table1[[#All],[BusinessUnitID]],Table1[[#All],[Description]],"",0,1)} -> Transactions related to guest rooms and overall hotel operations. Includes payroll for administrative staff, clerks and interns. | M98: =_xlfn.XLOOKUP($B98,ChartOfAccounts!A97:A182,ChartOfAccounts!B97:B182,"",0,1) | N98: =_xlfn.XLOOKUP($B98,ChartOfAccounts!A97:A182,ChartOfAccounts!D97:D182,0,1) -> 0 | O98: =_xlfn.XLOOKUP($B98,ChartOfAccounts!A97:A182,ChartOfAccounts!F97:F182,"",0,1) | P98: {=_xlfn.XLOOKUP($D98&$C98,PreparerInfo!A97:A109&PreparerInfo!C97:C109,PreparerInfo!B97:B109,"",0,1)} | Q98: =_xlfn.XLOOKUP($E98,Source!A97:A105,Source!B97:B105,"",0,1)
A99: 2033568 | B99: 43180 | C99: 2 | D99: 104 | E99: 1003 | F99: 44004 | G99: MCCONNELL,MARCOS | I99: -258 | J99: -258 | K99: =_xlfn.XLOOKUP($C99,Table1[BusinessUnitID],Table1[BusinessUnit],"",0) -> HOTEL | L99: {=_xlfn.XLOOKUP($C99,Table1[[#All],[BusinessUnitID]],Table1[[#All],[Description]],"",0,1)} -> Transactions related to guest rooms and overall hotel operations. Includes payroll for administrative staff, clerks and interns. | M99: =_xlfn.XLOOKUP($B99,ChartOfAccounts!A98:A183,ChartOfAccounts!B98:B183,"",0,1) | N99: =_xlfn.XLOOKUP($B99,ChartOfAccounts!A98:A183,ChartOfAccounts!D98:D183,0,1) -> 0 | O99: =_xlfn.XLOOKUP($B99,ChartOfAccounts!A98:A183,ChartOfAccounts!F98:F183,"",0,1) | P99: {=_xlfn.XLOOKUP($D99&$C99,PreparerInfo!A98:A110&PreparerInfo!C98:C110,PreparerInfo!B98:B110,"",0,1)} | Q99: =_xlfn.XLOOKUP($E99,Source!A98:A106,Source!B98:B106,"",0,1)
A100: 2033569 | B100: 11845 | C100: 2 | D100: 104 | E100: 1003 | F100: 44004 | G100: CAIN,HAVEN | H100: 258 | J100: 258 | K100: =_xlfn.XLOOKUP($C100,Table1[BusinessUnitID],Table1[BusinessUnit],"",0) -> HOTEL | L100: {=_xlfn.XLOOKUP($C100,Table1[[#All],[BusinessUnitID]],Table1[[#All],[Description]],"",0,1)} -> Transactions related to guest rooms and overall hotel operations. Includes payroll for administrative staff, clerks and interns. | M100: =_xlfn.XLOOKUP($B100,ChartOfAccounts!A99:A184,ChartOfAccounts!B99:B184,"",0,1) | N100: =_xlfn.XLOOKUP($B100,ChartOfAccounts!A99:A184,ChartOfAccounts!D99:D184,0,1) -> 0 | O100: =_xlfn.XLOOKUP($B100,ChartOfAccounts!A99:A184,ChartOfAccounts!F99:F184,"",0,1) | P100: {=_xlfn.XLOOKUP($D100&$C100,PreparerInfo!A99:A111&PreparerInfo!C99:C111,PreparerInfo!B99:B111,"",0,1)} | Q100: =_xlfn.XLOOKUP($E100,Source!A99:A107,Source!B99:B107,"",0,1)
...

Sheet use VLookup
A1: JENumber | B1: GLAccountNumber | C1: BusinessUnitID | D1: PreparerID | E1: SourceID | F1: EffectiveDate | G1: JEDescription | H1: Debit | I1: Credit | J1: Amount | K1: BusinessUnit | L1: BUDescription | M1: GLAccountName | N1: AccountType | O1: AccountClass | P1: PreparerName | Q1: Source
A2: 2033520 | B2: 76930 | C2: 1 | D2: 101 | E2: 1002 | F2: 44002 | G2: TELECOM GTA JUN 2016 | H2: 36.9 | J2: 36.9 | K2: =VLOOKUP($C2,Table1[#All],2,FALSE) -> FOOD SERVICE | L2: =VLOOKUP($C2,Table1[#All],3,FALSE) -> Transactions related to food and beverage service. Includes all guest transactions in the hotel restaurants, catering-related transactions and food service payroll. | M2: =IFERROR(VLOOKUP($B2,ChartOfAccounts!A1:B86,2,FALSE),"") -> Telecommunications - Other | N2: =IFERROR(VLOOKUP($B2,ChartOfAccounts!C1:D86,2,FALSE),"") -> Expenses | O2: =IFERROR(VLOOKUP($B2,ChartOfAccounts!E1:F86,2,FALSE),"") -> SG&A | P2: =IFERROR(VLOOKUP(D2,PreparerInfo!A1:B13,2,FALSE),"") -> Carolyn Slater|Food Operations Manager | Q2: =IFERROR(VLOOKUP(E2,Source!A1:B9,2,FALSE),"") -> CHECK
A3: 2033520 | B3: 11845 | C3: 1 | D3: 101 | E3: 1002 | F3: 44002 | G3: TELECOM GTA JUN 2016 | I3: -36.9 | J3: -36.9 | K3: =VLOOKUP($C3,Table1[#All],2,FALSE) -> FOOD SERVICE | L3: =VLOOKUP($C3,Table1[#All],3,FALSE) -> Transactions related to food and beverage service. Includes all guest transactions in the hotel restaurants, catering-related transactions and food service payroll. | M3: =IFERROR(VLOOKUP($B3,ChartOfAccounts!A2:B87,2,FALSE),"") -> Operating Bank Account | N3: =IFERROR(VLOOKUP($B3,ChartOfAccounts!C2:D87,2,FALSE),"") -> Assets | O3: =IFERROR(VLOOKUP($B3,ChartOfAccounts!E2:F87,2,FALSE),"") -> Cash | P3: =IFERROR(VLOOKUP(D3,PreparerInfo!A2:B14,2,FALSE),"") -> Carolyn Slater|Food Operations Manager | Q3: =IFERROR(VLOOKUP(E3,Source!A2:B10,2,FALSE),"") -> CHECK
A4: 2033521 | B4: 11845 | C4: 3 | D4: 102 | E4: 1001 | F4: 44002 | G4: CASH RECEIPTS | H4: 63.1 | J4: 63.1 | K4: =VLOOKUP($C4,Table1[#All],2,FALSE) -> HOTEL PANTRY | L4: =VLOOKUP($C4,Table1[#All],3,FALSE) -> Transactions related to the hotel convenience store, including some food and beverage costs. | M4: =IFERROR(VLOOKUP($B4,ChartOfAccounts!A3:B88,2,FALSE),"") -> Operating Bank Account | N4: =IFERROR(VLOOKUP($B4,ChartOfAccounts!C3:D88,2,FALSE),"") -> Assets | O4: =IFERROR(VLOOKUP($B4,ChartOfAccounts!E3:F88,2,FALSE),"") -> Cash | P4: =IFERROR(VLOOKUP(D4,PreparerInfo!A3:B15,2,FALSE),"") -> Elizabeth Rees|Food Operations Manager | Q4: =IFERROR(VLOOKUP(E4,Source!A3:B11,2,FALSE),"")
A5: 2033521 | B5: 43440 | C5: 3 | D5: 102 | E5: 1001 | F5: 44002 | G5: CASH RECEIPTS | I5: -63.1 | J5: -63.1 | K5: =VLOOKUP($C5,Table1[#All],2,FALSE) -> HOTEL PANTRY | L5: =VLOOKUP($C5,Table1[#All],3,FALSE) -> Transactions related to the hotel convenience store, including some food and beverage costs. | M5: =IFERROR(VLOOKUP($B5,ChartOfAccounts!A4:B89,2,FALSE),"") -> Sales - Other | N5: =IFERROR(VLOOKUP($B5,ChartOfAccounts!C4:D89,2,FALSE),"") -> Revenue | O5: =IFERROR(VLOOKUP($B5,ChartOfAccounts!E4:F89,2,FALSE),"") -> Sales-Other | P5: =IFERROR(VLOOKUP(D5,PreparerInfo!A4:B16,2,FALSE),"") -> Elizabeth Rees|Food Operations Manager | Q5: =IFERROR(VLOOKUP(E5,Source!A4:B12,2,FALSE),"")
