Workbook
Name _Hlk4423505: P4_Q6!$A$1

Sheet P4_Q11
A1: 11.The 2016 data is not broken down by month. Noah wants to estimate what the monthly gross wages are by month.
A2: To do so, Noah requests that you apply the percentage of gross wages earned each month in 2015 to the 2016 total gross wages to estimate the monthly expenditures in 2016.
A3: Display the month (sorted so January is listed first) and the predicted gross wages per month for 2016 (round this number to two decimal points).
A5: Below table columnA,B copied from P4_Q8
A6: 2015 | B6: 2015 Gross_Wages | C6: % of 2015 | D6: Predicted 2016
A7: Jan | B7: 10497752 | C7: =ROUND(Table13[[#This Row],[2015 Gross_Wages]]/$B$16,2) -> 0.16 | D7: =ROUND(Table13[[#This Row],[% of 2015]]*$B$17,2) -> 13748756
A8: Feb | B8: 10313416 | C8: =ROUND(Table13[[#This Row],[2015 Gross_Wages]]/$B$16,2) -> 0.15 | D8: =ROUND(Table13[[#This Row],[% of 2015]]*$B$17,2) -> 12889459
A9: Mar | B9: 11059608 | C9: =ROUND(Table13[[#This Row],[2015 Gross_Wages]]/$B$16,2) -> 0.16 | D9: =ROUND(Table13[[#This Row],[% of 2015]]*$B$17,2) -> 13748756
A10: Apr | B10: 11078106 | C10: =ROUND(Table13[[#This Row],[2015 Gross_Wages]]/$B$16,2) -> 0.16 | D10: =ROUND(Table13[[#This Row],[% of 2015]]*$B$17,2) -> 13748756
A11: May | B11: 13993523 | C11: =ROUND(Table13[[#This Row],[2015 Gross_Wages]]/$B$16,2) -> 0.21 | D11: =ROUND(Table13[[#This Row],[% of 2015]]*$B$17,2) -> 18045242
A12: Jun | B12: 10633648 | C12: =ROUND(Table13[[#This Row],[2015 Gross_Wages]]/$B$16,2) -> 0.16 | D12: =ROUND(Table13[[#This Row],[% of 2015]]*$B$17,2) -> 13748756
A15: Row Labels | B15: Sum of Gross_Wages
A16: 2015 | B16: 67576053
A17: 2016 | B17: 85929725
A18: Grand Total | B18: 153505778

Sheet P4_Q10
A1: 10. Make a table that displays the job code, the predicted 2017 gross wages for the job code, the percentage increase from 2015 to 2016, the gross wages for 2016 and the gross wages for 2015. Round all variables to two decimal places.
A2: For the purposes of this example, Noah only wants to predict 2017 expenses for the first 6 months of the year for each of job codes 001 through 008.
A3: Job code | B3: Predicted 2017 Gross Wages | C3: % Increase | D3: 2015 Gross Pay | E3: 2016 Gross Pay
A4: =TEXT(1,"000") -> 001 | B4: =ROUND(IFERROR((E4/D4)*E4,0),2) -> 26773556 | C4: =ROUND(IFERROR((E4-D4)/D4,0),2) -> 0.43 | D4: =ROUND(P4_Q9!$B8,2) -> 13178934 | E4: =ROUND(P4_Q9!$C8,2) -> 18784220
A5: =TEXT(2,"000") -> 002 | B5: =ROUND(IFERROR((E5/D5)*E5,0),2) -> 40695084 | C5: =ROUND(IFERROR((E5-D5)/D5,0),2) -> 0.01 | D5: =ROUND(P4_Q9!$B9,2) -> 39621371 | E5: =ROUND(P4_Q9!$C9,2) -> 40154639
A6: =TEXT(3,"000") -> 003 | B6: =ROUND(IFERROR((E6/D6)*E6,0),2) -> 1385929.5 | C6: =ROUND(IFERROR((E6-D6)/D6,0),2) -> -0.28 | D6: =ROUND(P4_Q9!$B10,2) -> 2678797 | E6: =ROUND(P4_Q9!$C10,2) -> 1926817
A7: =TEXT(4,"000") -> 004 | B7: =ROUND(IFERROR((E7/D7)*E7,0),2) -> 7272707 | C7: =ROUND(IFERROR((E7-D7)/D7,0),2) -> 0.48 | D7: =ROUND(P4_Q9!$B11,2) -> 3339832 | E7: =ROUND(P4_Q9!$C11,2) -> 4928450
A8: =TEXT(5,"000") -> 005 | B8: =ROUND(IFERROR((E8/D8)*E8,0),2) -> 165645.7 | C8: =ROUND(IFERROR((E8-D8)/D8,0),2) -> 0.01 | D8: =ROUND(P4_Q9!$B12,2) -> 162539 | E8: =ROUND(P4_Q9!$C12,2) -> 164085
A9: =TEXT(6,"000") -> 006 | B9: =ROUND(IFERROR((E9/D9)*E9,0),2) -> 13024980 | C9: =ROUND(IFERROR((E9-D9)/D9,0),2) -> 0.56 | D9: =ROUND(P4_Q9!$B13,2) -> 5376020 | E9: =ROUND(P4_Q9!$C13,2) -> 8367948
A10: =TEXT(7,"000") -> 007 | B10: =ROUND(IFERROR((E10/D10)*E10,0),2) -> 32832.3 | C10: =ROUND(IFERROR((E10-D10)/D10,0),2) -> -0.87 | D10: =ROUND(P4_Q9!$B14,2) -> 2014041 | E10: =ROUND(P4_Q9!$C14,2) -> 257149
A11: =TEXT(8,"000") -> 008 | B11: =ROUND(IFERROR((E11/D11)*E11,0),2) -> 6578863.7 | C11: =ROUND(IFERROR((E11-D11)/D11,0),2) -> 1.34 | D11: =ROUND(P4_Q9!$B15,2) -> 1204204 | E11: =ROUND(P4_Q9!$C15,2) -> 2814657

Sheet P4_Q9
A1: 1. Noah wants to predict his likely gross wage expenses for the first six months for each job code in 2017. To make the prediction, you will use the following formula:
A5: Answer: Please find the predicted 2017 wages for each job as below table
A6: Sum of Gross_Wages | B6: Column Labels
A7: Row Labels | B7: 2015 | C7: 2016 | D7: % Increase | E7: Predicted 2017 Wages
A8: 001 | B8: 13178934 | C8: 18784220 | D8: =IFERROR((C8-B8)/B8,0) -> 0.42532165 | E8: =IFERROR((C8/B8)*C8,0) -> 26773556
A9: 002 | B9: 39621371 | C9: 40154639 | D9: =IFERROR((C9-B9)/B9,0) -> 0.0134591 | E9: =IFERROR((C9/B9)*C9,0) -> 40695084
A10: 003 | B10: 2678797 | C10: 1926817 | D10: =IFERROR((C10-B10)/B10,0) -> -0.28071556 | E10: =IFERROR((C10/B10)*C10,0) -> 1385929.5
A11: 004 | B11: 3339832 | C11: 4928450 | D11: =IFERROR((C11-B11)/B11,0) -> 0.47565806 | E11: =IFERROR((C11/B11)*C11,0) -> 7272707
A12: 005 | B12: 162539 | C12: 164085 | D12: =IFERROR((C12-B12)/B12,0) -> 0.0095115634 | E12: =IFERROR((C12/B12)*C12,0) -> 165645.7
A13: 006 | B13: 5376020 | C13: 8367948 | D13: =IFERROR((C13-B13)/B13,0) -> 0.55653216 | E13: =IFERROR((C13/B13)*C13,0) -> 13024980
A14: 007 | B14: 2014041 | C14: 257149 | D14: =IFERROR((C14-B14)/B14,0) -> -0.87232186 | E14: =IFERROR((C14/B14)*C14,0) -> 32832.305
A15: 008 | B15: 1204204 | C15: 2814657 | D15: =IFERROR((C15-B15)/B15,0) -> 1.337359 | E15: =IFERROR((C15/B15)*C15,0) -> 6578863.7
A16: 009 | B16: 0 | C16: 6238118 | D16: =IFERROR((C16-B16)/B16,0) -> 0 | E16: =IFERROR((C16/B16)*C16,0) -> 0
A17: 010 | B17: 0 | C17: 1270293 | D17: =IFERROR((C17-B17)/B17,0) -> 0 | E17: =IFERROR((C17/B17)*C17,0) -> 0
A18: 011 | B18: 0 | C18: 70281 | D18: =IFERROR((C18-B18)/B18,0) -> 0 | E18: =IFERROR((C18/B18)*C18,0) -> 0
A19: 012 | B19: 0 | C19: 953068 | D19: =IFERROR((C19-B19)/B19,0) -> 0 | E19: =IFERROR((C19/B19)*C19,0) -> 0

Sheet P4_Q8
A1: 8. Noah wants to better understand monthly cash flows. To do this, he wants to know the monthly pattern of expenses for gross wages in 2015 (monthly wages are not available for 2016).
A2: That is, prepare a table that shows each month (sorted so January is listed first) and how much the amount of gross wages for that month differs from the average of the gross wages for the first six months.
A3: Positive values should show that the average for that month was more than the overall average. Using a formula, round your answers to two decimal places. Which month or months should Noah plan to have extra cash for higher-than-normal wage expenses?
A5: Answer: Noah should plan to have extra cash available in May, as it is the only month with higher-than-normal wage expenses during the first half of 2015.
A7: Row Labels | B7: Sum of Gross_Wages | C7: Difference
A8: Jan | B8: 10497752 | C8: =ROUND($B8-$B$15,2) -> -764923.5
A9: Feb | B9: 10313416 | C9: =ROUND($B9-$B$15,2) -> -949259.5
A10: Mar | B10: 11059608 | C10: =ROUND($B10-$B$15,2) -> -203067.5
A11: Apr | B11: 11078106 | C11: =ROUND($B11-$B$15,2) -> -184569.5
A12: May | B12: 13993523 | C12: =ROUND($B12-$B$15,2) -> 2730847.5
A13: Jun | B13: 10633648 | C13: =ROUND($B13-$B$15,2) -> -629027.5
A14: Grand Total | B14: 67576053
A15: Average | B15: =AVERAGE(B8:B13) -> 11262676

Sheet P4_Q7
A1: 7. Noah would like to know the percentage of each employee’s wages categorized into the different job codes for 2016. Display a chart that lists each employee in a separate row and each job code in a separate and unique column.
A2: Then, display the percentage of each employee’s 2016 pay that is associated with each job code (this means each employee’s row should sum to 100%, within 1% to 2% to accommodate for errors).
A3: Remove all observations that do not include an employee name or employees with no hours in 2016 on the list. For the final display, round the values to two decimal places using a formula. Sort the results by the employee’s name.
A4: Employee | B4: 001 | C4: 002 | D4: 003 | E4: 004 | F4: 005 | G4: 006 | H4: 007 | I4: 008 | J4: 009 | K4: 010 | L4: 011 | M4: 012
A5: Afton Call | B5: =ROUND(P4_Q7_Pivot!$B7,2) -> 0.08 | C5: =ROUND(P4_Q7_Pivot!$C7,2) -> 0 | D5: =ROUND(P4_Q7_Pivot!$D7,2) -> 0 | E5: =ROUND(P4_Q7_Pivot!$E7,2) -> 0.02 | F5: =ROUND(P4_Q7_Pivot!$F7,2) -> 0.1 | G5: =ROUND(P4_Q7_Pivot!$G7,2) -> 0 | H5: =ROUND(P4_Q7_Pivot!$H7,2) -> 0 | I5: =ROUND(P4_Q7_Pivot!$I7,2) -> 0.17 | J5: =ROUND(P4_Q7_Pivot!$J7,2) -> 0.25 | K5: =ROUND(P4_Q7_Pivot!$K7,2) -> 0.13 | L5: =ROUND(P4_Q7_Pivot!$L7,2) -> 0.13 | M5: =ROUND(P4_Q7_Pivot!$M7,2) -> 0.13
A6: Al Ramos | B6: =ROUND(P4_Q7_Pivot!$B8,2) -> 0 | C6: =ROUND(P4_Q7_Pivot!$C8,2) -> 0.95 | D6: =ROUND(P4_Q7_Pivot!$D8,2) -> 0 | E6: =ROUND(P4_Q7_Pivot!$E8,2) -> 0 | F6: =ROUND(P4_Q7_Pivot!$F8,2) -> 0 | G6: =ROUND(P4_Q7_Pivot!$G8,2) -> 0 | H6: =ROUND(P4_Q7_Pivot!$H8,2) -> 0 | I6: =ROUND(P4_Q7_Pivot!$I8,2) -> 0 | J6: =ROUND(P4_Q7_Pivot!$J8,2) -> 0.03 | K6: =ROUND(P4_Q7_Pivot!$K8,2) -> 0.02 | L6: =ROUND(P4_Q7_Pivot!$L8,2) -> 0 | M6: =ROUND(P4_Q7_Pivot!$M8,2) -> 0.01
A7: Alberta Gill | B7: =ROUND(P4_Q7_Pivot!$B9,2) -> 0 | C7: =ROUND(P4_Q7_Pivot!$C9,2) -> 0 | D7: =ROUND(P4_Q7_Pivot!$D9,2) -> 0.11 | E7: =ROUND(P4_Q7_Pivot!$E9,2) -> 0 | F7: =ROUND(P4_Q7_Pivot!$F9,2) -> 0 | G7: =ROUND(P4_Q7_Pivot!$G9,2) -> 0 | H7: =ROUND(P4_Q7_Pivot!$H9,2) -> 0 | I7: =ROUND(P4_Q7_Pivot!$I9,2) -> 0.22 | J7: =ROUND(P4_Q7_Pivot!$J9,2) -> 0.2 | K7: =ROUND(P4_Q7_Pivot!$K9,2) -> 0.19 | L7: =ROUND(P4_Q7_Pivot!$L9,2) -> 0 | M7: =ROUND(P4_Q7_Pivot!$M9,2) -> 0.28
A8: Allan Wood | B8: =ROUND(P4_Q7_Pivot!$B10,2) -> 0 | C8: =ROUND(P4_Q7_Pivot!$C10,2) -> 0.92 | D8: =ROUND(P4_Q7_Pivot!$D10,2) -> 0 | E8: =ROUND(P4_Q7_Pivot!$E10,2) -> 0 | F8: =ROUND(P4_Q7_Pivot!$F10,2) -> 0 | G8: =ROUND(P4_Q7_Pivot!$G10,2) -> 0 | H8: =ROUND(P4_Q7_Pivot!$H10,2) -> 0 | I8: =ROUND(P4_Q7_Pivot!$I10,2) -> 0 | J8: =ROUND(P4_Q7_Pivot!$J10,2) -> 0.07 | K8: =ROUND(P4_Q7_Pivot!$K10,2) -> 0.01 | L8: =ROUND(P4_Q7_Pivot!$L10,2) -> 0 | M8: =ROUND(P4_Q7_Pivot!$M10,2) -> 0
A9: Allen Price | B9: =ROUND(P4_Q7_Pivot!$B11,2) -> 0 | C9: =ROUND(P4_Q7_Pivot!$C11,2) -> 0 | D9: =ROUND(P4_Q7_Pivot!$D11,2) -> 0 | E9: =ROUND(P4_Q7_Pivot!$E11,2) -> 0 | F9: =ROUND(P4_Q7_Pivot!$F11,2) -> 0.04 | G9: =ROUND(P4_Q7_Pivot!$G11,2) -> 0 | H9: =ROUND(P4_Q7_Pivot!$H11,2) -> 0 | I9: =ROUND(P4_Q7_Pivot!$I11,2) -> 0.05 | J9: =ROUND(P4_Q7_Pivot!$J11,2) -> 0.62 | K9: =ROUND(P4_Q7_Pivot!$K11,2) -> 0.11 | L9: =ROUND(P4_Q7_Pivot!$L11,2) -> 0 | M9: =ROUND(P4_Q7_Pivot!$M11,2) -> 0.17
A10: Angel Watts | B10: =ROUND(P4_Q7_Pivot!$B12,2) -> 0 | C10: =ROUND(P4_Q7_Pivot!$C12,2) -> 0 | D10: =ROUND(P4_Q7_Pivot!$D12,2) -> 0 | E10: =ROUND(P4_Q7_Pivot!$E12,2) -> 0 | F10: =ROUND(P4_Q7_Pivot!$F12,2) -> 0.01 | G10: =ROUND(P4_Q7_Pivot!$G12,2) -> 0 | H10: =ROUND(P4_Q7_Pivot!$H12,2) -> 0 | I10: =ROUND(P4_Q7_Pivot!$I12,2) -> 0 | J10: =ROUND(P4_Q7_Pivot!$J12,2) -> 0.79 | K10: =ROUND(P4_Q7_Pivot!$K12,2) -> 0.2 | L10: =ROUND(P4_Q7_Pivot!$L12,2) -> 0 | M10: =ROUND(P4_Q7_Pivot!$M12,2) -> 0
A11: Antonio Torres | B11: =ROUND(P4_Q7_Pivot!$B13,2) -> 0.97 | C11: =ROUND(P4_Q7_Pivot!$C13,2) -> 0 | D11: =ROUND(P4_Q7_Pivot!$D13,2) -> 0 | E11: =ROUND(P4_Q7_Pivot!$E13,2) -> 0 | F11: =ROUND(P4_Q7_Pivot!$F13,2) -> 0 | G11: =ROUND(P4_Q7_Pivot!$G13,2) -> 0 | H11: =ROUND(P4_Q7_Pivot!$H13,2) -> 0 | I11: =ROUND(P4_Q7_Pivot!$I13,2) -> 0 | J11: =ROUND(P4_Q7_Pivot!$J13,2) -> 0.02 | K11: =ROUND(P4_Q7_Pivot!$K13,2) -> 0.01 | L11: =ROUND(P4_Q7_Pivot!$L13,2) -> 0 | M11: =ROUND(P4_Q7_Pivot!$M13,2) -> 0
A12: Barry Mckenzie | B12: =ROUND(P4_Q7_Pivot!$B14,2) -> 0.58 | C12: =ROUND(P4_Q7_Pivot!$C14,2) -> 0 | D12: =ROUND(P4_Q7_Pivot!$D14,2) -> 0 | E12: =ROUND(P4_Q7_Pivot!$E14,2) -> 0 | F12: =ROUND(P4_Q7_Pivot!$F14,2) -> 0 | G12: =ROUND(P4_Q7_Pivot!$G14,2) -> 0.1 | H12: =ROUND(P4_Q7_Pivot!$H14,2) -> 0.03 | I12: =ROUND(P4_Q7_Pivot!$I14,2) -> 0.24 | J12: =ROUND(P4_Q7_Pivot!$J14,2) -> 0.05 | K12: =ROUND(P4_Q7_Pivot!$K14,2) -> 0 | L12: =ROUND(P4_Q7_Pivot!$L14,2) -> 0 | M12: =ROUND(P4_Q7_Pivot!$M14,2) -> 0
A13: Beulah Gibbs | B13: =ROUND(P4_Q7_Pivot!$B15,2) -> 0.01 | C13: =ROUND(P4_Q7_Pivot!$C15,2) -> 0 | D13: =ROUND(P4_Q7_Pivot!$D15,2) -> 0 | E13: =ROUND(P4_Q7_Pivot!$E15,2) -> 0.59 | F13: =ROUND(P4_Q7_Pivot!$F15,2) -> 0 | G13: =ROUND(P4_Q7_Pivot!$G15,2) -> 0 | H13: =ROUND(P4_Q7_Pivot!$H15,2) -> 0 | I13: =ROUND(P4_Q7_Pivot!$I15,2) -> 0.22 | J13: =ROUND(P4_Q7_Pivot!$J15,2) -> 0.11 | K13: =ROUND(P4_Q7_Pivot!$K15,2) -> 0 | L13: =ROUND(P4_Q7_Pivot!$L15,2) -> 0 | M13: =ROUND(P4_Q7_Pivot!$M15,2) -> 0.07
A14: Brittany Carlson | B14: =ROUND(P4_Q7_Pivot!$B16,2) -> 0.06 | C14: =ROUND(P4_Q7_Pivot!$C16,2) -> 0.05 | D14: =ROUND(P4_Q7_Pivot!$D16,2) -> 0 | E14: =ROUND(P4_Q7_Pivot!$E16,2) -> 0 | F14: =ROUND(P4_Q7_Pivot!$F16,2) -> 0.04 | G14: =ROUND(P4_Q7_Pivot!$G16,2) -> 0 | H14: =ROUND(P4_Q7_Pivot!$H16,2) -> 0 | I14: =ROUND(P4_Q7_Pivot!$I16,2) -> 0 | J14: =ROUND(P4_Q7_Pivot!$J16,2) -> 0.71 | K14: =ROUND(P4_Q7_Pivot!$K16,2) -> 0.09 | L14: =ROUND(P4_Q7_Pivot!$L16,2) -> 0 | M14: =ROUND(P4_Q7_Pivot!$M16,2) -> 0.05
A15: Cary Foster | B15: =ROUND(P4_Q7_Pivot!$B17,2) -> 0 | C15: =ROUND(P4_Q7_Pivot!$C17,2) -> 0.82 | D15: =ROUND(P4_Q7_Pivot!$D17,2) -> 0 | E15: =ROUND(P4_Q7_Pivot!$E17,2) -> 0.03 | F15: =ROUND(P4_Q7_Pivot!$F17,2) -> 0 | G15: =ROUND(P4_Q7_Pivot!$G17,2) -> 0 | H15: =ROUND(P4_Q7_Pivot!$H17,2) -> 0 | I15: =ROUND(P4_Q7_Pivot!$I17,2) -> 0.06 | J15: =ROUND(P4_Q7_Pivot!$J17,2) -> 0.05 | K15: =ROUND(P4_Q7_Pivot!$K17,2) -> 0.02 | L15: =ROUND(P4_Q7_Pivot!$L17,2) -> 0 | M15: =ROUND(P4_Q7_Pivot!$M17,2) -> 0.01
A16: Cassandra Poole | B16: =ROUND(P4_Q7_Pivot!$B18,2) -> 0 | C16: =ROUND(P4_Q7_Pivot!$C18,2) -> 0.14 | D16: =ROUND(P4_Q7_Pivot!$D18,2) -> 0 | E16: =ROUND(P4_Q7_Pivot!$E18,2) -> 0.63 | F16: =ROUND(P4_Q7_Pivot!$F18,2) -> 0 | G16: =ROUND(P4_Q7_Pivot!$G18,2) -> 0 | H16: =ROUND(P4_Q7_Pivot!$H18,2) -> 0 | I16: =ROUND(P4_Q7_Pivot!$I18,2) -> 0.01 | J16: =ROUND(P4_Q7_Pivot!$J18,2) -> 0.22 | K16: =ROUND(P4_Q7_Pivot!$K18,2) -> 0 | L16: =ROUND(P4_Q7_Pivot!$L18,2) -> 0 | M16: =ROUND(P4_Q7_Pivot!$M18,2) -> 0
... A92: Grand Total | B92: =ROUND(P4_Q7_Pivot!$B94,2) -> 0.22 | C92: =ROUND(P4_Q7_Pivot!$C94,2) -> 0.48 | D92: =ROUND(P4_Q7_Pivot!$D94,2) -> 0.01 | E92: =ROUND(P4_Q7_Pivot!$E94,2) -> 0.06 | F92: =ROUND(P4_Q7_Pivot!$F94,2) -> 0 | G92: =ROUND(P4_Q7_Pivot!$G94,2) -> 0.1 | H92: =ROUND(P4_Q7_Pivot!$H94,2) -> 0 | I92: =ROUND(P4_Q7_Pivot!$I94,2) -> 0.02 | J92: =ROUND(P4_Q7_Pivot!$J94,2) -> 0.07 | K92: =ROUND(P4_Q7_Pivot!$K94,2) -> 0.01 | L92: =ROUND(P4_Q7_Pivot!$L94,2) -> 0 | M92: =ROUND(P4_Q7_Pivot!$M94,2) -> 0.01

Sheet P4_Q7_Pivot
A2: YEAR | B2: 2016
A3: Total_Hours | B3: (Multiple Items)
A5: Sum of Gross_Wages | B5: Column Labels
A6: Row Labels | B6: 001 | C6: 002 | D6: 003 | E6: 004 | F6: 005 | G6: 006 | H6: 007 | I6: 008 | J6: 009 | K6: 010 | L6: 011 | M6: 012 | N6: Grand Total
A7: Afton Call | B7: 0.08045977 | C7: 0 | D7: 0 | E7: 0.020114943 | F7: 0.098850575 | G7: 0 | H7: 0 | I7: 0.16896552 | J7: 0.2454023 | K7: 0.12873563 | L7: 0.12873563 | M7: 0.12873563 | N7: 1
A8: Al Ramos | B8: 0 | C8: 0.94568334 | D8: 0 | E8: 0 | F8: 0.00012967702 | G8: 0 | H8: 0 | I8: 0 | J8: 0.029177689 | K8: 0.016672862 | L8: 0 | M8: 0.0083364312 | N8: 1
A9: Alberta Gill | B9: 0 | C9: 0 | D9: 0.11276076 | E9: 0 | F9: 0 | G9: 0 | H9: 0 | I9: 0.22231654 | J9: 0.19529285 | K9: 0.19064228 | L9: 0 | M9: 0.27898758 | N9: 1
A10: Allan Wood | B10: 0 | C10: 0.91865142 | D10: 0 | E10: 0 | F10: 6.4435536e-06 | G10: 0 | H10: 0 | I10: 0 | J10: 0.066859601 | K10: 0.014482531 | L10: 0 | M10: 0 | N10: 1
A11: Allen Price | B11: 0 | C11: 0 | D11: 0 | E11: 0 | F11: 0.040136901 | G11: 0 | H11: 0 | I11: 0.051026758 | J11: 0.62258867 | K11: 0.11449907 | L11: 0 | M11: 0.1717486 | N11: 1
A12: Angel Watts | B12: 0 | C12: 0 | D12: 0 | E12: 0 | F12: 0.014218009 | G12: 0 | H12: 0 | I12: 0 | J12: 0.78862559 | K12: 0.1971564 | L12: 0 | M12: 0 | N12: 1
A13: Antonio Torres | B13: 0.96807903 | C13: 0.0014494014 | D13: 0 | E13: 0 | F13: 0 | G13: 0 | H13: 0 | I13: 0 | J13: 0.022705678 | K13: 0.0073710113 | L13: 0 | M13: 0.00039488136 | N13: 1
A14: Barry Mckenzie | B14: 0.57914343 | C14: 0.0044305867 | D14: 0 | E14: 0 | F14: 0.00042032195 | G14: 0.10285475 | H14: 0.028482343 | I14: 0.23567894 | J14: 0.047470571 | K14: 0.00050635276 | L14: 0 | M14: 0.0010127055 | N14: 1
A15: Beulah Gibbs | B15: 0.013085266 | C15: 0.00010468213 | D15: 0 | E15: 0.58763655 | F15: 0.00032872145 | G15: 0 | H15: 0 | I15: 0.22046448 | J15: 0.10599212 | K15: 0.00041872851 | L15: 0 | M15: 0.071969452 | N15: 1
A16: Brittany Carlson | B16: 0.059101655 | C16: 0.047281324 | D16: 0 | E16: 0 | F16: 0.042553191 | G16: 0 | H16: 0 | I16: 0 | J16: 0.70921986 | K16: 0.094562648 | L16: 0 | M16: 0.047281324 | N16: 1
A17: Cary Foster | B17: 0 | C17: 0.824037 | D17: 0 | E17: 0.034877779 | F17: 0 | G17: 0 | H17: 0 | I17: 0.060432289 | J17: 0.054495396 | K17: 0.017438356 | L17: 0 | M17: 0.008719178 | N17: 1
A18: Cassandra Poole | B18: 0 | C18: 0.138593 | D18: 0 | E18: 0.63357862 | F18: 0.00015491124 | G18: 0 | H18: 0 | I18: 0.0052860555 | J18: 0.21900449 | K18: 0.0033829266 | L18: 0 | M18: 0 | N18: 1
... A94: Grand Total | B94: 0.22314129 | C94: 0.4773242 | D94: 0.014024804 | E94: 0.058585223 | F94: 0.0019373677 | G94: 0.09947105 | H94: 0.0030562932 | I94: 0.022235151 | J94: 0.073879182 | K94: 0.014502489 | L94: 0.00083544077 | M94: 0.011007501 | N94: 1

Sheet P4_Q6
A1: 6. The company operates in two locations. Noah is concerned whether the company is paying a similar amount for employees at both locations. He prepared a pipe-delimited text file (Analytics_mindset_case_studies_locations.csv) for you that contains the names of all employees and their locations.
A2: This additional file contains two columns separated by a pipe, wherein the first column lists the name of the employee (FirstName LastName) and the second column provides the location where that employee works (either location one or two).
A3: Upload this data into Excel and prepare a table (or tables) that shows the total number of hours (include regular and overtime hours) employees in both locations worked in 2015 and 2016, the gross wages for each location in 2015 and in 2016, and the average pay for each location in 2015 and 2016 (i.e., pay per hour).
A4: Sort the data so location one is listed first. Clearly label each column. You can exclude the phantom entries you found in question 3. Does there appear to be any difference in pay based on the location? Why or why not?
A6: Answer
A7: As below table states, In 2015, Location 1 had an average pay of 261.09, while Location 2 had a significantly higher average pay of 917.33. In 2016, the same pattern continued, with Location 1 at 147.20 and Location 2 at 241.27.
A8: Although both locations experienced changes in total hours and wages, Location 2 consistently shows a higher average pay per hour than Location 1 in both years.
A9: This difference should be further investigated to determine whether it is justified by operational needs or reflects inefficiencies in workforce allocation.
A10: Emp_No | B10: (Multiple Items)
B12: Column Labels
B13: 2015 | D13: 2016
A14: Row Labels | B14: Sum of Total_Hours | C14: Sum of Gross_Wages | D14: Sum of Total_Hours | E14: Sum of Gross_Wages | F14: 2015 AVERAGE PAY | G14: 2016 AVERAGE PAY
A15: 1 | B15: 91416 | C15: 23867897 | D15: 209559 | E15: 30847595 | F15: =C15/B15 -> 261.09102 | G15: =E15/D15 -> 147.20243
A16: 2 | B16: 47647 | C16: 43708156 | D16: 220816 | E16: 53276861 | F16: =C16/B16 -> 917.3328 | G16: =E16/D16 -> 241.27265

Sheet P4_Q5
A1: 5. What was the total employee cost for all projects in 2016? The total employee cost should include everything paid for wages, Social Security and Medicaid, FUTA, SUTA and workers’ compensation.
A3: Answer: The total employee cost for all projects in 2016 is 97.524.520
A4: YEAR | B4: 2016
A6: Sum of Gross_Wages | B6: Sum of Fica_Medc | C6: Sum of Futa | D6: Sum of Suta | E6: Sum of Work_Comp | F6: Total
A7: 85929725 | B7: 8422378 | C7: 151485 | D7: 2120859 | E7: 900073 | F7: =SUM(A7:E7) -> 97524520

Sheet P4_Q4
A1: 4. In 2015, were there any employees who incurred overtime when they had not already worked 40 regular work hours during the pay period? Assume, for this problem, that all pay on the same date is for the same pay period.
A2: Return the name of the employee, the pay date, the total number of regular hours worked and the total number if overtime hours worked. Make sure only to list values if an employee worked less than 40 hours but listed some overtime hours. Sort the data by the employee name and then the pay date.
A4: Answer: There are employees who incurred overtime when they had not already worked 40 regular working hours during the pay period
A5: Emp_Name | B5: Pay_Date | C5: Sum of Reg_Hrs | D5: Sum of OT_Hrs | E5: Help column
A6: Al Ramos | B6: 42006 | C6: 25 | D6: 0 | E6: =IF(AND($C6<40,$D6>0),"Keep","")
A7: Al Ramos | B7: 42013 | C7: 8 | D7: 0 | E7: =IF(AND($C7<40,$D7>0),"Keep","")
A8: Al Ramos | B8: 42020 | C8: 43 | D8: 0 | E8: =IF(AND($C8<40,$D8>0),"Keep","")
A9: Al Ramos | B9: 42027 | C9: 42 | D9: 0 | E9: =IF(AND($C9<40,$D9>0),"Keep","")
A10: Al Ramos | B10: 42034 | C10: 41 | D10: 0 | E10: =IF(AND($C10<40,$D10>0),"Keep","")
A11: Al Ramos | B11: 42041 | C11: 40 | D11: 0 | E11: =IF(AND($C11<40,$D11>0),"Keep","")
A12: Al Ramos | B12: 42048 | C12: 39 | D12: 0 | E12: =IF(AND($C12<40,$D12>0),"Keep","")
A13: Al Ramos | B13: 42055 | C13: 36 | D13: 0 | E13: =IF(AND($C13<40,$D13>0),"Keep","")
A14: Al Ramos | B14: 42062 | C14: 35 | D14: 0 | E14: =IF(AND($C14<40,$D14>0),"Keep","")
A15: Al Ramos | B15: 42069 | C15: 40 | D15: 0 | E15: =IF(AND($C15<40,$D15>0),"Keep","")
A16: Al Ramos | B16: 42076 | C16: 435 | D16: 0 | E16: =IF(AND($C16<40,$D16>0),"Keep","")
A17: Al Ramos | B17: 42083 | C17: 38 | D17: 0 | E17: =IF(AND($C17<40,$D17>0),"Keep","")
... A2035: Yvette Miller | B2035: 42181 | C2035: 40 | D2035: 0 | E2035: =IF(AND($C2035<40,$D2035>0),"Keep","")

Sheet P4_Q4_pivot
A1: Emp_Name | B1: Pay_Date | C1: Sum of Reg_Hrs | D1: Sum of OT_Hrs
A2: Al Ramos | B2: 42006 | C2: 25 | D2: 0
A3: Al Ramos | B3: 42013 | C3: 8 | D3: 0
A4: Al Ramos | B4: 42020 | C4: 43 | D4: 0
A5: Al Ramos | B5: 42027 | C5: 42 | D5: 0
A6: Al Ramos | B6: 42034 | C6: 41 | D6: 0
A7: Al Ramos | B7: 42041 | C7: 40 | D7: 0
A8: Al Ramos | B8: 42048 | C8: 39 | D8: 0
A9: Al Ramos | B9: 42055 | C9: 36 | D9: 0
A10: Al Ramos | B10: 42062 | C10: 35 | D10: 0
A11: Al Ramos | B11: 42069 | C11: 40 | D11: 0
A12: Al Ramos | B12: 42076 | C12: 435 | D12: 0
A13: Al Ramos | B13: 42083 | C13: 38 | D13: 0
... A2031: Yvette Miller | B2031: 42181 | C2031: 40 | D2031: 0

Sheet P4_Q3
A1: 3. Noah knows there are some errors with the new system used in 2016. What is the total number of transactions entered in 2016 without an employee number? What was the total gross wage amount for these “phantom” entries? Make sure to use a descriptive title for each column.
A2: Total number of transaction without employee number is 68 and in total, 1805269 has been paid for these phantom entries
A3: YEAR | B3: 2016
A5: Emp_No | B5: Count of Emp_No | C5: Sum of Gross_Wages | D5: Sum of transaction count
A6: (blank) | C6: 1805269 | D6: 68
A7: Grand Total | C7: 1805269 | D7: 68

Sheet P4_Q2
A1: 2. To reduce overtime pay, Noah is considering shuffling employees from one job code to another. Which job codes have the most overtime pay in 2015? | K1: Answer: Office
A2: Job_Code | B2: Job_description | C2: Sum of OT_Hrs | D2: Sum of OT_Pay
A3: 001 | B3: Office | C3: 1277 | D3: 208754
A4: 006 | B4: Service | C4: 288 | D4: 190379
A5: 002 | B5: Sales | C5: 159 | D5: 101016
A6: 004 | B6: Proj Management | C6: 107 | D6: 54925
A7: 005 | B7: Installation | C7: 14 | D7: 37164
A8: 008 | B8: Employee Training | C8: 22 | D8: 30653
A9: 003 | B9: Travel | C9: 1 | D9: 5355
A10: 011 | B10: Internal Projects | C10: 0 | D10: 0
A11: 010 | B11: New Foreign Manufacturing Oversight | C11: 0 | D11: 0
A12: 012 | B12: Internal Auditing | C12: 0 | D12: 0
A13: 009 | B13: New Foreign Manufacturing Plant | C13: 0 | D13: 0
A14: 007 | B14: Customer Training | C14: 0 | D14: 0

Sheet P4_Q1
A1: 1. Which employees are earning the most overtime pay and how much did they earn in the first six months of 2015?
A2: Cindy Lunt
A4: OT_Hrs | B4: (Multiple Items)
A6: Emp_Name | B6: Sum of OT_Pay | C6: Sum of OT_Hrs
A7: Cindy Lunt | B7: 311569 | C7: 402
A8: Nettie Stevens | B8: 106029 | C8: 126
A9: Clarence Padilla | B9: 86542 | C9: 939
A10: Elisa Warren | B10: 58939 | C10: 43
A11: Deborah Bennett | B11: 36276 | C11: 8
A12: Kenny Robertson | B12: 8918 | C12: 25
A13: Tommy Graves | B13: 5790 | C13: 33
A14: Sue Riley | B14: 4410 | C14: 14
A15: Marc Wallace | B15: 2954 | C15: 80
A16: Jo Manning | B16: 2604 | C16: 62
A17: Lynn Perkins | B17: 1122 | C17: 8
A18: Stanley Peterson | B18: 915 | C18: 71
... A24: Norman Ruiz | B24: 132 | C24: 28

Sheet P3_Memo
A1: To: Noah
A2: Subject: Analysis of Payroll Increase from 2015 to 2016
A4: 1. Overview
A6: Based on the analysis of payroll data from 2015 to 2016, total payroll expenses increased significantly.
A7: However, this increase was not driven by an increase in employee count, as the number of employees decreased from 851 in 2015 to 804 in 2016 (see Table 1). Instead, the increase is primarily driven by changes in wages, working hours, and job-specific factors.
A9: Table 1: Employee Count Comparison (from P1_5Qs)
A16: 2. Key Drivers of Payroll Increase
A18: Using the aggregated results as below table 2, the three job codes with the largest positive wage differences are:
A20: 001 – Office
A21: 006 – Service
A22: 008 – Employee Training
A24: These job categories contributed the most to the overall payroll increase.
... A48: Several employees contributed significantly, including:
B49: Antonio Torres (increase in both hours and wages)
B50: Clarence Padilla (substantial increase in working hours)
A51: This indicates that both workload expansion and compensation adjustments contributed to the increase.
A52: 3.2 Service (006)
A53: The Service category experienced a significant increase in total wages, which is driven by a substantial increase in total working hours.
A54: While some employees also show increases in pay per hour, the main driver appears to be increased labor demand.
A55: 3.3 Employee Training (008)
A56: The Employee Training category shows an increase in total wages despite a decrease in pay per hour.
A57: This suggests that the increase is driven by higher working hours rather than changes in wage rates.
A59: Table 3: Employee-Level Details (from P3_Q2)
A158: 4. Additional Findings
A159: From the broader analysis (see supporting results in P1_5Qs), the increase in payroll is not due to employee growth but is instead driven by:
B160: Increased working hours
B161: Redistribution of workload across job categories
B162: Selective increases in compensation
A164: Table 4: Supporting Payroll & Hours Summary (from P1_5Qs)
A203: 5. Data Discrepancies
A204: Several data issues were identified during the analysis:
B205: Job code 144 appears to be invalid and likely results from an error in project code extraction
B206: Some employees show extremely large percentage changes due to missing or very small base values
B207: Certain records contain unusually high pay-per-hour values, suggesting potential data entry or allocation errors
B208: Missing or zero values for some employees in one of the years required exclusion to ensure valid comparisons
A210: 6. Conclusion
A211: In conclusion, the payroll increase in 2016 is primarily driven by higher working hours and increases in pay rates within key job categories.
A212: The Office, Service, and Employee Training categories are the main contributors to this change.

Sheet P3_Q2
A1: Job code | B1: Employee number | C1: Employee name | D1: 2015 hours | E1: 2015 gross pay | F1: 2015 gross pay per hour | G1: 2016 hours | H1: 2016 gross pay | I1: 2016 gross pay per hour | J1: Hours difference | K1: Gross pay difference | L1: Gross pay per hour difference
A2: =Q3_worksheet!A27 -> 001 | B2: =Q3_worksheet!B27 -> (blank) | C2: =Q3_worksheet!C27 -> 0 | D2: =Q3_worksheet!D27 -> 0 | E2: =Q3_worksheet!E27 -> 0 | F2: =IFERROR(E2/D2,0) -> 0 | G2: =Q3_worksheet!F27 -> 16565 | H2: =Q3_worksheet!G27 -> 12580 | I2: =IFERROR(H2/G2,0) -> 0.75943254 | J2: =G2-D2 -> 16565 | K2: =H2-E2 -> 12580 | L2: =I2-F2 -> 0.75943254
A3: =Q3_worksheet!A99 -> 002 | B3: =Q3_worksheet!B99 -> 195 | C3: =Q3_worksheet!C99 -> Al Ramos | D3: =Q3_worksheet!D99 -> 2548 | E3: =Q3_worksheet!E99 -> 2565652 | F3: =IFERROR(E3/D3,0) -> 1006.9278 | G3: =Q3_worksheet!F99 -> 911 | H3: =Q3_worksheet!G99 -> 2625338 | I3: =IFERROR(H3/G3,0) -> 2881.82 | J3: =G3-D3 -> -1637 | K3: =H3-E3 -> 59686 | L3: =I3-F3 -> 1874.8922
A4: =Q3_worksheet!A137 -> 003 | B4: =Q3_worksheet!B137 -> 404 | C4: =Q3_worksheet!C137 -> Alberta Gill | D4: =Q3_worksheet!D137 -> 133 | E4: =Q3_worksheet!E137 -> 198175 | F4: =IFERROR(E4/D4,0) -> 1490.0376 | G4: =Q3_worksheet!F137 -> 95 | H4: =Q3_worksheet!G137 -> 21919 | I4: =IFERROR(H4/G4,0) -> 230.72632 | J4: =G4-D4 -> -38 | K4: =H4-E4 -> -176256 | L4: =I4-F4 -> -1259.3113
A5: =Q3_worksheet!A321 -> 008 | B5: =Q3_worksheet!B321 -> 404 | C5: =Q3_worksheet!C321 -> Alberta Gill | D5: =Q3_worksheet!D321 -> 177 | E5: =Q3_worksheet!E321 -> 338153 | F5: =IFERROR(E5/D5,0) -> 1910.4689 | G5: =Q3_worksheet!F321 -> 185 | H5: =Q3_worksheet!G321 -> 43215 | I5: =IFERROR(H5/G5,0) -> 233.59459 | J5: =G5-D5 -> 8 | K5: =H5-E5 -> -294938 | L5: =I5-F5 -> -1676.8743
A6: =Q3_worksheet!A92 -> 002 | B6: =Q3_worksheet!B92 -> 106 | C6: =Q3_worksheet!C92 -> Allan Wood | D6: =Q3_worksheet!D92 -> 185 | E6: =Q3_worksheet!E92 -> 5310 | F6: =IFERROR(E6/D6,0) -> 28.702703 | G6: =Q3_worksheet!F92 -> 1010 | H6: =Q3_worksheet!G92 -> 2138536 | I6: =IFERROR(H6/G6,0) -> 2117.3624 | J6: =G6-D6 -> 825 | K6: =H6-E6 -> 2133226 | L6: =I6-F6 -> 2088.6597
A7: =Q3_worksheet!A32 -> 001 | B7: =Q3_worksheet!B32 -> 19 | C7: =Q3_worksheet!C32 -> Frank Diaz | D7: =Q3_worksheet!D32 -> 0 | E7: =Q3_worksheet!E32 -> 0 | F7: =IFERROR(E7/D7,0) -> 0 | G7: =Q3_worksheet!F32 -> 4 | H7: =Q3_worksheet!G32 -> 108 | I7: =IFERROR(H7/G7,0) -> 27 | J7: =G7-D7 -> 4 | K7: =H7-E7 -> 108 | L7: =I7-F7 -> 27
A8: =Q3_worksheet!A33 -> 001 | B8: =Q3_worksheet!B33 -> 22 | C8: =Q3_worksheet!C33 -> Marion Scott | D8: =Q3_worksheet!D33 -> 0 | E8: =Q3_worksheet!E33 -> 0 | F8: =IFERROR(E8/D8,0) -> 0 | G8: =Q3_worksheet!F33 -> 29 | H8: =Q3_worksheet!G33 -> 78931 | I8: =IFERROR(H8/G8,0) -> 2721.7586 | J8: =G8-D8 -> 29 | K8: =H8-E8 -> 78931 | L8: =I8-F8 -> 2721.7586
A9: =Q3_worksheet!A302 -> 008 | B9: =Q3_worksheet!B302 -> 304 | C9: =Q3_worksheet!C302 -> Allen Price | D9: =Q3_worksheet!D302 -> 19 | E9: =Q3_worksheet!E302 -> 437 | F9: =IFERROR(E9/D9,0) -> 23 | G9: =Q3_worksheet!F302 -> 7 | H9: =Q3_worksheet!G302 -> 164 | I9: =IFERROR(H9/G9,0) -> 23.428571 | J9: =G9-D9 -> -12 | K9: =H9-E9 -> -273 | L9: =I9-F9 -> 0.42857143
A10: =Q3_worksheet!A28 -> 001 | B10: =Q3_worksheet!B28 -> 1 | C10: =Q3_worksheet!C28 -> Antonio Torres | D10: =Q3_worksheet!D28 -> 911 | E10: =Q3_worksheet!E28 -> 2011582 | F10: =IFERROR(E10/D10,0) -> 2208.1032 | G10: =Q3_worksheet!F28 -> 1101 | H10: =Q3_worksheet!G28 -> 3005624 | I10: =IFERROR(H10/G10,0) -> 2729.9037 | J10: =G10-D10 -> 190 | K10: =H10-E10 -> 994042 | L10: =I10-F10 -> 521.80054
A11: =Q3_worksheet!A64 -> 001 | B11: =Q3_worksheet!B64 -> 391 | C11: =Q3_worksheet!C64 -> Barry Mckenzie | D11: =Q3_worksheet!D64 -> 405 | E11: =Q3_worksheet!E64 -> 446351 | F11: =IFERROR(E11/D11,0) -> 1102.1012 | G11: =Q3_worksheet!F64 -> 1620 | H11: =Q3_worksheet!G64 -> 471227 | I11: =IFERROR(H11/G11,0) -> 290.88086 | J11: =G11-D11 -> 1215 | K11: =H11-E11 -> 24876 | L11: =I11-F11 -> -811.22037
A12: =Q3_worksheet!A315 -> 008 | B12: =Q3_worksheet!B315 -> 391 | C12: =Q3_worksheet!C315 -> Barry Mckenzie | D12: =Q3_worksheet!D315 -> 12 | E12: =Q3_worksheet!E315 -> 309 | F12: =IFERROR(E12/D12,0) -> 25.75 | G12: =Q3_worksheet!F315 -> 745 | H12: =Q3_worksheet!G315 -> 191763 | I12: =IFERROR(H12/G12,0) -> 257.4 | J12: =G12-D12 -> 733 | K12: =H12-E12 -> 191454 | L12: =I12-F12 -> 231.65
A13: =Q3_worksheet!A38 -> 001 | B13: =Q3_worksheet!B38 -> 37 | C13: =Q3_worksheet!C38 -> Kirk Byrd | D13: =Q3_worksheet!D38 -> 0 | E13: =Q3_worksheet!E38 -> 0 | F13: =IFERROR(E13/D13,0) -> 0 | G13: =Q3_worksheet!F38 -> 5 | H13: =Q3_worksheet!G38 -> 1225 | I13: =IFERROR(H13/G13,0) -> 245 | J13: =G13-D13 -> 5 | K13: =H13-E13 -> 1225 | L13: =I13-F13 -> 245
A14: =Q3_worksheet!A149 -> 004 | B14: =Q3_worksheet!B149 -> 259 | C14: =Q3_worksheet!C149 -> Beulah Gibbs | D14: =Q3_worksheet!D149 -> 1154 | E14: =Q3_worksheet!E149 -> 401449 | F14: =IFERROR(E14/D14,0) -> 347.87608 | G14: =Q3_worksheet!F149 -> 2249 | H14: =Q3_worksheet!G149 -> 600648 | I14: =IFERROR(H14/G14,0) -> 267.07337 | J14: =G14-D14 -> 1095 | K14: =H14-E14 -> 199199 | L14: =I14-F14 -> -80.802717
A15: =Q3_worksheet!A40 -> 001 | B15: =Q3_worksheet!B40 -> 106 | C15: =Q3_worksheet!C40 -> Allan Wood | D15: =Q3_worksheet!D40 -> 646 | E15: =Q3_worksheet!E40 -> 227334 | F15: =IFERROR(E15/D15,0) -> 351.91022 | G15: =Q3_worksheet!F40 -> 0 | H15: =Q3_worksheet!G40 -> 0 | I15: =IFERROR(H15/G15,0) -> 0 | J15: =G15-D15 -> -646 | K15: =H15-E15 -> -227334 | L15: =I15-F15 -> -351.91022
A16: =Q3_worksheet!A296 -> 008 | B16: =Q3_worksheet!B296 -> 259 | C16: =Q3_worksheet!C296 -> Beulah Gibbs | D16: =Q3_worksheet!D296 -> 122 | E16: =Q3_worksheet!E296 -> 43012 | F16: =IFERROR(E16/D16,0) -> 352.55738 | G16: =Q3_worksheet!F296 -> 86 | H16: =Q3_worksheet!G296 -> 225346 | I16: =IFERROR(H16/G16,0) -> 2620.3023 | J16: =G16-D16 -> -36 | K16: =H16-E16 -> 182334 | L16: =I16-F16 -> 2267.7449
A17: =Q3_worksheet!A41 -> 001 | B17: =Q3_worksheet!B41 -> 168 | C17: =Q3_worksheet!C41 -> Brittany Carlson | D17: =Q3_worksheet!D41 -> 122 | E17: =Q3_worksheet!E41 -> 74453 | F17: =IFERROR(E17/D17,0) -> 610.27049 | G17: =Q3_worksheet!F41 -> 10 | H17: =Q3_worksheet!G41 -> 375 | I17: =IFERROR(H17/G17,0) -> 37.5 | J17: =G17-D17 -> -112 | K17: =H17-E17 -> -74078 | L17: =I17-F17 -> -572.77049
A18: =Q3_worksheet!A43 -> 001 | B18: =Q3_worksheet!B43 -> 194 | C18: =Q3_worksheet!C43 -> Hector Wright | D18: =Q3_worksheet!D43 -> 4 | E18: =Q3_worksheet!E43 -> 90 | F18: =IFERROR(E18/D18,0) -> 22.5 | G18: =Q3_worksheet!F43 -> 0 | H18: =Q3_worksheet!G43 -> 0 | I18: =IFERROR(H18/G18,0) -> 0 | J18: =G18-D18 -> -4 | K18: =H18-E18 -> -90 | L18: =I18-F18 -> -22.5
A19: =Q3_worksheet!A93 -> 002 | B19: =Q3_worksheet!B93 -> 168 | C19: =Q3_worksheet!C93 -> Brittany Carlson | D19: =Q3_worksheet!D93 -> 56 | E19: =Q3_worksheet!E93 -> 2100 | F19: =IFERROR(E19/D19,0) -> 37.5 | G19: =Q3_worksheet!F93 -> 8 | H19: =Q3_worksheet!G93 -> 300 | I19: =IFERROR(H19/G19,0) -> 37.5 | J19: =G19-D19 -> -48 | K19: =H19-E19 -> -1800 | L19: =I19-F19 -> 0
A20: =Q3_worksheet!A103 -> 002 | B20: =Q3_worksheet!B103 -> 249 | C20: =Q3_worksheet!C103 -> Cary Foster | D20: =Q3_worksheet!D103 -> 580 | E20: =Q3_worksheet!E103 -> 1953907 | F20: =IFERROR(E20/D20,0) -> 3368.8052 | G20: =Q3_worksheet!F103 -> 756 | H20: =Q3_worksheet!G103 -> 3089674 | I20: =IFERROR(H20/G20,0) -> 4086.8704 | J20: =G20-D20 -> 176 | K20: =H20-E20 -> 1135767 | L20: =I20-F20 -> 718.0652
A21: =Q3_worksheet!A148 -> 004 | B21: =Q3_worksheet!B148 -> 249 | C21: =Q3_worksheet!C148 -> Cary Foster | D21: =Q3_worksheet!D148 -> 78 | E21: =Q3_worksheet!E148 -> 247397 | F21: =IFERROR(E21/D21,0) -> 3171.7564 | G21: =Q3_worksheet!F148 -> 32 | H21: =Q3_worksheet!G148 -> 130772 | I21: =IFERROR(H21/G21,0) -> 4086.625 | J21: =G21-D21 -> -46 | K21: =H21-E21 -> -116625 | L21: =I21-F21 -> 914.86859
A22: =Q3_worksheet!A295 -> 008 | B22: =Q3_worksheet!B295 -> 249 | C22: =Q3_worksheet!C295 -> Cary Foster | D22: =Q3_worksheet!D295 -> 40 | E22: =Q3_worksheet!E295 -> 163462 | F22: =IFERROR(E22/D22,0) -> 4086.55 | G22: =Q3_worksheet!F295 -> 54 | H22: =Q3_worksheet!G295 -> 226587 | I22: =IFERROR(H22/G22,0) -> 4196.0556 | J22: =G22-D22 -> 14 | K22: =H22-E22 -> 63125 | L22: =I22-F22 -> 109.50556
A23: =Q3_worksheet!A95 -> 002 | B23: =Q3_worksheet!B95 -> 179 | C23: =Q3_worksheet!C95 -> Cassandra Poole | D23: =Q3_worksheet!D95 -> 225 | E23: =Q3_worksheet!E95 -> 183562 | F23: =IFERROR(E23/D23,0) -> 815.83111 | G23: =Q3_worksheet!F95 -> 677 | H23: =Q3_worksheet!G95 -> 297922 | I23: =IFERROR(H23/G23,0) -> 440.06204 | J23: =G23-D23 -> 452 | K23: =H23-E23 -> 114360 | L23: =I23-F23 -> -375.76907
A24: =Q3_worksheet!A49 -> 001 | B24: =Q3_worksheet!B49 -> 259 | C24: =Q3_worksheet!C49 -> Beulah Gibbs | D24: =Q3_worksheet!D49 -> 0 | E24: =Q3_worksheet!E49 -> 0 | F24: =IFERROR(E24/D24,0) -> 0 | G24: =Q3_worksheet!F49 -> 5 | H24: =Q3_worksheet!G49 -> 13375 | I24: =IFERROR(H24/G24,0) -> 2675 | J24: =G24-D24 -> 5 | K24: =H24-E24 -> 13375 | L24: =I24-F24 -> 2675
A25: =Q3_worksheet!A146 -> 004 | B25: =Q3_worksheet!B146 -> 179 | C25: =Q3_worksheet!C146 -> Cassandra Poole | D25: =Q3_worksheet!D146 -> 1497 | E25: =Q3_worksheet!E146 -> 1138379 | F25: =IFERROR(E25/D25,0) -> 760.44021 | G25: =Q3_worksheet!F146 -> 309 | H25: =Q3_worksheet!G146 -> 1361952 | I25: =IFERROR(H25/G25,0) -> 4407.6117 | J25: =G25-D25 -> -1188 | K25: =H25-E25 -> 223573 | L25: =I25-F25 -> 3647.1714
A26: =Q3_worksheet!A58 -> 001 | B26: =Q3_worksheet!B58 -> 368 | C26: =Q3_worksheet!C58 -> Cesar Greene | D26: =Q3_worksheet!D58 -> 1 | E26: =Q3_worksheet!E58 -> 245 | F26: =IFERROR(E26/D26,0) -> 245 | G26: =Q3_worksheet!F58 -> 175 | H26: =Q3_worksheet!G58 -> 42875 | I26: =IFERROR(H26/G26,0) -> 245 | J26: =G26-D26 -> 174 | K26: =H26-E26 -> 42630 | L26: =I26-F26 -> 0
A27: =Q3_worksheet!A205 -> 005 | B27: =Q3_worksheet!B205 -> 368 | C27: =Q3_worksheet!C205 -> Cesar Greene | D27: =Q3_worksheet!D205 -> 23 | E27: =Q3_worksheet!E205 -> 5194 | F27: =IFERROR(E27/D27,0) -> 225.82609 | G27: =Q3_worksheet!F205 -> 63 | H27: =Q3_worksheet!G205 -> 9894 | I27: =IFERROR(H27/G27,0) -> 157.04762 | J27: =G27-D27 -> 40 | K27: =H27-E27 -> 4700 | L27: =I27-F27 -> -68.778468
A28: =Q3_worksheet!A311 -> 008 | B28: =Q3_worksheet!B311 -> 368 | C28: =Q3_worksheet!C311 -> Cesar Greene | D28: =Q3_worksheet!D311 -> 86 | E28: =Q3_worksheet!E311 -> 18865 | F28: =IFERROR(E28/D28,0) -> 219.36047 | G28: =Q3_worksheet!F311 -> 465 | H28: =Q3_worksheet!G311 -> 113925 | I28: =IFERROR(H28/G28,0) -> 245 | J28: =G28-D28 -> 379 | K28: =H28-E28 -> 95060 | L28: =I28-F28 -> 25.639535
A29: =Q3_worksheet!A54 -> 001 | B29: =Q3_worksheet!B54 -> 352 | C29: =Q3_worksheet!C54 -> Myra Vega | D29: =Q3_worksheet!D54 -> 0 | E29: =Q3_worksheet!E54 -> 0 | F29: =IFERROR(E29/D29,0) -> 0 | G29: =Q3_worksheet!F54 -> 10 | H29: =Q3_worksheet!G54 -> 190 | I29: =IFERROR(H29/G29,0) -> 19 | J29: =G29-D29 -> 10 | K29: =H29-E29 -> 190 | L29: =I29-F29 -> 19
A30: =Q3_worksheet!A55 -> 001 | B30: =Q3_worksheet!B55 -> 357 | C30: =Q3_worksheet!C55 -> Jesus Peterson | D30: =Q3_worksheet!D55 -> 0 | E30: =Q3_worksheet!E55 -> 0 | F30: =IFERROR(E30/D30,0) -> 0 | G30: =Q3_worksheet!F55 -> 49 | H30: =Q3_worksheet!G55 -> 26875 | I30: =IFERROR(H30/G30,0) -> 548.46939 | J30: =G30-D30 -> 49 | K30: =H30-E30 -> 26875 | L30: =I30-F30 -> 548.46939
A31: =Q3_worksheet!A56 -> 001 | B31: =Q3_worksheet!B56 -> 357 | C31: =Q3_worksheet!C56 -> Stanley Peterson | D31: =Q3_worksheet!D56 -> 4 | E31: =Q3_worksheet!E56 -> 80 | F31: =IFERROR(E31/D31,0) -> 20 | G31: =Q3_worksheet!F56 -> 0 | H31: =Q3_worksheet!G56 -> 0 | I31: =IFERROR(H31/G31,0) -> 0 | J31: =G31-D31 -> -4 | K31: =H31-E31 -> -80 | L31: =I31-F31 -> -20
A32: =Q3_worksheet!A35 -> 001 | B32: =Q3_worksheet!B35 -> 27 | C32: =Q3_worksheet!C35 -> Cindy Lunt | D32: =Q3_worksheet!D35 -> 644 | E32: =Q3_worksheet!E35 -> 239490 | F32: =IFERROR(E32/D32,0) -> 371.87888 | G32: =Q3_worksheet!F35 -> 327 | H32: =Q3_worksheet!G35 -> 478089 | I32: =IFERROR(H32/G32,0) -> 1462.0459 | J32: =G32-D32 -> -317 | K32: =H32-E32 -> 238599 | L32: =I32-F32 -> 1090.167
A33: =Q3_worksheet!A86 -> 002 | B33: =Q3_worksheet!B86 -> 27 | C33: =Q3_worksheet!C86 -> Cindy Lunt | D33: =Q3_worksheet!D86 -> 783 | E33: =Q3_worksheet!E86 -> 271697 | F33: =IFERROR(E33/D33,0) -> 346.99489 | G33: =Q3_worksheet!F86 -> 418 | H33: =Q3_worksheet!G86 -> 470466 | I33: =IFERROR(H33/G33,0) -> 1125.5167 | J33: =G33-D33 -> -365 | K33: =H33-E33 -> 198769 | L33: =I33-F33 -> 778.52185
A34: =Q3_worksheet!A142 -> 004 | B34: =Q3_worksheet!B142 -> 27 | C34: =Q3_worksheet!C142 -> Cindy Lunt | D34: =Q3_worksheet!D142 -> 291 | E34: =Q3_worksheet!E142 -> 117275 | F34: =IFERROR(E34/D34,0) -> 403.00687 | G34: =Q3_worksheet!F142 -> 735 | H34: =Q3_worksheet!G142 -> 241714 | I34: =IFERROR(H34/G34,0) -> 328.86259 | J34: =G34-D34 -> 444 | K34: =H34-E34 -> 124439 | L34: =I34-F34 -> -74.144288
A35: =Q3_worksheet!A235 -> 006 | B35: =Q3_worksheet!B235 -> 27 | C35: =Q3_worksheet!C235 -> Cindy Lunt | D35: =Q3_worksheet!D235 -> 272 | E35: =Q3_worksheet!E235 -> 112760 | F35: =IFERROR(E35/D35,0) -> 414.55882 | G35: =Q3_worksheet!F235 -> 96 | H35: =Q3_worksheet!G235 -> 320313 | I35: =IFERROR(H35/G35,0) -> 3336.5938 | J35: =G35-D35 -> -176 | K35: =H35-E35 -> 207553 | L35: =I35-F35 -> 2922.0349
A36: =Q3_worksheet!A275 -> 008 | B36: =Q3_worksheet!B275 -> 27 | C36: =Q3_worksheet!C275 -> Cindy Lunt | D36: =Q3_worksheet!D275 -> 117 | E36: =Q3_worksheet!E275 -> 51942 | F36: =IFERROR(E36/D36,0) -> 443.94872 | G36: =Q3_worksheet!F275 -> 48 | H36: =Q3_worksheet!G275 -> 157076 | I36: =IFERROR(H36/G36,0) -> 3272.4167 | J36: =G36-D36 -> -69 | K36: =H36-E36 -> 105134 | L36: =I36-F36 -> 2828.4679
A37: =Q3_worksheet!A62 -> 001 | B37: =Q3_worksheet!B62 -> 385 | C37: =Q3_worksheet!C62 -> Lillian Jefferson | D37: =Q3_worksheet!D62 -> 82 | E37: =Q3_worksheet!E62 -> 1230 | F37: =IFERROR(E37/D37,0) -> 15 | G37: =Q3_worksheet!F62 -> 0 | H37: =Q3_worksheet!G62 -> 0 | I37: =IFERROR(H37/G37,0) -> 0 | J37: =G37-D37 -> -82 | K37: =H37-E37 -> -1230 | L37: =I37-F37 -> -15
A38: =Q3_worksheet!A225 -> 005 | B38: =Q3_worksheet!B225 -> 411 | C38: =Q3_worksheet!C225 -> Claire Edwards | D38: =Q3_worksheet!D225 -> 25 | E38: =Q3_worksheet!E225 -> 5625 | F38: =IFERROR(E38/D38,0) -> 225 | G38: =Q3_worksheet!F225 -> 25 | H38: =Q3_worksheet!G225 -> 573 | I38: =IFERROR(H38/G38,0) -> 22.92 | J38: =G38-D38 -> 0 | K38: =H38-E38 -> -5052 | L38: =I38-F38 -> -202.08
A39: =Q3_worksheet!A47 -> 001 | B39: =Q3_worksheet!B47 -> 239 | C39: =Q3_worksheet!C47 -> Clarence Padilla | D39: =Q3_worksheet!D47 -> 38339 | E39: =Q3_worksheet!E47 -> 1350365 | F39: =IFERROR(E39/D39,0) -> 35.221706 | G39: =Q3_worksheet!F47 -> 46219 | H39: =Q3_worksheet!G47 -> 1985158 | I39: =IFERROR(H39/G39,0) -> 42.951124 | J39: =G39-D39 -> 7880 | K39: =H39-E39 -> 634793 | L39: =I39-F39 -> 7.7294176
A40: =Q3_worksheet!A265 -> 007 | B40: =Q3_worksheet!B265 -> 239 | C40: =Q3_worksheet!C265 -> Clarence Padilla | D40: =Q3_worksheet!D265 -> 1406 | E40: =Q3_worksheet!E265 -> 61328 | F40: =IFERROR(E40/D40,0) -> 43.618777 | G40: =Q3_worksheet!F265 -> 105 | H40: =Q3_worksheet!G265 -> 24676 | I40: =IFERROR(H40/G40,0) -> 235.00952 | J40: =G40-D40 -> -1301 | K40: =H40-E40 -> -36652 | L40: =I40-F40 -> 191.39075
A41: =Q3_worksheet!A66 -> 001 | B41: =Q3_worksheet!B66 -> 398 | C41: =Q3_worksheet!C66 -> Mona Howard | D41: =Q3_worksheet!D66 -> 0 | E41: =Q3_worksheet!E66 -> 0 | F41: =IFERROR(E41/D41,0) -> 0 | G41: =Q3_worksheet!F66 -> 48 | H41: =Q3_worksheet!G66 -> 720 | I41: =IFERROR(H41/G41,0) -> 15 | J41: =G41-D41 -> 48 | K41: =H41-E41 -> 720 | L41: =I41-F41 -> 15
A42: =Q3_worksheet!A67 -> 001 | B42: =Q3_worksheet!B67 -> 400 | C42: =Q3_worksheet!C67 -> Roberto Ortega | D42: =Q3_worksheet!D67 -> 2725 | E42: =Q3_worksheet!E67 -> 56393 | F42: =IFERROR(E42/D42,0) -> 20.694679 | G42: =Q3_worksheet!F67 -> 0 | H42: =Q3_worksheet!G67 -> 0 | I42: =IFERROR(H42/G42,0) -> 0 | J42: =G42-D42 -> -2725 | K42: =H42-E42 -> -56393 | L42: =I42-F42 -> -20.694679
A43: =Q3_worksheet!A68 -> 001 | B43: =Q3_worksheet!B68 -> 401 | C43: =Q3_worksheet!C68 -> Maryann Cohen | D43: =Q3_worksheet!D68 -> 253 | E43: =Q3_worksheet!E68 -> 6630 | F43: =IFERROR(E43/D43,0) -> 26.205534 | G43: =Q3_worksheet!F68 -> 0 | H43: =Q3_worksheet!G68 -> 0 | I43: =IFERROR(H43/G43,0) -> 0 | J43: =G43-D43 -> -253 | K43: =H43-E43 -> -6630 | L43: =I43-F43 -> -26.205534
A44: =Q3_worksheet!A294 -> 008 | B44: =Q3_worksheet!B294 -> 239 | C44: =Q3_worksheet!C294 -> Clarence Padilla | D44: =Q3_worksheet!D294 -> 160 | E44: =Q3_worksheet!E294 -> 5876 | F44: =IFERROR(E44/D44,0) -> 36.725 | G44: =Q3_worksheet!F294 -> 10 | H44: =Q3_worksheet!G294 -> 2350 | I44: =IFERROR(H44/G44,0) -> 235 | J44: =G44-D44 -> -150 | K44: =H44-E44 -> -3526 | L44: =I44-F44 -> 198.275
A45: =Q3_worksheet!A70 -> 001 | B45: =Q3_worksheet!B70 -> 403 | C45: =Q3_worksheet!C70 -> Joyce Ferguson | D45: =Q3_worksheet!D70 -> 1 | E45: =Q3_worksheet!E70 -> 17 | F45: =IFERROR(E45/D45,0) -> 17 | G45: =Q3_worksheet!F70 -> 0 | H45: =Q3_worksheet!G70 -> 0 | I45: =IFERROR(H45/G45,0) -> 0 | J45: =G45-D45 -> -1 | K45: =H45-E45 -> -17 | L45: =I45-F45 -> -17
A46: =Q3_worksheet!A71 -> 001 | B46: =Q3_worksheet!B71 -> 405 | C46: =Q3_worksheet!C71 -> Lynn Perkins | D46: =Q3_worksheet!D71 -> 667 | E46: =Q3_worksheet!E71 -> 12325 | F46: =IFERROR(E46/D46,0) -> 18.478261 | G46: =Q3_worksheet!F71 -> 0 | H46: =Q3_worksheet!G71 -> 0 | I46: =IFERROR(H46/G46,0) -> 0 | J46: =G46-D46 -> -667 | K46: =H46-E46 -> -12325 | L46: =I46-F46 -> -18.478261
A47: =Q3_worksheet!A90 -> 002 | B47: =Q3_worksheet!B90 -> 38 | C47: =Q3_worksheet!C90 -> Conrad Walker | D47: =Q3_worksheet!D90 -> 1052 | E47: =Q3_worksheet!E90 -> 3981171 | F47: =IFERROR(E47/D47,0) -> 3784.3831 | G47: =Q3_worksheet!F90 -> 958 | H47: =Q3_worksheet!G90 -> 6232236 | I47: =IFERROR(H47/G47,0) -> 6505.4656 | J47: =G47-D47 -> -94 | K47: =H47-E47 -> 2251065 | L47: =I47-F47 -> 2721.0825
A48: =Q3_worksheet!A145 -> 004 | B48: =Q3_worksheet!B145 -> 169 | C48: =Q3_worksheet!C145 -> Cornelius Gibson | D48: =Q3_worksheet!D145 -> 316 | E48: =Q3_worksheet!E145 -> 228467 | F48: =IFERROR(E48/D48,0) -> 722.99684 | G48: =Q3_worksheet!F145 -> 807 | H48: =Q3_worksheet!G145 -> 270699 | I48: =IFERROR(H48/G48,0) -> 335.43866 | J48: =G48-D48 -> 491 | K48: =H48-E48 -> 42232 | L48: =I48-F48 -> -387.55817
A49: =Q3_worksheet!A284 -> 008 | B49: =Q3_worksheet!B284 -> 169 | C49: =Q3_worksheet!C284 -> Cornelius Gibson | D49: =Q3_worksheet!D284 -> 47 | E49: =Q3_worksheet!E284 -> 21289 | F49: =IFERROR(E49/D49,0) -> 452.95745 | G49: =Q3_worksheet!F284 -> 65 | H49: =Q3_worksheet!G284 -> 21838 | I49: =IFERROR(H49/G49,0) -> 335.96923 | J49: =G49-D49 -> 18 | K49: =H49-E49 -> 549 | L49: =I49-F49 -> -116.98822
A50: =Q3_worksheet!A75 -> 001 | B50: =Q3_worksheet!B75 -> 420 | C50: =Q3_worksheet!C75 -> Lyle Grant | D50: =Q3_worksheet!D75 -> 0 | E50: =Q3_worksheet!E75 -> 0 | F50: =IFERROR(E50/D50,0) -> 0 | G50: =Q3_worksheet!F75 -> 1 | H50: =Q3_worksheet!G75 -> 24 | I50: =IFERROR(H50/G50,0) -> 24 | J50: =G50-D50 -> 1 | K50: =H50-E50 -> 24 | L50: =I50-F50 -> 24
A51: =Q3_worksheet!A76 -> 001 | B51: =Q3_worksheet!B76 -> 421 | C51: =Q3_worksheet!C76 -> Emma Goodwin | D51: =Q3_worksheet!D76 -> 0 | E51: =Q3_worksheet!E76 -> 0 | F51: =IFERROR(E51/D51,0) -> 0 | G51: =Q3_worksheet!F76 -> 1412 | H51: =Q3_worksheet!G76 -> 133942 | I51: =IFERROR(H51/G51,0) -> 94.859773 | J51: =G51-D51 -> 1412 | K51: =H51-E51 -> 133942 | L51: =I51-F51 -> 94.859773
A52: =Q3_worksheet!A77 -> 001 | B52: =Q3_worksheet!B77 -> 422 | C52: =Q3_worksheet!C77 -> Afton Call | D52: =Q3_worksheet!D77 -> 0 | E52: =Q3_worksheet!E77 -> 0 | F52: =IFERROR(E52/D52,0) -> 0 | G52: =Q3_worksheet!F77 -> 10 | H52: =Q3_worksheet!G77 -> 140 | I52: =IFERROR(H52/G52,0) -> 14 | J52: =G52-D52 -> 10 | K52: =H52-E52 -> 140 | L52: =I52-F52 -> 14
A53: =Q3_worksheet!A78 -> 002 | B53: =Q3_worksheet!B78 -> (blank) | C53: =Q3_worksheet!C78 -> 0 | D53: =Q3_worksheet!D78 -> 0 | E53: =Q3_worksheet!E78 -> 0 | F53: =IFERROR(E53/D53,0) -> 0 | G53: =Q3_worksheet!F78 -> 0 | H53: =Q3_worksheet!G78 -> 0 | I53: =IFERROR(H53/G53,0) -> 0 | J53: =G53-D53 -> 0 | K53: =H53-E53 -> 0 | L53: =I53-F53 -> 0
A54: =Q3_worksheet!A79 -> 002 | B54: =Q3_worksheet!B79 -> 1 | C54: =Q3_worksheet!C79 -> Antonio Torres | D54: =Q3_worksheet!D79 -> 0 | E54: =Q3_worksheet!E79 -> 0 | F54: =IFERROR(E54/D54,0) -> 0 | G54: =Q3_worksheet!F79 -> 2 | H54: =Q3_worksheet!G79 -> 4500 | I54: =IFERROR(H54/G54,0) -> 2250 | J54: =G54-D54 -> 2 | K54: =H54-E54 -> 4500 | L54: =I54-F54 -> 2250
A55: =Q3_worksheet!A80 -> 002 | B55: =Q3_worksheet!B80 -> 3 | C55: =Q3_worksheet!C80 -> Melanie Green | D55: =Q3_worksheet!D80 -> 72 | E55: =Q3_worksheet!E80 -> 261510 | F55: =IFERROR(E55/D55,0) -> 3632.0833 | G55: =Q3_worksheet!F80 -> 0 | H55: =Q3_worksheet!G80 -> 0 | I55: =IFERROR(H55/G55,0) -> 0 | J55: =G55-D55 -> -72 | K55: =H55-E55 -> -261510 | L55: =I55-F55 -> -3632.0833
A56: =Q3_worksheet!A39 -> 001 | B56: =Q3_worksheet!B39 -> 44 | C56: =Q3_worksheet!C39 -> Dale Hamilton | D56: =Q3_worksheet!D39 -> 1040 | E56: =Q3_worksheet!E39 -> 100100 | F56: =IFERROR(E56/D56,0) -> 96.25 | G56: =Q3_worksheet!F39 -> 1000 | H56: =Q3_worksheet!G39 -> 96250 | I56: =IFERROR(H56/G56,0) -> 96.25 | J56: =G56-D56 -> -40 | K56: =H56-E56 -> -3850 | L56: =I56-F56 -> 0
A57: =Q3_worksheet!A65 -> 001 | B57: =Q3_worksheet!B65 -> 396 | C57: =Q3_worksheet!C65 -> Darryl Burgess | D57: =Q3_worksheet!D65 -> 35 | E57: =Q3_worksheet!E65 -> 832 | F57: =IFERROR(E57/D57,0) -> 23.771429 | G57: =Q3_worksheet!F65 -> 326 | H57: =Q3_worksheet!G65 -> 109210 | I57: =IFERROR(H57/G57,0) -> 335 | J57: =G57-D57 -> 291 | K57: =H57-E57 -> 108378 | L57: =I57-F57 -> 311.22857
A58: =Q3_worksheet!A115 -> 002 | B58: =Q3_worksheet!B115 -> 396 | C58: =Q3_worksheet!C115 -> Darryl Burgess | D58: =Q3_worksheet!D115 -> 9 | E58: =Q3_worksheet!E115 -> 288 | F58: =IFERROR(E58/D58,0) -> 32 | G58: =Q3_worksheet!F115 -> 155 | H58: =Q3_worksheet!G115 -> 51925 | I58: =IFERROR(H58/G58,0) -> 335 | J58: =G58-D58 -> 146 | K58: =H58-E58 -> 51637 | L58: =I58-F58 -> 303
A59: =Q3_worksheet!A154 -> 004 | B59: =Q3_worksheet!B154 -> 396 | C59: =Q3_worksheet!C154 -> Darryl Burgess | D59: =Q3_worksheet!D154 -> 78 | E59: =Q3_worksheet!E154 -> 2496 | F59: =IFERROR(E59/D59,0) -> 32 | G59: =Q3_worksheet!F154 -> 1100 | H59: =Q3_worksheet!G154 -> 377880 | I59: =IFERROR(H59/G59,0) -> 343.52727 | J59: =G59-D59 -> 1022 | K59: =H59-E59 -> 375384 | L59: =I59-F59 -> 311.52727
A60: =Q3_worksheet!A316 -> 008 | B60: =Q3_worksheet!B316 -> 396 | C60: =Q3_worksheet!C316 -> Darryl Burgess | D60: =Q3_worksheet!D316 -> 21 | E60: =Q3_worksheet!E316 -> 672 | F60: =IFERROR(E60/D60,0) -> 32 | G60: =Q3_worksheet!F316 -> 38 | H60: =Q3_worksheet!G316 -> 13645 | I60: =IFERROR(H60/G60,0) -> 359.07895 | J60: =G60-D60 -> 17 | K60: =H60-E60 -> 12973 | L60: =I60-F60 -> 327.07895
A61: =Q3_worksheet!A183 -> 005 | B61: =Q3_worksheet!B183 -> 204 | C61: =Q3_worksheet!C183 -> Deborah Bennett | D61: =Q3_worksheet!D183 -> 8 | E61: =Q3_worksheet!E183 -> 36276 | F61: =IFERROR(E61/D61,0) -> 4534.5 | G61: =Q3_worksheet!F183 -> 9 | H61: =Q3_worksheet!G183 -> 90 | I61: =IFERROR(H61/G61,0) -> 10 | J61: =G61-D61 -> 1 | K61: =H61-E61 -> -36186 | L61: =I61-F61 -> -4524.5
A62: =Q3_worksheet!A292 -> 008 | B62: =Q3_worksheet!B292 -> 204 | C62: =Q3_worksheet!C292 -> Deborah Bennett | D62: =Q3_worksheet!D292 -> 2 | E62: =Q3_worksheet!E292 -> 6046 | F62: =IFERROR(E62/D62,0) -> 3023 | G62: =Q3_worksheet!F292 -> 2 | H62: =Q3_worksheet!G292 -> 6296 | I62: =IFERROR(H62/G62,0) -> 3148 | J62: =G62-D62 -> 0 | K62: =H62-E62 -> 250 | L62: =I62-F62 -> 125
A63: =Q3_worksheet!A279 -> 008 | B63: =Q3_worksheet!B279 -> 53 | C63: =Q3_worksheet!C279 -> Delia Lopez | D63: =Q3_worksheet!D279 -> 2 | E63: =Q3_worksheet!E279 -> 50 | F63: =IFERROR(E63/D63,0) -> 25 | G63: =Q3_worksheet!F279 -> 1 | H63: =Q3_worksheet!G279 -> 25 | I63: =IFERROR(H63/G63,0) -> 25 | J63: =G63-D63 -> -1 | K63: =H63-E63 -> -25 | L63: =I63-F63 -> 0
A64: =Q3_worksheet!A141 -> 004 | B64: =Q3_worksheet!B141 -> 11 | C64: =Q3_worksheet!C141 -> Earnest Drake | D64: =Q3_worksheet!D141 -> 134 | E64: =Q3_worksheet!E141 -> 497557 | F64: =IFERROR(E64/D64,0) -> 3713.1119 | G64: =Q3_worksheet!F141 -> 147 | H64: =Q3_worksheet!G141 -> 554548 | I64: =IFERROR(H64/G64,0) -> 3772.4354 | J64: =G64-D64 -> 13 | K64: =H64-E64 -> 56991 | L64: =I64-F64 -> 59.323434
A65: =Q3_worksheet!A270 -> 008 | B65: =Q3_worksheet!B270 -> 11 | C65: =Q3_worksheet!C270 -> Earnest Drake | D65: =Q3_worksheet!D270 -> 8 | E65: =Q3_worksheet!E270 -> 30385 | F65: =IFERROR(E65/D65,0) -> 3798.125 | G65: =Q3_worksheet!F270 -> 59 | H65: =Q3_worksheet!G270 -> 218301 | I65: =IFERROR(H65/G65,0) -> 3700.0169 | J65: =G65-D65 -> 51 | K65: =H65-E65 -> 187916 | L65: =I65-F65 -> -98.108051
A66: =Q3_worksheet!A84 -> 002 | B66: =Q3_worksheet!B84 -> 20 | C66: =Q3_worksheet!C84 -> Ed Craig | D66: =Q3_worksheet!D84 -> 7791 | E66: =Q3_worksheet!E84 -> 2544989 | F66: =IFERROR(E66/D66,0) -> 326.65755 | G66: =Q3_worksheet!F84 -> 9127 | H66: =Q3_worksheet!G84 -> 2576936 | I66: =IFERROR(H66/G66,0) -> 282.34206 | J66: =G66-D66 -> 1336 | K66: =H66-E66 -> 31947 | L66: =I66-F66 -> -44.315492
A67: =Q3_worksheet!A42 -> 001 | B67: =Q3_worksheet!B42 -> 180 | C67: =Q3_worksheet!C42 -> Elisa Warren | D67: =Q3_worksheet!D42 -> 51 | E67: =Q3_worksheet!E42 -> 37782 | F67: =IFERROR(E67/D67,0) -> 740.82353 | G67: =Q3_worksheet!F42 -> 175 | H67: =Q3_worksheet!G42 -> 7510 | I67: =IFERROR(H67/G67,0) -> 42.914286 | J67: =G67-D67 -> 124 | K67: =H67-E67 -> -30272 | L67: =I67-F67 -> -697.90924
A68: =Q3_worksheet!A240 -> 006 | B68: =Q3_worksheet!B240 -> 180 | C68: =Q3_worksheet!C240 -> Elisa Warren | D68: =Q3_worksheet!D240 -> 389 | E68: =Q3_worksheet!E240 -> 162849 | F68: =IFERROR(E68/D68,0) -> 418.63496 | G68: =Q3_worksheet!F240 -> 203 | H68: =Q3_worksheet!G240 -> 155313 | I68: =IFERROR(H68/G68,0) -> 765.08867 | J68: =G68-D68 -> -186 | K68: =H68-E68 -> -7536 | L68: =I68-F68 -> 346.45371
A69: =Q3_worksheet!A94 -> 002 | B69: =Q3_worksheet!B94 -> 169 | C69: =Q3_worksheet!C94 -> Cornelius Gibson | D69: =Q3_worksheet!D94 -> 0 | E69: =Q3_worksheet!E94 -> 0 | F69: =IFERROR(E69/D69,0) -> 0 | G69: =Q3_worksheet!F94 -> 10 | H69: =Q3_worksheet!G94 -> 33751 | I69: =IFERROR(H69/G69,0) -> 3375.1 | J69: =G69-D69 -> 10 | K69: =H69-E69 -> 33751 | L69: =I69-F69 -> 3375.1
A70: =Q3_worksheet!A286 -> 008 | B70: =Q3_worksheet!B286 -> 180 | C70: =Q3_worksheet!C286 -> Elisa Warren | D70: =Q3_worksheet!D286 -> 408 | E70: =Q3_worksheet!E286 -> 113698 | F70: =IFERROR(E70/D70,0) -> 278.67157 | G70: =Q3_worksheet!F286 -> 14 | H70: =Q3_worksheet!G286 -> 3466 | I70: =IFERROR(H70/G70,0) -> 247.57143 | J70: =G70-D70 -> -394 | K70: =H70-E70 -> -110232 | L70: =I70-F70 -> -31.10014
A71: =Q3_worksheet!A96 -> 002 | B71: =Q3_worksheet!B96 -> 184 | C71: =Q3_worksheet!C96 -> Tammy Wilkins | D71: =Q3_worksheet!D96 -> 4 | E71: =Q3_worksheet!E96 -> 12013 | F71: =IFERROR(E71/D71,0) -> 3003.25 | G71: =Q3_worksheet!F96 -> 0 | H71: =Q3_worksheet!G96 -> 0 | I71: =IFERROR(H71/G71,0) -> 0 | J71: =G71-D71 -> -4 | K71: =H71-E71 -> -12013 | L71: =I71-F71 -> -3003.25
A72: =Q3_worksheet!A91 -> 002 | B72: =Q3_worksheet!B91 -> 45 | C72: =Q3_worksheet!C91 -> Ernesto Todd | D72: =Q3_worksheet!D91 -> 1040 | E72: =Q3_worksheet!E91 -> 10986664 | F72: =IFERROR(E72/D72,0) -> 10564.1 | G72: =Q3_worksheet!F91 -> 1000 | H72: =Q3_worksheet!G91 -> 10564100 | I72: =IFERROR(H72/G72,0) -> 10564.1 | J72: =G72-D72 -> -40 | K72: =H72-E72 -> -422564 | L72: =I72-F72 -> 0
A73: =Q3_worksheet!A98 -> 002 | B73: =Q3_worksheet!B98 -> 194 | C73: =Q3_worksheet!C98 -> Hector Wright | D73: =Q3_worksheet!D98 -> 4 | E73: =Q3_worksheet!E98 -> 90 | F73: =IFERROR(E73/D73,0) -> 22.5 | G73: =Q3_worksheet!F98 -> 0 | H73: =Q3_worksheet!G98 -> 0 | I73: =IFERROR(H73/G73,0) -> 0 | J73: =G73-D73 -> -4 | K73: =H73-E73 -> -90 | L73: =I73-F73 -> -22.5
A74: =Q3_worksheet!A60 -> 001 | B74: =Q3_worksheet!B60 -> 375 | C74: =Q3_worksheet!C60 -> Fannie Parks | D74: =Q3_worksheet!D60 -> 1 | E74: =Q3_worksheet!E60 -> 21 | F74: =IFERROR(E74/D74,0) -> 21 | G74: =Q3_worksheet!F60 -> 225 | H74: =Q3_worksheet!G60 -> 536 | I74: =IFERROR(H74/G74,0) -> 2.3822222 | J74: =G74-D74 -> 224 | K74: =H74-E74 -> 515 | L74: =I74-F74 -> -18.617778
A75: =Q3_worksheet!A152 -> 004 | B75: =Q3_worksheet!B152 -> 375 | C75: =Q3_worksheet!C152 -> Fannie Parks | D75: =Q3_worksheet!D152 -> 743 | E75: =Q3_worksheet!E152 -> 9901 | F75: =IFERROR(E75/D75,0) -> 13.325707 | G75: =Q3_worksheet!F152 -> 1350 | H75: =Q3_worksheet!G152 -> 3123 | I75: =IFERROR(H75/G75,0) -> 2.3133333 | J75: =G75-D75 -> 607 | K75: =H75-E75 -> -6778 | L75: =I75-F75 -> -11.012373
A76: =Q3_worksheet!A255 -> 006 | B76: =Q3_worksheet!B255 -> 375 | C76: =Q3_worksheet!C255 -> Fannie Parks | D76: =Q3_worksheet!D255 -> 36 | E76: =Q3_worksheet!E255 -> 474 | F76: =IFERROR(E76/D76,0) -> 13.166667 | G76: =Q3_worksheet!F255 -> 10 | H76: =Q3_worksheet!G255 -> 239 | I76: =IFERROR(H76/G76,0) -> 23.9 | J76: =G76-D76 -> -26 | K76: =H76-E76 -> -235 | L76: =I76-F76 -> 10.733333
A77: =Q3_worksheet!A102 -> 002 | B77: =Q3_worksheet!B102 -> 239 | C77: =Q3_worksheet!C102 -> Clarence Padilla | D77: =Q3_worksheet!D102 -> 225 | E77: =Q3_worksheet!E102 -> 39327 | F77: =IFERROR(E77/D77,0) -> 174.78667 | G77: =Q3_worksheet!F102 -> 0 | H77: =Q3_worksheet!G102 -> 0 | I77: =IFERROR(H77/G77,0) -> 0 | J77: =G77-D77 -> -225 | K77: =H77-E77 -> -39327 | L77: =I77-F77 -> -174.78667
A78: =Q3_worksheet!A74 -> 001 | B78: =Q3_worksheet!B74 -> 415 | C78: =Q3_worksheet!C74 -> Floyd Hunter | D78: =Q3_worksheet!D74 -> 8 | E78: =Q3_worksheet!E74 -> 23077 | F78: =IFERROR(E78/D78,0) -> 2884.625 | G78: =Q3_worksheet!F74 -> 18 | H78: =Q3_worksheet!G74 -> 51923 | I78: =IFERROR(H78/G78,0) -> 2884.6111 | J78: =G78-D78 -> 10 | K78: =H78-E78 -> 28846 | L78: =I78-F78 -> -0.013888889
A79: =Q3_worksheet!A104 -> 002 | B79: =Q3_worksheet!B104 -> 255 | C79: =Q3_worksheet!C104 -> Lois Moran | D79: =Q3_worksheet!D104 -> 2 | E79: =Q3_worksheet!E104 -> 36 | F79: =IFERROR(E79/D79,0) -> 18 | G79: =Q3_worksheet!F104 -> 0 | H79: =Q3_worksheet!G104 -> 0 | I79: =IFERROR(H79/G79,0) -> 0 | J79: =G79-D79 -> -2 | K79: =H79-E79 -> -36 | L79: =I79-F79 -> -18
A80: =Q3_worksheet!A105 -> 002 | B80: =Q3_worksheet!B105 -> 259 | C80: =Q3_worksheet!C105 -> Beulah Gibbs | D80: =Q3_worksheet!D105 -> 0 | E80: =Q3_worksheet!E105 -> 0 | F80: =IFERROR(E80/D80,0) -> 0 | G80: =Q3_worksheet!F105 -> 4 | H80: =Q3_worksheet!G105 -> 107 | I80: =IFERROR(H80/G80,0) -> 26.75 | J80: =G80-D80 -> 4 | K80: =H80-E80 -> 107 | L80: =I80-F80 -> 26.75
A81: =Q3_worksheet!A328 -> 008 | B81: =Q3_worksheet!B328 -> 415 | C81: =Q3_worksheet!C328 -> Floyd Hunter | D81: =Q3_worksheet!D328 -> 32 | E81: =Q3_worksheet!E328 -> 92308 | F81: =IFERROR(E81/D81,0) -> 2884.625 | G81: =Q3_worksheet!F328 -> 41 | H81: =Q3_worksheet!G328 -> 118271 | I81: =IFERROR(H81/G81,0) -> 2884.6585 | J81: =G81-D81 -> 9 | K81: =H81-E81 -> 25963 | L81: =I81-F81 -> 0.033536585
A82: =Q3_worksheet!A107 -> 002 | B82: =Q3_worksheet!B107 -> 281 | C82: =Q3_worksheet!C107 -> Marcia Neal | D82: =Q3_worksheet!D107 -> 7 | E82: =Q3_worksheet!E107 -> 182 | F82: =IFERROR(E82/D82,0) -> 26 | G82: =Q3_worksheet!F107 -> 0 | H82: =Q3_worksheet!G107 -> 0 | I82: =IFERROR(H82/G82,0) -> 0 | J82: =G82-D82 -> -7 | K82: =H82-E82 -> -182 | L82: =I82-F82 -> -26
A83: =Q3_worksheet!A108 -> 002 | B83: =Q3_worksheet!B108 -> 314 | C83: =Q3_worksheet!C108 -> Marianne Baldwin | D83: =Q3_worksheet!D108 -> 0 | E83: =Q3_worksheet!E108 -> 0 | F83: =IFERROR(E83/D83,0) -> 0 | G83: =Q3_worksheet!F108 -> 14 | H83: =Q3_worksheet!G108 -> 28287 | I83: =IFERROR(H83/G83,0) -> 2020.5 | J83: =G83-D83 -> 14 | K83: =H83-E83 -> 28287 | L83: =I83-F83 -> 2020.5
A84: =Q3_worksheet!A83 -> 002 | B84: =Q3_worksheet!B83 -> 19 | C84: =Q3_worksheet!C83 -> Frank Diaz | D84: =Q3_worksheet!D83 -> 20 | E84: =Q3_worksheet!E83 -> 540 | F84: =IFERROR(E84/D84,0) -> 27 | G84: =Q3_worksheet!F83 -> 6 | H84: =Q3_worksheet!G83 -> 162 | I84: =IFERROR(H84/G84,0) -> 27 | J84: =G84-D84 -> -14 | K84: =H84-E84 -> -378 | L84: =I84-F84 -> 0
A85: =Q3_worksheet!A110 -> 002 | B85: =Q3_worksheet!B110 -> 357 | C85: =Q3_worksheet!C110 -> Stanley Peterson | D85: =Q3_worksheet!D110 -> 36 | E85: =Q3_worksheet!E110 -> 360 | F85: =IFERROR(E85/D85,0) -> 10 | G85: =Q3_worksheet!F110 -> 0 | H85: =Q3_worksheet!G110 -> 0 | I85: =IFERROR(H85/G85,0) -> 0 | J85: =G85-D85 -> -36 | K85: =H85-E85 -> -360 | L85: =I85-F85 -> -10
A86: =Q3_worksheet!A111 -> 002 | B86: =Q3_worksheet!B111 -> 369 | C86: =Q3_worksheet!C111 -> Clark Morgan | D86: =Q3_worksheet!D111 -> 746 | E86: =Q3_worksheet!E111 -> 15666 | F86: =IFERROR(E86/D86,0) -> 21 | G86: =Q3_worksheet!F111 -> 0 | H86: =Q3_worksheet!G111 -> 0 | I86: =IFERROR(H86/G86,0) -> 0 | J86: =G86-D86 -> -746 | K86: =H86-E86 -> -15666 | L86: =I86-F86 -> -21
A87: =Q3_worksheet!A234 -> 006 | B87: =Q3_worksheet!B234 -> 19 | C87: =Q3_worksheet!C234 -> Frank Diaz | D87: =Q3_worksheet!D234 -> 49 | E87: =Q3_worksheet!E234 -> 1323 | F87: =IFERROR(E87/D87,0) -> 27 | G87: =Q3_worksheet!F234 -> 69 | H87: =Q3_worksheet!G234 -> 181303 | I87: =IFERROR(H87/G87,0) -> 2627.5797 | J87: =G87-D87 -> 20 | K87: =H87-E87 -> 179980 | L87: =I87-F87 -> 2600.5797
A88: =Q3_worksheet!A273 -> 008 | B88: =Q3_worksheet!B273 -> 19 | C88: =Q3_worksheet!C273 -> Frank Diaz | D88: =Q3_worksheet!D273 -> 3 | E88: =Q3_worksheet!E273 -> 81 | F88: =IFERROR(E88/D88,0) -> 27 | G88: =Q3_worksheet!F273 -> 46 | H88: =Q3_worksheet!G273 -> 124272 | I88: =IFERROR(H88/G88,0) -> 2701.5652 | J88: =G88-D88 -> 43 | K88: =H88-E88 -> 124191 | L88: =I88-F88 -> 2674.5652
A89: =Q3_worksheet!A114 -> 002 | B89: =Q3_worksheet!B114 -> 391 | C89: =Q3_worksheet!C114 -> Barry Mckenzie | D89: =Q3_worksheet!D114 -> 0 | E89: =Q3_worksheet!E114 -> 0 | F89: =IFERROR(E89/D89,0) -> 0 | G89: =Q3_worksheet!F114 -> 14 | H89: =Q3_worksheet!G114 -> 3605 | I89: =IFERROR(H89/G89,0) -> 257.5 | J89: =G89-D89 -> 14 | K89: =H89-E89 -> 3605 | L89: =I89-F89 -> 257.5
A90: =Q3_worksheet!A112 -> 002 | B90: =Q3_worksheet!B112 -> 381 | C90: =Q3_worksheet!C112 -> Frankie Mcdaniel | D90: =Q3_worksheet!D112 -> 954 | E90: =Q3_worksheet!E112 -> 2062718 | F90: =IFERROR(E90/D90,0) -> 2162.1782 | G90: =Q3_worksheet!F112 -> 915 | H90: =Q3_worksheet!G112 -> 234737 | I90: =IFERROR(H90/G90,0) -> 256.54317 | J90: =G90-D90 -> -39 | K90: =H90-E90 -> -1827981 | L90: =I90-F90 -> -1905.635
A91: =Q3_worksheet!A116 -> 002 | B91: =Q3_worksheet!B116 -> 398 | C91: =Q3_worksheet!C116 -> Mona Howard | D91: =Q3_worksheet!D116 -> 0 | E91: =Q3_worksheet!E116 -> 0 | F91: =IFERROR(E91/D91,0) -> 0 | G91: =Q3_worksheet!F116 -> 2 | H91: =Q3_worksheet!G116 -> 30 | I91: =IFERROR(H91/G91,0) -> 15 | J91: =G91-D91 -> 2 | K91: =H91-E91 -> 30 | L91: =I91-F91 -> 15
A92: =Q3_worksheet!A144 -> 004 | B92: =Q3_worksheet!B144 -> 133 | C92: =Q3_worksheet!C144 -> Geneva Moody | D92: =Q3_worksheet!D144 -> 152 | E92: =Q3_worksheet!E144 -> 142146 | F92: =IFERROR(E92/D92,0) -> 935.17105 | G92: =Q3_worksheet!F144 -> 146 | H92: =Q3_worksheet!G144 -> 434351 | I92: =IFERROR(H92/G92,0) -> 2975.0068 | J92: =G92-D92 -> -6 | K92: =H92-E92 -> 292205 | L92: =I92-F92 -> 2039.8358
A93: =Q3_worksheet!A170 -> 005 | B93: =Q3_worksheet!B170 -> 133 | C93: =Q3_worksheet!C170 -> Geneva Moody | D93: =Q3_worksheet!D170 -> 127 | E93: =Q3_worksheet!E170 -> 34570 | F93: =IFERROR(E93/D93,0) -> 272.20472 | G93: =Q3_worksheet!F170 -> 23 | H93: =Q3_worksheet!G170 -> 333 | I93: =IFERROR(H93/G93,0) -> 14.478261 | J93: =G93-D93 -> -104 | K93: =H93-E93 -> -34237 | L93: =I93-F93 -> -257.72646
A94: =Q3_worksheet!A119 -> 002 | B94: =Q3_worksheet!B119 -> 401 | C94: =Q3_worksheet!C119 -> Maryann Cohen | D94: =Q3_worksheet!D119 -> 11 | E94: =Q3_worksheet!E119 -> 286 | F94: =IFERROR(E94/D94,0) -> 26 | G94: =Q3_worksheet!F119 -> 0 | H94: =Q3_worksheet!G119 -> 0 | I94: =IFERROR(H94/G94,0) -> 0 | J94: =G94-D94 -> -11 | K94: =H94-E94 -> -286 | L94: =I94-F94 -> -26
A95: =Q3_worksheet!A281 -> 008 | B95: =Q3_worksheet!B281 -> 133 | C95: =Q3_worksheet!C281 -> Geneva Moody | D95: =Q3_worksheet!D281 -> 8 | E95: =Q3_worksheet!E281 -> 238 | F95: =IFERROR(E95/D95,0) -> 29.75 | G95: =Q3_worksheet!F281 -> 37 | H95: =Q3_worksheet!G281 -> 110075 | I95: =IFERROR(H95/G95,0) -> 2975 | J95: =G95-D95 -> 29 | K95: =H95-E95 -> 109837 | L95: =I95-F95 -> 2945.25
A96: =Q3_worksheet!A72 -> 001 | B96: =Q3_worksheet!B72 -> 406 | C96: =Q3_worksheet!C72 -> Grant Daniel | D96: =Q3_worksheet!D72 -> 2988 | E96: =Q3_worksheet!E72 -> 558169 | F96: =IFERROR(E96/D96,0) -> 186.80355 | G96: =Q3_worksheet!F72 -> 17031 | H96: =Q3_worksheet!G72 -> 896013 | I96: =IFERROR(H96/G96,0) -> 52.61071 | J96: =G96-D96 -> 14043 | K96: =H96-E96 -> 337844 | L96: =I96-F96 -> -134.19284
A97: =Q3_worksheet!A122 -> 002 | B97: =Q3_worksheet!B122 -> 417 | C97: =Q3_worksheet!C122 -> William Casey | D97: =Q3_worksheet!D122 -> 0 | E97: =Q3_worksheet!E122 -> 0 | F97: =IFERROR(E97/D97,0) -> 0 | G97: =Q3_worksheet!F122 -> 9474 | H97: =Q3_worksheet!G122 -> 20856 | I97: =IFERROR(H97/G97,0) -> 2.2013933 | J97: =G97-D97 -> 9474 | K97: =H97-E97 -> 20856 | L97: =I97-F97 -> 2.2013933
A98: =Q3_worksheet!A123 -> 003 | B98: =Q3_worksheet!B123 -> (blank) | C98: =Q3_worksheet!C123 -> 0 | D98: =Q3_worksheet!D123 -> 0 | E98: =Q3_worksheet!E123 -> 0 | F98: =IFERROR(E98/D98,0) -> 0 | G98: =Q3_worksheet!F123 -> 5340 | H98: =Q3_worksheet!G123 -> 746988 | I98: =IFERROR(H98/G98,0) -> 139.88539 | J98: =G98-D98 -> 5340 | K98: =H98-E98 -> 746988 | L98: =I98-F98 -> 139.88539
A99: =Q3_worksheet!A121 -> 002 | B99: =Q3_worksheet!B121 -> 406 | C99: =Q3_worksheet!C121 -> Grant Daniel | D99: =Q3_worksheet!D121 -> 1307 | E99: =Q3_worksheet!E121 -> 1005284 | F99: =IFERROR(E99/D99,0) -> 769.15379 | G99: =Q3_worksheet!F121 -> 15920 | H99: =Q3_worksheet!G121 -> 831203 | I99: =IFERROR(H99/G99,0) -> 52.211244 | J99: =G99-D99 -> 14613 | K99: =H99-E99 -> -174081 | L99: =I99-F99 -> -716.94254
A100: =Q3_worksheet!A125 -> 003 | B100: =Q3_worksheet!B125 -> 15 | C100: =Q3_worksheet!C125 -> Don Young | D100: =Q3_worksheet!D125 -> 19 | E100: =Q3_worksheet!E125 -> 52525 | F100: =IFERROR(E100/D100,0) -> 2764.4737 | G100: =Q3_worksheet!F125 -> 0 | H100: =Q3_worksheet!G125 -> 0 | I100: =IFERROR(H100/G100,0) -> 0 | J100: =G100-D100 -> -19 | K100: =H100-E100 -> -52525 | L100: =I100-F100 -> -2764.4737
...

Sheet P3_Q1
A1: Job code | B1: Employee number | C1: 2015 total hours | D1: 2015 gross pay | E1: 2015 gross pay per hour | F1: 2016 total hours | G1: 2016 gross pay | H1: 2016 gross pay per hour | I1: Hours difference | J1: Totral gross pay difference | K1: Gross pay per hour difference
A2: =Q3_worksheet!A13 -> 009 | B2: =Q3_worksheet!B13 -> New Foreign Manufacturing Plant | C2: =Q3_worksheet!C13 -> 0 | D2: =Q3_worksheet!D13 -> 0 | E2: =IFERROR(Table4[[#This Row],[2015 gross pay]]/Table4[[#This Row],[2015 total hours]],0) -> 0 | F2: =Q3_worksheet!E13 -> 24579 | G2: =Q3_worksheet!F13 -> 6238118 | H2: =IFERROR(Table4[[#This Row],[2016 gross pay]]/Table4[[#This Row],[2016 total hours]],0) -> 253.79869 | I2: =Table4[[#This Row],[2016 total hours]]-Table4[[#This Row],[2015 gross pay]] -> 24579 | J2: =Table4[[#This Row],[2016 gross pay]]-Table4[[#This Row],[2015 gross pay]] -> 6238118 | K2: =Table4[[#This Row],[2016 gross pay per hour]]-Table4[[#This Row],[2015 gross pay per hour]] -> 253.79869
A3: =Q3_worksheet!A5 -> 001 | B3: =Q3_worksheet!B5 -> Office | C3: =Q3_worksheet!C5 -> 89442 | D3: =Q3_worksheet!D5 -> 13178934 | E3: =IFERROR(Table4[[#This Row],[2015 gross pay]]/Table4[[#This Row],[2015 total hours]],0) -> 147.34615 | F3: =Q3_worksheet!E5 -> 283090 | G3: =Q3_worksheet!F5 -> 18784220 | H3: =IFERROR(Table4[[#This Row],[2016 gross pay]]/Table4[[#This Row],[2016 total hours]],0) -> 66.354234 | I3: =Table4[[#This Row],[2016 total hours]]-Table4[[#This Row],[2015 gross pay]] -> -12895844 | J3: =Table4[[#This Row],[2016 gross pay]]-Table4[[#This Row],[2015 gross pay]] -> 5605286 | K3: =Table4[[#This Row],[2016 gross pay per hour]]-Table4[[#This Row],[2015 gross pay per hour]] -> -80.991912
A4: =Q3_worksheet!A10 -> 006 | B4: =Q3_worksheet!B10 -> Service | C4: =Q3_worksheet!C10 -> 10406 | D4: =Q3_worksheet!D10 -> 5376020 | E4: =IFERROR(Table4[[#This Row],[2015 gross pay]]/Table4[[#This Row],[2015 total hours]],0) -> 516.62695 | F4: =Q3_worksheet!E10 -> 64249 | G4: =Q3_worksheet!F10 -> 8367948 | H4: =IFERROR(Table4[[#This Row],[2016 gross pay]]/Table4[[#This Row],[2016 total hours]],0) -> 130.24246 | I4: =Table4[[#This Row],[2016 total hours]]-Table4[[#This Row],[2015 gross pay]] -> -5311771 | J4: =Table4[[#This Row],[2016 gross pay]]-Table4[[#This Row],[2015 gross pay]] -> 2991928 | K4: =Table4[[#This Row],[2016 gross pay per hour]]-Table4[[#This Row],[2015 gross pay per hour]] -> -386.38448
A5: =Q3_worksheet!A12 -> 008 | B5: =Q3_worksheet!B12 -> Employee Training | C5: =Q3_worksheet!C12 -> 3843 | D5: =Q3_worksheet!D12 -> 1204204 | E5: =IFERROR(Table4[[#This Row],[2015 gross pay]]/Table4[[#This Row],[2015 total hours]],0) -> 313.34999 | F5: =Q3_worksheet!E12 -> 14072 | G5: =Q3_worksheet!F12 -> 2814657 | H5: =IFERROR(Table4[[#This Row],[2016 gross pay]]/Table4[[#This Row],[2016 total hours]],0) -> 200.01826 | I5: =Table4[[#This Row],[2016 total hours]]-Table4[[#This Row],[2015 gross pay]] -> -1190132 | J5: =Table4[[#This Row],[2016 gross pay]]-Table4[[#This Row],[2015 gross pay]] -> 1610453 | K5: =Table4[[#This Row],[2016 gross pay per hour]]-Table4[[#This Row],[2015 gross pay per hour]] -> -113.33172
A6: =Q3_worksheet!A8 -> 004 | B6: =Q3_worksheet!B8 -> Proj Management | C6: =Q3_worksheet!C8 -> 4784 | D6: =Q3_worksheet!D8 -> 3339832 | E6: =IFERROR(Table4[[#This Row],[2015 gross pay]]/Table4[[#This Row],[2015 total hours]],0) -> 698.12542 | F6: =Q3_worksheet!E8 -> 12359 | G6: =Q3_worksheet!F8 -> 4928450 | H6: =IFERROR(Table4[[#This Row],[2016 gross pay]]/Table4[[#This Row],[2016 total hours]],0) -> 398.77417 | I6: =Table4[[#This Row],[2016 total hours]]-Table4[[#This Row],[2015 gross pay]] -> -3327473 | J6: =Table4[[#This Row],[2016 gross pay]]-Table4[[#This Row],[2015 gross pay]] -> 1588618 | K6: =Table4[[#This Row],[2016 gross pay per hour]]-Table4[[#This Row],[2015 gross pay per hour]] -> -299.35125
A7: =Q3_worksheet!A14 -> 010 | B7: =Q3_worksheet!B14 -> New Foreign Manufacturing Oversight | C7: =Q3_worksheet!C14 -> 0 | D7: =Q3_worksheet!D14 -> 0 | E7: =IFERROR(Table4[[#This Row],[2015 gross pay]]/Table4[[#This Row],[2015 total hours]],0) -> 0 | F7: =Q3_worksheet!E14 -> 1300 | G7: =Q3_worksheet!F14 -> 1270293 | H7: =IFERROR(Table4[[#This Row],[2016 gross pay]]/Table4[[#This Row],[2016 total hours]],0) -> 977.14846 | I7: =Table4[[#This Row],[2016 total hours]]-Table4[[#This Row],[2015 gross pay]] -> 1300 | J7: =Table4[[#This Row],[2016 gross pay]]-Table4[[#This Row],[2015 gross pay]] -> 1270293 | K7: =Table4[[#This Row],[2016 gross pay per hour]]-Table4[[#This Row],[2015 gross pay per hour]] -> 977.14846
A8: =Q3_worksheet!A16 -> 012 | B8: =Q3_worksheet!B16 -> Internal Auditing | C8: =Q3_worksheet!C16 -> 0 | D8: =Q3_worksheet!D16 -> 0 | E8: =IFERROR(Table4[[#This Row],[2015 gross pay]]/Table4[[#This Row],[2015 total hours]],0) -> 0 | F8: =Q3_worksheet!E16 -> 1589 | G8: =Q3_worksheet!F16 -> 953068 | H8: =IFERROR(Table4[[#This Row],[2016 gross pay]]/Table4[[#This Row],[2016 total hours]],0) -> 599.79106 | I8: =Table4[[#This Row],[2016 total hours]]-Table4[[#This Row],[2015 gross pay]] -> 1589 | J8: =Table4[[#This Row],[2016 gross pay]]-Table4[[#This Row],[2015 gross pay]] -> 953068 | K8: =Table4[[#This Row],[2016 gross pay per hour]]-Table4[[#This Row],[2015 gross pay per hour]] -> 599.79106
A9: =Q3_worksheet!A6 -> 002 | B9: =Q3_worksheet!B6 -> Sales | C9: =Q3_worksheet!C6 -> 26247 | D9: =Q3_worksheet!D6 -> 39621371 | E9: =IFERROR(Table4[[#This Row],[2015 gross pay]]/Table4[[#This Row],[2015 total hours]],0) -> 1509.5581 | F9: =Q3_worksheet!E6 -> 52576 | G9: =Q3_worksheet!F6 -> 40154639 | H9: =IFERROR(Table4[[#This Row],[2016 gross pay]]/Table4[[#This Row],[2016 total hours]],0) -> 763.74466 | I9: =Table4[[#This Row],[2016 total hours]]-Table4[[#This Row],[2015 gross pay]] -> -39568795 | J9: =Table4[[#This Row],[2016 gross pay]]-Table4[[#This Row],[2015 gross pay]] -> 533268 | K9: =Table4[[#This Row],[2016 gross pay per hour]]-Table4[[#This Row],[2015 gross pay per hour]] -> -745.81343
A10: =Q3_worksheet!A15 -> 011 | B10: =Q3_worksheet!B15 -> Internal Projects | C10: =Q3_worksheet!C15 -> 0 | D10: =Q3_worksheet!D15 -> 0 | E10: =IFERROR(Table4[[#This Row],[2015 gross pay]]/Table4[[#This Row],[2015 total hours]],0) -> 0 | F10: =Q3_worksheet!E15 -> 100 | G10: =Q3_worksheet!F15 -> 70281 | H10: =IFERROR(Table4[[#This Row],[2016 gross pay]]/Table4[[#This Row],[2016 total hours]],0) -> 702.81 | I10: =Table4[[#This Row],[2016 total hours]]-Table4[[#This Row],[2015 gross pay]] -> 100 | J10: =Table4[[#This Row],[2016 gross pay]]-Table4[[#This Row],[2015 gross pay]] -> 70281 | K10: =Table4[[#This Row],[2016 gross pay per hour]]-Table4[[#This Row],[2015 gross pay per hour]] -> 702.81
A11: =Q3_worksheet!A9 -> 005 | B11: =Q3_worksheet!B9 -> Installation | C11: =Q3_worksheet!C9 -> 1430 | D11: =Q3_worksheet!D9 -> 162539 | E11: =IFERROR(Table4[[#This Row],[2015 gross pay]]/Table4[[#This Row],[2015 total hours]],0) -> 113.66364 | F11: =Q3_worksheet!E9 -> 2192 | G11: =Q3_worksheet!F9 -> 164085 | H11: =IFERROR(Table4[[#This Row],[2016 gross pay]]/Table4[[#This Row],[2016 total hours]],0) -> 74.856296 | I11: =Table4[[#This Row],[2016 total hours]]-Table4[[#This Row],[2015 gross pay]] -> -160347 | J11: =Table4[[#This Row],[2016 gross pay]]-Table4[[#This Row],[2015 gross pay]] -> 1546 | K11: =Table4[[#This Row],[2016 gross pay per hour]]-Table4[[#This Row],[2015 gross pay per hour]] -> -38.807341
A12: =Q3_worksheet!A17 -> 144 | B12: =Q3_worksheet!B17 -> 0 | C12: =Q3_worksheet!C17 -> 1 | D12: =Q3_worksheet!D17 -> 315 | E12: =IFERROR(Table4[[#This Row],[2015 gross pay]]/Table4[[#This Row],[2015 total hours]],0) -> 315 | F12: =Q3_worksheet!E17 -> 0 | G12: =Q3_worksheet!F17 -> 0 | H12: =IFERROR(Table4[[#This Row],[2016 gross pay]]/Table4[[#This Row],[2016 total hours]],0) -> 0 | I12: =Table4[[#This Row],[2016 total hours]]-Table4[[#This Row],[2015 gross pay]] -> -315 | J12: =Table4[[#This Row],[2016 gross pay]]-Table4[[#This Row],[2015 gross pay]] -> -315 | K12: =Table4[[#This Row],[2016 gross pay per hour]]-Table4[[#This Row],[2015 gross pay per hour]] -> -315
A13: =Q3_worksheet!A7 -> 003 | B13: =Q3_worksheet!B7 -> Travel | C13: =Q3_worksheet!C7 -> 1064 | D13: =Q3_worksheet!D7 -> 2678797 | E13: =IFERROR(Table4[[#This Row],[2015 gross pay]]/Table4[[#This Row],[2015 total hours]],0) -> 2517.6664 | F13: =Q3_worksheet!E7 -> 6054 | G13: =Q3_worksheet!F7 -> 1926817 | H13: =IFERROR(Table4[[#This Row],[2016 gross pay]]/Table4[[#This Row],[2016 total hours]],0) -> 318.27172 | I13: =Table4[[#This Row],[2016 total hours]]-Table4[[#This Row],[2015 gross pay]] -> -2672743 | J13: =Table4[[#This Row],[2016 gross pay]]-Table4[[#This Row],[2015 gross pay]] -> -751980 | K13: =Table4[[#This Row],[2016 gross pay per hour]]-Table4[[#This Row],[2015 gross pay per hour]] -> -2199.3946
A14: =Q3_worksheet!A11 -> 007 | B14: =Q3_worksheet!B11 -> Customer Training | C14: =Q3_worksheet!C11 -> 1846 | D14: =Q3_worksheet!D11 -> 2014041 | E14: =IFERROR(Table4[[#This Row],[2015 gross pay]]/Table4[[#This Row],[2015 total hours]],0) -> 1091.0298 | F14: =Q3_worksheet!E11 -> 443 | G14: =Q3_worksheet!F11 -> 257149 | H14: =IFERROR(Table4[[#This Row],[2016 gross pay]]/Table4[[#This Row],[2016 total hours]],0) -> 580.47178 | I14: =Table4[[#This Row],[2016 total hours]]-Table4[[#This Row],[2015 gross pay]] -> -2013598 | J14: =Table4[[#This Row],[2016 gross pay]]-Table4[[#This Row],[2015 gross pay]] -> -1756892 | K14: =Table4[[#This Row],[2016 gross pay per hour]]-Table4[[#This Row],[2015 gross pay per hour]] -> -510.55801
A15: note:job code 144, comes from project 14S1440, It most likely to be an project code error

Sheet Q3_worksheet
C2: YEAR | D2: Values
C3: 2015 | E3: 2016
A4: Job_code | B4: Job_description | C4: Total_Hours | D4: Gross_Wages | E4: Total_Hours | F4: Gross_Wages
A5: 001 | B5: Office | C5: 89442 | D5: 13178934 | E5: 283090 | F5: 18784220
A6: 002 | B6: Sales | C6: 26247 | D6: 39621371 | E6: 52576 | F6: 40154639
A7: 003 | B7: Travel | C7: 1064 | D7: 2678797 | E7: 6054 | F7: 1926817
A8: 004 | B8: Proj Management | C8: 4784 | D8: 3339832 | E8: 12359 | F8: 4928450
A9: 005 | B9: Installation | C9: 1430 | D9: 162539 | E9: 2192 | F9: 164085
A10: 006 | B10: Service | C10: 10406 | D10: 5376020 | E10: 64249 | F10: 8367948
A11: 007 | B11: Customer Training | C11: 1846 | D11: 2014041 | E11: 443 | F11: 257149
A12: 008 | B12: Employee Training | C12: 3843 | D12: 1204204 | E12: 14072 | F12: 2814657
A13: 009 | B13: New Foreign Manufacturing Plant | C13: 0 | D13: 0 | E13: 24579 | F13: 6238118
A14: 010 | B14: New Foreign Manufacturing Oversight | C14: 0 | D14: 0 | E14: 1300 | F14: 1270293
A15: 011 | B15: Internal Projects | C15: 0 | D15: 0 | E15: 100 | F15: 70281
A16: 012 | B16: Internal Auditing | C16: 0 | D16: 0 | E16: 1589 | F16: 953068
A17: 144 | C17: 1 | D17: 315
A18: 144, comes from project 14S1440, I think it is an error
D24: YEAR | E24: Values
D25: 2015 | E25: 2015 | F25: 2016 | G25: 2016
A26: Job_code | B26: Emp_No | C26: Emp_Name | D26: Sum of Total_Hours | E26: Sum of Gross_Wages | F26: Sum of Total_Hours | G26: Sum of Gross_Wages
A27: 001 | B27: (blank) | F27: 16565 | G27: 12580
A28: 001 | B28: 1 | C28: Antonio Torres | D28: 911 | E28: 2011582 | F28: 1101 | G28: 3005624
A29: 001 | B29: 3 | C29: Melanie Green | D29: 849 | E29: 2089458 | F29: 938 | G29: 720018
A30: 001 | B30: 7 | C30: Shelia Keller | D30: 3 | E30: 6868 | F30: 580 | G30: 1418184
A31: 001 | B31: 18 | C31: Marty Barnes | D31: 4998 | E31: 12840 | F31: 74200 | G31: 14840
A32: 001 | B32: 19 | C32: Frank Diaz | F32: 4 | G32: 108
A33: 001 | B33: 22 | C33: Marion Scott | F33: 29 | G33: 78931
A34: 001 | B34: 25 | C34: Tami Luna | D34: 4301 | E34: 1107808 | F34: 4947 | G34: 1100882
A35: 001 | B35: 27 | C35: Cindy Lunt | D35: 644 | E35: 239490 | F35: 327 | G35: 478089
A36: 001 | B36: 30 | C36: Joe Perry | D36: 2 | E36: 4873 | F36: 155 | G36: 38905
A37: 001 | B37: 34 | C37: Sheryl Hill | D37: 4 | E37: 20815 | F37: 108 | G37: 531011
A38: 001 | B38: 37 | C38: Kirk Byrd | F38: 5 | G38: 1225
A39: 001 | B39: 44 | C39: Dale Hamilton | D39: 1040 | E39: 100100 | F39: 1000 | G39: 96250
A40: 001 | B40: 106 | C40: Allan Wood | D40: 646 | E40: 227334
A41: 001 | B41: 168 | C41: Brittany Carlson | D41: 122 | E41: 74453 | F41: 10 | G41: 375
A42: 001 | B42: 180 | C42: Elisa Warren | D42: 51 | E42: 37782 | F42: 175 | G42: 7510
A43: 001 | B43: 194 | C43: Hector Wright | D43: 4 | E43: 90
A44: 001 | B44: 199 | C44: Nettie Stevens | D44: 6 | E44: 2142 | F44: 3 | G44: 1091
A45: 001 | B45: 203 | C45: Helen Paul | D45: 466 | E45: 3020213 | F45: 461 | G45: 2970103
A46: 001 | B46: 210 | C46: Kenny Robertson | D46: 743 | E46: 496408 | F46: 84 | G46: 199752
A47: 001 | B47: 239 | C47: Clarence Padilla | D47: 38339 | E47: 1350365 | F47: 46219 | G47: 1985158
A48: 001 | B48: 248 | C48: Jodi Powers | D48: 8710 | E48: 243317 | F48: 85874 | G48: 1760418
A49: 001 | B49: 259 | C49: Beulah Gibbs | F49: 5 | G49: 13375
A50: 001 | B50: 281 | C50: Marcia Neal | D50: 197 | E50: 1521 | F50: 15 | G50: 2795
A51: 001 | B51: 287 | C51: Levi Christensen | D51: 2101 | E51: 608482 | F51: 2729 | G51: 945065
A52: 001 | B52: 320 | C52: Terry Moreno | D52: 10 | E52: 35819 | F52: 95 | G52: 36539
A53: 001 | B53: 343 | C53: Tommy Graves | D53: 374 | E53: 13420 | F53: 275 | G53: 559
A54: 001 | B54: 352 | C54: Myra Vega | F54: 10 | G54: 190
A55: 001 | B55: 357 | C55: Jesus Peterson | F55: 49 | G55: 26875
A56: 001 | B56: 357 | C56: Stanley Peterson | D56: 4 | E56: 80
A57: 001 | B57: 358 | C57: Marc Wallace | D57: 11878 | E57: 290408 | F57: 8903 | G57: 1488029
A58: 001 | B58: 368 | C58: Cesar Greene | D58: 1 | E58: 245 | F58: 175 | G58: 42875
A59: 001 | B59: 374 | C59: Melvin Strickland | D59: 3543 | E59: 69540 | F59: 4829 | G59: 101409
A60: 001 | B60: 375 | C60: Fannie Parks | D60: 1 | E60: 21 | F60: 225 | G60: 536
A61: 001 | B61: 380 | C61: Preston Robinson | D61: 223 | E61: 1541 | F61: 205 | G61: 4305
A62: 001 | B62: 385 | C62: Lillian Jefferson | D62: 82 | E62: 1230
A63: 001 | B63: 386 | C63: Raquel Singleton | D63: 1313 | E63: 2167 | F63: 12175 | G63: 17045
A64: 001 | B64: 391 | C64: Barry Mckenzie | D64: 405 | E64: 446351 | F64: 1620 | G64: 471227
A65: 001 | B65: 396 | C65: Darryl Burgess | D65: 35 | E65: 832 | F65: 326 | G65: 109210
A66: 001 | B66: 398 | C66: Mona Howard | D66: 0 | E66: 0 | F66: 48 | G66: 720
A67: 001 | B67: 400 | C67: Roberto Ortega | D67: 2725 | E67: 56393
A68: 001 | B68: 401 | C68: Maryann Cohen | D68: 253 | E68: 6630
A69: 001 | B69: 402 | C69: Gwendolyn Alvarado | D69: 31 | E69: 396 | F69: 45 | G69: 90
A70: 001 | B70: 403 | C70: Joyce Ferguson | D70: 1 | E70: 17
A71: 001 | B71: 405 | C71: Lynn Perkins | D71: 667 | E71: 12325
A72: 001 | B72: 406 | C72: Grant Daniel | D72: 2988 | E72: 558169 | F72: 17031 | G72: 896013
A73: 001 | B73: 412 | C73: Norman Ruiz | D73: 763 | E73: 4332 | F73: 104 | G73: 20280
A74: 001 | B74: 415 | C74: Floyd Hunter | D74: 8 | E74: 23077 | F74: 18 | G74: 51923
A75: 001 | B75: 420 | C75: Lyle Grant | F75: 1 | G75: 24
A76: 001 | B76: 421 | C76: Emma Goodwin | F76: 1412 | G76: 133942
A77: 001 | B77: 422 | C77: Afton Call | F77: 10 | G77: 140
A78: 002 | B78: (blank) | F78: 0 | G78: 0
A79: 002 | B79: 1 | C79: Antonio Torres | D79: 0 | E79: 0 | F79: 2 | G79: 4500
A80: 002 | B80: 3 | C80: Melanie Green | D80: 72 | E80: 261510
A81: 002 | B81: 7 | C81: Shelia Keller | D81: 1688 | E81: 2167936 | F81: 4281 | G81: 1394867
A82: 002 | B82: 13 | C82: Mamie Day | D82: 209 | E82: 756533 | F82: 170 | G82: 789885
A83: 002 | B83: 19 | C83: Frank Diaz | D83: 20 | E83: 540 | F83: 6 | G83: 162
A84: 002 | B84: 20 | C84: Ed Craig | D84: 7791 | E84: 2544989 | F84: 9127 | G84: 2576936
A85: 002 | B85: 23 | C85: Mary Waters | D85: 14 | E85: 43485 | F85: 146 | G85: 521208
A86: 002 | B86: 27 | C86: Cindy Lunt | D86: 783 | E86: 271697 | F86: 418 | G86: 470466
A87: 002 | B87: 30 | C87: Joe Perry | D87: 163 | E87: 99040 | F87: 525 | G87: 131775
A88: 002 | B88: 34 | C88: Sheryl Hill | D88: 88 | E88: 318781 | F88: 51 | G88: 241627
A89: 002 | B89: 35 | C89: Leonard Wong | D89: 965 | E89: 2723086 | F89: 905 | G89: 2617701
A90: 002 | B90: 38 | C90: Conrad Walker | D90: 1052 | E90: 3981171 | F90: 958 | G90: 6232236
A91: 002 | B91: 45 | C91: Ernesto Todd | D91: 1040 | E91: 10986664 | F91: 1000 | G91: 10564100
A92: 002 | B92: 106 | C92: Allan Wood | D92: 185 | E92: 5310 | F92: 1010 | G92: 2138536
A93: 002 | B93: 168 | C93: Brittany Carlson | D93: 56 | E93: 2100 | F93: 8 | G93: 300
A94: 002 | B94: 169 | C94: Cornelius Gibson | F94: 10 | G94: 33751
A95: 002 | B95: 179 | C95: Cassandra Poole | D95: 225 | E95: 183562 | F95: 677 | G95: 297922
A96: 002 | B96: 184 | C96: Tammy Wilkins | D96: 4 | E96: 12013
A97: 002 | B97: 192 | C97: Mike Briggs | D97: 962 | E97: 2250629 | F97: 877 | G97: 2115772
A98: 002 | B98: 194 | C98: Hector Wright | D98: 4 | E98: 90
A99: 002 | B99: 195 | C99: Al Ramos | D99: 2548 | E99: 2565652 | F99: 911 | G99: 2625338
A100: 002 | B100: 199 | C100: Nettie Stevens | D100: 44 | E100: 27310 | F100: 14 | G100: 5455
A101: 002 | B101: 210 | C101: Kenny Robertson | D101: 321 | E101: 174783 | F101: 14 | G101: 33292
A102: 002 | B102: 239 | C102: Clarence Padilla | D102: 225 | E102: 39327
A103: 002 | B103: 249 | C103: Cary Foster | D103: 580 | E103: 1953907 | F103: 756 | G103: 3089674
A104: 002 | B104: 255 | C104: Lois Moran | D104: 2 | E104: 36
A105: 002 | B105: 259 | C105: Beulah Gibbs | F105: 4 | G105: 107
A106: 002 | B106: 269 | C106: Jo Manning | D106: 45 | E106: 1358 | F106: 10 | G106: 33925
...

Sheet P1_5Qs
A1: 1.What is the employees’ number in 2016 comparing to 2015? | I1: 3. which job categories contributed most to the increase?
A2: Row Labels | B2: Employee number | J2: YEAR | K2: Values
A3: 2015 | B3: 851 | J3: 2015 | L3: 2016
A4: 2016 | B4: 804 | I4: Job_description | J4: Sum of gross wages | K4: Difference | L4: Sum of gross wages | M4: Difference
A5: Grand Total | B5: 1655 | J5: 315
I6: Customer Training | J6: 2014041 | L6: 257149 | M6: -0.87232186
A7: The increase in payroll expenses in 2016 was not driven by an increase in the number of employees. | I7: Employee Training | J7: 1204204 | L7: 2814657 | M7: 1.337359
A8: In fact, the number of employees slightly decreased from 851 in 2015 to 804 in 2016. | I8: Installation | J8: 162539 | L8: 164085 | M8: 0.0095115634
I9: Internal Auditing | J9: 0 | L9: 953068
I10: Internal Projects | J10: 0 | L10: 70281
I11: New Foreign Manufacturing Oversight | J11: 0 | L11: 1270293
A12: 2.Did total salary per employee increase? | I12: New Foreign Manufacturing Plant | J12: 0 | L12: 6238118
A13: Total gross wages increased significantly from 67.6 million in 2015 to 85.9 million in 2016, representing a 27.16% increase. | I13: Office | J13: 13178934 | L13: 18784220 | M13: 0.42532165
A14: However, this increase was not uniform across all employees. | I14: Proj Management | J14: 3339832 | L14: 4928450 | M14: 0.47565806
A15: Some employees experienced substantial salary increases, while others saw decreases or were not present in both years. | I15: Sales | J15: 39621371 | L15: 40154639 | M15: 0.0134591
A16: Additionally, new employees appeared in 2016 while some from 2015 were no longer present. | I16: Service | J16: 5376020 | L16: 8367948 | M16: 0.55653216
A17: This suggests that the increase in payroll was driven by changes in workforce composition and significant salary increases for certain individuals, | I17: Travel | J17: 2678797 | L17: 1926817 | M17: -0.28071556
A18: rather than a consistent rise in salary across all employees. | I18: Grand Total | J18: 67576053 | L18: 85929725 | M18: 0.27160024
B19: Column Labels | I19: As aboved data showed, the main contributors to the payroll increase were: Employee Training: +133.74%; Service: +55.65%; Project Management: +47.57%; Office: +42.53%.
B20: 2015 | D20: 2016 | I20: In addition, some job categories such as Internal Auditing, Internal Projects, and New Foreign Manufacturing roles appeared only in 2016, contributing additional costs.
A21: Row Labels | B21: Sum of Gross_Wages | C21: Gross_Wages difference | D21: Sum of Gross_Wages | E21: Gross_Wages difference | I21: On the other hand, some categories like Customer Training (-87.23%) and Travel (-28.07%) saw decreases, partially offsetting the increase.
D22: 1805269 | I22: Overall, the increase was mainly driven by core operational roles and newly introduced job categories.
A23: Afton Call | D23: 1740
A24: Al Ramos | B24: 2565652 | D24: 2776128 | E24: 0.082036067
A25: Alberta Gill | B25: 536328 | D25: 194385 | E25: -0.63756321
A26: Allan Wood | B26: 232644 | D26: 2327908 | E26: 9.0063101
A27: Allen Price | B27: 437 | D27: 3214 | E27: 6.3546911 | I27: 4.Was the increase driven by overtime or regular hours?
A28: Angel Watts | B28: 427 | D28: 1055 | E28: 1.470726 | J28: Values | K28: YEAR
A29: Antonio Torres | B29: 2011582 | D29: 3104730 | E29: 0.54342701 | J29: Sum of OT_Hrs | L29: Sum of Reg_Hrs
A30: Barry Mckenzie | B30: 446660 | D30: 813662 | E30: 0.82165853 | I30: Job_description | J30: 2015 | K30: 2016 | L30: 2015 | M30: 2016 | N30: OT hours difference | O30: Reg hour difference
A31: Beulah Gibbs | B31: 444461 | D31: 1022142 | E31: 1.2997338 | J31: 1 | L31: 0 | N31: =$K31-$J31 -> -1 | O31: =$M31-$L31 -> 0
A32: Brendan Curry | B32: 61298 | I32: Customer Training | J32: 0 | K32: 0 | L32: 1846 | M32: 443 | N32: =$K32-$J32 -> 0 | O32: =$M32-$L32 -> -1403
A33: Brittany Carlson | B33: 76703 | D33: 6345 | E33: -0.91727833 | I33: Employee Training | J33: 22 | K33: 9 | L33: 3821 | M33: 14063 | N33: =$K33-$J33 -> -13 | O33: =$M33-$L33 -> 10242
A34: Carlton Mcdonald | B34: 467 | I34: Installation | J34: 14 | K34: 0 | L34: 1416 | M34: 2192 | N34: =$K34-$J34 -> -14 | O34: =$M34-$L34 -> 776
A35: Cary Foster | B35: 2364766 | D35: 3749436 | E35: 0.58554208 | I35: Internal Auditing | J35: 0 | K35: 0 | L35: 0 | M35: 1589 | N35: =$K35-$J35 -> 0 | O35: =$M35-$L35 -> 1589
A36: Cassandra Poole | B36: 1321941 | D36: 2149618 | E36: 0.62610737 | I36: Internal Projects | J36: 0 | K36: 0 | L36: 0 | M36: 100 | N36: =$K36-$J36 -> 0 | O36: =$M36-$L36 -> 100
A37: Cesar Greene | B37: 24304 | D37: 168752 | E37: 5.9433838 | I37: New Foreign Manufacturing Oversight | J37: 0 | K37: 0 | L37: 0 | M37: 1300 | N37: =$K37-$J37 -> 0 | O37: =$M37-$L37 -> 1300
A38: Cindy Lunt | B38: 793164 | D38: 1699516 | E38: 1.1427044 | I38: New Foreign Manufacturing Plant | J38: 0 | K38: 0 | L38: 0 | M38: 24579 | N38: =$K38-$J38 -> 0 | O38: =$M38-$L38 -> 24579
A39: Claire Edwards | B39: 5625 | D39: 8757 | E39: 0.5568 | I39: Office | J39: 1277 | K39: 990 | L39: 88165 | M39: 282100 | N39: =$K39-$J39 -> -287 | O39: =$M39-$L39 -> 193935
A40: Clarence Padilla | B40: 1456896 | D40: 2215837 | E40: 0.52093011 | I40: Proj Management | J40: 107 | K40: 166 | L40: 4677 | M40: 12193 | N40: =$K40-$J40 -> 59 | O40: =$M40-$L40 -> 7516
A41: Clark Morgan | B41: 15666 | I41: Sales | J41: 159 | K41: 310 | L41: 26088 | M41: 52266 | N41: =$K41-$J41 -> 151 | O41: =$M41-$L41 -> 26178
A42: Conrad Walker | B42: 3981171 | D42: 6616697 | E42: 0.66199769 | I42: Service | J42: 288 | K42: 705 | L42: 10118 | M42: 63544 | N42: =$K42-$J42 -> 417 | O42: =$M42-$L42 -> 53426
A43: Cornelius Gibson | B43: 249756 | D43: 628687 | E43: 1.5172048 | I43: Travel | J43: 1 | K43: 0 | L43: 1063 | M43: 6054 | N43: =$K43-$J43 -> -1 | O43: =$M43-$L43 -> 4991
A44: Dale Hamilton | B44: 100100 | D44: 96250 | E44: -0.038461538 | I44: Grand Total | J44: 1869 | K44: 2180 | L44: 137194 | M44: 460423 | N44: =$K44-$J44 -> 311 | O44: =$M44-$L44 -> 323229
A45: Darryl Burgess | B45: 4288 | D45: 555158 | E45: 128.46782 | I45: The increase in payroll was not driven by overtime hours, but was primarily due to a substantial rise in regular working hours
A46: Deborah Bennett | B46: 42322 | D46: 451828 | E46: 9.6759605 | I46: This indicated increased workload or operational expansion, rather than reliance on overtime.
A47: Delia Lopez | B47: 50 | D47: 19700 | E47: 393
A48: Don Young | B48: 80168
A49: Earnest Drake | B49: 527942 | D49: 1166662 | E49: 1.2098299
A50: Ed Craig | B50: 2544989 | D50: 2723833 | E50: 0.070272995
A51: Elisa Warren | B51: 314329 | D51: 334469 | E51: 0.064072994 | I51: 5. Were there any changes in employee benefits, payroll taxes, or related costs in 2016?
A52: Ellen Estrada | B52: 150
A53: Emma Goodwin | D53: 134867
A54: Ernesto Todd | B54: 10986664 | D54: 10564100 | E54: -0.038461538 | I54: Row Labels | J54: Sum of Fica_Medc | K54: Sum of Futa | L54: Sum of Suta | M54: Sum of Work_Comp
A55: Fannie Parks | B55: 11234 | D55: 6188 | E55: -0.44917216 | I55: 2015 | J55: 9164766 | K55: 165147 | L55: 2045092 | M55: 1012011
A56: Floyd Hunter | B56: 115385 | D56: 408311 | E56: 2.5386835 | I56: 2016 | J56: 8422378 | K56: 151485 | L56: 2120859 | M56: 900073
A57: Frank Diaz | B57: 1944 | D57: 309139 | E57: 158.02212 | I57: Grand Total | J57: 17587144 | K57: 316632 | L57: 4165951 | M57: 1912084
A58: Frankie Mcdaniel | B58: 2062718 | D58: 421171 | E58: -0.79581746 | I58: There were no major policy changes or cost increases in benefits or payroll taxes.
A59: Geneva Moody | B59: 176954 | D59: 548210 | E59: 2.0980368
A60: Grant Daniel | B60: 3126977 | D60: 4926288 | E60: 0.57541549
A61: Gwendolyn Alvarado | B61: 7632 | D61: 2439 | E61: -0.68042453
A62: Hector Wright | B62: 4095 | D62: 16200 | E62: 2.956044
A63: Helen Paul | B63: 6040432 | D63: 6481695 | E63: 0.073051563
A64: Jesus Peterson | D64: 347701
A65: Jo Manning | B65: 7560 | D65: 561429 | E65: 73.263095
A66: Jodi Powers | B66: 243317 | D66: 1952586 | E66: 7.0248647
A67: Joe Perry | B67: 391540 | D67: 245478 | E67: -0.3730449
A68: Joyce Ferguson | B68: 1836
A69: Katie Hodges | B69: 374 | D69: 29686 | E69: 78.374332
A70: Kelly Murray | B70: 264
A71: Kenny Robertson | B71: 734208 | D71: 880508 | E71: 0.19926233
A72: Kirk Byrd | B72: 3626 | D72: 18299 | E72: 4.0466078
A73: Leonard Wong | B73: 2723086 | D73: 2894625 | E73: 0.062994338
A74: Leslie Dean | B74: 0
A75: Levi Christensen | B75: 926548 | D75: 1345295 | E75: 0.45194313
A76: Lillian Jefferson | B76: 1230
A77: Lois Moran | B77: 36 | D77: 720 | E77: 19
A78: Lyle Grant | D78: 5116
A79: Lynette Alvarez | D79: 1074
A80: Lynn Perkins | B80: 12325
A81: Lynne Soto | B81: 116 | D81: 2112 | E81: 17.206897
A82: Mamie Day | B82: 3089699 | D82: 2378686 | E82: -0.23012371
A83: Marc Wallace | B83: 290408 | D83: 1550374 | E83: 4.3386064
A84: Marcia Neal | B84: 3393 | D84: 33244 | E84: 8.797819
A85: Marguerite Thornton | B85: 0
A86: Marianne Baldwin | B86: 609 | D86: 118667 | E86: 193.8555
A87: Marie Hudson | B87: 56550 | D87: 7395 | E87: -0.86923077
A88: Marion Scott | B88: 108526 | D88: 361029 | E88: 2.326659
A89: Mark Sharp | D89: 644
A90: Marty Barnes | B90: 12840 | D90: 15730 | E90: 0.22507788
A91: Mary Waters | B91: 165817 | D91: 1007983 | E91: 5.0788882
A92: Maryann Cohen | B92: 9880
A93: Maxine Tyler | B93: 344 | D93: 2893 | E93: 7.4098837
A94: Melanie Green | B94: 2350968 | D94: 769250 | E94: -0.67279436
A95: Melvin Strickland | B95: 104912 | D95: 185241 | E95: 0.76567981
A96: Michele Lee | B96: 423 | D96: 7578 | E96: 16.914894
A97: Mike Briggs | B97: 2250635 | D97: 2346863 | E97: 0.042755933
A98: Mona Howard | B98: 786 | D98: 32754 | E98: 40.671756
A99: Morris Glover | B99: 930 | D99: 4935 | E99: 4.3064516
A100: Myra Vega | B100: 7961 | D100: 3909 | E100: -0.50898128
...

Sheet 2015&2016 append
A1: Emp_No | B1: Job | C1: Emp_Name | D1: Reg_Hrs | E1: OT_Hrs | F1: Gross_Wages | G1: Fica_Medc | H1: Futa | I1: Suta | J1: Work_Comp | K1: YEAR | L1: Job_code | M1: Job_description | N1: Department | O1: Location | P1: Total_Hours | Q1: transaction count
A2: 195 | B2: 14005 | C2: Al Ramos | D2: 0 | E2: 0 | F2: 0 | G2: 214 | H2: 16 | I2: 68 | J2: 8 | K2: 2015 | L2: =IF(OR(MID(B2,3,1)="H",MID(B2,3,1)="S"),MID(B2,4,3),MID(B2,3,3)) -> 005 | M2: =_xlfn.XLOOKUP(_2015_2016_append_[[#This Row],[Job_code]],Analytics_mindset_case_studies_IntegrateCo_jobcodes[Code_text],Analytics_mindset_case_studies_IntegrateCo_jobcodes[Job_Description],"",0) -> Installation | N2: =IF(OR(MID(B2,3,1)="H",MID(B2,3,1)="S"),MID(B2,3,1),"") | O2: =IFERROR(VLOOKUP(_2015_2016_append_[[#This Row],[Emp_Name]],Analytics_mindset_case_studies_IntegrateCo_locations[#All],2,FALSE),"") -> 2 | P2: =_2015_2016_append_[[#This Row],[Reg_Hrs]]+_2015_2016_append_[[#This Row],[OT_Hrs]] -> 0 | Q2: 1
A3: 195 | B3: 14H002 | C3: Al Ramos | D3: 25 | E3: 0 | F3: 70558 | G3: 5047 | H3: 396 | I3: 1583 | J3: 183 | K3: 2015 | L3: =IF(OR(MID(B3,3,1)="H",MID(B3,3,1)="S"),MID(B3,4,3),MID(B3,3,3)) -> 002 | M3: =_xlfn.XLOOKUP(_2015_2016_append_[[#This Row],[Job_code]],Analytics_mindset_case_studies_IntegrateCo_jobcodes[Code_text],Analytics_mindset_case_studies_IntegrateCo_jobcodes[Job_Description],"",0) -> Sales | N3: =IF(OR(MID(B3,3,1)="H",MID(B3,3,1)="S"),MID(B3,3,1),"") -> H | O3: =IFERROR(VLOOKUP(_2015_2016_append_[[#This Row],[Emp_Name]],Analytics_mindset_case_studies_IntegrateCo_locations[#All],2,FALSE),"") -> 2 | P3: =_2015_2016_append_[[#This Row],[Reg_Hrs]]+_2015_2016_append_[[#This Row],[OT_Hrs]] -> 25 | Q3: 1
A4: 195 | B4: 14H010 | C4: Al Ramos | D4: 0 | E4: 0 | F4: 0 | G4: 3229 | H4: 253 | I4: 1013 | J4: 117 | K4: 2015 | L4: =IF(OR(MID(B4,3,1)="H",MID(B4,3,1)="S"),MID(B4,4,3),MID(B4,3,3)) -> 010 | M4: =_xlfn.XLOOKUP(_2015_2016_append_[[#This Row],[Job_code]],Analytics_mindset_case_studies_IntegrateCo_jobcodes[Code_text],Analytics_mindset_case_studies_IntegrateCo_jobcodes[Job_Description],"",0) -> New Foreign Manufacturing Oversight | N4: =IF(OR(MID(B4,3,1)="H",MID(B4,3,1)="S"),MID(B4,3,1),"") -> H | O4: =IFERROR(VLOOKUP(_2015_2016_append_[[#This Row],[Emp_Name]],Analytics_mindset_case_studies_IntegrateCo_locations[#All],2,FALSE),"") -> 2 | P4: =_2015_2016_append_[[#This Row],[Reg_Hrs]]+_2015_2016_append_[[#This Row],[OT_Hrs]] -> 0 | Q4: 1
A5: 106 | B5: 14002 | C5: Allan Wood | D5: 19 | E5: 0 | F5: 380 | G5: 2907 | H5: 228 | I5: 912 | J5: 608 | K5: 2015 | L5: =IF(OR(MID(B5,3,1)="H",MID(B5,3,1)="S"),MID(B5,4,3),MID(B5,3,3)) -> 002 | M5: =_xlfn.XLOOKUP(_2015_2016_append_[[#This Row],[Job_code]],Analytics_mindset_case_studies_IntegrateCo_jobcodes[Code_text],Analytics_mindset_case_studies_IntegrateCo_jobcodes[Job_Description],"",0) -> Sales | N5: =IF(OR(MID(B5,3,1)="H",MID(B5,3,1)="S"),MID(B5,3,1),"") | O5: =IFERROR(VLOOKUP(_2015_2016_append_[[#This Row],[Emp_Name]],Analytics_mindset_case_studies_IntegrateCo_locations[#All],2,FALSE),"") -> 1 | P5: =_2015_2016_append_[[#This Row],[Reg_Hrs]]+_2015_2016_append_[[#This Row],[OT_Hrs]] -> 19 | Q5: 1
A6: 106 | B6: 14005 | C6: Allan Wood | D6: 0 | E6: 0 | F6: 0 | G6: 230 | H6: 18 | I6: 72 | J6: 48 | K6: 2015 | L6: =IF(OR(MID(B6,3,1)="H",MID(B6,3,1)="S"),MID(B6,4,3),MID(B6,3,3)) -> 005 | M6: =_xlfn.XLOOKUP(_2015_2016_append_[[#This Row],[Job_code]],Analytics_mindset_case_studies_IntegrateCo_jobcodes[Code_text],Analytics_mindset_case_studies_IntegrateCo_jobcodes[Job_Description],"",0) -> Installation | N6: =IF(OR(MID(B6,3,1)="H",MID(B6,3,1)="S"),MID(B6,3,1),"") | O6: =IFERROR(VLOOKUP(_2015_2016_append_[[#This Row],[Emp_Name]],Analytics_mindset_case_studies_IntegrateCo_locations[#All],2,FALSE),"") -> 1 | P6: =_2015_2016_append_[[#This Row],[Reg_Hrs]]+_2015_2016_append_[[#This Row],[OT_Hrs]] -> 0 | Q6: 1
A7: 106 | B7: 14010 | C7: Allan Wood | D7: 0 | E7: 0 | F7: 0 | G7: 2448 | H7: 192 | I7: 768 | J7: 512 | K7: 2015 | L7: =IF(OR(MID(B7,3,1)="H",MID(B7,3,1)="S"),MID(B7,4,3),MID(B7,3,3)) -> 010 | M7: =_xlfn.XLOOKUP(_2015_2016_append_[[#This Row],[Job_code]],Analytics_mindset_case_studies_IntegrateCo_jobcodes[Code_text],Analytics_mindset_case_studies_IntegrateCo_jobcodes[Job_Description],"",0) -> New Foreign Manufacturing Oversight | N7: =IF(OR(MID(B7,3,1)="H",MID(B7,3,1)="S"),MID(B7,3,1),"") | O7: =IFERROR(VLOOKUP(_2015_2016_append_[[#This Row],[Emp_Name]],Analytics_mindset_case_studies_IntegrateCo_locations[#All],2,FALSE),"") -> 1 | P7: =_2015_2016_append_[[#This Row],[Reg_Hrs]]+_2015_2016_append_[[#This Row],[OT_Hrs]] -> 0 | Q7: 1
A8: 106 | B8: 14012 | C8: Allan Wood | D8: 0 | E8: 0 | F8: 0 | G8: 3672 | H8: 288 | I8: 1152 | J8: 768 | K8: 2015 | L8: =IF(OR(MID(B8,3,1)="H",MID(B8,3,1)="S"),MID(B8,4,3),MID(B8,3,3)) -> 012 | M8: =_xlfn.XLOOKUP(_2015_2016_append_[[#This Row],[Job_code]],Analytics_mindset_case_studies_IntegrateCo_jobcodes[Code_text],Analytics_mindset_case_studies_IntegrateCo_jobcodes[Job_Description],"",0) -> Internal Auditing | N8: =IF(OR(MID(B8,3,1)="H",MID(B8,3,1)="S"),MID(B8,3,1),"") | O8: =IFERROR(VLOOKUP(_2015_2016_append_[[#This Row],[Emp_Name]],Analytics_mindset_case_studies_IntegrateCo_locations[#All],2,FALSE),"") -> 1 | P8: =_2015_2016_append_[[#This Row],[Reg_Hrs]]+_2015_2016_append_[[#This Row],[OT_Hrs]] -> 0 | Q8: 1
A9: 304 | B9: 14H010 | C9: Allen Price | D9: 0 | E9: 0 | F9: 0 | G9: 2658 | H9: 208 | I9: 834 | J9: 589 | K9: 2015 | L9: =IF(OR(MID(B9,3,1)="H",MID(B9,3,1)="S"),MID(B9,4,3),MID(B9,3,3)) -> 010 | M9: =_xlfn.XLOOKUP(_2015_2016_append_[[#This Row],[Job_code]],Analytics_mindset_case_studies_IntegrateCo_jobcodes[Code_text],Analytics_mindset_case_studies_IntegrateCo_jobcodes[Job_Description],"",0) -> New Foreign Manufacturing Oversight | N9: =IF(OR(MID(B9,3,1)="H",MID(B9,3,1)="S"),MID(B9,3,1),"") -> H | O9: =IFERROR(VLOOKUP(_2015_2016_append_[[#This Row],[Emp_Name]],Analytics_mindset_case_studies_IntegrateCo_locations[#All],2,FALSE),"") -> 1 | P9: =_2015_2016_append_[[#This Row],[Reg_Hrs]]+_2015_2016_append_[[#This Row],[OT_Hrs]] -> 0 | Q9: 1
A10: 304 | B10: 14H012 | C10: Allen Price | D10: 0 | E10: 0 | F10: 0 | G10: 3988 | H10: 313 | I10: 1251 | J10: 883 | K10: 2015 | L10: =IF(OR(MID(B10,3,1)="H",MID(B10,3,1)="S"),MID(B10,4,3),MID(B10,3,3)) -> 012 | M10: =_xlfn.XLOOKUP(_2015_2016_append_[[#This Row],[Job_code]],Analytics_mindset_case_studies_IntegrateCo_jobcodes[Code_text],Analytics_mindset_case_studies_IntegrateCo_jobcodes[Job_Description],"",0) -> Internal Auditing | N10: =IF(OR(MID(B10,3,1)="H",MID(B10,3,1)="S"),MID(B10,3,1),"") -> H | O10: =IFERROR(VLOOKUP(_2015_2016_append_[[#This Row],[Emp_Name]],Analytics_mindset_case_studies_IntegrateCo_locations[#All],2,FALSE),"") -> 1 | P10: =_2015_2016_append_[[#This Row],[Reg_Hrs]]+_2015_2016_append_[[#This Row],[OT_Hrs]] -> 0 | Q10: 1
A11: 274 | B11: 14005 | C11: Angel Watts | D11: 0 | E11: 0 | F11: 0 | G11: 115 | H11: 8 | I11: 35 | J11: 15 | K11: 2015 | L11: =IF(OR(MID(B11,3,1)="H",MID(B11,3,1)="S"),MID(B11,4,3),MID(B11,3,3)) -> 005 | M11: =_xlfn.XLOOKUP(_2015_2016_append_[[#This Row],[Job_code]],Analytics_mindset_case_studies_IntegrateCo_jobcodes[Code_text],Analytics_mindset_case_studies_IntegrateCo_jobcodes[Job_Description],"",0) -> Installation | N11: =IF(OR(MID(B11,3,1)="H",MID(B11,3,1)="S"),MID(B11,3,1),"") | O11: =IFERROR(VLOOKUP(_2015_2016_append_[[#This Row],[Emp_Name]],Analytics_mindset_case_studies_IntegrateCo_locations[#All],2,FALSE),"") -> 2 | P11: =_2015_2016_append_[[#This Row],[Reg_Hrs]]+_2015_2016_append_[[#This Row],[OT_Hrs]] -> 0 | Q11: 1
A12: 274 | B12: 14H010 | C12: Angel Watts | D12: 0 | E12: 0 | F12: 0 | G12: 306 | H12: 24 | I12: 96 | J12: 64 | K12: 2015 | L12: =IF(OR(MID(B12,3,1)="H",MID(B12,3,1)="S"),MID(B12,4,3),MID(B12,3,3)) -> 010 | M12: =_xlfn.XLOOKUP(_2015_2016_append_[[#This Row],[Job_code]],Analytics_mindset_case_studies_IntegrateCo_jobcodes[Code_text],Analytics_mindset_case_studies_IntegrateCo_jobcodes[Job_Description],"",0) -> New Foreign Manufacturing Oversight | N12: =IF(OR(MID(B12,3,1)="H",MID(B12,3,1)="S"),MID(B12,3,1),"") -> H | O12: =IFERROR(VLOOKUP(_2015_2016_append_[[#This Row],[Emp_Name]],Analytics_mindset_case_studies_IntegrateCo_locations[#All],2,FALSE),"") -> 2 | P12: =_2015_2016_append_[[#This Row],[Reg_Hrs]]+_2015_2016_append_[[#This Row],[OT_Hrs]] -> 0 | Q12: 1
A13: 274 | B13: 14H012 | C13: Angel Watts | D13: 0 | E13: 0 | F13: 0 | G13: 306 | H13: 133 | I13: 529 | J13: 64 | K13: 2015 | L13: =IF(OR(MID(B13,3,1)="H",MID(B13,3,1)="S"),MID(B13,4,3),MID(B13,3,3)) -> 012 | M13: =_xlfn.XLOOKUP(_2015_2016_append_[[#This Row],[Job_code]],Analytics_mindset_case_studies_IntegrateCo_jobcodes[Code_text],Analytics_mindset_case_studies_IntegrateCo_jobcodes[Job_Description],"",0) -> Internal Auditing | N13: =IF(OR(MID(B13,3,1)="H",MID(B13,3,1)="S"),MID(B13,3,1),"") -> H | O13: =IFERROR(VLOOKUP(_2015_2016_append_[[#This Row],[Emp_Name]],Analytics_mindset_case_studies_IntegrateCo_locations[#All],2,FALSE),"") -> 2 | P13: =_2015_2016_append_[[#This Row],[Reg_Hrs]]+_2015_2016_append_[[#This Row],[OT_Hrs]] -> 0 | Q13: 1
... A863: 179 | B863: 15005 | C863: Cassandra Poole | D863: 1 | E863: 0 | F863: 9 | G863: 66 | H863: 6 | I863: 21 | J863: 14 | K863: 2016 | L863: =IF(OR(MID(B863,3,1)="H",MID(B863,3,1)="S"),MID(B863,4,3),MID(B863,3,3)) -> 005 | M863: =_xlfn.XLOOKUP(_2015_2016_append_[[#This Row],[Job_code]],Analytics_mindset_case_studies_IntegrateCo_jobcodes[Code_text],Analytics_mindset_case_studies_IntegrateCo_jobcodes[Job_Description],"",0) -> Installation | N863: =IF(OR(MID(B863,3,1)="H",MID(B863,3,1)="S"),MID(B863,3,1),"") | O863: =IFERROR(VLOOKUP(_2015_2016_append_[[#This Row],[Emp_Name]],Analytics_mindset_case_studies_IntegrateCo_locations[#All],2,FALSE),"") -> 2 | P863: =_2015_2016_append_[[#This Row],[Reg_Hrs]]+_2015_2016_append_[[#This Row],[OT_Hrs]] -> 1 | Q863: 1
B864: 15005 | D864: 1 | E864: 0 | F864: 12 | G864: 92 | H864: 8 | I864: 27 | J864: 19 | K864: 2016 | L864: =IF(OR(MID(B864,3,1)="H",MID(B864,3,1)="S"),MID(B864,4,3),MID(B864,3,3)) -> 005 | M864: =_xlfn.XLOOKUP(_2015_2016_append_[[#This Row],[Job_code]],Analytics_mindset_case_studies_IntegrateCo_jobcodes[Code_text],Analytics_mindset_case_studies_IntegrateCo_jobcodes[Job_Description],"",0) -> Installation | N864: =IF(OR(MID(B864,3,1)="H",MID(B864,3,1)="S"),MID(B864,3,1),"") | O864: =IFERROR(VLOOKUP(_2015_2016_append_[[#This Row],[Emp_Name]],Analytics_mindset_case_studies_IntegrateCo_locations[#All],2,FALSE),"") | P864: =_2015_2016_append_[[#This Row],[Reg_Hrs]]+_2015_2016_append_[[#This Row],[OT_Hrs]] -> 1 | Q864: 1
A865: 192 | B865: 15005 | C865: Mike Briggs | D865: 1 | E865: 0 | F865: 9 | G865: 61 | H865: 5 | I865: 27 | J865: 8 | K865: 2016 | L865: =IF(OR(MID(B865,3,1)="H",MID(B865,3,1)="S"),MID(B865,4,3),MID(B865,3,3)) -> 005 | M865: =_xlfn.XLOOKUP(_2015_2016_append_[[#This Row],[Job_code]],Analytics_mindset_case_studies_IntegrateCo_jobcodes[Code_text],Analytics_mindset_case_studies_IntegrateCo_jobcodes[Job_Description],"",0) -> Installation | N865: =IF(OR(MID(B865,3,1)="H",MID(B865,3,1)="S"),MID(B865,3,1),"") | O865: =IFERROR(VLOOKUP(_2015_2016_append_[[#This Row],[Emp_Name]],Analytics_mindset_case_studies_IntegrateCo_locations[#All],2,FALSE),"") -> 2 | P865: =_2015_2016_append_[[#This Row],[Reg_Hrs]]+_2015_2016_append_[[#This Row],[OT_Hrs]] -> 1 | Q865: 1
A866: 195 | B866: 15005 | C866: Al Ramos | D866: 1 | E866: 0 | F866: 15 | G866: 107 | H866: 9 | I866: 34 | J866: 2 | K866: 2016 | L866: =IF(OR(MID(B866,3,1)="H",MID(B866,3,1)="S"),MID(B866,4,3),MID(B866,3,3)) -> 005 | M866: =_xlfn.XLOOKUP(_2015_2016_append_[[#This Row],[Job_code]],Analytics_mindset_case_studies_IntegrateCo_jobcodes[Code_text],Analytics_mindset_case_studies_IntegrateCo_jobcodes[Job_Description],"",0) -> Installation | N866: =IF(OR(MID(B866,3,1)="H",MID(B866,3,1)="S"),MID(B866,3,1),"") | O866: =IFERROR(VLOOKUP(_2015_2016_append_[[#This Row],[Emp_Name]],Analytics_mindset_case_studies_IntegrateCo_locations[#All],2,FALSE),"") -> 2 | P866: =_2015_2016_append_[[#This Row],[Reg_Hrs]]+_2015_2016_append_[[#This Row],[OT_Hrs]] -> 1 | Q866: 1
A867: 199 | B867: 15005 | C867: Nettie Stevens | D867: 1 | E867: 0 | F867: 12 | G867: 81 | H867: 5 | I867: 27 | J867: 22 | K867: 2016 | L867: =IF(OR(MID(B867,3,1)="H",MID(B867,3,1)="S"),MID(B867,4,3),MID(B867,3,3)) -> 005 | M867: =_xlfn.XLOOKUP(_2015_2016_append_[[#This Row],[Job_code]],Analytics_mindset_case_studies_IntegrateCo_jobcodes[Code_text],Analytics_mindset_case_studies_IntegrateCo_jobcodes[Job_Description],"",0) -> Installation | N867: =IF(OR(MID(B867,3,1)="H",MID(B867,3,1)="S"),MID(B867,3,1),"") | O867: =IFERROR(VLOOKUP(_2015_2016_append_[[#This Row],[Emp_Name]],Analytics_mindset_case_studies_IntegrateCo_locations[#All],2,FALSE),"") -> 2 | P867: =_2015_2016_append_[[#This Row],[Reg_Hrs]]+_2015_2016_append_[[#This Row],[OT_Hrs]] -> 1 | Q867: 1
A868: 274 | B868: 15005 | C868: Angel Watts | D868: 1 | E868: 0 | F868: 15 | G868: 114 | H868: 9 | I868: 36 | J868: 24 | K868: 2016 | L868: =IF(OR(MID(B868,3,1)="H",MID(B868,3,1)="S"),MID(B868,4,3),MID(B868,3,3)) -> 005 | M868: =_xlfn.XLOOKUP(_2015_2016_append_[[#This Row],[Job_code]],Analytics_mindset_case_studies_IntegrateCo_jobcodes[Code_text],Analytics_mindset_case_studies_IntegrateCo_jobcodes[Job_Description],"",0) -> Installation | N868: =IF(OR(MID(B868,3,1)="H",MID(B868,3,1)="S"),MID(B868,3,1),"") | O868: =IFERROR(VLOOKUP(_2015_2016_append_[[#This Row],[Emp_Name]],Analytics_mindset_case_studies_IntegrateCo_locations[#All],2,FALSE),"") -> 2 | P868: =_2015_2016_append_[[#This Row],[Reg_Hrs]]+_2015_2016_append_[[#This Row],[OT_Hrs]] -> 1 | Q868: 1
A869: 27 | B869: 15005 | C869: Cindy Lunt | D869: 1 | E869: 0 | F869: 6 | G869: 42 | H869: 5 | I869: 12 | J869: 1 | K869: 2016 | L869: =IF(OR(MID(B869,3,1)="H",MID(B869,3,1)="S"),MID(B869,4,3),MID(B869,3,3)) -> 005 | M869: =_xlfn.XLOOKUP(_2015_2016_append_[[#This Row],[Job_code]],Analytics_mindset_case_studies_IntegrateCo_jobcodes[Code_text],Analytics_mindset_case_studies_IntegrateCo_jobcodes[Job_Description],"",0) -> Installation | N869: =IF(OR(MID(B869,3,1)="H",MID(B869,3,1)="S"),MID(B869,3,1),"") | O869: =IFERROR(VLOOKUP(_2015_2016_append_[[#This Row],[Emp_Name]],Analytics_mindset_case_studies_IntegrateCo_locations[#All],2,FALSE),"") -> 1 | P869: =_2015_2016_append_[[#This Row],[Reg_Hrs]]+_2015_2016_append_[[#This Row],[OT_Hrs]] -> 1 | Q869: 1
A870: 201 | B870: 15005 | C870: Michele Lee | D870: 1 | E870: 0 | F870: 9 | G870: 69 | H870: 5 | I870: 22 | J870: 15 | K870: 2016 | L870: =IF(OR(MID(B870,3,1)="H",MID(B870,3,1)="S"),MID(B870,4,3),MID(B870,3,3)) -> 005 | M870: =_xlfn.XLOOKUP(_2015_2016_append_[[#This Row],[Job_code]],Analytics_mindset_case_studies_IntegrateCo_jobcodes[Code_text],Analytics_mindset_case_studies_IntegrateCo_jobcodes[Job_Description],"",0) -> Installation | N870: =IF(OR(MID(B870,3,1)="H",MID(B870,3,1)="S"),MID(B870,3,1),"") | O870: =IFERROR(VLOOKUP(_2015_2016_append_[[#This Row],[Emp_Name]],Analytics_mindset_case_studies_IntegrateCo_locations[#All],2,FALSE),"") -> 1 | P870: =_2015_2016_append_[[#This Row],[Reg_Hrs]]+_2015_2016_append_[[#This Row],[OT_Hrs]] -> 1 | Q870: 1
A871: 203 | B871: 15005 | C871: Helen Paul | D871: 1 | E871: 0 | F871: 21 | G871: 151 | H871: 14 | I871: 46 | J871: 6 | K871: 2016 | L871: =IF(OR(MID(B871,3,1)="H",MID(B871,3,1)="S"),MID(B871,4,3),MID(B871,3,3)) -> 005 | M871: =_xlfn.XLOOKUP(_2015_2016_append_[[#This Row],[Job_code]],Analytics_mindset_case_studies_IntegrateCo_jobcodes[Code_text],Analytics_mindset_case_studies_IntegrateCo_jobcodes[Job_Description],"",0) -> Installation | N871: =IF(OR(MID(B871,3,1)="H",MID(B871,3,1)="S"),MID(B871,3,1),"") | O871: =IFERROR(VLOOKUP(_2015_2016_append_[[#This Row],[Emp_Name]],Analytics_mindset_case_studies_IntegrateCo_locations[#All],2,FALSE),"") -> 1 | P871: =_2015_2016_append_[[#This Row],[Reg_Hrs]]+_2015_2016_append_[[#This Row],[OT_Hrs]] -> 1 | Q871: 1
A872: 259 | B872: 15005 | C872: Beulah Gibbs | D872: 1 | E872: 0 | F872: 9 | G872: 68 | H872: 6 | I872: 21 | J872: 14 | K872: 2016 | L872: =IF(OR(MID(B872,3,1)="H",MID(B872,3,1)="S"),MID(B872,4,3),MID(B872,3,3)) -> 005 | M872: =_xlfn.XLOOKUP(_2015_2016_append_[[#This Row],[Job_code]],Analytics_mindset_case_studies_IntegrateCo_jobcodes[Code_text],Analytics_mindset_case_studies_IntegrateCo_jobcodes[Job_Description],"",0) -> Installation | N872: =IF(OR(MID(B872,3,1)="H",MID(B872,3,1)="S"),MID(B872,3,1),"") | O872: =IFERROR(VLOOKUP(_2015_2016_append_[[#This Row],[Emp_Name]],Analytics_mindset_case_studies_IntegrateCo_locations[#All],2,FALSE),"") -> 2 | P872: =_2015_2016_append_[[#This Row],[Reg_Hrs]]+_2015_2016_append_[[#This Row],[OT_Hrs]] -> 1 | Q872: 1
A873: 320 | B873: 15005 | C873: Terry Moreno | D873: 1 | E873: 0 | F873: 3 | G873: 23 | H873: 1 | I873: 6 | J873: 5 | K873: 2016 | L873: =IF(OR(MID(B873,3,1)="H",MID(B873,3,1)="S"),MID(B873,4,3),MID(B873,3,3)) -> 005 | M873: =_xlfn.XLOOKUP(_2015_2016_append_[[#This Row],[Job_code]],Analytics_mindset_case_studies_IntegrateCo_jobcodes[Code_text],Analytics_mindset_case_studies_IntegrateCo_jobcodes[Job_Description],"",0) -> Installation | N873: =IF(OR(MID(B873,3,1)="H",MID(B873,3,1)="S"),MID(B873,3,1),"") | O873: =IFERROR(VLOOKUP(_2015_2016_append_[[#This Row],[Emp_Name]],Analytics_mindset_case_studies_IntegrateCo_locations[#All],2,FALSE),"") -> 2 | P873: =_2015_2016_append_[[#This Row],[Reg_Hrs]]+_2015_2016_append_[[#This Row],[OT_Hrs]] -> 1 | Q873: 1
A874: 396 | B874: 15005 | C874: Darryl Burgess | D874: 1 | E874: 0 | F874: 9 | G874: 67 | H874: 6 | I874: 26 | J874: 38 | K874: 2016 | L874: =IF(OR(MID(B874,3,1)="H",MID(B874,3,1)="S"),MID(B874,4,3),MID(B874,3,3)) -> 005 | M874: =_xlfn.XLOOKUP(_2015_2016_append_[[#This Row],[Job_code]],Analytics_mindset_case_studies_IntegrateCo_jobcodes[Code_text],Analytics_mindset_case_studies_IntegrateCo_jobcodes[Job_Description],"",0) -> Installation | N874: =IF(OR(MID(B874,3,1)="H",MID(B874,3,1)="S"),MID(B874,3,1),"") | O874: =IFERROR(VLOOKUP(_2015_2016_append_[[#This Row],[Emp_Name]],Analytics_mindset_case_studies_IntegrateCo_locations[#All],2,FALSE),"") -> 1 | P874: =_2015_2016_append_[[#This Row],[Reg_Hrs]]+_2015_2016_append_[[#This Row],[OT_Hrs]] -> 1 | Q874: 1
A875: 210 | B875: 15005 | C875: Kenny Robertson | D875: 1 | E875: 0 | F875: 6 | G875: 4 | H875: 2 | I875: 25 | J875: 14 | K875: 2016 | L875: =IF(OR(MID(B875,3,1)="H",MID(B875,3,1)="S"),MID(B875,4,3),MID(B875,3,3)) -> 005 | M875: =_xlfn.XLOOKUP(_2015_2016_append_[[#This Row],[Job_code]],Analytics_mindset_case_studies_IntegrateCo_jobcodes[Code_text],Analytics_mindset_case_studies_IntegrateCo_jobcodes[Job_Description],"",0) -> Installation | N875: =IF(OR(MID(B875,3,1)="H",MID(B875,3,1)="S"),MID(B875,3,1),"") | O875: =IFERROR(VLOOKUP(_2015_2016_append_[[#This Row],[Emp_Name]],Analytics_mindset_case_studies_IntegrateCo_locations[#All],2,FALSE),"") -> 1 | P875: =_2015_2016_append_[[#This Row],[Reg_Hrs]]+_2015_2016_append_[[#This Row],[OT_Hrs]] -> 1 | Q875: 1
A876: 411 | B876: 15005 | C876: Claire Edwards | D876: 1 | E876: 0 | F876: 9 | G876: 69 | H876: 5 | I876: 22 | J876: 14 | K876: 2016 | L876: =IF(OR(MID(B876,3,1)="H",MID(B876,3,1)="S"),MID(B876,4,3),MID(B876,3,3)) -> 005 | M876: =_xlfn.XLOOKUP(_2015_2016_append_[[#This Row],[Job_code]],Analytics_mindset_case_studies_IntegrateCo_jobcodes[Code_text],Analytics_mindset_case_studies_IntegrateCo_jobcodes[Job_Description],"",0) -> Installation | N876: =IF(OR(MID(B876,3,1)="H",MID(B876,3,1)="S"),MID(B876,3,1),"") | O876: =IFERROR(VLOOKUP(_2015_2016_append_[[#This Row],[Emp_Name]],Analytics_mindset_case_studies_IntegrateCo_locations[#All],2,FALSE),"") -> 1 | P876: =_2015_2016_append_[[#This Row],[Reg_Hrs]]+_2015_2016_append_[[#This Row],[OT_Hrs]] -> 1 | Q876: 1
... A1036: 375 | B1036: 15S004 | C1036: Fannie Parks | D1036: 45 | E1036: 0 | F1036: 99 | G1036: 758 | H1036: 59 | I1036: 238 | J1036: 164 | K1036: 2016 | L1036: =IF(OR(MID(B1036,3,1)="H",MID(B1036,3,1)="S"),MID(B1036,4,3),MID(B1036,3,3)) -> 004 | M1036: =_xlfn.XLOOKUP(_2015_2016_append_[[#This Row],[Job_code]],Analytics_mindset_case_studies_IntegrateCo_jobcodes[Code_text],Analytics_mindset_case_studies_IntegrateCo_jobcodes[Job_Description],"",0) -> Proj Management | N1036: =IF(OR(MID(B1036,3,1)="H",MID(B1036,3,1)="S"),MID(B1036,3,1),"") -> S | O1036: =IFERROR(VLOOKUP(_2015_2016_append_[[#This Row],[Emp_Name]],Analytics_mindset_case_studies_IntegrateCo_locations[#All],2,FALSE),"") -> 2 | P1036: =_2015_2016_append_[[#This Row],[Reg_Hrs]]+_2015_2016_append_[[#This Row],[OT_Hrs]] -> 45 | Q1036: 1
B1037: 15S005 | D1037: 3 | E1037: 0 | F1037: 69 | G1037: 528 | H1037: 41 | I1037: 166 | J1037: 114 | K1037: 2016 | L1037: =IF(OR(MID(B1037,3,1)="H",MID(B1037,3,1)="S"),MID(B1037,4,3),MID(B1037,3,3)) -> 005 | M1037: =_xlfn.XLOOKUP(_2015_2016_append_[[#This Row],[Job_code]],Analytics_mindset_case_studies_IntegrateCo_jobcodes[Code_text],Analytics_mindset_case_studies_IntegrateCo_jobcodes[Job_Description],"",0) -> Installation | N1037: =IF(OR(MID(B1037,3,1)="H",MID(B1037,3,1)="S"),MID(B1037,3,1),"") -> S | O1037: =IFERROR(VLOOKUP(_2015_2016_append_[[#This Row],[Emp_Name]],Analytics_mindset_case_studies_IntegrateCo_locations[#All],2,FALSE),"") | P1037: =_2015_2016_append_[[#This Row],[Reg_Hrs]]+_2015_2016_append_[[#This Row],[OT_Hrs]] -> 3 | Q1037: 1
A1038: 357 | B1038: 15S006 | C1038: Jesus Peterson | D1038: 3 | E1038: 0 | F1038: 75 | G1038: 494 | H1038: 39 | I1038: 155 | J1038: 124 | K1038: 2016 | L1038: =IF(OR(MID(B1038,3,1)="H",MID(B1038,3,1)="S"),MID(B1038,4,3),MID(B1038,3,3)) -> 006 | M1038: =_xlfn.XLOOKUP(_2015_2016_append_[[#This Row],[Job_code]],Analytics_mindset_case_studies_IntegrateCo_jobcodes[Code_text],Analytics_mindset_case_studies_IntegrateCo_jobcodes[Job_Description],"",0) -> Service | N1038: =IF(OR(MID(B1038,3,1)="H",MID(B1038,3,1)="S"),MID(B1038,3,1),"") -> S | O1038: =IFERROR(VLOOKUP(_2015_2016_append_[[#This Row],[Emp_Name]],Analytics_mindset_case_studies_IntegrateCo_locations[#All],2,FALSE),"") -> 2 | P1038: =_2015_2016_append_[[#This Row],[Reg_Hrs]]+_2015_2016_append_[[#This Row],[OT_Hrs]] -> 3 | Q1038: 1
A1039: 281 | B1039: 15S006 | C1039: Marcia Neal | D1039: 2 | E1039: 2 | F1039: 130 | G1039: 929 | H1039: 73 | I1039: 292 | J1039: 21 | K1039: 2016 | L1039: =IF(OR(MID(B1039,3,1)="H",MID(B1039,3,1)="S"),MID(B1039,4,3),MID(B1039,3,3)) -> 006 | M1039: =_xlfn.XLOOKUP(_2015_2016_append_[[#This Row],[Job_code]],Analytics_mindset_case_studies_IntegrateCo_jobcodes[Code_text],Analytics_mindset_case_studies_IntegrateCo_jobcodes[Job_Description],"",0) -> Service | N1039: =IF(OR(MID(B1039,3,1)="H",MID(B1039,3,1)="S"),MID(B1039,3,1),"") -> S | O1039: =IFERROR(VLOOKUP(_2015_2016_append_[[#This Row],[Emp_Name]],Analytics_mindset_case_studies_IntegrateCo_locations[#All],2,FALSE),"") -> 2 | P1039: =_2015_2016_append_[[#This Row],[Reg_Hrs]]+_2015_2016_append_[[#This Row],[OT_Hrs]] -> 4 | Q1039: 1
A1040: 99 | B1040: 15S006 | C1040: Sue Riley | D1040: 16 | E1040: 0 | F1040: 360 | G1040: 2665 | H1040: 209 | I1040: 836 | J1040: 595 | K1040: 2016 | L1040: =IF(OR(MID(B1040,3,1)="H",MID(B1040,3,1)="S"),MID(B1040,4,3),MID(B1040,3,3)) -> 006 | M1040: =_xlfn.XLOOKUP(_2015_2016_append_[[#This Row],[Job_code]],Analytics_mindset_case_studies_IntegrateCo_jobcodes[Code_text],Analytics_mindset_case_studies_IntegrateCo_jobcodes[Job_Description],"",0) -> Service | N1040: =IF(OR(MID(B1040,3,1)="H",MID(B1040,3,1)="S"),MID(B1040,3,1),"") -> S | O1040: =IFERROR(VLOOKUP(_2015_2016_append_[[#This Row],[Emp_Name]],Analytics_mindset_case_studies_IntegrateCo_locations[#All],2,FALSE),"") -> 2 | P1040: =_2015_2016_append_[[#This Row],[Reg_Hrs]]+_2015_2016_append_[[#This Row],[OT_Hrs]] -> 16 | Q1040: 1
A1041: 27 | B1041: 15S006 | C1041: Cindy Lunt | D1041: 2 | E1041: 0 | F1041: 61 | G1041: 416 | H1041: 33 | I1041: 131 | J1041: 101 | K1041: 2016 | L1041: =IF(OR(MID(B1041,3,1)="H",MID(B1041,3,1)="S"),MID(B1041,4,3),MID(B1041,3,3)) -> 006 | M1041: =_xlfn.XLOOKUP(_2015_2016_append_[[#This Row],[Job_code]],Analytics_mindset_case_studies_IntegrateCo_jobcodes[Code_text],Analytics_mindset_case_studies_IntegrateCo_jobcodes[Job_Description],"",0) -> Service | N1041: =IF(OR(MID(B1041,3,1)="H",MID(B1041,3,1)="S"),MID(B1041,3,1),"") -> S | O1041: =IFERROR(VLOOKUP(_2015_2016_append_[[#This Row],[Emp_Name]],Analytics_mindset_case_studies_IntegrateCo_locations[#All],2,FALSE),"") -> 1 | P1041: =_2015_2016_append_[[#This Row],[Reg_Hrs]]+_2015_2016_append_[[#This Row],[OT_Hrs]] -> 2 | Q1041: 1
A1042: 19 | B1042: 15S006 | C1042: Frank Diaz | D1042: 2 | E1042: 0 | F1042: 54 | G1042: 397 | H1042: 31 | I1042: 125 | J1042: 89 | K1042: 2016 | L1042: =IF(OR(MID(B1042,3,1)="H",MID(B1042,3,1)="S"),MID(B1042,4,3),MID(B1042,3,3)) -> 006 | M1042: =_xlfn.XLOOKUP(_2015_2016_append_[[#This Row],[Job_code]],Analytics_mindset_case_studies_IntegrateCo_jobcodes[Code_text],Analytics_mindset_case_studies_IntegrateCo_jobcodes[Job_Description],"",0) -> Service | N1042: =IF(OR(MID(B1042,3,1)="H",MID(B1042,3,1)="S"),MID(B1042,3,1),"") -> S | O1042: =IFERROR(VLOOKUP(_2015_2016_append_[[#This Row],[Emp_Name]],Analytics_mindset_case_studies_IntegrateCo_locations[#All],2,FALSE),"") -> 1 | P1042: =_2015_2016_append_[[#This Row],[Reg_Hrs]]+_2015_2016_append_[[#This Row],[OT_Hrs]] -> 2 | Q1042: 1
A1043: 203 | B1043: 15S006 | C1043: Helen Paul | D1043: 8 | E1043: 0 | F1043: 51849 | G1043: 3741 | H1043: 293 | I1043: 1174 | J1043: 64 | K1043: 2016 | L1043: =IF(OR(MID(B1043,3,1)="H",MID(B1043,3,1)="S"),MID(B1043,4,3),MID(B1043,3,3)) -> 006 | M1043: =_xlfn.XLOOKUP(_2015_2016_append_[[#This Row],[Job_code]],Analytics_mindset_case_studies_IntegrateCo_jobcodes[Code_text],Analytics_mindset_case_studies_IntegrateCo_jobcodes[Job_Description],"",0) -> Service | N1043: =IF(OR(MID(B1043,3,1)="H",MID(B1043,3,1)="S"),MID(B1043,3,1),"") -> S | O1043: =IFERROR(VLOOKUP(_2015_2016_append_[[#This Row],[Emp_Name]],Analytics_mindset_case_studies_IntegrateCo_locations[#All],2,FALSE),"") -> 1 | P1043: =_2015_2016_append_[[#This Row],[Reg_Hrs]]+_2015_2016_append_[[#This Row],[OT_Hrs]] -> 8 | Q1043: 1
A1044: 357 | B1044: 15S008 | C1044: Jesus Peterson | D1044: 5 | E1044: 0 | F1044: 125 | G1044: 83 | H1044: 6 | I1044: 26 | J1044: 2 | K1044: 2016 | L1044: =IF(OR(MID(B1044,3,1)="H",MID(B1044,3,1)="S"),MID(B1044,4,3),MID(B1044,3,3)) -> 008 | M1044: =_xlfn.XLOOKUP(_2015_2016_append_[[#This Row],[Job_code]],Analytics_mindset_case_studies_IntegrateCo_jobcodes[Code_text],Analytics_mindset_case_studies_IntegrateCo_jobcodes[Job_Description],"",0) -> Employee Training | N1044: =IF(OR(MID(B1044,3,1)="H",MID(B1044,3,1)="S"),MID(B1044,3,1),"") -> S | O1044: =IFERROR(VLOOKUP(_2015_2016_append_[[#This Row],[Emp_Name]],Analytics_mindset_case_studies_IntegrateCo_locations[#All],2,FALSE),"") -> 2 | P1044: =_2015_2016_append_[[#This Row],[Reg_Hrs]]+_2015_2016_append_[[#This Row],[OT_Hrs]] -> 5 | Q1044: 1
B1045: 15S008 | D1045: 5 | E1045: 0 | F1045: 115 | G1045: 88 | H1045: 7 | I1045: 28 | J1045: 19 | K1045: 2016 | L1045: =IF(OR(MID(B1045,3,1)="H",MID(B1045,3,1)="S"),MID(B1045,4,3),MID(B1045,3,3)) -> 008 | M1045: =_xlfn.XLOOKUP(_2015_2016_append_[[#This Row],[Job_code]],Analytics_mindset_case_studies_IntegrateCo_jobcodes[Code_text],Analytics_mindset_case_studies_IntegrateCo_jobcodes[Job_Description],"",0) -> Employee Training | N1045: =IF(OR(MID(B1045,3,1)="H",MID(B1045,3,1)="S"),MID(B1045,3,1),"") -> S | O1045: =IFERROR(VLOOKUP(_2015_2016_append_[[#This Row],[Emp_Name]],Analytics_mindset_case_studies_IntegrateCo_locations[#All],2,FALSE),"") | P1045: =_2015_2016_append_[[#This Row],[Reg_Hrs]]+_2015_2016_append_[[#This Row],[OT_Hrs]] -> 5 | Q1045: 1
A1046: 259 | B1046: 15S008 | C1046: Beulah Gibbs | D1046: 5 | E1046: 0 | F1046: 1338 | G1046: 99 | H1046: 8 | I1046: 31 | J1046: 22 | K1046: 2016 | L1046: =IF(OR(MID(B1046,3,1)="H",MID(B1046,3,1)="S"),MID(B1046,4,3),MID(B1046,3,3)) -> 008 | M1046: =_xlfn.XLOOKUP(_2015_2016_append_[[#This Row],[Job_code]],Analytics_mindset_case_studies_IntegrateCo_jobcodes[Code_text],Analytics_mindset_case_studies_IntegrateCo_jobcodes[Job_Description],"",0) -> Employee Training | N1046: =IF(OR(MID(B1046,3,1)="H",MID(B1046,3,1)="S"),MID(B1046,3,1),"") -> S | O1046: =IFERROR(VLOOKUP(_2015_2016_append_[[#This Row],[Emp_Name]],Analytics_mindset_case_studies_IntegrateCo_locations[#All],2,FALSE),"") -> 2 | P1046: =_2015_2016_append_[[#This Row],[Reg_Hrs]]+_2015_2016_append_[[#This Row],[OT_Hrs]] -> 5 | Q1046: 1
A1047: 422 | B1047: 15S009 | C1047: Afton Call | D1047: 14 | E1047: 0 | F1047: 196 | G1047: 1499 | H1047: 118 | I1047: 47 | J1047: 324 | K1047: 2016 | L1047: =IF(OR(MID(B1047,3,1)="H",MID(B1047,3,1)="S"),MID(B1047,4,3),MID(B1047,3,3)) -> 009 | M1047: =_xlfn.XLOOKUP(_2015_2016_append_[[#This Row],[Job_code]],Analytics_mindset_case_studies_IntegrateCo_jobcodes[Code_text],Analytics_mindset_case_studies_IntegrateCo_jobcodes[Job_Description],"",0) -> New Foreign Manufacturing Plant | N1047: =IF(OR(MID(B1047,3,1)="H",MID(B1047,3,1)="S"),MID(B1047,3,1),"") -> S | O1047: =IFERROR(VLOOKUP(_2015_2016_append_[[#This Row],[Emp_Name]],Analytics_mindset_case_studies_IntegrateCo_locations[#All],2,FALSE),"") -> 1 | P1047: =_2015_2016_append_[[#This Row],[Reg_Hrs]]+_2015_2016_append_[[#This Row],[OT_Hrs]] -> 14 | Q1047: 1
A1048: 368 | B1048: 15S009 | C1048: Cesar Greene | D1048: 16 | E1048: 0 | F1048: 392 | G1048: 2466 | H1048: 194 | I1048: 774 | J1048: 649 | K1048: 2016 | L1048: =IF(OR(MID(B1048,3,1)="H",MID(B1048,3,1)="S"),MID(B1048,4,3),MID(B1048,3,3)) -> 009 | M1048: =_xlfn.XLOOKUP(_2015_2016_append_[[#This Row],[Job_code]],Analytics_mindset_case_studies_IntegrateCo_jobcodes[Code_text],Analytics_mindset_case_studies_IntegrateCo_jobcodes[Job_Description],"",0) -> New Foreign Manufacturing Plant | N1048: =IF(OR(MID(B1048,3,1)="H",MID(B1048,3,1)="S"),MID(B1048,3,1),"") -> S | O1048: =IFERROR(VLOOKUP(_2015_2016_append_[[#This Row],[Emp_Name]],Analytics_mindset_case_studies_IntegrateCo_locations[#All],2,FALSE),"") -> 2 | P1048: =_2015_2016_append_[[#This Row],[Reg_Hrs]]+_2015_2016_append_[[#This Row],[OT_Hrs]] -> 16 | Q1048: 1
A1049: 281 | B1049: 15S009 | C1049: Marcia Neal | D1049: 16 | E1049: 0 | F1049: 416 | G1049: 2972 | H1049: 233 | I1049: 933 | J1049: 672 | K1049: 2016 | L1049: =IF(OR(MID(B1049,3,1)="H",MID(B1049,3,1)="S"),MID(B1049,4,3),MID(B1049,3,3)) -> 009 | M1049: =_xlfn.XLOOKUP(_2015_2016_append_[[#This Row],[Job_code]],Analytics_mindset_case_studies_IntegrateCo_jobcodes[Code_text],Analytics_mindset_case_studies_IntegrateCo_jobcodes[Job_Description],"",0) -> New Foreign Manufacturing Plant | N1049: =IF(OR(MID(B1049,3,1)="H",MID(B1049,3,1)="S"),MID(B1049,3,1),"") -> S | O1049: =IFERROR(VLOOKUP(_2015_2016_append_[[#This Row],[Emp_Name]],Analytics_mindset_case_studies_IntegrateCo_locations[#All],2,FALSE),"") -> 2 | P1049: =_2015_2016_append_[[#This Row],[Reg_Hrs]]+_2015_2016_append_[[#This Row],[OT_Hrs]] -> 16 | Q1049: 1
A1050: 27 | B1050: 15S009 | C1050: Cindy Lunt | D1050: 4 | E1050: 0 | F1050: 122 | G1050: 832 | H1050: 65 | I1050: 261 | J1050: 201 | K1050: 2016 | L1050: =IF(OR(MID(B1050,3,1)="H",MID(B1050,3,1)="S"),MID(B1050,4,3),MID(B1050,3,3)) -> 009 | M1050: =_xlfn.XLOOKUP(_2015_2016_append_[[#This Row],[Job_code]],Analytics_mindset_case_studies_IntegrateCo_jobcodes[Code_text],Analytics_mindset_case_studies_IntegrateCo_jobcodes[Job_Description],"",0) -> New Foreign Manufacturing Plant | N1050: =IF(OR(MID(B1050,3,1)="H",MID(B1050,3,1)="S"),MID(B1050,3,1),"") -> S | O1050: =IFERROR(VLOOKUP(_2015_2016_append_[[#This Row],[Emp_Name]],Analytics_mindset_case_studies_IntegrateCo_locations[#All],2,FALSE),"") -> 1 | P1050: =_2015_2016_append_[[#This Row],[Reg_Hrs]]+_2015_2016_append_[[#This Row],[OT_Hrs]] -> 4 | Q1050: 1
A1051: 352 | B1051: 15S009 | C1051: Myra Vega | D1051: 8 | E1051: 0 | F1051: 152 | G1051: 702 | H1051: 55 | I1051: 22 | J1051: 251 | K1051: 2016 | L1051: =IF(OR(MID(B1051,3,1)="H",MID(B1051,3,1)="S"),MID(B1051,4,3),MID(B1051,3,3)) -> 009 | M1051: =_xlfn.XLOOKUP(_2015_2016_append_[[#This Row],[Job_code]],Analytics_mindset_case_studies_IntegrateCo_jobcodes[Code_text],Analytics_mindset_case_studies_IntegrateCo_jobcodes[Job_Description],"",0) -> New Foreign Manufacturing Plant | N1051: =IF(OR(MID(B1051,3,1)="H",MID(B1051,3,1)="S"),MID(B1051,3,1),"") -> S | O1051: =IFERROR(VLOOKUP(_2015_2016_append_[[#This Row],[Emp_Name]],Analytics_mindset_case_studies_IntegrateCo_locations[#All],2,FALSE),"") -> 1 | P1051: =_2015_2016_append_[[#This Row],[Reg_Hrs]]+_2015_2016_append_[[#This Row],[OT_Hrs]] -> 8 | Q1051: 1
A1052: 380 | B1052: 15S009 | C1052: Preston Robinson | D1052: 19 | E1052: 0 | F1052: 399 | G1052: 2587 | H1052: 203 | I1052: 812 | J1052: 66 | K1052: 2016 | L1052: =IF(OR(MID(B1052,3,1)="H",MID(B1052,3,1)="S"),MID(B1052,4,3),MID(B1052,3,3)) -> 009 | M1052: =_xlfn.XLOOKUP(_2015_2016_append_[[#This Row],[Job_code]],Analytics_mindset_case_studies_IntegrateCo_jobcodes[Code_text],Analytics_mindset_case_studies_IntegrateCo_jobcodes[Job_Description],"",0) -> New Foreign Manufacturing Plant | N1052: =IF(OR(MID(B1052,3,1)="H",MID(B1052,3,1)="S"),MID(B1052,3,1),"") -> S | O1052: =IFERROR(VLOOKUP(_2015_2016_append_[[#This Row],[Emp_Name]],Analytics_mindset_case_studies_IntegrateCo_locations[#All],2,FALSE),"") -> 2 | P1052: =_2015_2016_append_[[#This Row],[Reg_Hrs]]+_2015_2016_append_[[#This Row],[OT_Hrs]] -> 19 | Q1052: 1
A1053: 421 | B1053: 15S009 | C1053: Emma Goodwin | D1053: 3 | E1053: 0 | F1053: 42 | G1053: 298 | H1053: 23 | I1053: 94 | J1053: 7 | K1053: 2016 | L1053: =IF(OR(MID(B1053,3,1)="H",MID(B1053,3,1)="S"),MID(B1053,4,3),MID(B1053,3,3)) -> 009 | M1053: =_xlfn.XLOOKUP(_2015_2016_append_[[#This Row],[Job_code]],Analytics_mindset_case_studies_IntegrateCo_jobcodes[Code_text],Analytics_mindset_case_studies_IntegrateCo_jobcodes[Job_Description],"",0) -> New Foreign Manufacturing Plant | N1053: =IF(OR(MID(B1053,3,1)="H",MID(B1053,3,1)="S"),MID(B1053,3,1),"") -> S | O1053: =IFERROR(VLOOKUP(_2015_2016_append_[[#This Row],[Emp_Name]],Analytics_mindset_case_studies_IntegrateCo_locations[#All],2,FALSE),"") -> 1 | P1053: =_2015_2016_append_[[#This Row],[Reg_Hrs]]+_2015_2016_append_[[#This Row],[OT_Hrs]] -> 3 | Q1053: 1
A1054: 375 | B1054: 15S009 | C1054: Fannie Parks | D1054: 7 | E1054: 0 | F1054: 154 | G1054: 1178 | H1054: 92 | I1054: 37 | J1054: 255 | K1054: 2016 | L1054: =IF(OR(MID(B1054,3,1)="H",MID(B1054,3,1)="S"),MID(B1054,4,3),MID(B1054,3,3)) -> 009 | M1054: =_xlfn.XLOOKUP(_2015_2016_append_[[#This Row],[Job_code]],Analytics_mindset_case_studies_IntegrateCo_jobcodes[Code_text],Analytics_mindset_case_studies_IntegrateCo_jobcodes[Job_Description],"",0) -> New Foreign Manufacturing Plant | N1054: =IF(OR(MID(B1054,3,1)="H",MID(B1054,3,1)="S"),MID(B1054,3,1),"") -> S | O1054: =IFERROR(VLOOKUP(_2015_2016_append_[[#This Row],[Emp_Name]],Analytics_mindset_case_studies_IntegrateCo_locations[#All],2,FALSE),"") -> 2 | P1054: =_2015_2016_append_[[#This Row],[Reg_Hrs]]+_2015_2016_append_[[#This Row],[OT_Hrs]] -> 7 | Q1054: 1
A1055: 38 | B1055: 15S009 | C1055: Conrad Walker | D1055: 26 | E1055: 0 | F1055: 106245 | G1055: 7945 | H1055: 623 | I1055: 2493 | J1055: 281 | K1055: 2016 | L1055: =IF(OR(MID(B1055,3,1)="H",MID(B1055,3,1)="S"),MID(B1055,4,3),MID(B1055,3,3)) -> 009 | M1055: =_xlfn.XLOOKUP(_2015_2016_append_[[#This Row],[Job_code]],Analytics_mindset_case_studies_IntegrateCo_jobcodes[Code_text],Analytics_mindset_case_studies_IntegrateCo_jobcodes[Job_Description],"",0) -> New Foreign Manufacturing Plant | N1055: =IF(OR(MID(B1055,3,1)="H",MID(B1055,3,1)="S"),MID(B1055,3,1),"") -> S | O1055: =IFERROR(VLOOKUP(_2015_2016_append_[[#This Row],[Emp_Name]],Analytics_mindset_case_studies_IntegrateCo_locations[#All],2,FALSE),"") -> 2 | P1055: =_2015_2016_append_[[#This Row],[Reg_Hrs]]+_2015_2016_append_[[#This Row],[OT_Hrs]] -> 26 | Q1055: 1
A1056: 381 | B1056: 15S009 | C1056: Frankie Mcdaniel | D1056: 13 | E1056: 0 | F1056: 28125 | G1056: 1795 | H1056: 141 | I1056: 563 | J1056: 75 | K1056: 2016 | L1056: =IF(OR(MID(B1056,3,1)="H",MID(B1056,3,1)="S"),MID(B1056,4,3),MID(B1056,3,3)) -> 009 | M1056: =_xlfn.XLOOKUP(_2015_2016_append_[[#This Row],[Job_code]],Analytics_mindset_case_studies_IntegrateCo_jobcodes[Code_text],Analytics_mindset_case_studies_IntegrateCo_jobcodes[Job_Description],"",0) -> New Foreign Manufacturing Plant | N1056: =IF(OR(MID(B1056,3,1)="H",MID(B1056,3,1)="S"),MID(B1056,3,1),"") -> S | O1056: =IFERROR(VLOOKUP(_2015_2016_append_[[#This Row],[Emp_Name]],Analytics_mindset_case_studies_IntegrateCo_locations[#All],2,FALSE),"") -> 1 | P1056: =_2015_2016_append_[[#This Row],[Reg_Hrs]]+_2015_2016_append_[[#This Row],[OT_Hrs]] -> 13 | Q1056: 1
A1057: 20 | B1057: 15S011 | C1057: Ed Craig | D1057: 20 | E1057: 0 | F1057: 5777 | G1057: 391 | H1057: 306 | I1057: 1226 | J1057: 77 | K1057: 2016 | L1057: =IF(OR(MID(B1057,3,1)="H",MID(B1057,3,1)="S"),MID(B1057,4,3),MID(B1057,3,3)) -> 011 | M1057: =_xlfn.XLOOKUP(_2015_2016_append_[[#This Row],[Job_code]],Analytics_mindset_case_studies_IntegrateCo_jobcodes[Code_text],Analytics_mindset_case_studies_IntegrateCo_jobcodes[Job_Description],"",0) -> Internal Projects | N1057: =IF(OR(MID(B1057,3,1)="H",MID(B1057,3,1)="S"),MID(B1057,3,1),"") -> S | O1057: =IFERROR(VLOOKUP(_2015_2016_append_[[#This Row],[Emp_Name]],Analytics_mindset_case_studies_IntegrateCo_locations[#All],2,FALSE),"") -> 1 | P1057: =_2015_2016_append_[[#This Row],[Reg_Hrs]]+_2015_2016_append_[[#This Row],[OT_Hrs]] -> 20 | Q1057: 1
... A1072: 45 | B1072: 16002 | C1072: Ernesto Todd | D1072: 960 | E1072: 0 | F1072: 10141536 | G1072: 746304 | H1072: 177 | I1072: 67562 | J1072: 14066 | K1072: 2016 | L1072: =IF(OR(MID(B1072,3,1)="H",MID(B1072,3,1)="S"),MID(B1072,4,3),MID(B1072,3,3)) -> 002 | M1072: =_xlfn.XLOOKUP(_2015_2016_append_[[#This Row],[Job_code]],Analytics_mindset_case_studies_IntegrateCo_jobcodes[Code_text],Analytics_mindset_case_studies_IntegrateCo_jobcodes[Job_Description],"",0) -> Sales | N1072: =IF(OR(MID(B1072,3,1)="H",MID(B1072,3,1)="S"),MID(B1072,3,1),"") | O1072: =IFERROR(VLOOKUP(_2015_2016_append_[[#This Row],[Emp_Name]],Analytics_mindset_case_studies_IntegrateCo_locations[#All],2,FALSE),"") -> 2 | P1072: =_2015_2016_append_[[#This Row],[Reg_Hrs]]+_2015_2016_append_[[#This Row],[OT_Hrs]] -> 960 | Q1072: 1
B1073: 16005 | D1073: 0 | E1073: 0 | F1073: 0 | G1073: 0 | H1073: 0 | I1073: 0 | J1073: 0 | K1073: 2016 | L1073: =IF(OR(MID(B1073,3,1)="H",MID(B1073,3,1)="S"),MID(B1073,4,3),MID(B1073,3,3)) -> 005 | M1073: =_xlfn.XLOOKUP(_2015_2016_append_[[#This Row],[Job_code]],Analytics_mindset_case_studies_IntegrateCo_jobcodes[Code_text],Analytics_mindset_case_studies_IntegrateCo_jobcodes[Job_Description],"",0) -> Installation | N1073: =IF(OR(MID(B1073,3,1)="H",MID(B1073,3,1)="S"),MID(B1073,3,1),"") | O1073: =IFERROR(VLOOKUP(_2015_2016_append_[[#This Row],[Emp_Name]],Analytics_mindset_case_studies_IntegrateCo_locations[#All],2,FALSE),"") | P1073: =_2015_2016_append_[[#This Row],[Reg_Hrs]]+_2015_2016_append_[[#This Row],[OT_Hrs]] -> 0 | Q1073: 1
A1074: 407 | B1074: 16005 | C1074: Maxine Tyler | D1074: 1 | E1074: 0 | F1074: 15 | G1074: 115 | H1074: 0 | I1074: 36 | J1074: 24 | K1074: 2016 | L1074: =IF(OR(MID(B1074,3,1)="H",MID(B1074,3,1)="S"),MID(B1074,4,3),MID(B1074,3,3)) -> 005 | M1074: =_xlfn.XLOOKUP(_2015_2016_append_[[#This Row],[Job_code]],Analytics_mindset_case_studies_IntegrateCo_jobcodes[Code_text],Analytics_mindset_case_studies_IntegrateCo_jobcodes[Job_Description],"",0) -> Installation | N1074: =IF(OR(MID(B1074,3,1)="H",MID(B1074,3,1)="S"),MID(B1074,3,1),"") | O1074: =IFERROR(VLOOKUP(_2015_2016_append_[[#This Row],[Emp_Name]],Analytics_mindset_case_studies_IntegrateCo_locations[#All],2,FALSE),"") -> 1 | P1074: =_2015_2016_append_[[#This Row],[Reg_Hrs]]+_2015_2016_append_[[#This Row],[OT_Hrs]] -> 1 | Q1074: 1
A1075: 53 | B1075: 16005 | C1075: Delia Lopez | D1075: 15 | E1075: 0 | F1075: 225 | G1075: 1583 | H1075: 49 | I1075: 499 | J1075: 371 | K1075: 2016 | L1075: =IF(OR(MID(B1075,3,1)="H",MID(B1075,3,1)="S"),MID(B1075,4,3),MID(B1075,3,3)) -> 005 | M1075: =_xlfn.XLOOKUP(_2015_2016_append_[[#This Row],[Job_code]],Analytics_mindset_case_studies_IntegrateCo_jobcodes[Code_text],Analytics_mindset_case_studies_IntegrateCo_jobcodes[Job_Description],"",0) -> Installation | N1075: =IF(OR(MID(B1075,3,1)="H",MID(B1075,3,1)="S"),MID(B1075,3,1),"") | O1075: =IFERROR(VLOOKUP(_2015_2016_append_[[#This Row],[Emp_Name]],Analytics_mindset_case_studies_IntegrateCo_locations[#All],2,FALSE),"") -> 2 | P1075: =_2015_2016_append_[[#This Row],[Reg_Hrs]]+_2015_2016_append_[[#This Row],[OT_Hrs]] -> 15 | Q1075: 1
A1076: 260 | B1076: 16005 | C1076: Nichole Fox | D1076: 23 | E1076: 0 | F1076: 342 | G1076: 2462 | H1076: 5 | I1076: 78 | J1076: 569 | K1076: 2016 | L1076: =IF(OR(MID(B1076,3,1)="H",MID(B1076,3,1)="S"),MID(B1076,4,3),MID(B1076,3,3)) -> 005 | M1076: =_xlfn.XLOOKUP(_2015_2016_append_[[#This Row],[Job_code]],Analytics_mindset_case_studies_IntegrateCo_jobcodes[Code_text],Analytics_mindset_case_studies_IntegrateCo_jobcodes[Job_Description],"",0) -> Installation | N1076: =IF(OR(MID(B1076,3,1)="H",MID(B1076,3,1)="S"),MID(B1076,3,1),"") | O1076: =IFERROR(VLOOKUP(_2015_2016_append_[[#This Row],[Emp_Name]],Analytics_mindset_case_studies_IntegrateCo_locations[#All],2,FALSE),"") -> 2 | P1076: =_2015_2016_append_[[#This Row],[Reg_Hrs]]+_2015_2016_append_[[#This Row],[OT_Hrs]] -> 23 | Q1076: 1
A1077: 422 | B1077: 16005 | C1077: Afton Call | D1077: 6 | E1077: 0 | F1077: 78 | G1077: 596 | H1077: 37 | I1077: 187 | J1077: 126 | K1077: 2016 | L1077: =IF(OR(MID(B1077,3,1)="H",MID(B1077,3,1)="S"),MID(B1077,4,3),MID(B1077,3,3)) -> 005 | M1077: =_xlfn.XLOOKUP(_2015_2016_append_[[#This Row],[Job_code]],Analytics_mindset_case_studies_IntegrateCo_jobcodes[Code_text],Analytics_mindset_case_studies_IntegrateCo_jobcodes[Job_Description],"",0) -> Installation | N1077: =IF(OR(MID(B1077,3,1)="H",MID(B1077,3,1)="S"),MID(B1077,3,1),"") | O1077: =IFERROR(VLOOKUP(_2015_2016_append_[[#This Row],[Emp_Name]],Analytics_mindset_case_studies_IntegrateCo_locations[#All],2,FALSE),"") -> 1 | P1077: =_2015_2016_append_[[#This Row],[Reg_Hrs]]+_2015_2016_append_[[#This Row],[OT_Hrs]] -> 6 | Q1077: 1
A1078: 376 | B1078: 16005 | C1078: Katie Hodges | D1078: 23 | E1078: 0 | F1078: 327 | G1078: 2385 | H1078: 69 | I1078: 744 | J1078: 53 | K1078: 2016 | L1078: =IF(OR(MID(B1078,3,1)="H",MID(B1078,3,1)="S"),MID(B1078,4,3),MID(B1078,3,3)) -> 005 | M1078: =_xlfn.XLOOKUP(_2015_2016_append_[[#This Row],[Job_code]],Analytics_mindset_case_studies_IntegrateCo_jobcodes[Code_text],Analytics_mindset_case_studies_IntegrateCo_jobcodes[Job_Description],"",0) -> Installation | N1078: =IF(OR(MID(B1078,3,1)="H",MID(B1078,3,1)="S"),MID(B1078,3,1),"") | O1078: =IFERROR(VLOOKUP(_2015_2016_append_[[#This Row],[Emp_Name]],Analytics_mindset_case_studies_IntegrateCo_locations[#All],2,FALSE),"") -> 1 | P1078: =_2015_2016_append_[[#This Row],[Reg_Hrs]]+_2015_2016_append_[[#This Row],[OT_Hrs]] -> 23 | Q1078: 1
A1079: 398 | B1079: 16005 | C1079: Mona Howard | D1079: 20 | E1079: 0 | F1079: 279 | G1079: 2015 | H1079: 81 | I1079: 624 | J1079: 454 | K1079: 2016 | L1079: =IF(OR(MID(B1079,3,1)="H",MID(B1079,3,1)="S"),MID(B1079,4,3),MID(B1079,3,3)) -> 005 | M1079: =_xlfn.XLOOKUP(_2015_2016_append_[[#This Row],[Job_code]],Analytics_mindset_case_studies_IntegrateCo_jobcodes[Code_text],Analytics_mindset_case_studies_IntegrateCo_jobcodes[Job_Description],"",0) -> Installation | N1079: =IF(OR(MID(B1079,3,1)="H",MID(B1079,3,1)="S"),MID(B1079,3,1),"") | O1079: =IFERROR(VLOOKUP(_2015_2016_append_[[#This Row],[Emp_Name]],Analytics_mindset_case_studies_IntegrateCo_locations[#All],2,FALSE),"") -> 2 | P1079: =_2015_2016_append_[[#This Row],[Reg_Hrs]]+_2015_2016_append_[[#This Row],[OT_Hrs]] -> 20 | Q1079: 1
A1080: 269 | B1080: 16005 | C1080: Jo Manning | D1080: 22 | E1080: 0 | F1080: 330 | G1080: 2325 | H1080: 31 | I1080: 61 | J1080: 475 | K1080: 2016 | L1080: =IF(OR(MID(B1080,3,1)="H",MID(B1080,3,1)="S"),MID(B1080,4,3),MID(B1080,3,3)) -> 005 | M1080: =_xlfn.XLOOKUP(_2015_2016_append_[[#This Row],[Job_code]],Analytics_mindset_case_studies_IntegrateCo_jobcodes[Code_text],Analytics_mindset_case_studies_IntegrateCo_jobcodes[Job_Description],"",0) -> Installation | N1080: =IF(OR(MID(B1080,3,1)="H",MID(B1080,3,1)="S"),MID(B1080,3,1),"") | O1080: =IFERROR(VLOOKUP(_2015_2016_append_[[#This Row],[Emp_Name]],Analytics_mindset_case_studies_IntegrateCo_locations[#All],2,FALSE),"") -> 2 | P1080: =_2015_2016_append_[[#This Row],[Reg_Hrs]]+_2015_2016_append_[[#This Row],[OT_Hrs]] -> 22 | Q1080: 1
A1081: 357 | B1081: 16005 | C1081: Jesus Peterson | D1081: 24 | E1081: 0 | F1081: 339 | G1081: 2295 | H1081: 39 | I1081: 727 | J1081: 541 | K1081: 2016 | L1081: =IF(OR(MID(B1081,3,1)="H",MID(B1081,3,1)="S"),MID(B1081,4,3),MID(B1081,3,3)) -> 005 | M1081: =_xlfn.XLOOKUP(_2015_2016_append_[[#This Row],[Job_code]],Analytics_mindset_case_studies_IntegrateCo_jobcodes[Code_text],Analytics_mindset_case_studies_IntegrateCo_jobcodes[Job_Description],"",0) -> Installation | N1081: =IF(OR(MID(B1081,3,1)="H",MID(B1081,3,1)="S"),MID(B1081,3,1),"") | O1081: =IFERROR(VLOOKUP(_2015_2016_append_[[#This Row],[Emp_Name]],Analytics_mindset_case_studies_IntegrateCo_locations[#All],2,FALSE),"") -> 2 | P1081: =_2015_2016_append_[[#This Row],[Reg_Hrs]]+_2015_2016_append_[[#This Row],[OT_Hrs]] -> 24 | Q1081: 1
B1082: 16005 | D1082: 1 | E1082: 0 | F1082: 15 | G1082: 113 | H1082: 0 | I1082: 36 | J1082: 25 | K1082: 2016 | L1082: =IF(OR(MID(B1082,3,1)="H",MID(B1082,3,1)="S"),MID(B1082,4,3),MID(B1082,3,3)) -> 005 | M1082: =_xlfn.XLOOKUP(_2015_2016_append_[[#This Row],[Job_code]],Analytics_mindset_case_studies_IntegrateCo_jobcodes[Code_text],Analytics_mindset_case_studies_IntegrateCo_jobcodes[Job_Description],"",0) -> Installation | N1082: =IF(OR(MID(B1082,3,1)="H",MID(B1082,3,1)="S"),MID(B1082,3,1),"") | O1082: =IFERROR(VLOOKUP(_2015_2016_append_[[#This Row],[Emp_Name]],Analytics_mindset_case_studies_IntegrateCo_locations[#All],2,FALSE),"") | P1082: =_2015_2016_append_[[#This Row],[Reg_Hrs]]+_2015_2016_append_[[#This Row],[OT_Hrs]] -> 1 | Q1082: 1
A1083: 314 | B1083: 16005 | C1083: Marianne Baldwin | D1083: 23 | E1083: 0 | F1083: 288 | G1083: 2194 | H1083: 5 | I1083: 694 | J1083: 477 | K1083: 2016 | L1083: =IF(OR(MID(B1083,3,1)="H",MID(B1083,3,1)="S"),MID(B1083,4,3),MID(B1083,3,3)) -> 005 | M1083: =_xlfn.XLOOKUP(_2015_2016_append_[[#This Row],[Job_code]],Analytics_mindset_case_studies_IntegrateCo_jobcodes[Code_text],Analytics_mindset_case_studies_IntegrateCo_jobcodes[Job_Description],"",0) -> Installation | N1083: =IF(OR(MID(B1083,3,1)="H",MID(B1083,3,1)="S"),MID(B1083,3,1),"") | O1083: =IFERROR(VLOOKUP(_2015_2016_append_[[#This Row],[Emp_Name]],Analytics_mindset_case_studies_IntegrateCo_locations[#All],2,FALSE),"") -> 1 | P1083: =_2015_2016_append_[[#This Row],[Reg_Hrs]]+_2015_2016_append_[[#This Row],[OT_Hrs]] -> 23 | Q1083: 1
A1084: 400 | B1084: 16005 | C1084: Roberto Ortega | D1084: 2 | E1084: 0 | F1084: 30 | G1084: 191 | H1084: 15 | I1084: 6 | J1084: 8 | K1084: 2016 | L1084: =IF(OR(MID(B1084,3,1)="H",MID(B1084,3,1)="S"),MID(B1084,4,3),MID(B1084,3,3)) -> 005 | M1084: =_xlfn.XLOOKUP(_2015_2016_append_[[#This Row],[Job_code]],Analytics_mindset_case_studies_IntegrateCo_jobcodes[Code_text],Analytics_mindset_case_studies_IntegrateCo_jobcodes[Job_Description],"",0) -> Installation | N1084: =IF(OR(MID(B1084,3,1)="H",MID(B1084,3,1)="S"),MID(B1084,3,1),"") | O1084: =IFERROR(VLOOKUP(_2015_2016_append_[[#This Row],[Emp_Name]],Analytics_mindset_case_studies_IntegrateCo_locations[#All],2,FALSE),"") -> 1 | P1084: =_2015_2016_append_[[#This Row],[Reg_Hrs]]+_2015_2016_append_[[#This Row],[OT_Hrs]] -> 2 | Q1084: 1
A1085: 368 | B1085: 16005 | C1085: Cesar Greene | D1085: 24 | E1085: 0 | F1085: 339 | G1085: 2266 | H1085: 54 | I1085: 705 | J1085: 552 | K1085: 2016 | L1085: =IF(OR(MID(B1085,3,1)="H",MID(B1085,3,1)="S"),MID(B1085,4,3),MID(B1085,3,3)) -> 005 | M1085: =_xlfn.XLOOKUP(_2015_2016_append_[[#This Row],[Job_code]],Analytics_mindset_case_studies_IntegrateCo_jobcodes[Code_text],Analytics_mindset_case_studies_IntegrateCo_jobcodes[Job_Description],"",0) -> Installation | N1085: =IF(OR(MID(B1085,3,1)="H",MID(B1085,3,1)="S"),MID(B1085,3,1),"") | O1085: =IFERROR(VLOOKUP(_2015_2016_append_[[#This Row],[Emp_Name]],Analytics_mindset_case_studies_IntegrateCo_locations[#All],2,FALSE),"") -> 2 | P1085: =_2015_2016_append_[[#This Row],[Reg_Hrs]]+_2015_2016_append_[[#This Row],[OT_Hrs]] -> 24 | Q1085: 1
A1086: 415 | B1086: 16005 | C1086: Floyd Hunter | D1086: 8 | E1086: 0 | F1086: 120 | G1086: 892 | H1086: 48 | I1086: 279 | J1086: 2 | K1086: 2016 | L1086: =IF(OR(MID(B1086,3,1)="H",MID(B1086,3,1)="S"),MID(B1086,4,3),MID(B1086,3,3)) -> 005 | M1086: =_xlfn.XLOOKUP(_2015_2016_append_[[#This Row],[Job_code]],Analytics_mindset_case_studies_IntegrateCo_jobcodes[Code_text],Analytics_mindset_case_studies_IntegrateCo_jobcodes[Job_Description],"",0) -> Installation | N1086: =IF(OR(MID(B1086,3,1)="H",MID(B1086,3,1)="S"),MID(B1086,3,1),"") | O1086: =IFERROR(VLOOKUP(_2015_2016_append_[[#This Row],[Emp_Name]],Analytics_mindset_case_studies_IntegrateCo_locations[#All],2,FALSE),"") -> 2 | P1086: =_2015_2016_append_[[#This Row],[Reg_Hrs]]+_2015_2016_append_[[#This Row],[OT_Hrs]] -> 8 | Q1086: 1
A1087: 34 | B1087: 16005 | C1087: Sheryl Hill | D1087: 24 | E1087: 0 | F1087: 360 | G1087: 2589 | H1087: 2 | I1087: 4 | J1087: 598 | K1087: 2016 | L1087: =IF(OR(MID(B1087,3,1)="H",MID(B1087,3,1)="S"),MID(B1087,4,3),MID(B1087,3,3)) -> 005 | M1087: =_xlfn.XLOOKUP(_2015_2016_append_[[#This Row],[Job_code]],Analytics_mindset_case_studies_IntegrateCo_jobcodes[Code_text],Analytics_mindset_case_studies_IntegrateCo_jobcodes[Job_Description],"",0) -> Installation | N1087: =IF(OR(MID(B1087,3,1)="H",MID(B1087,3,1)="S"),MID(B1087,3,1),"") | O1087: =IFERROR(VLOOKUP(_2015_2016_append_[[#This Row],[Emp_Name]],Analytics_mindset_case_studies_IntegrateCo_locations[#All],2,FALSE),"") -> 1 | P1087: =_2015_2016_append_[[#This Row],[Reg_Hrs]]+_2015_2016_append_[[#This Row],[OT_Hrs]] -> 24 | Q1087: 1
A1088: 281 | B1088: 16005 | C1088: Marcia Neal | D1088: 24 | E1088: 0 | F1088: 348 | G1088: 2527 | H1088: 45 | I1088: 786 | J1088: 547 | K1088: 2016 | L1088: =IF(OR(MID(B1088,3,1)="H",MID(B1088,3,1)="S"),MID(B1088,4,3),MID(B1088,3,3)) -> 005 | M1088: =_xlfn.XLOOKUP(_2015_2016_append_[[#This Row],[Job_code]],Analytics_mindset_case_studies_IntegrateCo_jobcodes[Code_text],Analytics_mindset_case_studies_IntegrateCo_jobcodes[Job_Description],"",0) -> Installation | N1088: =IF(OR(MID(B1088,3,1)="H",MID(B1088,3,1)="S"),MID(B1088,3,1),"") | O1088: =IFERROR(VLOOKUP(_2015_2016_append_[[#This Row],[Emp_Name]],Analytics_mindset_case_studies_IntegrateCo_locations[#All],2,FALSE),"") -> 2 | P1088: =_2015_2016_append_[[#This Row],[Reg_Hrs]]+_2015_2016_append_[[#This Row],[OT_Hrs]] -> 24 | Q1088: 1
B1089: 16005 | D1089: 1 | E1089: 0 | F1089: 15 | G1089: 115 | H1089: 9 | I1089: 36 | J1089: 24 | K1089: 2016 | L1089: =IF(OR(MID(B1089,3,1)="H",MID(B1089,3,1)="S"),MID(B1089,4,3),MID(B1089,3,3)) -> 005 | M1089: =_xlfn.XLOOKUP(_2015_2016_append_[[#This Row],[Job_code]],Analytics_mindset_case_studies_IntegrateCo_jobcodes[Code_text],Analytics_mindset_case_studies_IntegrateCo_jobcodes[Job_Description],"",0) -> Installation | N1089: =IF(OR(MID(B1089,3,1)="H",MID(B1089,3,1)="S"),MID(B1089,3,1),"") | O1089: =IFERROR(VLOOKUP(_2015_2016_append_[[#This Row],[Emp_Name]],Analytics_mindset_case_studies_IntegrateCo_locations[#All],2,FALSE),"") | P1089: =_2015_2016_append_[[#This Row],[Reg_Hrs]]+_2015_2016_append_[[#This Row],[OT_Hrs]] -> 1 | Q1089: 1
A1090: 345 | B1090: 16005 | C1090: Sidney Hansen | D1090: 8 | E1090: 0 | F1090: 120 | G1090: 915 | H1090: 0 | I1090: 29 | J1090: 192 | K1090: 2016 | L1090: =IF(OR(MID(B1090,3,1)="H",MID(B1090,3,1)="S"),MID(B1090,4,3),MID(B1090,3,3)) -> 005 | M1090: =_xlfn.XLOOKUP(_2015_2016_append_[[#This Row],[Job_code]],Analytics_mindset_case_studies_IntegrateCo_jobcodes[Code_text],Analytics_mindset_case_studies_IntegrateCo_jobcodes[Job_Description],"",0) -> Installation | N1090: =IF(OR(MID(B1090,3,1)="H",MID(B1090,3,1)="S"),MID(B1090,3,1),"") | O1090: =IFERROR(VLOOKUP(_2015_2016_append_[[#This Row],[Emp_Name]],Analytics_mindset_case_studies_IntegrateCo_locations[#All],2,FALSE),"") -> 1 | P1090: =_2015_2016_append_[[#This Row],[Reg_Hrs]]+_2015_2016_append_[[#This Row],[OT_Hrs]] -> 8 | Q1090: 1
B1091: 16005 | D1091: 1 | E1091: 0 | F1091: 15 | G1091: 115 | H1091: 8 | I1091: 36 | J1091: 23 | K1091: 2016 | L1091: =IF(OR(MID(B1091,3,1)="H",MID(B1091,3,1)="S"),MID(B1091,4,3),MID(B1091,3,3)) -> 005 | M1091: =_xlfn.XLOOKUP(_2015_2016_append_[[#This Row],[Job_code]],Analytics_mindset_case_studies_IntegrateCo_jobcodes[Code_text],Analytics_mindset_case_studies_IntegrateCo_jobcodes[Job_Description],"",0) -> Installation | N1091: =IF(OR(MID(B1091,3,1)="H",MID(B1091,3,1)="S"),MID(B1091,3,1),"") | O1091: =IFERROR(VLOOKUP(_2015_2016_append_[[#This Row],[Emp_Name]],Analytics_mindset_case_studies_IntegrateCo_locations[#All],2,FALSE),"") | P1091: =_2015_2016_append_[[#This Row],[Reg_Hrs]]+_2015_2016_append_[[#This Row],[OT_Hrs]] -> 1 | Q1091: 1
A1092: 179 | B1092: 16005 | C1092: Cassandra Poole | D1092: 24 | E1092: 0 | F1092: 324 | G1092: 2335 | H1092: 23 | I1092: 533 | J1092: 537 | K1092: 2016 | L1092: =IF(OR(MID(B1092,3,1)="H",MID(B1092,3,1)="S"),MID(B1092,4,3),MID(B1092,3,3)) -> 005 | M1092: =_xlfn.XLOOKUP(_2015_2016_append_[[#This Row],[Job_code]],Analytics_mindset_case_studies_IntegrateCo_jobcodes[Code_text],Analytics_mindset_case_studies_IntegrateCo_jobcodes[Job_Description],"",0) -> Installation | N1092: =IF(OR(MID(B1092,3,1)="H",MID(B1092,3,1)="S"),MID(B1092,3,1),"") | O1092: =IFERROR(VLOOKUP(_2015_2016_append_[[#This Row],[Emp_Name]],Analytics_mindset_case_studies_IntegrateCo_locations[#All],2,FALSE),"") -> 2 | P1092: =_2015_2016_append_[[#This Row],[Reg_Hrs]]+_2015_2016_append_[[#This Row],[OT_Hrs]] -> 24 | Q1092: 1
B1093: 16005 | D1093: 21 | E1093: 0 | F1093: 300 | G1093: 198 | H1093: 59 | I1093: 626 | J1093: 499 | K1093: 2016 | L1093: =IF(OR(MID(B1093,3,1)="H",MID(B1093,3,1)="S"),MID(B1093,4,3),MID(B1093,3,3)) -> 005 | M1093: =_xlfn.XLOOKUP(_2015_2016_append_[[#This Row],[Job_code]],Analytics_mindset_case_studies_IntegrateCo_jobcodes[Code_text],Analytics_mindset_case_studies_IntegrateCo_jobcodes[Job_Description],"",0) -> Installation | N1093: =IF(OR(MID(B1093,3,1)="H",MID(B1093,3,1)="S"),MID(B1093,3,1),"") | O1093: =IFERROR(VLOOKUP(_2015_2016_append_[[#This Row],[Emp_Name]],Analytics_mindset_case_studies_IntegrateCo_locations[#All],2,FALSE),"") | P1093: =_2015_2016_append_[[#This Row],[Reg_Hrs]]+_2015_2016_append_[[#This Row],[OT_Hrs]] -> 21 | Q1093: 1
A1094: 413 | B1094: 16005 | C1094: Lynette Alvarez | D1094: 6 | E1094: 0 | F1094: 90 | G1094: 668 | H1094: 51 | I1094: 208 | J1094: 149 | K1094: 2016 | L1094: =IF(OR(MID(B1094,3,1)="H",MID(B1094,3,1)="S"),MID(B1094,4,3),MID(B1094,3,3)) -> 005 | M1094: =_xlfn.XLOOKUP(_2015_2016_append_[[#This Row],[Job_code]],Analytics_mindset_case_studies_IntegrateCo_jobcodes[Code_text],Analytics_mindset_case_studies_IntegrateCo_jobcodes[Job_Description],"",0) -> Installation | N1094: =IF(OR(MID(B1094,3,1)="H",MID(B1094,3,1)="S"),MID(B1094,3,1),"") | O1094: =IFERROR(VLOOKUP(_2015_2016_append_[[#This Row],[Emp_Name]],Analytics_mindset_case_studies_IntegrateCo_locations[#All],2,FALSE),"") -> 1 | P1094: =_2015_2016_append_[[#This Row],[Reg_Hrs]]+_2015_2016_append_[[#This Row],[OT_Hrs]] -> 6 | Q1094: 1
A1095: 192 | B1095: 16005 | C1095: Mike Briggs | D1095: 22 | E1095: 0 | F1095: 312 | G1095: 2124 | H1095: 8 | I1095: 702 | J1095: 32 | K1095: 2016 | L1095: =IF(OR(MID(B1095,3,1)="H",MID(B1095,3,1)="S"),MID(B1095,4,3),MID(B1095,3,3)) -> 005 | M1095: =_xlfn.XLOOKUP(_2015_2016_append_[[#This Row],[Job_code]],Analytics_mindset_case_studies_IntegrateCo_jobcodes[Code_text],Analytics_mindset_case_studies_IntegrateCo_jobcodes[Job_Description],"",0) -> Installation | N1095: =IF(OR(MID(B1095,3,1)="H",MID(B1095,3,1)="S"),MID(B1095,3,1),"") | O1095: =IFERROR(VLOOKUP(_2015_2016_append_[[#This Row],[Emp_Name]],Analytics_mindset_case_studies_IntegrateCo_locations[#All],2,FALSE),"") -> 2 | P1095: =_2015_2016_append_[[#This Row],[Reg_Hrs]]+_2015_2016_append_[[#This Row],[OT_Hrs]] -> 22 | Q1095: 1
A1096: 133 | B1096: 16005 | C1096: Geneva Moody | D1096: 23 | E1096: 0 | F1096: 333 | G1096: 2434 | H1096: 32 | I1096: 719 | J1096: 521 | K1096: 2016 | L1096: =IF(OR(MID(B1096,3,1)="H",MID(B1096,3,1)="S"),MID(B1096,4,3),MID(B1096,3,3)) -> 005 | M1096: =_xlfn.XLOOKUP(_2015_2016_append_[[#This Row],[Job_code]],Analytics_mindset_case_studies_IntegrateCo_jobcodes[Code_text],Analytics_mindset_case_studies_IntegrateCo_jobcodes[Job_Description],"",0) -> Installation | N1096: =IF(OR(MID(B1096,3,1)="H",MID(B1096,3,1)="S"),MID(B1096,3,1),"") | O1096: =IFERROR(VLOOKUP(_2015_2016_append_[[#This Row],[Emp_Name]],Analytics_mindset_case_studies_IntegrateCo_locations[#All],2,FALSE),"") -> 1 | P1096: =_2015_2016_append_[[#This Row],[Reg_Hrs]]+_2015_2016_append_[[#This Row],[OT_Hrs]] -> 23 | Q1096: 1
A1097: 195 | B1097: 16005 | C1097: Al Ramos | D1097: 23 | E1097: 0 | F1097: 345 | G1097: 2476 | H1097: 22 | I1097: 481 | J1097: 94 | K1097: 2016 | L1097: =IF(OR(MID(B1097,3,1)="H",MID(B1097,3,1)="S"),MID(B1097,4,3),MID(B1097,3,3)) -> 005 | M1097: =_xlfn.XLOOKUP(_2015_2016_append_[[#This Row],[Job_code]],Analytics_mindset_case_studies_IntegrateCo_jobcodes[Code_text],Analytics_mindset_case_studies_IntegrateCo_jobcodes[Job_Description],"",0) -> Installation | N1097: =IF(OR(MID(B1097,3,1)="H",MID(B1097,3,1)="S"),MID(B1097,3,1),"") | O1097: =IFERROR(VLOOKUP(_2015_2016_append_[[#This Row],[Emp_Name]],Analytics_mindset_case_studies_IntegrateCo_locations[#All],2,FALSE),"") -> 2 | P1097: =_2015_2016_append_[[#This Row],[Reg_Hrs]]+_2015_2016_append_[[#This Row],[OT_Hrs]] -> 23 | Q1097: 1
A1098: 199 | B1098: 16005 | C1098: Nettie Stevens | D1098: 24 | E1098: 0 | F1098: 333 | G1098: 236 | H1098: 24 | I1098: 48 | J1098: 499 | K1098: 2016 | L1098: =IF(OR(MID(B1098,3,1)="H",MID(B1098,3,1)="S"),MID(B1098,4,3),MID(B1098,3,3)) -> 005 | M1098: =_xlfn.XLOOKUP(_2015_2016_append_[[#This Row],[Job_code]],Analytics_mindset_case_studies_IntegrateCo_jobcodes[Code_text],Analytics_mindset_case_studies_IntegrateCo_jobcodes[Job_Description],"",0) -> Installation | N1098: =IF(OR(MID(B1098,3,1)="H",MID(B1098,3,1)="S"),MID(B1098,3,1),"") | O1098: =IFERROR(VLOOKUP(_2015_2016_append_[[#This Row],[Emp_Name]],Analytics_mindset_case_studies_IntegrateCo_locations[#All],2,FALSE),"") -> 2 | P1098: =_2015_2016_append_[[#This Row],[Reg_Hrs]]+_2015_2016_append_[[#This Row],[OT_Hrs]] -> 24 | Q1098: 1
A1099: 27 | B1099: 16005 | C1099: Cindy Lunt | D1099: 23 | E1099: 0 | F1099: 315 | G1099: 2195 | H1099: 35 | I1099: 65 | J1099: 464 | K1099: 2016 | L1099: =IF(OR(MID(B1099,3,1)="H",MID(B1099,3,1)="S"),MID(B1099,4,3),MID(B1099,3,3)) -> 005 | M1099: =_xlfn.XLOOKUP(_2015_2016_append_[[#This Row],[Job_code]],Analytics_mindset_case_studies_IntegrateCo_jobcodes[Code_text],Analytics_mindset_case_studies_IntegrateCo_jobcodes[Job_Description],"",0) -> Installation | N1099: =IF(OR(MID(B1099,3,1)="H",MID(B1099,3,1)="S"),MID(B1099,3,1),"") | O1099: =IFERROR(VLOOKUP(_2015_2016_append_[[#This Row],[Emp_Name]],Analytics_mindset_case_studies_IntegrateCo_locations[#All],2,FALSE),"") -> 1 | P1099: =_2015_2016_append_[[#This Row],[Reg_Hrs]]+_2015_2016_append_[[#This Row],[OT_Hrs]] -> 23 | Q1099: 1
A1100: 201 | B1100: 16005 | C1100: Michele Lee | D1100: 23 | E1100: 0 | F1100: 324 | G1100: 2486 | H1100: 4 | I1100: 773 | J1100: 53 | K1100: 2016 | L1100: =IF(OR(MID(B1100,3,1)="H",MID(B1100,3,1)="S"),MID(B1100,4,3),MID(B1100,3,3)) -> 005 | M1100: =_xlfn.XLOOKUP(_2015_2016_append_[[#This Row],[Job_code]],Analytics_mindset_case_studies_IntegrateCo_jobcodes[Code_text],Analytics_mindset_case_studies_IntegrateCo_jobcodes[Job_Description],"",0) -> Installation | N1100: =IF(OR(MID(B1100,3,1)="H",MID(B1100,3,1)="S"),MID(B1100,3,1),"") | O1100: =IFERROR(VLOOKUP(_2015_2016_append_[[#This Row],[Emp_Name]],Analytics_mindset_case_studies_IntegrateCo_locations[#All],2,FALSE),"") -> 1 | P1100: =_2015_2016_append_[[#This Row],[Reg_Hrs]]+_2015_2016_append_[[#This Row],[OT_Hrs]] -> 23 | Q1100: 1
A1101: 203 | B1101: 16005 | C1101: Helen Paul | D1101: 24 | E1101: 0 | F1101: 492 | G1101: 3568 | H1101: 23 | I1101: 576 | J1101: 62 | K1101: 2016 | L1101: =IF(OR(MID(B1101,3,1)="H",MID(B1101,3,1)="S"),MID(B1101,4,3),MID(B1101,3,3)) -> 005 | M1101: =_xlfn.XLOOKUP(_2015_2016_append_[[#This Row],[Job_code]],Analytics_mindset_case_studies_IntegrateCo_jobcodes[Code_text],Analytics_mindset_case_studies_IntegrateCo_jobcodes[Job_Description],"",0) -> Installation | N1101: =IF(OR(MID(B1101,3,1)="H",MID(B1101,3,1)="S"),MID(B1101,3,1),"") | O1101: =IFERROR(VLOOKUP(_2015_2016_append_[[#This Row],[Emp_Name]],Analytics_mindset_case_studies_IntegrateCo_locations[#All],2,FALSE),"") -> 1 | P1101: =_2015_2016_append_[[#This Row],[Reg_Hrs]]+_2015_2016_append_[[#This Row],[OT_Hrs]] -> 24 | Q1101: 1
A1102: 259 | B1102: 16005 | C1102: Beulah Gibbs | D1102: 23 | E1102: 0 | F1102: 321 | G1102: 2384 | H1102: 45 | I1102: 751 | J1102: 519 | K1102: 2016 | L1102: =IF(OR(MID(B1102,3,1)="H",MID(B1102,3,1)="S"),MID(B1102,4,3),MID(B1102,3,3)) -> 005 | M1102: =_xlfn.XLOOKUP(_2015_2016_append_[[#This Row],[Job_code]],Analytics_mindset_case_studies_IntegrateCo_jobcodes[Code_text],Analytics_mindset_case_studies_IntegrateCo_jobcodes[Job_Description],"",0) -> Installation | N1102: =IF(OR(MID(B1102,3,1)="H",MID(B1102,3,1)="S"),MID(B1102,3,1),"") | O1102: =IFERROR(VLOOKUP(_2015_2016_append_[[#This Row],[Emp_Name]],Analytics_mindset_case_studies_IntegrateCo_locations[#All],2,FALSE),"") -> 2 | P1102: =_2015_2016_append_[[#This Row],[Reg_Hrs]]+_2015_2016_append_[[#This Row],[OT_Hrs]] -> 23 | Q1102: 1
A1103: 320 | B1103: 16005 | C1103: Terry Moreno | D1103: 24 | E1103: 0 | F1103: 327 | G1103: 2501 | H1103: 17 | I1103: 456 | J1103: 557 | K1103: 2016 | L1103: =IF(OR(MID(B1103,3,1)="H",MID(B1103,3,1)="S"),MID(B1103,4,3),MID(B1103,3,3)) -> 005 | M1103: =_xlfn.XLOOKUP(_2015_2016_append_[[#This Row],[Job_code]],Analytics_mindset_case_studies_IntegrateCo_jobcodes[Code_text],Analytics_mindset_case_studies_IntegrateCo_jobcodes[Job_Description],"",0) -> Installation | N1103: =IF(OR(MID(B1103,3,1)="H",MID(B1103,3,1)="S"),MID(B1103,3,1),"") | O1103: =IFERROR(VLOOKUP(_2015_2016_append_[[#This Row],[Emp_Name]],Analytics_mindset_case_studies_IntegrateCo_locations[#All],2,FALSE),"") -> 2 | P1103: =_2015_2016_append_[[#This Row],[Reg_Hrs]]+_2015_2016_append_[[#This Row],[OT_Hrs]] -> 24 | Q1103: 1
A1104: 396 | B1104: 16005 | C1104: Darryl Burgess | D1104: 24 | E1104: 0 | F1104: 345 | G1104: 2636 | H1104: 37 | I1104: 816 | J1104: 1633 | K1104: 2016 | L1104: =IF(OR(MID(B1104,3,1)="H",MID(B1104,3,1)="S"),MID(B1104,4,3),MID(B1104,3,3)) -> 005 | M1104: =_xlfn.XLOOKUP(_2015_2016_append_[[#This Row],[Job_code]],Analytics_mindset_case_studies_IntegrateCo_jobcodes[Code_text],Analytics_mindset_case_studies_IntegrateCo_jobcodes[Job_Description],"",0) -> Installation | N1104: =IF(OR(MID(B1104,3,1)="H",MID(B1104,3,1)="S"),MID(B1104,3,1),"") | O1104: =IFERROR(VLOOKUP(_2015_2016_append_[[#This Row],[Emp_Name]],Analytics_mindset_case_studies_IntegrateCo_locations[#All],2,FALSE),"") -> 1 | P1104: =_2015_2016_append_[[#This Row],[Reg_Hrs]]+_2015_2016_append_[[#This Row],[OT_Hrs]] -> 24 | Q1104: 1
A1105: 409 | B1105: 16005 | C1105: Sally Bailey | D1105: 20 | E1105: 0 | F1105: 282 | G1105: 2158 | H1105: 44 | I1105: 678 | J1105: 466 | K1105: 2016 | L1105: =IF(OR(MID(B1105,3,1)="H",MID(B1105,3,1)="S"),MID(B1105,4,3),MID(B1105,3,3)) -> 005 | M1105: =_xlfn.XLOOKUP(_2015_2016_append_[[#This Row],[Job_code]],Analytics_mindset_case_studies_IntegrateCo_jobcodes[Code_text],Analytics_mindset_case_studies_IntegrateCo_jobcodes[Job_Description],"",0) -> Installation | N1105: =IF(OR(MID(B1105,3,1)="H",MID(B1105,3,1)="S"),MID(B1105,3,1),"") | O1105: =IFERROR(VLOOKUP(_2015_2016_append_[[#This Row],[Emp_Name]],Analytics_mindset_case_studies_IntegrateCo_locations[#All],2,FALSE),"") -> 2 | P1105: =_2015_2016_append_[[#This Row],[Reg_Hrs]]+_2015_2016_append_[[#This Row],[OT_Hrs]] -> 20 | Q1105: 1
B1106: 16005 | D1106: 2 | E1106: 0 | F1106: 30 | G1106: 23 | H1106: 18 | I1106: 72 | J1106: 48 | K1106: 2016 | L1106: =IF(OR(MID(B1106,3,1)="H",MID(B1106,3,1)="S"),MID(B1106,4,3),MID(B1106,3,3)) -> 005 | M1106: =_xlfn.XLOOKUP(_2015_2016_append_[[#This Row],[Job_code]],Analytics_mindset_case_studies_IntegrateCo_jobcodes[Code_text],Analytics_mindset_case_studies_IntegrateCo_jobcodes[Job_Description],"",0) -> Installation | N1106: =IF(OR(MID(B1106,3,1)="H",MID(B1106,3,1)="S"),MID(B1106,3,1),"") | O1106: =IFERROR(VLOOKUP(_2015_2016_append_[[#This Row],[Emp_Name]],Analytics_mindset_case_studies_IntegrateCo_locations[#All],2,FALSE),"") | P1106: =_2015_2016_append_[[#This Row],[Reg_Hrs]]+_2015_2016_append_[[#This Row],[OT_Hrs]] -> 2 | Q1106: 1
A1107: 210 | B1107: 16005 | C1107: Kenny Robertson | D1107: 22 | E1107: 0 | F1107: 276 | G1107: 1958 | H1107: 51 | I1107: 1234 | J1107: 757 | K1107: 2016 | L1107: =IF(OR(MID(B1107,3,1)="H",MID(B1107,3,1)="S"),MID(B1107,4,3),MID(B1107,3,3)) -> 005 | M1107: =_xlfn.XLOOKUP(_2015_2016_append_[[#This Row],[Job_code]],Analytics_mindset_case_studies_IntegrateCo_jobcodes[Code_text],Analytics_mindset_case_studies_IntegrateCo_jobcodes[Job_Description],"",0) -> Installation | N1107: =IF(OR(MID(B1107,3,1)="H",MID(B1107,3,1)="S"),MID(B1107,3,1),"") | O1107: =IFERROR(VLOOKUP(_2015_2016_append_[[#This Row],[Emp_Name]],Analytics_mindset_case_studies_IntegrateCo_locations[#All],2,FALSE),"") -> 1 | P1107: =_2015_2016_append_[[#This Row],[Reg_Hrs]]+_2015_2016_append_[[#This Row],[OT_Hrs]] -> 22 | Q1107: 1
A1108: 276 | B1108: 16005 | C1108: Morris Glover | D1108: 18 | E1108: 0 | F1108: 252 | G1108: 1825 | H1108: 48 | I1108: 575 | J1108: 412 | K1108: 2016 | L1108: =IF(OR(MID(B1108,3,1)="H",MID(B1108,3,1)="S"),MID(B1108,4,3),MID(B1108,3,3)) -> 005 | M1108: =_xlfn.XLOOKUP(_2015_2016_append_[[#This Row],[Job_code]],Analytics_mindset_case_studies_IntegrateCo_jobcodes[Code_text],Analytics_mindset_case_studies_IntegrateCo_jobcodes[Job_Description],"",0) -> Installation | N1108: =IF(OR(MID(B1108,3,1)="H",MID(B1108,3,1)="S"),MID(B1108,3,1),"") | O1108: =IFERROR(VLOOKUP(_2015_2016_append_[[#This Row],[Emp_Name]],Analytics_mindset_case_studies_IntegrateCo_locations[#All],2,FALSE),"") -> 1 | P1108: =_2015_2016_append_[[#This Row],[Reg_Hrs]]+_2015_2016_append_[[#This Row],[OT_Hrs]] -> 18 | Q1108: 1
A1109: 204 | B1109: 16005 | C1109: Deborah Bennett | D1109: 9 | E1109: 0 | F1109: 90 | G1109: 653 | H1109: 32 | I1109: 152 | J1109: 148 | K1109: 2016 | L1109: =IF(OR(MID(B1109,3,1)="H",MID(B1109,3,1)="S"),MID(B1109,4,3),MID(B1109,3,3)) -> 005 | M1109: =_xlfn.XLOOKUP(_2015_2016_append_[[#This Row],[Job_code]],Analytics_mindset_case_studies_IntegrateCo_jobcodes[Code_text],Analytics_mindset_case_studies_IntegrateCo_jobcodes[Job_Description],"",0) -> Installation | N1109: =IF(OR(MID(B1109,3,1)="H",MID(B1109,3,1)="S"),MID(B1109,3,1),"") | O1109: =IFERROR(VLOOKUP(_2015_2016_append_[[#This Row],[Emp_Name]],Analytics_mindset_case_studies_IntegrateCo_locations[#All],2,FALSE),"") -> 1 | P1109: =_2015_2016_append_[[#This Row],[Reg_Hrs]]+_2015_2016_append_[[#This Row],[OT_Hrs]] -> 9 | Q1109: 1
A1110: 411 | B1110: 16005 | C1110: Claire Edwards | D1110: 23 | E1110: 0 | F1110: 339 | G1110: 2592 | H1110: 52 | I1110: 811 | J1110: 524 | K1110: 2016 | L1110: =IF(OR(MID(B1110,3,1)="H",MID(B1110,3,1)="S"),MID(B1110,4,3),MID(B1110,3,3)) -> 005 | M1110: =_xlfn.XLOOKUP(_2015_2016_append_[[#This Row],[Job_code]],Analytics_mindset_case_studies_IntegrateCo_jobcodes[Code_text],Analytics_mindset_case_studies_IntegrateCo_jobcodes[Job_Description],"",0) -> Installation | N1110: =IF(OR(MID(B1110,3,1)="H",MID(B1110,3,1)="S"),MID(B1110,3,1),"") | O1110: =IFERROR(VLOOKUP(_2015_2016_append_[[#This Row],[Emp_Name]],Analytics_mindset_case_studies_IntegrateCo_locations[#All],2,FALSE),"") -> 1 | P1110: =_2015_2016_append_[[#This Row],[Reg_Hrs]]+_2015_2016_append_[[#This Row],[OT_Hrs]] -> 23 | Q1110: 1
A1111: 402 | B1111: 16005 | C1111: Gwendolyn Alvarado | D1111: 22 | E1111: 0 | F1111: 330 | G1111: 2322 | H1111: 67 | I1111: 971 | J1111: 1567 | K1111: 2016 | L1111: =IF(OR(MID(B1111,3,1)="H",MID(B1111,3,1)="S"),MID(B1111,4,3),MID(B1111,3,3)) -> 005 | M1111: =_xlfn.XLOOKUP(_2015_2016_append_[[#This Row],[Job_code]],Analytics_mindset_case_studies_IntegrateCo_jobcodes[Code_text],Analytics_mindset_case_studies_IntegrateCo_jobcodes[Job_Description],"",0) -> Installation | N1111: =IF(OR(MID(B1111,3,1)="H",MID(B1111,3,1)="S"),MID(B1111,3,1),"") | O1111: =IFERROR(VLOOKUP(_2015_2016_append_[[#This Row],[Emp_Name]],Analytics_mindset_case_studies_IntegrateCo_locations[#All],2,FALSE),"") -> 2 | P1111: =_2015_2016_append_[[#This Row],[Reg_Hrs]]+_2015_2016_append_[[#This Row],[OT_Hrs]] -> 22 | Q1111: 1
A1112: 153 | B1112: 16005 | C1112: Lynne Soto | D1112: 22 | E1112: 0 | F1112: 303 | G1112: 2244 | H1112: 53 | I1112: 707 | J1112: 484 | K1112: 2016 | L1112: =IF(OR(MID(B1112,3,1)="H",MID(B1112,3,1)="S"),MID(B1112,4,3),MID(B1112,3,3)) -> 005 | M1112: =_xlfn.XLOOKUP(_2015_2016_append_[[#This Row],[Job_code]],Analytics_mindset_case_studies_IntegrateCo_jobcodes[Code_text],Analytics_mindset_case_studies_IntegrateCo_jobcodes[Job_Description],"",0) -> Installation | N1112: =IF(OR(MID(B1112,3,1)="H",MID(B1112,3,1)="S"),MID(B1112,3,1),"") | O1112: =IFERROR(VLOOKUP(_2015_2016_append_[[#This Row],[Emp_Name]],Analytics_mindset_case_studies_IntegrateCo_locations[#All],2,FALSE),"") -> 2 | P1112: =_2015_2016_append_[[#This Row],[Reg_Hrs]]+_2015_2016_append_[[#This Row],[OT_Hrs]] -> 22 | Q1112: 1
A1113: 11 | B1113: 16005 | C1113: Earnest Drake | D1113: 24 | E1113: 0 | F1113: 329 | G1113: 2434 | H1113: 28 | I1113: 663 | J1113: 491 | K1113: 2016 | L1113: =IF(OR(MID(B1113,3,1)="H",MID(B1113,3,1)="S"),MID(B1113,4,3),MID(B1113,3,3)) -> 005 | M1113: =_xlfn.XLOOKUP(_2015_2016_append_[[#This Row],[Job_code]],Analytics_mindset_case_studies_IntegrateCo_jobcodes[Code_text],Analytics_mindset_case_studies_IntegrateCo_jobcodes[Job_Description],"",0) -> Installation | N1113: =IF(OR(MID(B1113,3,1)="H",MID(B1113,3,1)="S"),MID(B1113,3,1),"") | O1113: =IFERROR(VLOOKUP(_2015_2016_append_[[#This Row],[Emp_Name]],Analytics_mindset_case_studies_IntegrateCo_locations[#All],2,FALSE),"") -> 1 | P1113: =_2015_2016_append_[[#This Row],[Reg_Hrs]]+_2015_2016_append_[[#This Row],[OT_Hrs]] -> 24 | Q1113: 1
A1114: 304 | B1114: 16005 | C1114: Allen Price | D1114: 4 | E1114: 0 | F1114: 60 | G1114: 44 | H1114: 0 | I1114: 136 | J1114: 97 | K1114: 2016 | L1114: =IF(OR(MID(B1114,3,1)="H",MID(B1114,3,1)="S"),MID(B1114,4,3),MID(B1114,3,3)) -> 005 | M1114: =_xlfn.XLOOKUP(_2015_2016_append_[[#This Row],[Job_code]],Analytics_mindset_case_studies_IntegrateCo_jobcodes[Code_text],Analytics_mindset_case_studies_IntegrateCo_jobcodes[Job_Description],"",0) -> Installation | N1114: =IF(OR(MID(B1114,3,1)="H",MID(B1114,3,1)="S"),MID(B1114,3,1),"") | O1114: =IFERROR(VLOOKUP(_2015_2016_append_[[#This Row],[Emp_Name]],Analytics_mindset_case_studies_IntegrateCo_locations[#All],2,FALSE),"") -> 1 | P1114: =_2015_2016_append_[[#This Row],[Reg_Hrs]]+_2015_2016_append_[[#This Row],[OT_Hrs]] -> 4 | Q1114: 1
A1115: 106 | B1115: 16005 | C1115: Allan Wood | D1115: 1 | E1115: 0 | F1115: 15 | G1115: 108 | H1115: 2 | I1115: 33 | J1115: 2 | K1115: 2016 | L1115: =IF(OR(MID(B1115,3,1)="H",MID(B1115,3,1)="S"),MID(B1115,4,3),MID(B1115,3,3)) -> 005 | M1115: =_xlfn.XLOOKUP(_2015_2016_append_[[#This Row],[Job_code]],Analytics_mindset_case_studies_IntegrateCo_jobcodes[Code_text],Analytics_mindset_case_studies_IntegrateCo_jobcodes[Job_Description],"",0) -> Installation | N1115: =IF(OR(MID(B1115,3,1)="H",MID(B1115,3,1)="S"),MID(B1115,3,1),"") | O1115: =IFERROR(VLOOKUP(_2015_2016_append_[[#This Row],[Emp_Name]],Analytics_mindset_case_studies_IntegrateCo_locations[#All],2,FALSE),"") -> 1 | P1115: =_2015_2016_append_[[#This Row],[Reg_Hrs]]+_2015_2016_append_[[#This Row],[OT_Hrs]] -> 1 | Q1115: 1
A1116: 37 | B1116: 16005 | C1116: Kirk Byrd | D1116: 18 | E1116: 0 | F1116: 267 | G1116: 1826 | H1116: 31 | I1116: 573 | J1116: 43 | K1116: 2016 | L1116: =IF(OR(MID(B1116,3,1)="H",MID(B1116,3,1)="S"),MID(B1116,4,3),MID(B1116,3,3)) -> 005 | M1116: =_xlfn.XLOOKUP(_2015_2016_append_[[#This Row],[Job_code]],Analytics_mindset_case_studies_IntegrateCo_jobcodes[Code_text],Analytics_mindset_case_studies_IntegrateCo_jobcodes[Job_Description],"",0) -> Installation | N1116: =IF(OR(MID(B1116,3,1)="H",MID(B1116,3,1)="S"),MID(B1116,3,1),"") | O1116: =IFERROR(VLOOKUP(_2015_2016_append_[[#This Row],[Emp_Name]],Analytics_mindset_case_studies_IntegrateCo_locations[#All],2,FALSE),"") -> 2 | P1116: =_2015_2016_append_[[#This Row],[Reg_Hrs]]+_2015_2016_append_[[#This Row],[OT_Hrs]] -> 18 | Q1116: 1
A1117: 180 | B1117: 16005 | C1117: Elisa Warren | D1117: 24 | E1117: 0 | F1117: 339 | G1117: 2256 | H1117: 42 | I1117: 712 | J1117: 557 | K1117: 2016 | L1117: =IF(OR(MID(B1117,3,1)="H",MID(B1117,3,1)="S"),MID(B1117,4,3),MID(B1117,3,3)) -> 005 | M1117: =_xlfn.XLOOKUP(_2015_2016_append_[[#This Row],[Job_code]],Analytics_mindset_case_studies_IntegrateCo_jobcodes[Code_text],Analytics_mindset_case_studies_IntegrateCo_jobcodes[Job_Description],"",0) -> Installation | N1117: =IF(OR(MID(B1117,3,1)="H",MID(B1117,3,1)="S"),MID(B1117,3,1),"") | O1117: =IFERROR(VLOOKUP(_2015_2016_append_[[#This Row],[Emp_Name]],Analytics_mindset_case_studies_IntegrateCo_locations[#All],2,FALSE),"") -> 2 | P1117: =_2015_2016_append_[[#This Row],[Reg_Hrs]]+_2015_2016_append_[[#This Row],[OT_Hrs]] -> 24 | Q1117: 1
A1118: 352 | B1118: 16005 | C1118: Myra Vega | D1118: 21 | E1118: 0 | F1118: 318 | G1118: 2152 | H1118: 52 | I1118: 671 | J1118: 49 | K1118: 2016 | L1118: =IF(OR(MID(B1118,3,1)="H",MID(B1118,3,1)="S"),MID(B1118,4,3),MID(B1118,3,3)) -> 005 | M1118: =_xlfn.XLOOKUP(_2015_2016_append_[[#This Row],[Job_code]],Analytics_mindset_case_studies_IntegrateCo_jobcodes[Code_text],Analytics_mindset_case_studies_IntegrateCo_jobcodes[Job_Description],"",0) -> Installation | N1118: =IF(OR(MID(B1118,3,1)="H",MID(B1118,3,1)="S"),MID(B1118,3,1),"") | O1118: =IFERROR(VLOOKUP(_2015_2016_append_[[#This Row],[Emp_Name]],Analytics_mindset_case_studies_IntegrateCo_locations[#All],2,FALSE),"") -> 1 | P1118: =_2015_2016_append_[[#This Row],[Reg_Hrs]]+_2015_2016_append_[[#This Row],[OT_Hrs]] -> 21 | Q1118: 1
... A1125: 168 | B1125: 16005 | C1125: Brittany Carlson | D1125: 17 | E1125: 0 | F1125: 255 | G1125: 1892 | H1125: 33 | I1125: 602 | J1125: 419 | K1125: 2016 | L1125: =IF(OR(MID(B1125,3,1)="H",MID(B1125,3,1)="S"),MID(B1125,4,3),MID(B1125,3,3)) -> 005 | M1125: =_xlfn.XLOOKUP(_2015_2016_append_[[#This Row],[Job_code]],Analytics_mindset_case_studies_IntegrateCo_jobcodes[Code_text],Analytics_mindset_case_studies_IntegrateCo_jobcodes[Job_Description],"",0) -> Installation | N1125: =IF(OR(MID(B1125,3,1)="H",MID(B1125,3,1)="S"),MID(B1125,3,1),"") | O1125: =IFERROR(VLOOKUP(_2015_2016_append_[[#This Row],[Emp_Name]],Analytics_mindset_case_studies_IntegrateCo_locations[#All],2,FALSE),"") -> 2 | P1125: =_2015_2016_append_[[#This Row],[Reg_Hrs]]+_2015_2016_append_[[#This Row],[OT_Hrs]] -> 17 | Q1125: 1
B1126: 16005 | D1126: 8 | E1126: 0 | F1126: 120 | G1126: 916 | H1126: 36 | I1126: 286 | J1126: 19 | K1126: 2016 | L1126: =IF(OR(MID(B1126,3,1)="H",MID(B1126,3,1)="S"),MID(B1126,4,3),MID(B1126,3,3)) -> 005 | M1126: =_xlfn.XLOOKUP(_2015_2016_append_[[#This Row],[Job_code]],Analytics_mindset_case_studies_IntegrateCo_jobcodes[Code_text],Analytics_mindset_case_studies_IntegrateCo_jobcodes[Job_Description],"",0) -> Installation | N1126: =IF(OR(MID(B1126,3,1)="H",MID(B1126,3,1)="S"),MID(B1126,3,1),"") | O1126: =IFERROR(VLOOKUP(_2015_2016_append_[[#This Row],[Emp_Name]],Analytics_mindset_case_studies_IntegrateCo_locations[#All],2,FALSE),"") | P1126: =_2015_2016_append_[[#This Row],[Reg_Hrs]]+_2015_2016_append_[[#This Row],[OT_Hrs]] -> 8 | Q1126: 1
A1127: 399 | B1127: 16005 | C1127: Yvette Miller | D1127: 23 | E1127: 0 | F1127: 345 | G1127: 2644 | H1127: 45 | I1127: 829 | J1127: 9 | K1127: 2016 | L1127: =IF(OR(MID(B1127,3,1)="H",MID(B1127,3,1)="S"),MID(B1127,4,3),MID(B1127,3,3)) -> 005 | M1127: =_xlfn.XLOOKUP(_2015_2016_append_[[#This Row],[Job_code]],Analytics_mindset_case_studies_IntegrateCo_jobcodes[Code_text],Analytics_mindset_case_studies_IntegrateCo_jobcodes[Job_Description],"",0) -> Installation | N1127: =IF(OR(MID(B1127,3,1)="H",MID(B1127,3,1)="S"),MID(B1127,3,1),"") | O1127: =IFERROR(VLOOKUP(_2015_2016_append_[[#This Row],[Emp_Name]],Analytics_mindset_case_studies_IntegrateCo_locations[#All],2,FALSE),"") -> 2 | P1127: =_2015_2016_append_[[#This Row],[Reg_Hrs]]+_2015_2016_append_[[#This Row],[OT_Hrs]] -> 23 | Q1127: 1
A1128: 381 | B1128: 16005 | C1128: Frankie Mcdaniel | D1128: 24 | E1128: 0 | F1128: 360 | G1128: 2343 | H1128: 38 | I1128: 702 | J1128: 98 | K1128: 2016 | L1128: =IF(OR(MID(B1128,3,1)="H",MID(B1128,3,1)="S"),MID(B1128,4,3),MID(B1128,3,3)) -> 005 | M1128: =_xlfn.XLOOKUP(_2015_2016_append_[[#This Row],[Job_code]],Analytics_mindset_case_studies_IntegrateCo_jobcodes[Code_text],Analytics_mindset_case_studies_IntegrateCo_jobcodes[Job_Description],"",0) -> Installation | N1128: =IF(OR(MID(B1128,3,1)="H",MID(B1128,3,1)="S"),MID(B1128,3,1),"") | O1128: =IFERROR(VLOOKUP(_2015_2016_append_[[#This Row],[Emp_Name]],Analytics_mindset_case_studies_IntegrateCo_locations[#All],2,FALSE),"") -> 1 | P1128: =_2015_2016_append_[[#This Row],[Reg_Hrs]]+_2015_2016_append_[[#This Row],[OT_Hrs]] -> 24 | Q1128: 1
...

Sheet 2015Transformed Data
A1: Emp_No | B1: Job | C1: Emp_Name | D1: Reg_Hrs | E1: OT_Hrs | F1: Gross_Wages | G1: Fica_Medc | H1: Futa | I1: Suta | J1: Work_Comp | K1: YEAR | L1: Job_code | M1: Department | N1: Location | O1: YEAR2
A2: 195 | B2: 14005 | C2: Al Ramos | D2: 0 | E2: 0 | F2: 0 | G2: 214 | H2: 16 | I2: 68 | J2: 8 | K2: 2015 | L2: =IF(OR(MID(B2,3,1)="H",MID(B2,3,1)="S"),MID(B2,4,3),MID(B2,3,3)) -> 005 | M2: =IF(OR(MID(B2,3,1)="H",MID(B2,3,1)="S"),MID(B2,3,1),"") | N2: =IF(RIGHT(B2,2)="SG","SG",IF(RIGHT(B2,1)="B","B","")) | O2: 2015
A3: 195 | B3: 14H002 | C3: Al Ramos | D3: 25 | E3: 0 | F3: 70558 | G3: 5047 | H3: 396 | I3: 1583 | J3: 183 | K3: 2015 | L3: =IF(OR(MID(B3,3,1)="H",MID(B3,3,1)="S"),MID(B3,4,3),MID(B3,3,3)) -> 002 | M3: =IF(OR(MID(B3,3,1)="H",MID(B3,3,1)="S"),MID(B3,3,1),"") -> H | N3: =IF(RIGHT(B3,2)="SG","SG",IF(RIGHT(B3,1)="B","B","")) | O3: 2015
A4: 195 | B4: 14H010 | C4: Al Ramos | D4: 0 | E4: 0 | F4: 0 | G4: 3229 | H4: 253 | I4: 1013 | J4: 117 | K4: 2015 | L4: =IF(OR(MID(B4,3,1)="H",MID(B4,3,1)="S"),MID(B4,4,3),MID(B4,3,3)) -> 010 | M4: =IF(OR(MID(B4,3,1)="H",MID(B4,3,1)="S"),MID(B4,3,1),"") -> H | N4: =IF(RIGHT(B4,2)="SG","SG",IF(RIGHT(B4,1)="B","B","")) | O4: 2015
A5: 106 | B5: 14002 | C5: Allan Wood | D5: 19 | E5: 0 | F5: 380 | G5: 2907 | H5: 228 | I5: 912 | J5: 608 | K5: 2015 | L5: =IF(OR(MID(B5,3,1)="H",MID(B5,3,1)="S"),MID(B5,4,3),MID(B5,3,3)) -> 002 | M5: =IF(OR(MID(B5,3,1)="H",MID(B5,3,1)="S"),MID(B5,3,1),"") | N5: =IF(RIGHT(B5,2)="SG","SG",IF(RIGHT(B5,1)="B","B","")) | O5: 2015
A6: 106 | B6: 14005 | C6: Allan Wood | D6: 0 | E6: 0 | F6: 0 | G6: 230 | H6: 18 | I6: 72 | J6: 48 | K6: 2015 | L6: =IF(OR(MID(B6,3,1)="H",MID(B6,3,1)="S"),MID(B6,4,3),MID(B6,3,3)) -> 005 | M6: =IF(OR(MID(B6,3,1)="H",MID(B6,3,1)="S"),MID(B6,3,1),"") | N6: =IF(RIGHT(B6,2)="SG","SG",IF(RIGHT(B6,1)="B","B","")) | O6: 2015
A7: 106 | B7: 14010 | C7: Allan Wood | D7: 0 | E7: 0 | F7: 0 | G7: 2448 | H7: 192 | I7: 768 | J7: 512 | K7: 2015 | L7: =IF(OR(MID(B7,3,1)="H",MID(B7,3,1)="S"),MID(B7,4,3),MID(B7,3,3)) -> 010 | M7: =IF(OR(MID(B7,3,1)="H",MID(B7,3,1)="S"),MID(B7,3,1),"") | N7: =IF(RIGHT(B7,2)="SG","SG",IF(RIGHT(B7,1)="B","B","")) | O7: 2015
A8: 106 | B8: 14012 | C8: Allan Wood | D8: 0 | E8: 0 | F8: 0 | G8: 3672 | H8: 288 | I8: 1152 | J8: 768 | K8: 2015 | L8: =IF(OR(MID(B8,3,1)="H",MID(B8,3,1)="S"),MID(B8,4,3),MID(B8,3,3)) -> 012 | M8: =IF(OR(MID(B8,3,1)="H",MID(B8,3,1)="S"),MID(B8,3,1),"") | N8: =IF(RIGHT(B8,2)="SG","SG",IF(RIGHT(B8,1)="B","B","")) | O8: 2015
A9: 304 | B9: 14H010 | C9: Allen Price | D9: 0 | E9: 0 | F9: 0 | G9: 2658 | H9: 208 | I9: 834 | J9: 589 | K9: 2015 | L9: =IF(OR(MID(B9,3,1)="H",MID(B9,3,1)="S"),MID(B9,4,3),MID(B9,3,3)) -> 010 | M9: =IF(OR(MID(B9,3,1)="H",MID(B9,3,1)="S"),MID(B9,3,1),"") -> H | N9: =IF(RIGHT(B9,2)="SG","SG",IF(RIGHT(B9,1)="B","B","")) | O9: 2015
A10: 304 | B10: 14H012 | C10: Allen Price | D10: 0 | E10: 0 | F10: 0 | G10: 3988 | H10: 313 | I10: 1251 | J10: 883 | K10: 2015 | L10: =IF(OR(MID(B10,3,1)="H",MID(B10,3,1)="S"),MID(B10,4,3),MID(B10,3,3)) -> 012 | M10: =IF(OR(MID(B10,3,1)="H",MID(B10,3,1)="S"),MID(B10,3,1),"") -> H | N10: =IF(RIGHT(B10,2)="SG","SG",IF(RIGHT(B10,1)="B","B","")) | O10: 2015
A11: 274 | B11: 14005 | C11: Angel Watts | D11: 0 | E11: 0 | F11: 0 | G11: 115 | H11: 8 | I11: 35 | J11: 15 | K11: 2015 | L11: =IF(OR(MID(B11,3,1)="H",MID(B11,3,1)="S"),MID(B11,4,3),MID(B11,3,3)) -> 005 | M11: =IF(OR(MID(B11,3,1)="H",MID(B11,3,1)="S"),MID(B11,3,1),"") | N11: =IF(RIGHT(B11,2)="SG","SG",IF(RIGHT(B11,1)="B","B","")) | O11: 2015
A12: 274 | B12: 14H010 | C12: Angel Watts | D12: 0 | E12: 0 | F12: 0 | G12: 306 | H12: 24 | I12: 96 | J12: 64 | K12: 2015 | L12: =IF(OR(MID(B12,3,1)="H",MID(B12,3,1)="S"),MID(B12,4,3),MID(B12,3,3)) -> 010 | M12: =IF(OR(MID(B12,3,1)="H",MID(B12,3,1)="S"),MID(B12,3,1),"") -> H | N12: =IF(RIGHT(B12,2)="SG","SG",IF(RIGHT(B12,1)="B","B","")) | O12: 2015
A13: 274 | B13: 14H012 | C13: Angel Watts | D13: 0 | E13: 0 | F13: 0 | G13: 306 | H13: 133 | I13: 529 | J13: 64 | K13: 2015 | L13: =IF(OR(MID(B13,3,1)="H",MID(B13,3,1)="S"),MID(B13,4,3),MID(B13,3,3)) -> 012 | M13: =IF(OR(MID(B13,3,1)="H",MID(B13,3,1)="S"),MID(B13,3,1),"") -> H | N13: =IF(RIGHT(B13,2)="SG","SG",IF(RIGHT(B13,1)="B","B","")) | O13: 2015
... A852: 201 | B852: 15S009 | C852: Michele Lee | D852: 0 | E852: 0 | F852: 0 | G852: 1927 | H852: 0 | I852: 0 | J852: 416 | K852: 2015 | L852: =IF(OR(MID(B852,3,1)="H",MID(B852,3,1)="S"),MID(B852,4,3),MID(B852,3,3)) -> 009 | M852: =IF(OR(MID(B852,3,1)="H",MID(B852,3,1)="S"),MID(B852,3,1),"") -> S | N852: =IF(RIGHT(B852,2)="SG","SG",IF(RIGHT(B852,1)="B","B","")) | O852: 2015

Sheet 2016Data
A1: Job | B1: Emp_ID | C1: Emp_No | D1: Emp_Name | E1: Reg_Hrs | F1: OT_Hrs | G1: Gross_Wages | H1: Fica_Medc | I1: Futa | J1: Suta | K1: Work_Comp | L1: YEAR | M1: Job_code | N1: Department | O1: Location | P1: YEAR2
A2: 15001 | B2: W05781 | C2: 44 | D2: Dale Hamilton | E2: 40 | F2: 0 | G2: 3850 | H2: 29453 | I2: 231 | J2: 924 | K2: 481 | L2: 2016 | M2: =IF(OR(MID(A2,3,1)="H",MID(A2,3,1)="S"),MID(A2,4,3),MID(A2,3,3)) -> 001 | N2: =IF(OR(MID(A2,3,1)="H",MID(A2,3,1)="S"),MID(A2,3,1),"") | O2: =IF(RIGHT(A2,2)="SG","SG",IF(RIGHT(A2,1)="B","B","")) | P2: 2016
A3: 15002 | B3: U05779 | C3: 45 | D3: Ernesto Todd | E3: 40 | F3: 0 | G3: 422564 | H3: 30984 | I3: 243 | J3: 9721 | K3: 528 | L3: 2016 | M3: =IF(OR(MID(A3,3,1)="H",MID(A3,3,1)="S"),MID(A3,4,3),MID(A3,3,3)) -> 002 | N3: =IF(OR(MID(A3,3,1)="H",MID(A3,3,1)="S"),MID(A3,3,1),"") | O3: =IF(RIGHT(A3,2)="SG","SG",IF(RIGHT(A3,1)="B","B","")) | P3: 2016
A4: 15005 | B4: I07737 | C4: 422 | D4: Afton Call | E4: 1 | F4: 0 | G4: 3 | H4: 24 | I4: 1 | J4: 8 | K4: 5 | L4: 2016 | M4: =IF(OR(MID(A4,3,1)="H",MID(A4,3,1)="S"),MID(A4,4,3),MID(A4,3,3)) -> 005 | N4: =IF(OR(MID(A4,3,1)="H",MID(A4,3,1)="S"),MID(A4,3,1),"") | O4: =IF(RIGHT(A4,2)="SG","SG",IF(RIGHT(A4,1)="B","B","")) | P4: 2016
A5: 15005 | B5: S05921 | C5: 269 | D5: Jo Manning | E5: 1 | F5: 0 | G5: 9 | H5: 61 | I5: 4 | J5: 2 | K5: 14 | L5: 2016 | M5: =IF(OR(MID(A5,3,1)="H",MID(A5,3,1)="S"),MID(A5,4,3),MID(A5,3,3)) -> 005 | N5: =IF(OR(MID(A5,3,1)="H",MID(A5,3,1)="S"),MID(A5,3,1),"") | O5: =IF(RIGHT(A5,2)="SG","SG",IF(RIGHT(A5,1)="B","B","")) | P5: 2016
A6: 15005 | B6: Z06120 | C6: 357 | D6: Jesus Peterson | E6: 1 | F6: 0 | G6: 12 | H6: 81 | I6: 7 | J6: 24 | K6: 21 | L6: 2016 | M6: =IF(OR(MID(A6,3,1)="H",MID(A6,3,1)="S"),MID(A6,4,3),MID(A6,3,3)) -> 005 | N6: =IF(OR(MID(A6,3,1)="H",MID(A6,3,1)="S"),MID(A6,3,1),"") | O6: =IF(RIGHT(A6,2)="SG","SG",IF(RIGHT(A6,1)="B","B","")) | P6: 2016
A7: 15005 | B7: U05971 | C7: 314 | D7: Marianne Baldwin | E7: 1 | F7: 0 | G7: 3 | H7: 23 | I7: 3 | J7: 6 | K7: 7 | L7: 2016 | M7: =IF(OR(MID(A7,3,1)="H",MID(A7,3,1)="S"),MID(A7,4,3),MID(A7,3,3)) -> 005 | N7: =IF(OR(MID(A7,3,1)="H",MID(A7,3,1)="S"),MID(A7,3,1),"") | O7: =IF(RIGHT(A7,2)="SG","SG",IF(RIGHT(A7,1)="B","B","")) | P7: 2016
A8: 15005 | B8: S06809 | C8: 400 | D8: Roberto Ortega | E8: 1 | F8: 0 | G8: 15 | H8: 93 | I8: 8 | J8: 3 | K8: 5 | L8: 2016 | M8: =IF(OR(MID(A8,3,1)="H",MID(A8,3,1)="S"),MID(A8,4,3),MID(A8,3,3)) -> 005 | N8: =IF(OR(MID(A8,3,1)="H",MID(A8,3,1)="S"),MID(A8,3,1),"") | O8: =IF(RIGHT(A8,2)="SG","SG",IF(RIGHT(A8,1)="B","B","")) | P8: 2016
A9: 15005 | B9: V07604 | C9: 415 | D9: Floyd Hunter | E9: 1 | F9: 0 | G9: 15 | H9: 1 | I9: 8 | J9: 32 | K9: 26 | L9: 2016 | M9: =IF(OR(MID(A9,3,1)="H",MID(A9,3,1)="S"),MID(A9,4,3),MID(A9,3,3)) -> 005 | N9: =IF(OR(MID(A9,3,1)="H",MID(A9,3,1)="S"),MID(A9,3,1),"") | O9: =IF(RIGHT(A9,2)="SG","SG",IF(RIGHT(A9,1)="B","B","")) | P9: 2016
A10: 15005 | B10: V05780 | C10: 34 | D10: Sheryl Hill | E10: 1 | F10: 0 | G10: 15 | H10: 105 | I10: 9 | J10: 33 | K10: 24 | L10: 2016 | M10: =IF(OR(MID(A10,3,1)="H",MID(A10,3,1)="S"),MID(A10,4,3),MID(A10,3,3)) -> 005 | N10: =IF(OR(MID(A10,3,1)="H",MID(A10,3,1)="S"),MID(A10,3,1),"") | O10: =IF(RIGHT(A10,2)="SG","SG",IF(RIGHT(A10,1)="B","B","")) | P10: 2016
A11: 15005 | B11: R07120 | C11: 281 | D11: Marcia Neal | E11: 1 | F11: 0 | G11: 6 | H11: 42 | I11: 3 | J11: 13 | K11: 1 | L11: 2016 | M11: =IF(OR(MID(A11,3,1)="H",MID(A11,3,1)="S"),MID(A11,4,3),MID(A11,3,3)) -> 005 | N11: =IF(OR(MID(A11,3,1)="H",MID(A11,3,1)="S"),MID(A11,3,1),"") | O11: =IF(RIGHT(A11,2)="SG","SG",IF(RIGHT(A11,1)="B","B","")) | P11: 2016
A12: 15005 | B12: L05892 | C12: 179 | D12: Cassandra Poole | E12: 1 | F12: 0 | G12: 9 | H12: 66 | I12: 6 | J12: 21 | K12: 14 | L12: 2016 | M12: =IF(OR(MID(A12,3,1)="H",MID(A12,3,1)="S"),MID(A12,4,3),MID(A12,3,3)) -> 005 | N12: =IF(OR(MID(A12,3,1)="H",MID(A12,3,1)="S"),MID(A12,3,1),"") | O12: =IF(RIGHT(A12,2)="SG","SG",IF(RIGHT(A12,1)="B","B","")) | P12: 2016
A13: 15005 | E13: 1 | F13: 0 | G13: 12 | H13: 92 | I13: 8 | J13: 27 | K13: 19 | L13: 2016 | M13: =IF(OR(MID(A13,3,1)="H",MID(A13,3,1)="S"),MID(A13,4,3),MID(A13,3,3)) -> 005 | N13: =IF(OR(MID(A13,3,1)="H",MID(A13,3,1)="S"),MID(A13,3,1),"") | O13: =IF(RIGHT(A13,2)="SG","SG",IF(RIGHT(A13,1)="B","B","")) | P13: 2016
A14: 15005 | B14: E05885 | C14: 192 | D14: Mike Briggs | E14: 1 | F14: 0 | G14: 9 | H14: 61 | I14: 5 | J14: 27 | K14: 8 | L14: 2016 | M14: =IF(OR(MID(A14,3,1)="H",MID(A14,3,1)="S"),MID(A14,4,3),MID(A14,3,3)) -> 005 | N14: =IF(OR(MID(A14,3,1)="H",MID(A14,3,1)="S"),MID(A14,3,1),"") | O14: =IF(RIGHT(A14,2)="SG","SG",IF(RIGHT(A14,1)="B","B","")) | P14: 2016
A15: 15005 | B15: F05886 | C15: 195 | D15: Al Ramos | E15: 1 | F15: 0 | G15: 15 | H15: 107 | I15: 9 | J15: 34 | K15: 2 | L15: 2016 | M15: =IF(OR(MID(A15,3,1)="H",MID(A15,3,1)="S"),MID(A15,4,3),MID(A15,3,3)) -> 005 | N15: =IF(OR(MID(A15,3,1)="H",MID(A15,3,1)="S"),MID(A15,3,1),"") | O15: =IF(RIGHT(A15,2)="SG","SG",IF(RIGHT(A15,1)="B","B","")) | P15: 2016
A16: 15005 | B16: D06172 | C16: 199 | D16: Nettie Stevens | E16: 1 | F16: 0 | G16: 12 | H16: 81 | I16: 5 | J16: 27 | K16: 22 | L16: 2016 | M16: =IF(OR(MID(A16,3,1)="H",MID(A16,3,1)="S"),MID(A16,4,3),MID(A16,3,3)) -> 005 | N16: =IF(OR(MID(A16,3,1)="H",MID(A16,3,1)="S"),MID(A16,3,1),"") | O16: =IF(RIGHT(A16,2)="SG","SG",IF(RIGHT(A16,1)="B","B","")) | P16: 2016
A17: 15005 | B17: U05923 | C17: 274 | D17: Angel Watts | E17: 1 | F17: 0 | G17: 15 | H17: 114 | I17: 9 | J17: 36 | K17: 24 | L17: 2016 | M17: =IF(OR(MID(A17,3,1)="H",MID(A17,3,1)="S"),MID(A17,4,3),MID(A17,3,3)) -> 005 | N17: =IF(OR(MID(A17,3,1)="H",MID(A17,3,1)="S"),MID(A17,3,1),"") | O17: =IF(RIGHT(A17,2)="SG","SG",IF(RIGHT(A17,1)="B","B","")) | P17: 2016
A18: 15005 | B18: L05796 | C18: 27 | D18: Cindy Lunt | E18: 1 | F18: 0 | G18: 6 | H18: 42 | I18: 5 | J18: 12 | K18: 1 | L18: 2016 | M18: =IF(OR(MID(A18,3,1)="H",MID(A18,3,1)="S"),MID(A18,4,3),MID(A18,3,3)) -> 005 | N18: =IF(OR(MID(A18,3,1)="H",MID(A18,3,1)="S"),MID(A18,3,1),"") | O18: =IF(RIGHT(A18,2)="SG","SG",IF(RIGHT(A18,1)="B","B","")) | P18: 2016
A19: 15005 | B19: I05889 | C19: 201 | D19: Michele Lee | E19: 1 | F19: 0 | G19: 9 | H19: 69 | I19: 5 | J19: 22 | K19: 15 | L19: 2016 | M19: =IF(OR(MID(A19,3,1)="H",MID(A19,3,1)="S"),MID(A19,4,3),MID(A19,3,3)) -> 005 | N19: =IF(OR(MID(A19,3,1)="H",MID(A19,3,1)="S"),MID(A19,3,1),"") | O19: =IF(RIGHT(A19,2)="SG","SG",IF(RIGHT(A19,1)="B","B","")) | P19: 2016
A20: 15005 | B20: J05890 | C20: 203 | D20: Helen Paul | E20: 1 | F20: 0 | G20: 21 | H20: 151 | I20: 14 | J20: 46 | K20: 6 | L20: 2016 | M20: =IF(OR(MID(A20,3,1)="H",MID(A20,3,1)="S"),MID(A20,4,3),MID(A20,3,3)) -> 005 | N20: =IF(OR(MID(A20,3,1)="H",MID(A20,3,1)="S"),MID(A20,3,1),"") | O20: =IF(RIGHT(A20,2)="SG","SG",IF(RIGHT(A20,1)="B","B","")) | P20: 2016
A21: 15005 | B21: L05916 | C21: 259 | D21: Beulah Gibbs | E21: 1 | F21: 0 | G21: 9 | H21: 68 | I21: 6 | J21: 21 | K21: 14 | L21: 2016 | M21: =IF(OR(MID(A21,3,1)="H",MID(A21,3,1)="S"),MID(A21,4,3),MID(A21,3,3)) -> 005 | N21: =IF(OR(MID(A21,3,1)="H",MID(A21,3,1)="S"),MID(A21,3,1),"") | O21: =IF(RIGHT(A21,2)="SG","SG",IF(RIGHT(A21,1)="B","B","")) | P21: 2016
A22: 15005 | B22: L05988 | C22: 320 | D22: Terry Moreno | E22: 1 | F22: 0 | G22: 3 | H22: 23 | I22: 1 | J22: 6 | K22: 5 | L22: 2016 | M22: =IF(OR(MID(A22,3,1)="H",MID(A22,3,1)="S"),MID(A22,4,3),MID(A22,3,3)) -> 005 | N22: =IF(OR(MID(A22,3,1)="H",MID(A22,3,1)="S"),MID(A22,3,1),"") | O22: =IF(RIGHT(A22,2)="SG","SG",IF(RIGHT(A22,1)="B","B","")) | P22: 2016
A23: 15005 | B23: X06718 | C23: 396 | D23: Darryl Burgess | E23: 1 | F23: 0 | G23: 9 | H23: 67 | I23: 6 | J23: 26 | K23: 38 | L23: 2016 | M23: =IF(OR(MID(A23,3,1)="H",MID(A23,3,1)="S"),MID(A23,4,3),MID(A23,3,3)) -> 005 | N23: =IF(OR(MID(A23,3,1)="H",MID(A23,3,1)="S"),MID(A23,3,1),"") | O23: =IF(RIGHT(A23,2)="SG","SG",IF(RIGHT(A23,1)="B","B","")) | P23: 2016
A24: 15005 | B24: R05896 | C24: 210 | D24: Kenny Robertson | E24: 1 | F24: 0 | G24: 6 | H24: 4 | I24: 2 | J24: 25 | K24: 14 | L24: 2016 | M24: =IF(OR(MID(A24,3,1)="H",MID(A24,3,1)="S"),MID(A24,4,3),MID(A24,3,3)) -> 005 | N24: =IF(OR(MID(A24,3,1)="H",MID(A24,3,1)="S"),MID(A24,3,1),"") | O24: =IF(RIGHT(A24,2)="SG","SG",IF(RIGHT(A24,1)="B","B","")) | P24: 2016
A25: 15005 | B25: B07466 | C25: 411 | D25: Claire Edwards | E25: 1 | F25: 0 | G25: 9 | H25: 69 | I25: 5 | J25: 22 | K25: 14 | L25: 2016 | M25: =IF(OR(MID(A25,3,1)="H",MID(A25,3,1)="S"),MID(A25,4,3),MID(A25,3,3)) -> 005 | N25: =IF(OR(MID(A25,3,1)="H",MID(A25,3,1)="S"),MID(A25,3,1),"") | O25: =IF(RIGHT(A25,2)="SG","SG",IF(RIGHT(A25,1)="B","B","")) | P25: 2016
... A185: 15S004 | B185: J06178 | C185: 375 | D185: Fannie Parks | E185: 45 | F185: 0 | G185: 99 | H185: 758 | I185: 59 | J185: 238 | K185: 164 | L185: 2016 | M185: =IF(OR(MID(A185,3,1)="H",MID(A185,3,1)="S"),MID(A185,4,3),MID(A185,3,3)) -> 004 | N185: =IF(OR(MID(A185,3,1)="H",MID(A185,3,1)="S"),MID(A185,3,1),"") -> S | O185: =IF(RIGHT(A185,2)="SG","SG",IF(RIGHT(A185,1)="B","B","")) | P185: 2016
A186: 15S005 | E186: 3 | F186: 0 | G186: 69 | H186: 528 | I186: 41 | J186: 166 | K186: 114 | L186: 2016 | M186: =IF(OR(MID(A186,3,1)="H",MID(A186,3,1)="S"),MID(A186,4,3),MID(A186,3,3)) -> 005 | N186: =IF(OR(MID(A186,3,1)="H",MID(A186,3,1)="S"),MID(A186,3,1),"") -> S | O186: =IF(RIGHT(A186,2)="SG","SG",IF(RIGHT(A186,1)="B","B","")) | P186: 2016
A187: 15S006 | B187: Z06120 | C187: 357 | D187: Jesus Peterson | E187: 3 | F187: 0 | G187: 75 | H187: 494 | I187: 39 | J187: 155 | K187: 124 | L187: 2016 | M187: =IF(OR(MID(A187,3,1)="H",MID(A187,3,1)="S"),MID(A187,4,3),MID(A187,3,3)) -> 006 | N187: =IF(OR(MID(A187,3,1)="H",MID(A187,3,1)="S"),MID(A187,3,1),"") -> S | O187: =IF(RIGHT(A187,2)="SG","SG",IF(RIGHT(A187,1)="B","B","")) | P187: 2016
A188: 15S006 | B188: R07120 | C188: 281 | D188: Marcia Neal | E188: 2 | F188: 2 | G188: 130 | H188: 929 | I188: 73 | J188: 292 | K188: 21 | L188: 2016 | M188: =IF(OR(MID(A188,3,1)="H",MID(A188,3,1)="S"),MID(A188,4,3),MID(A188,3,3)) -> 006 | N188: =IF(OR(MID(A188,3,1)="H",MID(A188,3,1)="S"),MID(A188,3,1),"") -> S | O188: =IF(RIGHT(A188,2)="SG","SG",IF(RIGHT(A188,1)="B","B","")) | P188: 2016
A189: 15S006 | B189: E05813 | C189: 99 | D189: Sue Riley | E189: 16 | F189: 0 | G189: 360 | H189: 2665 | I189: 209 | J189: 836 | K189: 595 | L189: 2016 | M189: =IF(OR(MID(A189,3,1)="H",MID(A189,3,1)="S"),MID(A189,4,3),MID(A189,3,3)) -> 006 | N189: =IF(OR(MID(A189,3,1)="H",MID(A189,3,1)="S"),MID(A189,3,1),"") -> S | O189: =IF(RIGHT(A189,2)="SG","SG",IF(RIGHT(A189,1)="B","B","")) | P189: 2016
A190: 15S006 | B190: L05796 | C190: 27 | D190: Cindy Lunt | E190: 2 | F190: 0 | G190: 61 | H190: 416 | I190: 33 | J190: 131 | K190: 101 | L190: 2016 | M190: =IF(OR(MID(A190,3,1)="H",MID(A190,3,1)="S"),MID(A190,4,3),MID(A190,3,3)) -> 006 | N190: =IF(OR(MID(A190,3,1)="H",MID(A190,3,1)="S"),MID(A190,3,1),"") -> S | O190: =IF(RIGHT(A190,2)="SG","SG",IF(RIGHT(A190,1)="B","B","")) | P190: 2016
A191: 15S006 | B191: X05782 | C191: 19 | D191: Frank Diaz | E191: 2 | F191: 0 | G191: 54 | H191: 397 | I191: 31 | J191: 125 | K191: 89 | L191: 2016 | M191: =IF(OR(MID(A191,3,1)="H",MID(A191,3,1)="S"),MID(A191,4,3),MID(A191,3,3)) -> 006 | N191: =IF(OR(MID(A191,3,1)="H",MID(A191,3,1)="S"),MID(A191,3,1),"") -> S | O191: =IF(RIGHT(A191,2)="SG","SG",IF(RIGHT(A191,1)="B","B","")) | P191: 2016
A192: 15S006 | B192: J05890 | C192: 203 | D192: Helen Paul | E192: 8 | F192: 0 | G192: 51849 | H192: 3741 | I192: 293 | J192: 1174 | K192: 64 | L192: 2016 | M192: =IF(OR(MID(A192,3,1)="H",MID(A192,3,1)="S"),MID(A192,4,3),MID(A192,3,3)) -> 006 | N192: =IF(OR(MID(A192,3,1)="H",MID(A192,3,1)="S"),MID(A192,3,1),"") -> S | O192: =IF(RIGHT(A192,2)="SG","SG",IF(RIGHT(A192,1)="B","B","")) | P192: 2016
A193: 15S008 | B193: Z06120 | C193: 357 | D193: Jesus Peterson | E193: 5 | F193: 0 | G193: 125 | H193: 83 | I193: 6 | J193: 26 | K193: 2 | L193: 2016 | M193: =IF(OR(MID(A193,3,1)="H",MID(A193,3,1)="S"),MID(A193,4,3),MID(A193,3,3)) -> 008 | N193: =IF(OR(MID(A193,3,1)="H",MID(A193,3,1)="S"),MID(A193,3,1),"") -> S | O193: =IF(RIGHT(A193,2)="SG","SG",IF(RIGHT(A193,1)="B","B","")) | P193: 2016
A194: 15S008 | E194: 5 | F194: 0 | G194: 115 | H194: 88 | I194: 7 | J194: 28 | K194: 19 | L194: 2016 | M194: =IF(OR(MID(A194,3,1)="H",MID(A194,3,1)="S"),MID(A194,4,3),MID(A194,3,3)) -> 008 | N194: =IF(OR(MID(A194,3,1)="H",MID(A194,3,1)="S"),MID(A194,3,1),"") -> S | O194: =IF(RIGHT(A194,2)="SG","SG",IF(RIGHT(A194,1)="B","B","")) | P194: 2016
A195: 15S008 | B195: L05916 | C195: 259 | D195: Beulah Gibbs | E195: 5 | F195: 0 | G195: 1338 | H195: 99 | I195: 8 | J195: 31 | K195: 22 | L195: 2016 | M195: =IF(OR(MID(A195,3,1)="H",MID(A195,3,1)="S"),MID(A195,4,3),MID(A195,3,3)) -> 008 | N195: =IF(OR(MID(A195,3,1)="H",MID(A195,3,1)="S"),MID(A195,3,1),"") -> S | O195: =IF(RIGHT(A195,2)="SG","SG",IF(RIGHT(A195,1)="B","B","")) | P195: 2016
A196: 15S009 | B196: I07737 | C196: 422 | D196: Afton Call | E196: 14 | F196: 0 | G196: 196 | H196: 1499 | I196: 118 | J196: 47 | K196: 324 | L196: 2016 | M196: =IF(OR(MID(A196,3,1)="H",MID(A196,3,1)="S"),MID(A196,4,3),MID(A196,3,3)) -> 009 | N196: =IF(OR(MID(A196,3,1)="H",MID(A196,3,1)="S"),MID(A196,3,1),"") -> S | O196: =IF(RIGHT(A196,2)="SG","SG",IF(RIGHT(A196,1)="B","B","")) | P196: 2016
A197: 15S009 | B197: F06150 | C197: 368 | D197: Cesar Greene | E197: 16 | F197: 0 | G197: 392 | H197: 2466 | I197: 194 | J197: 774 | K197: 649 | L197: 2016 | M197: =IF(OR(MID(A197,3,1)="H",MID(A197,3,1)="S"),MID(A197,4,3),MID(A197,3,3)) -> 009 | N197: =IF(OR(MID(A197,3,1)="H",MID(A197,3,1)="S"),MID(A197,3,1),"") -> S | O197: =IF(RIGHT(A197,2)="SG","SG",IF(RIGHT(A197,1)="B","B","")) | P197: 2016
A198: 15S009 | B198: R07120 | C198: 281 | D198: Marcia Neal | E198: 16 | F198: 0 | G198: 416 | H198: 2972 | I198: 233 | J198: 933 | K198: 672 | L198: 2016 | M198: =IF(OR(MID(A198,3,1)="H",MID(A198,3,1)="S"),MID(A198,4,3),MID(A198,3,3)) -> 009 | N198: =IF(OR(MID(A198,3,1)="H",MID(A198,3,1)="S"),MID(A198,3,1),"") -> S | O198: =IF(RIGHT(A198,2)="SG","SG",IF(RIGHT(A198,1)="B","B","")) | P198: 2016
A199: 15S009 | B199: L05796 | C199: 27 | D199: Cindy Lunt | E199: 4 | F199: 0 | G199: 122 | H199: 832 | I199: 65 | J199: 261 | K199: 201 | L199: 2016 | M199: =IF(OR(MID(A199,3,1)="H",MID(A199,3,1)="S"),MID(A199,4,3),MID(A199,3,3)) -> 009 | N199: =IF(OR(MID(A199,3,1)="H",MID(A199,3,1)="S"),MID(A199,3,1),"") -> S | O199: =IF(RIGHT(A199,2)="SG","SG",IF(RIGHT(A199,1)="B","B","")) | P199: 2016
A200: 15S009 | B200: E06077 | C200: 352 | D200: Myra Vega | E200: 8 | F200: 0 | G200: 152 | H200: 702 | I200: 55 | J200: 22 | K200: 251 | L200: 2016 | M200: =IF(OR(MID(A200,3,1)="H",MID(A200,3,1)="S"),MID(A200,4,3),MID(A200,3,3)) -> 009 | N200: =IF(OR(MID(A200,3,1)="H",MID(A200,3,1)="S"),MID(A200,3,1),"") -> S | O200: =IF(RIGHT(A200,2)="SG","SG",IF(RIGHT(A200,1)="B","B","")) | P200: 2016
A201: 15S009 | B201: T06330 | C201: 380 | D201: Preston Robinson | E201: 19 | F201: 0 | G201: 399 | H201: 2587 | I201: 203 | J201: 812 | K201: 66 | L201: 2016 | M201: =IF(OR(MID(A201,3,1)="H",MID(A201,3,1)="S"),MID(A201,4,3),MID(A201,3,3)) -> 009 | N201: =IF(OR(MID(A201,3,1)="H",MID(A201,3,1)="S"),MID(A201,3,1),"") -> S | O201: =IF(RIGHT(A201,2)="SG","SG",IF(RIGHT(A201,1)="B","B","")) | P201: 2016
A202: 15S009 | B202: H07736 | C202: 421 | D202: Emma Goodwin | E202: 3 | F202: 0 | G202: 42 | H202: 298 | I202: 23 | J202: 94 | K202: 7 | L202: 2016 | M202: =IF(OR(MID(A202,3,1)="H",MID(A202,3,1)="S"),MID(A202,4,3),MID(A202,3,3)) -> 009 | N202: =IF(OR(MID(A202,3,1)="H",MID(A202,3,1)="S"),MID(A202,3,1),"") -> S | O202: =IF(RIGHT(A202,2)="SG","SG",IF(RIGHT(A202,1)="B","B","")) | P202: 2016
A203: 15S009 | B203: J06178 | C203: 375 | D203: Fannie Parks | E203: 7 | F203: 0 | G203: 154 | H203: 1178 | I203: 92 | J203: 37 | K203: 255 | L203: 2016 | M203: =IF(OR(MID(A203,3,1)="H",MID(A203,3,1)="S"),MID(A203,4,3),MID(A203,3,3)) -> 009 | N203: =IF(OR(MID(A203,3,1)="H",MID(A203,3,1)="S"),MID(A203,3,1),"") -> S | O203: =IF(RIGHT(A203,2)="SG","SG",IF(RIGHT(A203,1)="B","B","")) | P203: 2016
A204: 15S009 | B204: M06109 | C204: 38 | D204: Conrad Walker | E204: 26 | F204: 0 | G204: 106245 | H204: 7945 | I204: 623 | J204: 2493 | K204: 281 | L204: 2016 | M204: =IF(OR(MID(A204,3,1)="H",MID(A204,3,1)="S"),MID(A204,4,3),MID(A204,3,3)) -> 009 | N204: =IF(OR(MID(A204,3,1)="H",MID(A204,3,1)="S"),MID(A204,3,1),"") -> S | O204: =IF(RIGHT(A204,2)="SG","SG",IF(RIGHT(A204,1)="B","B","")) | P204: 2016
A205: 15S009 | B205: U06331 | C205: 381 | D205: Frankie Mcdaniel | E205: 13 | F205: 0 | G205: 28125 | H205: 1795 | I205: 141 | J205: 563 | K205: 75 | L205: 2016 | M205: =IF(OR(MID(A205,3,1)="H",MID(A205,3,1)="S"),MID(A205,4,3),MID(A205,3,3)) -> 009 | N205: =IF(OR(MID(A205,3,1)="H",MID(A205,3,1)="S"),MID(A205,3,1),"") -> S | O205: =IF(RIGHT(A205,2)="SG","SG",IF(RIGHT(A205,1)="B","B","")) | P205: 2016
A206: 15S011 | B206: J05794 | C206: 20 | D206: Ed Craig | E206: 20 | F206: 0 | G206: 5777 | H206: 391 | I206: 306 | J206: 1226 | K206: 77 | L206: 2016 | M206: =IF(OR(MID(A206,3,1)="H",MID(A206,3,1)="S"),MID(A206,4,3),MID(A206,3,3)) -> 011 | N206: =IF(OR(MID(A206,3,1)="H",MID(A206,3,1)="S"),MID(A206,3,1),"") -> S | O206: =IF(RIGHT(A206,2)="SG","SG",IF(RIGHT(A206,1)="B","B","")) | P206: 2016
... A221: 16002 | B221: U05779 | C221: 45 | D221: Ernesto Todd | E221: 960 | F221: 0 | G221: 10141536 | H221: 746304 | I221: 177 | J221: 67562 | K221: 14066 | L221: 2016 | M221: =IF(OR(MID(A221,3,1)="H",MID(A221,3,1)="S"),MID(A221,4,3),MID(A221,3,3)) -> 002 | N221: =IF(OR(MID(A221,3,1)="H",MID(A221,3,1)="S"),MID(A221,3,1),"") | O221: =IF(RIGHT(A221,2)="SG","SG",IF(RIGHT(A221,1)="B","B","")) | P221: 2016
A222: 16005 | E222: 0 | F222: 0 | G222: 0 | H222: 0 | I222: 0 | J222: 0 | K222: 0 | L222: 2016 | M222: =IF(OR(MID(A222,3,1)="H",MID(A222,3,1)="S"),MID(A222,4,3),MID(A222,3,3)) -> 005 | N222: =IF(OR(MID(A222,3,1)="H",MID(A222,3,1)="S"),MID(A222,3,1),"") | O222: =IF(RIGHT(A222,2)="SG","SG",IF(RIGHT(A222,1)="B","B","")) | P222: 2016
A223: 16005 | B223: P07287 | C223: 407 | D223: Maxine Tyler | E223: 1 | F223: 0 | G223: 15 | H223: 115 | I223: 0 | J223: 36 | K223: 24 | L223: 2016 | M223: =IF(OR(MID(A223,3,1)="H",MID(A223,3,1)="S"),MID(A223,4,3),MID(A223,3,3)) -> 005 | N223: =IF(OR(MID(A223,3,1)="H",MID(A223,3,1)="S"),MID(A223,3,1),"") | O223: =IF(RIGHT(A223,2)="SG","SG",IF(RIGHT(A223,1)="B","B","")) | P223: 2016
A224: 16005 | B224: N05798 | C224: 53 | D224: Delia Lopez | E224: 15 | F224: 0 | G224: 225 | H224: 1583 | I224: 49 | J224: 499 | K224: 371 | L224: 2016 | M224: =IF(OR(MID(A224,3,1)="H",MID(A224,3,1)="S"),MID(A224,4,3),MID(A224,3,3)) -> 005 | N224: =IF(OR(MID(A224,3,1)="H",MID(A224,3,1)="S"),MID(A224,3,1),"") | O224: =IF(RIGHT(A224,2)="SG","SG",IF(RIGHT(A224,1)="B","B","")) | P224: 2016
A225: 16005 | B225: P05919 | C225: 260 | D225: Nichole Fox | E225: 23 | F225: 0 | G225: 342 | H225: 2462 | I225: 5 | J225: 78 | K225: 569 | L225: 2016 | M225: =IF(OR(MID(A225,3,1)="H",MID(A225,3,1)="S"),MID(A225,4,3),MID(A225,3,3)) -> 005 | N225: =IF(OR(MID(A225,3,1)="H",MID(A225,3,1)="S"),MID(A225,3,1),"") | O225: =IF(RIGHT(A225,2)="SG","SG",IF(RIGHT(A225,1)="B","B","")) | P225: 2016
A226: 16005 | B226: I07737 | C226: 422 | D226: Afton Call | E226: 6 | F226: 0 | G226: 78 | H226: 596 | I226: 37 | J226: 187 | K226: 126 | L226: 2016 | M226: =IF(OR(MID(A226,3,1)="H",MID(A226,3,1)="S"),MID(A226,4,3),MID(A226,3,3)) -> 005 | N226: =IF(OR(MID(A226,3,1)="H",MID(A226,3,1)="S"),MID(A226,3,1),"") | O226: =IF(RIGHT(A226,2)="SG","SG",IF(RIGHT(A226,1)="B","B","")) | P226: 2016
A227: 16005 | B227: S06185 | C227: 376 | D227: Katie Hodges | E227: 23 | F227: 0 | G227: 327 | H227: 2385 | I227: 69 | J227: 744 | K227: 53 | L227: 2016 | M227: =IF(OR(MID(A227,3,1)="H",MID(A227,3,1)="S"),MID(A227,4,3),MID(A227,3,3)) -> 005 | N227: =IF(OR(MID(A227,3,1)="H",MID(A227,3,1)="S"),MID(A227,3,1),"") | O227: =IF(RIGHT(A227,2)="SG","SG",IF(RIGHT(A227,1)="B","B","")) | P227: 2016
A228: 16005 | B228: J06730 | C228: 398 | D228: Mona Howard | E228: 20 | F228: 0 | G228: 279 | H228: 2015 | I228: 81 | J228: 624 | K228: 454 | L228: 2016 | M228: =IF(OR(MID(A228,3,1)="H",MID(A228,3,1)="S"),MID(A228,4,3),MID(A228,3,3)) -> 005 | N228: =IF(OR(MID(A228,3,1)="H",MID(A228,3,1)="S"),MID(A228,3,1),"") | O228: =IF(RIGHT(A228,2)="SG","SG",IF(RIGHT(A228,1)="B","B","")) | P228: 2016
A229: 16005 | B229: S05921 | C229: 269 | D229: Jo Manning | E229: 22 | F229: 0 | G229: 330 | H229: 2325 | I229: 31 | J229: 61 | K229: 475 | L229: 2016 | M229: =IF(OR(MID(A229,3,1)="H",MID(A229,3,1)="S"),MID(A229,4,3),MID(A229,3,3)) -> 005 | N229: =IF(OR(MID(A229,3,1)="H",MID(A229,3,1)="S"),MID(A229,3,1),"") | O229: =IF(RIGHT(A229,2)="SG","SG",IF(RIGHT(A229,1)="B","B","")) | P229: 2016
A230: 16005 | B230: Z06120 | C230: 357 | D230: Jesus Peterson | E230: 24 | F230: 0 | G230: 339 | H230: 2295 | I230: 39 | J230: 727 | K230: 541 | L230: 2016 | M230: =IF(OR(MID(A230,3,1)="H",MID(A230,3,1)="S"),MID(A230,4,3),MID(A230,3,3)) -> 005 | N230: =IF(OR(MID(A230,3,1)="H",MID(A230,3,1)="S"),MID(A230,3,1),"") | O230: =IF(RIGHT(A230,2)="SG","SG",IF(RIGHT(A230,1)="B","B","")) | P230: 2016
A231: 16005 | E231: 1 | F231: 0 | G231: 15 | H231: 113 | I231: 0 | J231: 36 | K231: 25 | L231: 2016 | M231: =IF(OR(MID(A231,3,1)="H",MID(A231,3,1)="S"),MID(A231,4,3),MID(A231,3,3)) -> 005 | N231: =IF(OR(MID(A231,3,1)="H",MID(A231,3,1)="S"),MID(A231,3,1),"") | O231: =IF(RIGHT(A231,2)="SG","SG",IF(RIGHT(A231,1)="B","B","")) | P231: 2016
A232: 16005 | B232: U05971 | C232: 314 | D232: Marianne Baldwin | E232: 23 | F232: 0 | G232: 288 | H232: 2194 | I232: 5 | J232: 694 | K232: 477 | L232: 2016 | M232: =IF(OR(MID(A232,3,1)="H",MID(A232,3,1)="S"),MID(A232,4,3),MID(A232,3,3)) -> 005 | N232: =IF(OR(MID(A232,3,1)="H",MID(A232,3,1)="S"),MID(A232,3,1),"") | O232: =IF(RIGHT(A232,2)="SG","SG",IF(RIGHT(A232,1)="B","B","")) | P232: 2016
A233: 16005 | B233: S06809 | C233: 400 | D233: Roberto Ortega | E233: 2 | F233: 0 | G233: 30 | H233: 191 | I233: 15 | J233: 6 | K233: 8 | L233: 2016 | M233: =IF(OR(MID(A233,3,1)="H",MID(A233,3,1)="S"),MID(A233,4,3),MID(A233,3,3)) -> 005 | N233: =IF(OR(MID(A233,3,1)="H",MID(A233,3,1)="S"),MID(A233,3,1),"") | O233: =IF(RIGHT(A233,2)="SG","SG",IF(RIGHT(A233,1)="B","B","")) | P233: 2016
A234: 16005 | B234: F06150 | C234: 368 | D234: Cesar Greene | E234: 24 | F234: 0 | G234: 339 | H234: 2266 | I234: 54 | J234: 705 | K234: 552 | L234: 2016 | M234: =IF(OR(MID(A234,3,1)="H",MID(A234,3,1)="S"),MID(A234,4,3),MID(A234,3,3)) -> 005 | N234: =IF(OR(MID(A234,3,1)="H",MID(A234,3,1)="S"),MID(A234,3,1),"") | O234: =IF(RIGHT(A234,2)="SG","SG",IF(RIGHT(A234,1)="B","B","")) | P234: 2016
A235: 16005 | B235: V07604 | C235: 415 | D235: Floyd Hunter | E235: 8 | F235: 0 | G235: 120 | H235: 892 | I235: 48 | J235: 279 | K235: 2 | L235: 2016 | M235: =IF(OR(MID(A235,3,1)="H",MID(A235,3,1)="S"),MID(A235,4,3),MID(A235,3,3)) -> 005 | N235: =IF(OR(MID(A235,3,1)="H",MID(A235,3,1)="S"),MID(A235,3,1),"") | O235: =IF(RIGHT(A235,2)="SG","SG",IF(RIGHT(A235,1)="B","B","")) | P235: 2016
A236: 16005 | B236: V05780 | C236: 34 | D236: Sheryl Hill | E236: 24 | F236: 0 | G236: 360 | H236: 2589 | I236: 2 | J236: 4 | K236: 598 | L236: 2016 | M236: =IF(OR(MID(A236,3,1)="H",MID(A236,3,1)="S"),MID(A236,4,3),MID(A236,3,3)) -> 005 | N236: =IF(OR(MID(A236,3,1)="H",MID(A236,3,1)="S"),MID(A236,3,1),"") | O236: =IF(RIGHT(A236,2)="SG","SG",IF(RIGHT(A236,1)="B","B","")) | P236: 2016
A237: 16005 | B237: R07120 | C237: 281 | D237: Marcia Neal | E237: 24 | F237: 0 | G237: 348 | H237: 2527 | I237: 45 | J237: 786 | K237: 547 | L237: 2016 | M237: =IF(OR(MID(A237,3,1)="H",MID(A237,3,1)="S"),MID(A237,4,3),MID(A237,3,3)) -> 005 | N237: =IF(OR(MID(A237,3,1)="H",MID(A237,3,1)="S"),MID(A237,3,1),"") | O237: =IF(RIGHT(A237,2)="SG","SG",IF(RIGHT(A237,1)="B","B","")) | P237: 2016
A238: 16005 | E238: 1 | F238: 0 | G238: 15 | H238: 115 | I238: 9 | J238: 36 | K238: 24 | L238: 2016 | M238: =IF(OR(MID(A238,3,1)="H",MID(A238,3,1)="S"),MID(A238,4,3),MID(A238,3,3)) -> 005 | N238: =IF(OR(MID(A238,3,1)="H",MID(A238,3,1)="S"),MID(A238,3,1),"") | O238: =IF(RIGHT(A238,2)="SG","SG",IF(RIGHT(A238,1)="B","B","")) | P238: 2016
A239: 16005 | B239: T06066 | C239: 345 | D239: Sidney Hansen | E239: 8 | F239: 0 | G239: 120 | H239: 915 | I239: 0 | J239: 29 | K239: 192 | L239: 2016 | M239: =IF(OR(MID(A239,3,1)="H",MID(A239,3,1)="S"),MID(A239,4,3),MID(A239,3,3)) -> 005 | N239: =IF(OR(MID(A239,3,1)="H",MID(A239,3,1)="S"),MID(A239,3,1),"") | O239: =IF(RIGHT(A239,2)="SG","SG",IF(RIGHT(A239,1)="B","B","")) | P239: 2016
A240: 16005 | E240: 1 | F240: 0 | G240: 15 | H240: 115 | I240: 8 | J240: 36 | K240: 23 | L240: 2016 | M240: =IF(OR(MID(A240,3,1)="H",MID(A240,3,1)="S"),MID(A240,4,3),MID(A240,3,3)) -> 005 | N240: =IF(OR(MID(A240,3,1)="H",MID(A240,3,1)="S"),MID(A240,3,1),"") | O240: =IF(RIGHT(A240,2)="SG","SG",IF(RIGHT(A240,1)="B","B","")) | P240: 2016
